# ğŸ” ä½œç”¨åŸŸä¸ Upvalue æœºåˆ¶è¯¦è§£

> **æŠ€æœ¯æ·±åº¦**ï¼šâ­â­â­â­â­  
> **é¢„è®¡é˜…è¯»æ—¶é—´**ï¼š20åˆ†é’Ÿ  
> **å‰ç½®çŸ¥è¯†**ï¼š[é€’å½’ä¸‹é™è§£æ](recursive_descent.md)ã€[è¯­å¥è§£æ](statement_parsing.md)

---

## ğŸ“‹ ç›®å½•

- [æ¦‚è¿°](#æ¦‚è¿°)
- [å±€éƒ¨å˜é‡ç®¡ç†æœºåˆ¶](#å±€éƒ¨å˜é‡ç®¡ç†æœºåˆ¶)
- [Upvalue æœºåˆ¶è¯¦è§£](#upvalue-æœºåˆ¶è¯¦è§£)
- [Upvalue å…³é—­æœºåˆ¶](#upvalue-å…³é—­æœºåˆ¶)
- [å¤æ‚é—­åŒ…åœºæ™¯](#å¤æ‚é—­åŒ…åœºæ™¯)
- [å…³é”®æ•°æ®ç»“æ„](#å…³é”®æ•°æ®ç»“æ„)
- [ä»£ç ç”Ÿæˆä¸æ€§èƒ½åˆ†æ](#ä»£ç ç”Ÿæˆä¸æ€§èƒ½åˆ†æ)
- [è°ƒè¯•ä¸å®è·µæŒ‡å—](#è°ƒè¯•ä¸å®è·µæŒ‡å—)

---

## ğŸ¯ æ¦‚è¿°

ä½œç”¨åŸŸç®¡ç†æ˜¯ Lua ç¼–è¯‘å™¨æœ€ç²¾å¦™çš„éƒ¨åˆ†ä¹‹ä¸€ï¼Œå®ƒå®ç°äº†**è¯æ³•ä½œç”¨åŸŸ**ï¼ˆLexical Scopingï¼‰å’Œ**é—­åŒ…**ï¼ˆClosureï¼‰æœºåˆ¶ã€‚ç†è§£ä½œç”¨åŸŸç®¡ç†å¯¹äºæŒæ¡ Lua çš„é«˜çº§ç‰¹æ€§è‡³å…³é‡è¦ã€‚

### ä»€ä¹ˆæ˜¯ä½œç”¨åŸŸï¼Ÿ

**ä½œç”¨åŸŸ**ï¼ˆScopeï¼‰å®šä¹‰äº†å˜é‡çš„å¯è§æ€§å’Œç”Ÿå‘½å‘¨æœŸï¼š

```lua
local x = 1        -- å…¨å±€ä½œç”¨åŸŸä¸­çš„å±€éƒ¨å˜é‡

function f()
    local y = 2    -- f çš„ä½œç”¨åŸŸ
    
    do
        local z = 3  -- do å—çš„ä½œç”¨åŸŸ
        print(x, y, z)  -- 1 2 3ï¼ˆéƒ½å¯è§ï¼‰
    end
    
    print(x, y)    -- 1 2ï¼ˆz ä¸å¯è§ï¼‰
    -- print(z)    -- é”™è¯¯ï¼šz å·²ç¦»å¼€ä½œç”¨åŸŸ
end
```

### è¯æ³•ä½œç”¨åŸŸ vs åŠ¨æ€ä½œç”¨åŸŸ

| ç‰¹æ€§ | è¯æ³•ä½œç”¨åŸŸï¼ˆLexical Scopingï¼‰ | åŠ¨æ€ä½œç”¨åŸŸï¼ˆDynamic Scopingï¼‰ |
|------|-------------------------------|------------------------------|
| **å®šä¹‰** | å˜é‡ç»‘å®šåœ¨ç¼–è¯‘æ—¶ç¡®å®š | å˜é‡ç»‘å®šåœ¨è¿è¡Œæ—¶ç¡®å®š |
| **æŸ¥æ‰¾è§„åˆ™** | æ ¹æ®ä»£ç ç»“æ„ï¼ˆåµŒå¥—ï¼‰ | æ ¹æ®è°ƒç”¨æ ˆ |
| **Lua é‡‡ç”¨** | âœ… æ˜¯ | âŒ å¦ |
| **ä¼˜ç‚¹** | å¯é¢„æµ‹ã€æ˜“ä¼˜åŒ–ã€æ”¯æŒé—­åŒ… | çµæ´» |
| **ç¼ºç‚¹** | ä¸å¤Ÿçµæ´» | éš¾ä»¥æ¨ç†ã€æ€§èƒ½å·® |

**ç¤ºä¾‹å¯¹æ¯”**ï¼š

```lua
-- è¯æ³•ä½œç”¨åŸŸï¼ˆLua å®é™…è¡Œä¸ºï¼‰
local x = 1

function f()
    print(x)  -- æ€»æ˜¯æ‰“å° 1ï¼ˆå®šä¹‰æ—¶çš„ xï¼‰
end

function g()
    local x = 2
    f()  -- æ‰“å° 1ï¼ˆä¸æ˜¯ 2ï¼ï¼‰
end

g()  -- è¾“å‡ºï¼š1
```

å¦‚æœæ˜¯åŠ¨æ€ä½œç”¨åŸŸï¼ˆLua ä¸æ˜¯ï¼‰ï¼Œ`f()` ä¼šæ‰“å° `2`ï¼ˆè°ƒç”¨æ—¶çš„ xï¼‰ã€‚

### Lua ä½œç”¨åŸŸè§„åˆ™

**1. å—çº§ä½œç”¨åŸŸ**ï¼š

```lua
do
    local x = 1
end
-- x ä¸å¯è§

if condition then
    local y = 2
end
-- y ä¸å¯è§

for i = 1, 10 do
    local z = 3
end
-- i å’Œ z éƒ½ä¸å¯è§
```

**2. å‡½æ•°ä½œç”¨åŸŸ**ï¼š

```lua
function f()
    local x = 1  -- x çš„ä½œç”¨åŸŸæ˜¯æ•´ä¸ªå‡½æ•° f
    
    function g()
        print(x)  -- g å¯ä»¥è®¿é—® f çš„å±€éƒ¨å˜é‡ï¼ˆé—­åŒ…ï¼‰
    end
    
    return g
end
```

**3. å˜é‡é®è”½ï¼ˆShadowingï¼‰**ï¼š

```lua
local x = 1

function f()
    local x = 2  -- é®è”½å¤–å±‚çš„ x
    print(x)     -- 2
end

print(x)  -- 1
```

### é—­åŒ…ï¼ˆClosureï¼‰çš„æ ¸å¿ƒ

**é—­åŒ… = å‡½æ•° + æ•è·çš„å¤–éƒ¨å˜é‡**

```lua
function make_counter()
    local count = 0  -- å¤–éƒ¨å˜é‡
    
    return function()  -- é—­åŒ…
        count = count + 1  -- æ•è· count
        return count
    end
end

local c1 = make_counter()
print(c1())  -- 1
print(c1())  -- 2

local c2 = make_counter()
print(c2())  -- 1ï¼ˆç‹¬ç«‹çš„é—­åŒ…ï¼‰
```

**å…³é”®é—®é¢˜**ï¼š
- `count` æ˜¯ `make_counter` çš„å±€éƒ¨å˜é‡ï¼Œå‡½æ•°è¿”å›ååº”è¯¥é”€æ¯
- ä½†é—­åŒ…å‡½æ•°ä»éœ€è®¿é—® `count`
- **è§£å†³æ–¹æ¡ˆ**ï¼šUpvalue æœºåˆ¶

### Upvalue æœºåˆ¶ç®€ä»‹

**Upvalue** æ˜¯ Lua å®ç°é—­åŒ…çš„æ ¸å¿ƒæœºåˆ¶ï¼š

```
â”Œâ”€â”€â”€â”€â”€â”€â”€â”€â”€â”€â”€â”€â”€â”€â”€â”€â”€â”
â”‚ å‡½æ•°åŸå‹ (Proto)â”‚
â”‚                 â”‚
â”‚ upvalues[]      â”‚â”€â”€â”€â”
â””â”€â”€â”€â”€â”€â”€â”€â”€â”€â”€â”€â”€â”€â”€â”€â”€â”€â”˜   â”‚
                      â”‚
                      â–¼
                â”Œâ”€â”€â”€â”€â”€â”€â”€â”€â”€â”€â”
                â”‚ Upvalue  â”‚
                â”‚          â”‚
                â”‚ v â”€â”€â”€â”€â”€â”€â”€â”¼â”€â”€â†’ å±€éƒ¨å˜é‡æˆ–TValue
                â””â”€â”€â”€â”€â”€â”€â”€â”€â”€â”€â”˜
```

**ä¸¤ç§çŠ¶æ€**ï¼š

1. **Open Upvalue**ï¼šæŒ‡å‘æ ˆä¸Šçš„å±€éƒ¨å˜é‡
   ```
   Upvalue.v â”€â”€â†’ æ ˆä¸Šçš„å˜é‡
   ```

2. **Closed Upvalue**ï¼šå±€éƒ¨å˜é‡å·²ç¦»å¼€ä½œç”¨åŸŸï¼Œå€¼è¢«å¤åˆ¶åˆ°å †ä¸Š
   ```
   Upvalue.v â”€â”€â†’ Upvalue.u.valueï¼ˆå †ä¸Šï¼‰
   ```

### ä½œç”¨åŸŸç®¡ç†çš„æŒ‘æˆ˜

```mermaid
graph TD
    A[ä½œç”¨åŸŸæŒ‘æˆ˜] --> B[å˜é‡æŸ¥æ‰¾æ•ˆç‡]
    A --> C[é—­åŒ…å®ç°]
    A --> D[å†…å­˜ç®¡ç†]
    
    B --> B1[å±€éƒ¨å˜é‡ï¼šO1 æŸ¥æ‰¾]
    B --> B2[Upvalueï¼šO1 æŸ¥æ‰¾]
    B --> B3[å…¨å±€å˜é‡ï¼šå“ˆå¸ŒæŸ¥æ‰¾]
    
    C --> C1[æ•è·å¤–éƒ¨å˜é‡]
    C --> C2[å¤šå±‚åµŒå¥—é—­åŒ…]
    C --> C3[Upvalue å…±äº«]
    
    D --> D1[ä½•æ—¶å…³é—­ Upvalue]
    D --> D2[åƒåœ¾å›æ”¶é›†æˆ]
    D --> D3[é¿å…å†…å­˜æ³„æ¼]
```

### ç¼–è¯‘å™¨ vs è™šæ‹ŸæœºèŒè´£

| é˜¶æ®µ | èŒè´£ |
|------|------|
| **ç¼–è¯‘æœŸ** | - è¯†åˆ«å±€éƒ¨å˜é‡å’Œ upvalue<br>- ç”Ÿæˆå˜é‡æŸ¥æ‰¾æŒ‡ä»¤<br>- æ’å…¥ OP_CLOSE æŒ‡ä»¤ |
| **è¿è¡ŒæœŸ** | - åˆ›å»º Upvalue å¯¹è±¡<br>- ç®¡ç† Open/Closed çŠ¶æ€<br>- æ‰§è¡Œ GETUPVAL/SETUPVAL æŒ‡ä»¤ |

### ç›¸å…³æŒ‡ä»¤

| æŒ‡ä»¤ | æ“ä½œ | è¯´æ˜ |
|------|------|------|
| `GETLOCAL` | `R(A) = R(B)` | è¯»å–å±€éƒ¨å˜é‡ |
| `SETLOCAL` | `R(A) = R(B)` | å†™å…¥å±€éƒ¨å˜é‡ |
| `GETUPVAL` | `R(A) = UpValue[B]` | è¯»å– upvalue |
| `SETUPVAL` | `UpValue[B] = R(A)` | å†™å…¥ upvalue |
| `GETGLOBAL` | `R(A) = _G[K(Bx)]` | è¯»å–å…¨å±€å˜é‡ |
| `SETGLOBAL` | `_G[K(Bx)] = R(A)` | å†™å…¥å…¨å±€å˜é‡ |
| `CLOSE` | å…³é—­æ ˆä¸Šçš„ upvalue | ç¦»å¼€ä½œç”¨åŸŸæ—¶è°ƒç”¨ |
| `CLOSURE` | åˆ›å»ºé—­åŒ… | åŒ…å« upvalue åˆ—è¡¨ |

---

## ğŸ—‚ï¸ å±€éƒ¨å˜é‡ç®¡ç†æœºåˆ¶

å±€éƒ¨å˜é‡å­˜å‚¨åœ¨å‡½æ•°æ ˆå¸§ä¸­ï¼Œé€šè¿‡å¯„å­˜å™¨ç¼–å·å¿«é€Ÿè®¿é—®ã€‚

### å˜é‡å£°æ˜ï¼šnew_localvar

```c
// æ¥è‡ª lparser.c
static void new_localvar(LexState *ls, TString *name, int n) {
    FuncState *fs = ls->fs;
    
    // æ£€æŸ¥å˜é‡æ•°é‡é™åˆ¶
    luaX_checklimit(ls, fs->nactvar + n + 1, LUAI_MAXVARS, "local variables");
    
    // æ³¨å†Œå˜é‡
    fs->actvar[fs->nactvar + n] = cast(unsigned short, registerlocalvar(ls, name));
}

static int registerlocalvar(LexState *ls, TString *varname) {
    FuncState *fs = ls->fs;
    Proto *f = fs->f;
    int oldsize = f->sizelocvars;
    
    // æ‰©å±• locvars æ•°ç»„
    luaM_growvector(ls->L, f->locvars, fs->nlocvars, f->sizelocvars,
                    LocVar, SHRT_MAX, "too many local variables");
    
    while (oldsize < f->sizelocvars) 
        f->locvars[oldsize++].varname = NULL;
    
    // è®°å½•å˜é‡å
    f->locvars[fs->nlocvars].varname = varname;
    luaC_objbarrier(ls->L, f, varname);
    
    return fs->nlocvars++;
}
```

### å˜é‡æ¿€æ´»ï¼šadjustlocalvars

```c
static void adjustlocalvars(LexState *ls, int nvars) {
    FuncState *fs = ls->fs;
    
    // å¢åŠ æ´»åŠ¨å˜é‡æ•°
    fs->nactvar = cast_byte(fs->nactvar + nvars);
    
    // è®¾ç½®å˜é‡ä½œç”¨åŸŸèµ·å§‹ç‚¹
    for (; nvars; nvars--) {
        getlocvar(fs, fs->nactvar - nvars).startpc = fs->pc;
    }
}

#define getlocvar(fs, i) ((fs)->f->locvars[(fs)->actvar[i]])
```

### å˜é‡æŸ¥æ‰¾ï¼šsinglevar

```c
static void singlevar(LexState *ls, expdesc *var) {
    TString *varname = str_checkname(ls);
    FuncState *fs = ls->fs;
    
    // 1. æŸ¥æ‰¾å±€éƒ¨å˜é‡
    if (singlevaraux(fs, varname, var, 1) == VGLOBAL)
        // 2. ä¸æ˜¯å±€éƒ¨å˜é‡ï¼Œå½“ä½œå…¨å±€å˜é‡
        var->u.s.info = luaK_stringK(fs, varname);
}

static int singlevaraux(FuncState *fs, TString *n, expdesc *var, int base) {
    if (fs == NULL) {
        // åˆ°è¾¾æœ€å¤–å±‚ï¼Œæ˜¯å…¨å±€å˜é‡
        init_exp(var, VGLOBAL, 0);
        return VGLOBAL;
    }
    else {
        // åœ¨å½“å‰å‡½æ•°ä¸­æŸ¥æ‰¾
        int v = searchvar(fs, n);
        
        if (v >= 0) {
            // æ‰¾åˆ°å±€éƒ¨å˜é‡
            init_exp(var, VLOCAL, v);
            if (!base)
                markupval(fs, v);  // æ ‡è®°ä¸º upvalue
            return VLOCAL;
        }
        else {
            // é€’å½’åˆ°å¤–å±‚å‡½æ•°æŸ¥æ‰¾
            if (singlevaraux(fs->prev, n, var, 0) == VGLOBAL)
                return VGLOBAL;
            
            // å¤–å±‚æ‰¾åˆ°äº†ï¼Œåˆ›å»º upvalue
            var->u.s.info = indexupvalue(fs, n, var);
            var->k = VUPVAL;
            return VUPVAL;
        }
    }
}
```

**æŸ¥æ‰¾æµç¨‹å›¾**ï¼š

```mermaid
graph TD
    A[singlevar] --> B[searchvar: å½“å‰å‡½æ•°]
    B -->|æ‰¾åˆ°| C[VLOCAL å±€éƒ¨å˜é‡]
    B -->|æœªæ‰¾åˆ°| D[singlevaraux: å¤–å±‚å‡½æ•°]
    D -->|æ‰¾åˆ°| E[VUPVAL upvalue]
    D -->|æœªæ‰¾åˆ°| F[ç»§ç»­å‘å¤–]
    F --> G[åˆ°è¾¾æœ€å¤–å±‚]
    G --> H[VGLOBAL å…¨å±€å˜é‡]
```

### searchvarï¼šåœ¨å½“å‰å‡½æ•°æŸ¥æ‰¾

```c
static int searchvar(FuncState *fs, TString *n) {
    int i;
    
    // ä»åå‘å‰æŸ¥æ‰¾ï¼ˆæ”¯æŒå˜é‡é®è”½ï¼‰
    for (i = fs->nactvar - 1; i >= 0; i--) {
        if (n == getlocvar(fs, i).varname)
            return i;  // è¿”å›å¯„å­˜å™¨ç´¢å¼•
    }
    
    return -1;  // æœªæ‰¾åˆ°
}
```

**ç¤ºä¾‹ï¼šå˜é‡é®è”½**

```lua
local x = 1
do
    local x = 2  -- é®è”½å¤–å±‚ x
    print(x)     -- 2
end
print(x)  -- 1
```

```c
// ç¼–è¯‘æ—¶ï¼š
// nactvar = 0, locvars = []
// è§£æ "local x = 1":
//   registerlocalvar("x")  -> locvars[0] = {varname="x", startpc=?, endpc=?}
//   adjustlocalvars(1)     -> nactvar = 1, locvars[0].startpc = pc
//   actvar[0] = 0
//
// è¿›å…¥ do å—ï¼š
// è§£æ "local x = 2":
//   registerlocalvar("x")  -> locvars[1] = {varname="x", startpc=?, endpc=?}
//   adjustlocalvars(1)     -> nactvar = 2, locvars[1].startpc = pc
//   actvar[1] = 1
//
// åœ¨ do å—ä¸­æŸ¥æ‰¾ "x":
//   searchvar(fs, "x")
//   -> ä»åå‘å‰ï¼ši=1, locvars[actvar[1]].varname == "x"  âœ“
//   -> è¿”å› 1ï¼ˆå†…å±‚ x çš„å¯„å­˜å™¨ï¼‰
//
// ç¦»å¼€ do å—ï¼š
//   removevars(ls, 1)
//   -> nactvar = 1, locvars[1].endpc = pc
//
// å¤–å±‚æŸ¥æ‰¾ "x":
//   searchvar(fs, "x")
//   -> ä»åå‘å‰ï¼ši=0, locvars[actvar[0]].varname == "x"  âœ“
//   -> è¿”å› 0ï¼ˆå¤–å±‚ x çš„å¯„å­˜å™¨ï¼‰
```

### å˜é‡ç§»é™¤ï¼šremovevars

```c
static void removevars(LexState *ls, int tolevel) {
    FuncState *fs = ls->fs;
    
    // ç§»é™¤åˆ°æŒ‡å®šå±‚æ¬¡
    while (fs->nactvar > tolevel) {
        // è®¾ç½®ä½œç”¨åŸŸç»“æŸç‚¹
        getlocvar(fs, --fs->nactvar).endpc = fs->pc;
    }
}
```

### LocVar ç»“æ„

```c
typedef struct LocVar {
    TString *varname;  // å˜é‡å
    int startpc;       // ä½œç”¨åŸŸèµ·å§‹ PC
    int endpc;         // ä½œç”¨åŸŸç»“æŸ PC
} LocVar;
```

**è°ƒè¯•ä¿¡æ¯**ï¼š
- `startpc` å’Œ `endpc` ç”¨äºè°ƒè¯•å™¨æ˜¾ç¤ºå˜é‡
- è¿è¡Œæ—¶ä¸ä½¿ç”¨ï¼ˆå±€éƒ¨å˜é‡ç›´æ¥ç”¨å¯„å­˜å™¨ç´¢å¼•ï¼‰

### ç¤ºä¾‹ï¼šå˜é‡ç”Ÿå‘½å‘¨æœŸ

```lua
function f()
    local a = 1     -- startpc = 0
    
    do
        local b = 2  -- startpc = 2
        print(a, b)
    end              -- b.endpc = 5
    
    local c = 3      -- startpc = 6
    print(a, c)
end                  -- a.endpc = 8, c.endpc = 8
```

**LocVar æ•°ç»„**ï¼š

```
locvars[0] = {varname="a", startpc=0, endpc=8}
locvars[1] = {varname="b", startpc=2, endpc=5}
locvars[2] = {varname="c", startpc=6, endpc=8}
```

### ä½œç”¨åŸŸåµŒå¥—ç¤ºä¾‹

```lua
local x = 1        -- å±‚çº§ 0

function outer()
    local y = 2    -- å±‚çº§ 1
    
    function inner()
        local z = 3  -- å±‚çº§ 2
        print(x, y, z)  -- è®¿é—® 3 ä¸ªå±‚çº§
    end
    
    return inner
end
```

**å˜é‡æŸ¥æ‰¾**ï¼š
- `z`ï¼šå±‚çº§ 2ï¼ŒVLOCALï¼ˆå½“å‰å‡½æ•°ï¼‰
- `y`ï¼šå±‚çº§ 1ï¼ŒVUPVALï¼ˆå¤–å±‚å‡½æ•°ï¼‰
- `x`ï¼šå±‚çº§ 0ï¼ŒVUPVALï¼ˆæœ€å¤–å±‚å‡½æ•°ï¼‰

---

## ğŸ”— Upvalue æœºåˆ¶è¯¦è§£

Upvalue æ˜¯ Lua å®ç°é—­åŒ…çš„æ ¸å¿ƒï¼Œå…è®¸å‡½æ•°è®¿é—®å¤–éƒ¨ä½œç”¨åŸŸçš„å±€éƒ¨å˜é‡ã€‚

### Upvalue çš„åˆ›å»ºï¼šindexupvalue

```c
static int indexupvalue(FuncState *fs, TString *name, expdesc *v) {
    int i;
    Proto *f = fs->f;
    int oldsize = f->sizeupvalues;
    
    // æŸ¥æ‰¾æ˜¯å¦å·²å­˜åœ¨
    for (i = 0; i < f->nups; i++) {
        if (fs->upvalues[i].k == v->k && fs->upvalues[i].info == v->u.s.info)
            return i;  // å¤ç”¨å·²æœ‰ upvalue
    }
    
    // åˆ›å»ºæ–° upvalue
    luaX_checklimit(fs->ls, f->nups + 1, LUAI_MAXUPVALUES, "upvalues");
    luaM_growvector(fs->ls->L, f->upvalues, f->nups, f->sizeupvalues,
                    TString *, MAX_INT, "");
    
    while (oldsize < f->sizeupvalues) 
        f->upvalues[oldsize++] = NULL;
    
    f->upvalues[f->nups] = name;
    luaC_objbarrier(fs->ls->L, f, name);
    
    // è®°å½• upvalue ä¿¡æ¯
    lua_assert(v->k == VLOCAL || v->k == VUPVAL);
    fs->upvalues[f->nups].k = cast_byte(v->k);
    fs->upvalues[f->nups].info = cast_byte(v->u.s.info);
    
    return f->nups++;
}
```

### Upvalue æè¿°ç¬¦

```c
// ç¼–è¯‘æœŸ upvalue ä¿¡æ¯ï¼ˆåœ¨ FuncState ä¸­ï¼‰
typedef struct upvaldesc {
    lu_byte k;       // VLOCAL æˆ– VUPVAL
    lu_byte info;    // å±€éƒ¨å˜é‡ç´¢å¼• æˆ– å¤–å±‚ upvalue ç´¢å¼•
} upvaldesc;
```

**k å­—æ®µçš„å«ä¹‰**ï¼š

| å€¼ | å«ä¹‰ | info æŒ‡å‘ |
|----|------|----------|
| `VLOCAL` | ç›´æ¥å¤–å±‚çš„å±€éƒ¨å˜é‡ | å¤–å±‚å‡½æ•°çš„å±€éƒ¨å˜é‡ç´¢å¼• |
| `VUPVAL` | æ›´å¤–å±‚çš„ upvalue | å¤–å±‚å‡½æ•°çš„ upvalue ç´¢å¼• |

**ç¤ºä¾‹**ï¼š

```lua
function level0()
    local x = 1           -- level0 çš„å±€éƒ¨å˜é‡ 0
    
    function level1()
        local y = 2       -- level1 çš„å±€éƒ¨å˜é‡ 0
        
        function level2()
            print(x, y)   -- level2 è®¿é—® x å’Œ y
        end
        
        return level2
    end
    
    return level1
end
```

**level2 çš„ upvalue ä¿¡æ¯**ï¼š

```c
// level2.upvalues:
// upvalues[0] = {k=VUPVAL, info=0}  // x æ¥è‡ª level1 çš„ upvalue[0]
// upvalues[1] = {k=VLOCAL, info=0}  // y æ¥è‡ª level1 çš„å±€éƒ¨å˜é‡[0]

// level1.upvalues:
// upvalues[0] = {k=VLOCAL, info=0}  // x æ¥è‡ª level0 çš„å±€éƒ¨å˜é‡[0]
```

### markupvalï¼šæ ‡è®°å˜é‡è¢«æ•è·

```c
static void markupval(FuncState *fs, int level) {
    BlockCnt *bl = fs->bl;
    
    while (bl && bl->nactvar > level) 
        bl = bl->previous;
    
    if (bl) 
        bl->upval = 1;  // æ ‡è®°å—åŒ…å« upvalue
}
```

**ä½œç”¨**ï¼š
- æ ‡è®°å“ªäº›å—éœ€è¦åœ¨ç¦»å¼€æ—¶å…³é—­ upvalue
- ç”Ÿæˆ `OP_CLOSE` æŒ‡ä»¤

### CLOSURE æŒ‡ä»¤ç”Ÿæˆ

```c
static void pushclosure(LexState *ls, FuncState *func, expdesc *v) {
    FuncState *fs = ls->fs;
    Proto *f = fs->f;
    int oldsize = f->sizep;
    int i;
    
    // æ·»åŠ å­å‡½æ•°åŸå‹
    luaM_growvector(ls->L, f->p, fs->np, f->sizep, Proto *, MAXARG_Bx, "constant table overflow");
    while (oldsize < f->sizep) f->p[oldsize++] = NULL;
    f->p[fs->np++] = func->f;
    luaC_objbarrier(ls->L, f, func->f);
    
    // ç”Ÿæˆ CLOSURE æŒ‡ä»¤
    init_exp(v, VRELOCABLE, luaK_codeABx(fs, OP_CLOSURE, 0, fs->np - 1));
    
    // ç”Ÿæˆ upvalue æŒ‡ä»¤
    for (i = 0; i < func->f->nups; i++) {
        OpCode o = (func->upvalues[i].k == VLOCAL) ? OP_MOVE : OP_GETUPVAL;
        luaK_codeABC(fs, o, 0, func->upvalues[i].info, 0);
    }
    
    luaK_exp2nextreg(fs, v);
}
```

**CLOSURE æŒ‡ä»¤æ ¼å¼**ï¼š

```
CLOSURE R(A) Bx    ; R(A) = closure(KPROTO[Bx])

; åè·Ÿ nups æ¡ä¼ªæŒ‡ä»¤ï¼š
MOVE 0 B 0         ; upvalue[i] = R(B)ï¼ˆå±€éƒ¨å˜é‡ï¼‰
GETUPVAL 0 B 0     ; upvalue[i] = upvalue[B]ï¼ˆå¤–å±‚ upvalueï¼‰
```

### ç¤ºä¾‹ï¼šé—­åŒ…ç”Ÿæˆ

```lua
function make_counter()
    local count = 0
    
    return function()
        count = count + 1
        return count
    end
end
```

**å­—èŠ‚ç **ï¼š

```
function <make_counter>:
[1] LOADK      R0 K0     ; K0 = 0, count = 0
[2] CLOSURE    R1 <inner>
[3] MOVE       0  R0      ; upvalue[0] = countï¼ˆä¼ªæŒ‡ä»¤ï¼‰
[4] RETURN     R1 2
[5] RETURN     R0 1

function <inner>:  (1 upvalue)
[1] GETUPVAL   R0 U0     ; count
[2] ADD        R0 R0 K0  ; K0 = 1
[3] SETUPVAL   R0 U0     ; count = count + 1
[4] GETUPVAL   R0 U0
[5] RETURN     R0 2
[6] RETURN     R0 1
```

### Upvalue å¯¹è±¡ç»“æ„ï¼ˆè¿è¡Œæ—¶ï¼‰

```c
// æ¥è‡ª lobject.h
typedef struct UpVal {
    CommonHeader;
    TValue *v;          // æŒ‡å‘å€¼çš„æŒ‡é’ˆ
    union {
        TValue value;   // closed æ—¶å­˜å‚¨å€¼
        struct {        // open æ—¶çš„é“¾è¡¨èŠ‚ç‚¹
            struct UpVal *prev;
            struct UpVal *next;
        } l;
    } u;
} UpVal;
```

**Open vs Closed**ï¼š

```
Open Upvalue:
â”Œâ”€â”€â”€â”€â”€â”€â”€â”€â”€â”€â”
â”‚ UpVal    â”‚
â”‚ v â”€â”€â”€â”€â”€â”€â”€â”¼â”€â”€â”€â†’ æ ˆä¸Šçš„å±€éƒ¨å˜é‡
â”‚ u.l.next â”‚
â””â”€â”€â”€â”€â”€â”€â”€â”€â”€â”€â”˜

Closed Upvalue:
â”Œâ”€â”€â”€â”€â”€â”€â”€â”€â”€â”€â”
â”‚ UpVal    â”‚
â”‚ v â”€â”€â”€â”€â”€â”€â”€â”¼â”€â”€â”€â†’ u.valueï¼ˆå†…éƒ¨å­˜å‚¨ï¼‰
â”‚ u.value  â”‚ = 42
â””â”€â”€â”€â”€â”€â”€â”€â”€â”€â”€â”˜
```

### Open Upvalue é“¾è¡¨

è™šæ‹Ÿæœºç»´æŠ¤ä¸€ä¸ªå…¨å±€çš„ open upvalue é“¾è¡¨ï¼š

```c
// æ¥è‡ª lstate.h
typedef struct global_State {
    // ...
    UpVal *uvhead;  // åŒå‘é“¾è¡¨å¤´
    // ...
} global_State;
```

**é“¾è¡¨ç»„ç»‡**ï¼š

```
lua_State.openupval â”€â”€â”€â†’ UpVal â†â†’ UpVal â†â†’ UpVal â†â†’ uvhead
                          (æ ˆä¸Š)   (æ ˆä¸Š)   (æ ˆä¸Š)
```

**æ’åºè§„åˆ™**ï¼šæŒ‰æ ˆåœ°å€ä»é«˜åˆ°ä½æ’åˆ—

---

## ğŸ”’ Upvalue å…³é—­æœºåˆ¶

å½“å±€éƒ¨å˜é‡ç¦»å¼€ä½œç”¨åŸŸæ—¶ï¼ŒæŒ‡å‘å®ƒçš„ upvalue å¿…é¡»"å…³é—­"ï¼Œå°†å€¼ä»æ ˆå¤åˆ¶åˆ°å †ã€‚

### ä½•æ—¶å…³é—­ Upvalueï¼Ÿ

```lua
function outer()
    local x = 1
    
    local f = function()
        print(x)  -- æ•è· x
    end
    
    return f
end  -- â† è¿™é‡Œå…³é—­ upvalueï¼ˆx ç¦»å¼€ä½œç”¨åŸŸï¼‰

local func = outer()
func()  -- ä»èƒ½è®¿é—® xï¼ˆå·²å…³é—­çš„ upvalueï¼‰
```

### OP_CLOSE æŒ‡ä»¤ç”Ÿæˆ

```c
static void leaveblock(FuncState *fs) {
    BlockCnt *bl = fs->bl;
    
    fs->bl = bl->previous;
    removevars(fs->ls, bl->nactvar);
    
    // å¦‚æœå—åŒ…å« upvalueï¼Œç”Ÿæˆ CLOSE æŒ‡ä»¤
    if (bl->upval)
        luaK_codeABC(fs, OP_CLOSE, bl->nactvar, 0, 0);
    
    fs->freereg = fs->nactvar;
    luaK_patchtohere(fs, bl->breaklist);
}
```

### OP_CLOSE æŒ‡ä»¤æ‰§è¡Œ

```c
// æ¥è‡ª lvm.c
case OP_CLOSE: {
    luaF_close(L, ra);  // å…³é—­ >= R(A) çš„æ‰€æœ‰ upvalue
    continue;
}

// æ¥è‡ª lfunc.c
void luaF_close(lua_State *L, StkId level) {
    UpVal *uv;
    global_State *g = G(L);
    
    // éå† open upvalue é“¾è¡¨
    while (L->openupval != NULL && (uv = gco2uv(L->openupval))->v >= level) {
        GCObject *o = obj2gco(uv);
        lua_assert(!isblack(o) && uv->v != &uv->u.value);
        
        L->openupval = uv->next;  // ä»é“¾è¡¨ç§»é™¤
        
        if (isdead(g, o))
            luaF_freeupval(L, uv);  // GC å·²æ ‡è®°ï¼Œç›´æ¥é‡Šæ”¾
        else {
            // å…³é—­ï¼šå¤åˆ¶å€¼åˆ°å †
            setobj(L, &uv->u.value, uv->v);
            uv->v = &uv->u.value;  // æŒ‡å‘å†…éƒ¨å­˜å‚¨
            luaC_linkupval(L, uv);  // åŠ å…¥ GC ç°è‰²é“¾è¡¨
        }
    }
}
```

**å…³é—­æµç¨‹**ï¼š

```mermaid
graph TD
    A[OP_CLOSE R] --> B[éå† openupval é“¾è¡¨]
    B --> C{upval.v >= R?}
    C -->|å¦| D[åœæ­¢]
    C -->|æ˜¯| E{GC å·²æ ‡è®°æ­»äº¡?}
    E -->|æ˜¯| F[é‡Šæ”¾ upvalue]
    E -->|å¦| G[å¤åˆ¶å€¼åˆ° u.value]
    G --> H[upval.v = &u.value]
    H --> I[åŠ å…¥ GC ç°è‰²é“¾è¡¨]
    I --> B
```

### ç¤ºä¾‹ï¼šUpvalue å…³é—­æ—¶æœº

```lua
function make_functions()
    local funcs = {}
    
    for i = 1, 3 do
        funcs[i] = function()
            return i
        end
    end  -- â† OP_CLOSEï¼ˆi ç¦»å¼€ä½œç”¨åŸŸï¼‰
    
    return funcs
end

local f = make_functions()
print(f[1]())  -- 3ï¼ˆä¸æ˜¯ 1ï¼ï¼‰
print(f[2]())  -- 3
print(f[3]())  -- 3
```

**é—®é¢˜**ï¼šæ‰€æœ‰é—­åŒ…å…±äº«åŒä¸€ä¸ª `i` çš„ upvalueï¼Œå¾ªç¯ç»“æŸæ—¶ `i=3`ã€‚

**ä¿®æ­£**ï¼š

```lua
function make_functions()
    local funcs = {}
    
    for i = 1, 3 do
        local j = i  -- æ¯æ¬¡å¾ªç¯åˆ›å»ºæ–°å˜é‡
        funcs[i] = function()
            return j
        end
    end
    
    return funcs
end

local f = make_functions()
print(f[1]())  -- 1
print(f[2]())  -- 2
print(f[3]())  -- 3
```

### Upvalue ä¸ GC çš„äº¤äº’

**1. Open Upvalue**ï¼š
- ä¸å½’ GC ç®¡ç†ï¼ˆåœ¨ openupval é“¾è¡¨ä¸­ï¼‰
- æ ˆå›æ”¶æ—¶è‡ªåŠ¨å…³é—­

**2. Closed Upvalue**ï¼š
- å½’ GC ç®¡ç†ï¼ˆåŠ å…¥ç°è‰²é“¾è¡¨ï¼‰
- è¢«é—­åŒ…å¼•ç”¨æ—¶ä¿æŒå­˜æ´»
- æ— å¼•ç”¨æ—¶å›æ”¶

**GC æ ‡è®°é˜¶æ®µ**ï¼š

```c
// æ¥è‡ª lgc.c
static void traverseclosure(global_State *g, Closure *cl) {
    int i;
    
    if (cl->c.isC) {
        // C é—­åŒ…
        for (i = 0; i < cl->c.nupvalues; i++)
            markvalue(g, &cl->c.upvalue[i]);
    }
    else {
        // Lua é—­åŒ…
        markobject(g, cl->l.p);  // æ ‡è®°å‡½æ•°åŸå‹
        for (i = 0; i < cl->l.nupvalues; i++)
            markobject(g, cl->l.upvals[i]);  // æ ‡è®° upvalue
    }
}
```

### å†…å­˜å¸ƒå±€

**Closure å¯¹è±¡**ï¼š

```c
typedef struct Closure {
    CommonHeader;
    lu_byte isC;
    lu_byte nupvalues;
    // ...
} Closure;

// Lua é—­åŒ…
typedef struct LClosure {
    // ... ç»§æ‰¿ Closure ...
    struct Proto *p;
    UpVal *upvals[1];  // å¯å˜é•¿åº¦æ•°ç»„
} LClosure;
```

**å†…å­˜ç¤ºä¾‹**ï¼š

```
â”Œâ”€â”€â”€â”€â”€â”€â”€â”€â”€â”€â”€â”€â”€â”€â”
â”‚ LClosure     â”‚
â”‚ p â”€â”€â”€â”€â”€â”€â”€â”€â”€â” â”‚
â”‚ upvals[0] â”€â”€â”¼â”€â”¼â”€â†’ UpVal
â”‚ upvals[1] â”€â”€â”¼â”€â”¼â”€â†’ UpVal
â””â”€â”€â”€â”€â”€â”€â”€â”€â”€â”€â”€â”€â”€â”¼â”€â”˜
              â”‚
              â–¼
         â”Œâ”€â”€â”€â”€â”€â”€â”€â”€â”€â”
         â”‚ Proto   â”‚
         â”‚ code[]  â”‚
         â”‚ k[]     â”‚
         â””â”€â”€â”€â”€â”€â”€â”€â”€â”€â”˜
```

---

## ğŸŒ å¤æ‚é—­åŒ…åœºæ™¯

### å¤šå±‚åµŒå¥—é—­åŒ…

```lua
function level1()
    local a = 1
    
    function level2()
        local b = 2
        
        function level3()
            local c = 3
            
            function level4()
                print(a, b, c)  -- è®¿é—®å¤šå±‚å¤–éƒ¨å˜é‡
            end
            
            return level4
        end
        
        return level3
    end
    
    return level2
end

local f = level1()()()
f()  -- è¾“å‡ºï¼š1 2 3
```

**Upvalue é“¾æ¡**ï¼š

```
level4:
  upvalues[0] = {k=VUPVAL, info=0}  â†’ level3.upvalues[0] (a)
  upvalues[1] = {k=VUPVAL, info=1}  â†’ level3.upvalues[1] (b)
  upvalues[2] = {k=VLOCAL, info=0}  â†’ level3 çš„å±€éƒ¨å˜é‡ c

level3:
  upvalues[0] = {k=VUPVAL, info=0}  â†’ level2.upvalues[0] (a)
  upvalues[1] = {k=VLOCAL, info=0}  â†’ level2 çš„å±€éƒ¨å˜é‡ b

level2:
  upvalues[0] = {k=VLOCAL, info=0}  â†’ level1 çš„å±€éƒ¨å˜é‡ a
```

### é€’å½’é—­åŒ…

```lua
function make_factorial()
    local function fact(n)
        if n <= 1 then return 1
        else return n * fact(n - 1)  -- é€’å½’å¼•ç”¨è‡ªèº«
        end
    end
    return fact
end

local f = make_factorial()
print(f(5))  -- 120
```

**ç¼–è¯‘å¤„ç†**ï¼š

```c
// localfunc å‡½æ•°
static void localfunc(LexState *ls) {
    expdesc v, b;
    FuncState *fs = ls->fs;
    
    new_localvar(ls, str_checkname(ls), 0);  // å…ˆå£°æ˜å˜é‡
    init_exp(&v, VLOCAL, fs->freereg);
    luaK_reserveregs(fs, 1);
    adjustlocalvars(ls, 1);  // ç«‹å³æ¿€æ´»ï¼ˆå…è®¸é€’å½’ï¼ï¼‰
    
    body(ls, &b, 0, ls->linenumber);
    luaK_storevar(fs, &v, &b);
    
    // ä¿®æ­£è°ƒè¯•ä¿¡æ¯
    getlocvar(fs, fs->nactvar - 1).startpc = fs->pc;
}
```

**å…³é”®**ï¼š`adjustlocalvars(ls, 1)` åœ¨è§£æå‡½æ•°ä½“ä¹‹å‰è°ƒç”¨ï¼Œä½¿å‡½æ•°ååœ¨è‡ªå·±çš„å‡½æ•°ä½“å†…å¯è§ã€‚

### é—­åŒ…æ•°ç»„ï¼ˆå¸¸è§é™·é˜±ï¼‰

**é”™è¯¯ç‰ˆæœ¬**ï¼š

```lua
function make_buttons()
    local buttons = {}
    
    for i = 1, 5 do
        buttons[i] = function()
            print("Button " .. i)
        end
    end
    
    return buttons
end

local btns = make_buttons()
btns[1]()  -- Button 6ï¼ˆä¸æ˜¯ 1ï¼ï¼‰
btns[2]()  -- Button 6
```

**é—®é¢˜åˆ†æ**ï¼š

```
æ‰€æœ‰é—­åŒ…å…±äº«åŒä¸€ä¸ª upvalueï¼ˆiï¼‰
å¾ªç¯ç»“æŸæ—¶ i = 6ï¼ˆfor å¾ªç¯çš„ç‰¹æ€§ï¼‰
æ‰€æœ‰é—­åŒ…è¯»å–åˆ° i = 6
```

**å­—èŠ‚ç **ï¼š

```
function <make_buttons>:
[1]  NEWTABLE   R0 5 0
[2]  LOADK      R1 K0      ; K0 = 1, (for index)
[3]  LOADK      R2 K1      ; K1 = 5, (for limit)
[4]  LOADK      R3 K0      ; K0 = 1, (for step)
[5]  FORPREP    R1 [12]

; å¾ªç¯ä½“
[6]  CLOSURE    R5 <inner>
[7]  MOVE       0  R4      ; upvalue[0] = iï¼ˆæ‰€æœ‰é—­åŒ…å…±äº«ï¼ï¼‰
[8]  SETTABLE   R0 R4 R5
[9]  FORLOOP    R1 [6]

; å¾ªç¯ç»“æŸï¼Œi = 6
[10] RETURN     R0 2
```

**æ­£ç¡®ç‰ˆæœ¬**ï¼š

```lua
function make_buttons()
    local buttons = {}
    
    for i = 1, 5 do
        local j = i  -- æ¯æ¬¡å¾ªç¯åˆ›å»ºæ–°å˜é‡
        buttons[i] = function()
            print("Button " .. j)
        end
    end
    
    return buttons
end

local btns = make_buttons()
btns[1]()  -- Button 1 âœ“
btns[2]()  -- Button 2 âœ“
```

**å­—èŠ‚ç **ï¼š

```
; å¾ªç¯ä½“
[6]  MOVE       R5 R4      ; j = iï¼ˆæ–°å±€éƒ¨å˜é‡ï¼‰
[7]  CLOSURE    R6 <inner>
[8]  MOVE       0  R5      ; upvalue[0] = jï¼ˆç‹¬ç«‹çš„å˜é‡ï¼ï¼‰
[9]  SETTABLE   R0 R4 R6
[10] CLOSE      R5         ; å…³é—­ j çš„ upvalue
[11] FORLOOP    R1 [6]
```

### é—­åŒ…ä½œä¸ºè¿”å›å€¼

```lua
function make_adder(x)
    return function(y)
        return x + y
    end
end

local add5 = make_adder(5)
print(add5(10))  -- 15
print(add5(20))  -- 25

local add10 = make_adder(10)
print(add10(10))  -- 20
```

**å†…å­˜çŠ¶æ€**ï¼š

```
add5 é—­åŒ…:
â”Œâ”€â”€â”€â”€â”€â”€â”€â”€â”€â”€â”€â”€â”€â”€â”
â”‚ LClosure     â”‚
â”‚ upvals[0] â”€â”€â”€â”¼â”€â”€â†’ UpVal (closed)
â””â”€â”€â”€â”€â”€â”€â”€â”€â”€â”€â”€â”€â”€â”€â”˜      â”‚ v â†’ u.value = 5

add10 é—­åŒ…:
â”Œâ”€â”€â”€â”€â”€â”€â”€â”€â”€â”€â”€â”€â”€â”€â”
â”‚ LClosure     â”‚
â”‚ upvals[0] â”€â”€â”€â”¼â”€â”€â†’ UpVal (closed)
â””â”€â”€â”€â”€â”€â”€â”€â”€â”€â”€â”€â”€â”€â”€â”˜      â”‚ v â†’ u.value = 10
```

ä¸¤ä¸ªé—­åŒ…æœ‰**ç‹¬ç«‹çš„ upvalue å¯¹è±¡**ï¼Œäº’ä¸å½±å“ã€‚

### å…±äº« Upvalue

```lua
function make_counter()
    local count = 0
    
    local function inc()
        count = count + 1
        return count
    end
    
    local function get()
        return count
    end
    
    return inc, get
end

local increment, get_value = make_counter()
print(increment())  -- 1
print(increment())  -- 2
print(get_value())  -- 2ï¼ˆå…±äº«åŒä¸€ä¸ª countï¼‰
```

**å†…å­˜çŠ¶æ€**ï¼š

```
inc é—­åŒ…:                get é—­åŒ…:
â”Œâ”€â”€â”€â”€â”€â”€â”€â”€â”€â”€â”€â”€â”€â”€â”        â”Œâ”€â”€â”€â”€â”€â”€â”€â”€â”€â”€â”€â”€â”€â”€â”
â”‚ LClosure     â”‚        â”‚ LClosure     â”‚
â”‚ upvals[0] â”€â”€â”€â”¼â”€â”€â”€â”    â”‚ upvals[0] â”€â”€â”€â”¼â”€â”€â”€â”
â””â”€â”€â”€â”€â”€â”€â”€â”€â”€â”€â”€â”€â”€â”€â”˜   â”‚    â””â”€â”€â”€â”€â”€â”€â”€â”€â”€â”€â”€â”€â”€â”€â”˜   â”‚
                   â”‚                       â”‚
                   â””â”€â”€â†’ UpVal (å…±äº«) â†â”€â”€â”€â”€â”€â”˜
                         â”‚ v â†’ u.value = 2
```

**å®ç°æœºåˆ¶**ï¼š

```c
// indexupvalue å‡½æ•°ä¼šæ£€æŸ¥æ˜¯å¦å·²å­˜åœ¨
for (i = 0; i < f->nups; i++) {
    if (fs->upvalues[i].k == v->k && fs->upvalues[i].info == v->u.s.info)
        return i;  // å¤ç”¨å·²æœ‰ upvalue
}
```

### å¤æ‚ç¤ºä¾‹ï¼šè®¡æ•°å™¨å·¥å‚

```lua
function make_counter_factory()
    local counters = {}
    local next_id = 0
    
    return function()  -- åˆ›å»ºè®¡æ•°å™¨
        next_id = next_id + 1
        local id = next_id
        local count = 0
        
        local counter = {
            inc = function()
                count = count + 1
                return count
            end,
            
            dec = function()
                count = count - 1
                return count
            end,
            
            get = function()
                return count
            end,
            
            id = function()
                return id
            end
        }
        
        counters[id] = counter
        return counter
    end
end

local create = make_counter_factory()

local c1 = create()
print(c1.inc())  -- 1
print(c1.inc())  -- 2

local c2 = create()
print(c2.inc())  -- 1
print(c2.get())  -- 1
print(c1.get())  -- 2ï¼ˆç‹¬ç«‹ï¼‰
```

**Upvalue åˆ†æ**ï¼š

```
create é—­åŒ…:
  upvalues[0] = countersï¼ˆsharedï¼‰
  upvalues[1] = next_idï¼ˆsharedï¼‰

c1.inc é—­åŒ…:
  upvalues[0] = countï¼ˆc1 ç‹¬æœ‰ï¼‰

c1.dec é—­åŒ…:
  upvalues[0] = countï¼ˆä¸ c1.inc å…±äº«ï¼‰

c1.get é—­åŒ…:
  upvalues[0] = countï¼ˆä¸ c1.incã€c1.dec å…±äº«ï¼‰

c1.id é—­åŒ…:
  upvalues[0] = idï¼ˆc1 ç‹¬æœ‰ï¼‰

c2.* é—­åŒ…:
  æœ‰ç‹¬ç«‹çš„ count å’Œ id upvalue
```

---

## ğŸ—„ï¸ å…³é”®æ•°æ®ç»“æ„

### FuncStateï¼šå‡½æ•°çŠ¶æ€

```c
typedef struct FuncState {
    Proto *f;                 // å‡½æ•°åŸå‹
    Table *h;                 // æŸ¥æ‰¾å¸¸é‡çš„å“ˆå¸Œè¡¨
    struct FuncState *prev;   // å¤–å±‚å‡½æ•°
    struct LexState *ls;      // è¯æ³•çŠ¶æ€
    struct lua_State *L;      // Lua çŠ¶æ€
    struct BlockCnt *bl;      // å½“å‰å—
    int pc;                   // ä¸‹ä¸€æ¡æŒ‡ä»¤çš„ä½ç½®
    int lasttarget;           // æœ€åè·³è½¬ç›®æ ‡
    int jpc;                  // å¾…ä¿®æ­£çš„è·³è½¬é“¾è¡¨
    int freereg;              // ç¬¬ä¸€ä¸ªç©ºé—²å¯„å­˜å™¨
    int nk;                   // k æ•°ç»„å…ƒç´ æ•°
    int np;                   // p æ•°ç»„å…ƒç´ æ•°
    short nlocvars;           // locvars æ•°ç»„å…ƒç´ æ•°
    lu_byte nactvar;          // æ´»åŠ¨å±€éƒ¨å˜é‡æ•°
    upvaldesc upvalues[LUAI_MAXUPVALUES];  // upvalue æè¿°ç¬¦
    unsigned short actvar[LUAI_MAXVARS];   // æ´»åŠ¨å˜é‡ç´¢å¼•
} FuncState;
```

**å­—æ®µè¯¦è§£**ï¼š

| å­—æ®µ | ç±»å‹ | è¯´æ˜ |
|------|------|------|
| `f` | `Proto*` | æ­£åœ¨æ„å»ºçš„å‡½æ•°åŸå‹ |
| `prev` | `FuncState*` | å¤–å±‚å‡½æ•°ï¼ˆå½¢æˆé“¾è¡¨ï¼‰ |
| `nactvar` | `lu_byte` | å½“å‰æ´»åŠ¨çš„å±€éƒ¨å˜é‡æ•° |
| `freereg` | `int` | ç¬¬ä¸€ä¸ªç©ºé—²å¯„å­˜å™¨ç´¢å¼• |
| `actvar[]` | `unsigned short[]` | æ´»åŠ¨å˜é‡ç´¢å¼•åˆ° locvars çš„æ˜ å°„ |
| `upvalues[]` | `upvaldesc[]` | upvalue æè¿°ç¬¦æ•°ç»„ |

**actvar æ•°ç»„ç¤ºä¾‹**ï¼š

```lua
function f()
    local a = 1  -- actvar[0] = 0ï¼ˆlocvars ç´¢å¼•ï¼‰
    local b = 2  -- actvar[1] = 1
    do
        local c = 3  -- actvar[2] = 2
    end
    -- c ç¦»å¼€ä½œç”¨åŸŸï¼Œnactvar = 2
    local d = 4  -- actvar[2] = 3ï¼ˆå¤ç”¨ç´¢å¼• 2ï¼‰
end
```

### BlockCntï¼šå—è®¡æ•°å™¨

```c
typedef struct BlockCnt {
    struct BlockCnt *previous;  // å¤–å±‚å—
    int breaklist;              // break è·³è½¬é“¾è¡¨
    lu_byte nactvar;            // å—å¼€å§‹æ—¶çš„æ´»åŠ¨å˜é‡æ•°
    lu_byte upval;              // æ˜¯å¦æœ‰ upvalue
    lu_byte isbreakable;        // æ˜¯å¦å¯ break
} BlockCnt;
```

**å—é“¾ç¤ºä¾‹**ï¼š

```lua
function f()
    -- bl = NULL
    do
        -- bl = {previous=NULL, nactvar=0, upval=0}
        while condition do
            -- bl = {previous=&outer_bl, nactvar=0, upval=0, isbreakable=1}
            local x = 1
            -- nactvar = 1
        end
    end
end
```

### Protoï¼šå‡½æ•°åŸå‹

```c
typedef struct Proto {
    CommonHeader;
    TValue *k;                // å¸¸é‡æ•°ç»„
    Instruction *code;        // å­—èŠ‚ç æ•°ç»„
    struct Proto **p;         // å­å‡½æ•°åŸå‹æ•°ç»„
    int *lineinfo;            // è°ƒè¯•ï¼šè¡Œå·ä¿¡æ¯
    struct LocVar *locvars;   // è°ƒè¯•ï¼šå±€éƒ¨å˜é‡ä¿¡æ¯
    TString **upvalues;       // upvalue åå­—æ•°ç»„
    TString *source;          // æºæ–‡ä»¶å
    int sizeupvalues;
    int sizek;
    int sizecode;
    int sizelineinfo;
    int sizep;
    int sizelocvars;
    int linedefined;
    int lastlinedefined;
    GCObject *gclist;
    lu_byte nups;             // upvalue æ•°é‡
    lu_byte numparams;        // å‚æ•°æ•°é‡
    lu_byte is_vararg;
    lu_byte maxstacksize;
} Proto;
```

**é‡è¦å­—æ®µ**ï¼š

| å­—æ®µ | è¯´æ˜ |
|------|------|
| `nups` | upvalue æ•°é‡ |
| `upvalues[]` | upvalue åå­—ï¼ˆè°ƒè¯•ç”¨ï¼‰ |
| `locvars[]` | å±€éƒ¨å˜é‡ä¿¡æ¯ï¼ˆè°ƒè¯•ç”¨ï¼‰ |
| `p[]` | å­å‡½æ•°åŸå‹ï¼ˆåµŒå¥—å‡½æ•°ï¼‰ |

### UpValï¼šè¿è¡Œæ—¶ Upvalue

```c
typedef struct UpVal {
    CommonHeader;
    TValue *v;          // æŒ‡å‘å€¼
    union {
        TValue value;   // closed çŠ¶æ€å­˜å‚¨
        struct {        // open çŠ¶æ€é“¾è¡¨
            struct UpVal *prev;
            struct UpVal *next;
        } l;
    } u;
} UpVal;
```

**çŠ¶æ€è½¬æ¢**ï¼š

```
åˆ›å»º:
â”Œâ”€â”€â”€â”€â”€â”€â”€â”€â”€â”€â”
â”‚ UpVal    â”‚ (open)
â”‚ v â”€â”€â”€â”€â”€â”€â”€â”¼â”€â”€â†’ æ ˆä¸Šå˜é‡ R(n)
â”‚ u.l.next â”‚
â””â”€â”€â”€â”€â”€â”€â”€â”€â”€â”€â”˜

å…³é—­ (OP_CLOSE):
â”Œâ”€â”€â”€â”€â”€â”€â”€â”€â”€â”€â”
â”‚ UpVal    â”‚ (closed)
â”‚ v â”€â”€â”€â”€â”€â”€â”€â”¼â”€â”€â†’ u.value
â”‚ u.value  â”‚ = <å¤åˆ¶çš„å€¼>
â””â”€â”€â”€â”€â”€â”€â”€â”€â”€â”€â”˜
```

### LClosureï¼šLua é—­åŒ…

```c
typedef struct LClosure {
    ClosureHeader;
    struct Proto *p;
    UpVal *upvals[1];  // å¯å˜é•¿åº¦æ•°ç»„
} LClosure;

#define ClosureHeader \
    CommonHeader; lu_byte isC; lu_byte nupvalues; GCObject *gclist; \
    struct Table *env
```

**å†…å­˜å¸ƒå±€**ï¼š

```
å‡è®¾é—­åŒ…æœ‰ 3 ä¸ª upvalue:
â”Œâ”€â”€â”€â”€â”€â”€â”€â”€â”€â”€â”€â”€â”€â”€â”€â”€â”€â”€â”€â”€â”€â”€â”€â”€â”€â”
â”‚ CommonHeader            â”‚
â”‚ isC = 0                 â”‚
â”‚ nupvalues = 3           â”‚
â”‚ gclist                  â”‚
â”‚ env                     â”‚
â”‚ p â”€â”€â”€â”€â”€â”€â”€â”€â”€â”€â”€â”€â”€â”€â”€â”€â”€â”    â”‚
â”‚ upvals[0] â”€â”€â”€â”€â”€â”€â”€â”€â”€â”¼â”€â”  â”‚
â”‚ upvals[1] â”€â”€â”€â”€â”€â”€â”€â”€â”€â”¼â”€â”¼â”€â”â”‚
â”‚ upvals[2] â”€â”€â”€â”€â”€â”€â”€â”€â”€â”¼â”€â”¼â”€â”¼â”¤
â””â”€â”€â”€â”€â”€â”€â”€â”€â”€â”€â”€â”€â”€â”€â”€â”€â”€â”€â”€â”€â”¼â”€â”¼â”€â”¼â”˜
                     â”‚ â”‚ â”‚
                     â”‚ â”‚ â””â”€â”€â†’ UpVal
                     â”‚ â””â”€â”€â”€â”€â†’ UpVal
                     â””â”€â”€â”€â”€â”€â”€â†’ UpVal
```

---

## ğŸ“ˆ ä»£ç ç”Ÿæˆä¸æ€§èƒ½åˆ†æ

### å®Œæ•´é—­åŒ…ç¤ºä¾‹çš„å­—èŠ‚ç 

**Lua ä»£ç **ï¼š

```lua
function outer(x)
    local y = x * 2
    
    local function middle(z)
        local w = y + z
        
        local function inner(a)
            return x + y + w + a
        end
        
        return inner
    end
    
    return middle
end

local f = outer(10)
local g = f(5)
print(g(1))  -- 10 + 20 + 25 + 1 = 56
```

**å­—èŠ‚ç åˆ†æ**ï¼š

```
function <outer> (1 param, 3 slots, 1 upvalue, 2 locals, 2 constants, 1 function)
[1] MUL        R1 R0 K0     ; y = x * 2, K0 = 2
[2] CLOSURE    R2 <middle>
[3] MOVE       0  R0         ; middle.upvalues[0] = x
[4] MOVE       0  R1         ; middle.upvalues[1] = y
[5] RETURN     R2 2
[6] RETURN     R0 1

function <middle> (1 param, 3 slots, 2 upvalues, 2 locals, 0 constants, 1 function)
[1] GETUPVAL   R1 U1        ; y
[2] ADD        R1 R1 R0     ; w = y + z
[3] CLOSURE    R2 <inner>
[4] GETUPVAL   0  U0         ; inner.upvalues[0] = x (from outer upvalue)
[5] GETUPVAL   0  U1         ; inner.upvalues[1] = y (from outer upvalue)
[6] MOVE       0  R1         ; inner.upvalues[2] = w (from local)
[7] RETURN     R2 2
[8] RETURN     R0 1

function <inner> (1 param, 2 slots, 3 upvalues, 1 local, 0 constants, 0 functions)
[1] GETUPVAL   R1 U0        ; x
[2] GETUPVAL   R2 U1        ; y
[3] ADD        R1 R1 R2     ; x + y
[4] GETUPVAL   R2 U2        ; w
[5] ADD        R1 R1 R2     ; (x + y) + w
[6] ADD        R1 R1 R0     ; ((x + y) + w) + a
[7] RETURN     R1 2
[8] RETURN     R0 1
```

**Upvalue ç»§æ‰¿é“¾**ï¼š

```
outer:
  å±€éƒ¨å˜é‡: x, y

middle:
  upvalues[0] = x (VLOCAL from outer)
  upvalues[1] = y (VLOCAL from outer)
  å±€éƒ¨å˜é‡: z, w

inner:
  upvalues[0] = x (VUPVAL from middle.upvalues[0])
  upvalues[1] = y (VUPVAL from middle.upvalues[1])
  upvalues[2] = w (VLOCAL from middle)
  å±€éƒ¨å˜é‡: a
```

### æ€§èƒ½åˆ†æ

**1. å±€éƒ¨å˜é‡è®¿é—®ï¼ˆæœ€å¿«ï¼‰**ï¼š

```lua
local x = 1
local y = x + 1  -- ç›´æ¥å¯„å­˜å™¨æ“ä½œ
```

```
LOADK R0 K0
ADD   R1 R0 K1
```

**æ€§èƒ½**ï¼šO(1)ï¼Œå•å‘¨æœŸæŒ‡ä»¤

**2. Upvalue è®¿é—®ï¼ˆå¿«ï¼‰**ï¼š

```lua
function f()
    local x = 1
    return function()
        return x  -- upvalue è®¿é—®
    end
end
```

```
GETUPVAL R0 U0
```

**æ€§èƒ½**ï¼šO(1)ï¼Œä½†æ¯”å±€éƒ¨å˜é‡æ…¢ï¼ˆéœ€è¦é—´æ¥å¯»å€ï¼‰

**3. å…¨å±€å˜é‡è®¿é—®ï¼ˆæ…¢ï¼‰**ï¼š

```lua
function f()
    return math.sin(x)  -- å…¨å±€å˜é‡
end
```

```
GETGLOBAL R0 'math'
GETTABLE  R0 R0 K0   ; K0 = "sin"
GETGLOBAL R1 'x'
CALL      R0 2 2
```

**æ€§èƒ½**ï¼šO(log n) æˆ– O(1)ï¼ˆå“ˆå¸Œè¡¨æŸ¥æ‰¾ï¼‰ï¼Œæ¯” upvalue æ…¢ 3-5 å€

**æ€§èƒ½å¯¹æ¯”è¡¨**ï¼š

| è®¿é—®ç±»å‹ | æŒ‡ä»¤ | æ—¶é—´å¤æ‚åº¦ | ç›¸å¯¹é€Ÿåº¦ |
|---------|------|-----------|---------|
| å±€éƒ¨å˜é‡ | MOVE | O(1) | 1xï¼ˆåŸºå‡†ï¼‰ |
| Upvalue | GETUPVAL | O(1) | ~1.5x |
| å…¨å±€å˜é‡ | GETGLOBAL | O(1) æˆ– O(log n) | ~3-5x |

### ä¼˜åŒ–å»ºè®®

**1. å±€éƒ¨åŒ–é¢‘ç¹è®¿é—®çš„å…¨å±€å˜é‡**ï¼š

```lua
-- æ…¢
for i = 1, 1000000 do
    local x = math.sin(i)
end

-- å¿«ï¼ˆçº¦ 2-3 å€ï¼‰
local sin = math.sin
for i = 1, 1000000 do
    local x = sin(i)
end
```

**2. é¿å…ä¸å¿…è¦çš„é—­åŒ…**ï¼š

```lua
-- æ…¢ï¼ˆæ¯æ¬¡è°ƒç”¨åˆ›å»ºæ–°é—­åŒ…ï¼‰
function f()
    return function() return 1 end
end

-- å¿«ï¼ˆé—­åŒ…å…±äº«ï¼‰
local function helper() return 1 end
function f()
    return helper
end
```

**3. æœ€å°åŒ– upvalue æ•°é‡**ï¼š

```lua
-- æ…¢ï¼ˆ4 ä¸ª upvalueï¼‰
function outer()
    local a, b, c, d = 1, 2, 3, 4
    return function()
        return a + b + c + d
    end
end

-- å¿«ï¼ˆ1 ä¸ª upvalueï¼‰
function outer()
    local sum = 1 + 2 + 3 + 4
    return function()
        return sum
    end
end
```

### å†…å­˜å¼€é”€

**é—­åŒ…å¯¹è±¡å¤§å°**ï¼š

```c
sizeof(LClosure) = sizeof(ClosureHeader) + sizeof(Proto*) + n * sizeof(UpVal*)
                 â‰ˆ 32 + 8 + n * 8  ï¼ˆ64ä½ç³»ç»Ÿï¼‰
```

**ç¤ºä¾‹**ï¼š
- 0 ä¸ª upvalueï¼š~40 å­—èŠ‚
- 3 ä¸ª upvalueï¼š~64 å­—èŠ‚
- 10 ä¸ª upvalueï¼š~112 å­—èŠ‚

**Upvalue å¯¹è±¡å¤§å°**ï¼š

```c
sizeof(UpVal) = sizeof(CommonHeader) + sizeof(TValue*) + sizeof(union)
              â‰ˆ 8 + 8 + 16 = 32 å­—èŠ‚
```

---

## ğŸ› ï¸ è°ƒè¯•ä¸å®è·µæŒ‡å—

### GDB è°ƒè¯• Upvalue

```bash
$ gdb ./lua
(gdb) break luaF_newLclosure
(gdb) run test.lua
```

**æŸ¥çœ‹é—­åŒ…ä¿¡æ¯**ï¼š

```gdb
# é—­åŒ…å¯¹è±¡
(gdb) print *(LClosure*)cl
$1 = {
  isC = 0,
  nupvalues = 2,
  p = 0x...,
  upvals = {0x..., 0x...}
}

# ç¬¬ä¸€ä¸ª upvalue
(gdb) print *(UpVal*)cl->upvals[0]
$2 = {
  v = 0x...,  # æŒ‡å‘çš„å€¼
  u = {
    value = {...},
    l = {prev = 0x..., next = 0x...}
  }
}

# æŸ¥çœ‹ upvalue çš„å€¼
(gdb) print *(TValue*)cl->upvals[0]->v
$3 = {value = {n = 42}, tt = 3}  # LUA_TNUMBER
```

**è·Ÿè¸ª upvalue å…³é—­**ï¼š

```gdb
(gdb) break luaF_close
(gdb) continue

# æŸ¥çœ‹è¦å…³é—­çš„ upvalue
(gdb) print level  # æ ˆçº§åˆ«
(gdb) print L->openupval  # open upvalue é“¾è¡¨

# å•æ­¥æ‰§è¡Œå…³é—­è¿‡ç¨‹
(gdb) next
```

### å¯è§†åŒ–ä½œç”¨åŸŸé“¾

**è¾…åŠ©å‡½æ•°**ï¼š

```lua
-- debug_scopes.lua
function print_scopes()
    local level = 1
    print("=== Scope Chain ===")
    
    while true do
        local info = debug.getinfo(level, "nSlu")
        if not info then break end
        
        print(string.format("Level %d: %s (%s:%d)",
            level, info.name or "<main>", info.short_src, info.currentline))
        
        -- æ‰“å°å±€éƒ¨å˜é‡
        local i = 1
        while true do
            local name, value = debug.getlocal(level, i)
            if not name then break end
            if not string.match(name, "^%(") then  -- è·³è¿‡å†…éƒ¨å˜é‡
                print(string.format("  local %s = %s", name, tostring(value)))
            end
            i = i + 1
        end
        
        -- æ‰“å° upvalue
        if info.func then
            local i = 1
            while true do
                local name, value = debug.getupvalue(info.func, i)
                if not name then break end
                print(string.format("  upvalue %s = %s", name, tostring(value)))
                i = i + 1
            end
        end
        
        level = level + 1
    end
end

-- ä½¿ç”¨ç¤ºä¾‹
function outer()
    local x = 1
    
    function middle()
        local y = 2
        
        function inner()
            local z = 3
            print_scopes()
        end
        
        return inner
    end
    
    return middle
end

outer()()()
```

**è¾“å‡º**ï¼š

```
=== Scope Chain ===
Level 1: inner (test.lua:10)
  local z = 3
  upvalue y = 2
  upvalue x = 1
Level 2: middle (test.lua:6)
  local y = 2
  upvalue x = 1
Level 3: outer (test.lua:2)
  local x = 1
Level 4: <main> (test.lua:1)
```

### å¸¸è§é™·é˜±

**é™·é˜± 1ï¼šå¾ªç¯å˜é‡é—­åŒ…**

```lua
-- âŒ é”™è¯¯
local funcs = {}
for i = 1, 3 do
    funcs[i] = function() return i end
end
print(funcs[1]())  -- 4ï¼ˆä¸æ˜¯ 1ï¼‰

-- âœ“ æ­£ç¡®
local funcs = {}
for i = 1, 3 do
    local j = i
    funcs[i] = function() return j end
end
print(funcs[1]())  -- 1
```

**é™·é˜± 2ï¼šä¿®æ”¹ upvalue**

```lua
function make_getter_setter()
    local value = 0
    
    local function get()
        return value
    end
    
    local function set(v)
        value = v  -- ä¿®æ”¹å…±äº«çš„ upvalue
    end
    
    return get, set
end

local get, set = make_getter_setter()
print(get())  -- 0
set(42)
print(get())  -- 42ï¼ˆupvalue æ˜¯å¯å˜çš„ï¼‰
```

**é™·é˜± 3ï¼šUpvalue ç”Ÿå‘½å‘¨æœŸ**

```lua
-- âŒ å±é™©
local funcs = {}

do
    local x = 1
    funcs[1] = function() return x end
end  -- x çš„ upvalue åœ¨è¿™é‡Œå…³é—­

print(funcs[1]())  -- 1ï¼ˆä»ç„¶æœ‰æ•ˆï¼Œå› ä¸º upvalue å·²å…³é—­ï¼‰
```

### æœ€ä½³å®è·µ

**1. æ˜ç¡®é—­åŒ…æ„å›¾**ï¼š

```lua
-- å¥½ï¼šæ¸…æ™°çš„é—­åŒ…
function make_multiplier(factor)
    return function(x)
        return x * factor
    end
end

-- å·®ï¼šä¸å¿…è¦çš„é—­åŒ…
function make_multiplier(factor)
    local function multiply(x)
        return x * factor
    end
    return multiply  -- ä¸ºä»€ä¹ˆä¸ç›´æ¥è¿”å›ï¼Ÿ
end
```

**2. é¿å…è¿‡åº¦é—­åŒ…**ï¼š

```lua
-- å·®ï¼šæ¯æ¬¡è°ƒç”¨åˆ›å»ºæ–°é—­åŒ…
function process(list)
    return table.map(list, function(x) return x * 2 end)
end

-- å¥½ï¼šå¤ç”¨é—­åŒ…
local function double(x) return x * 2 end
function process(list)
    return table.map(list, double)
end
```

**3. æ–‡æ¡£åŒ– upvalue**ï¼š

```lua
function make_counter()
    local count = 0  -- upvalue: è®¡æ•°å™¨çŠ¶æ€
    
    --- å¢åŠ è®¡æ•°å™¨
    -- @return æ–°çš„è®¡æ•°å€¼
    local function inc()
        count = count + 1
        return count
    end
    
    return inc
end
```

### æ€§èƒ½æµ‹è¯•

```lua
-- benchmark.lua
local function benchmark(name, f, iterations)
    local start = os.clock()
    for i = 1, iterations do
        f()
    end
    local elapsed = os.clock() - start
    print(string.format("%s: %.3f seconds", name, elapsed))
end

local N = 10000000

-- æµ‹è¯• 1ï¼šå±€éƒ¨å˜é‡
benchmark("Local variable", function()
    local x = 1
    local y = x + 1
end, N)

-- æµ‹è¯• 2ï¼šUpvalue
local x = 1
benchmark("Upvalue", function()
    local y = x + 1
end, N)

-- æµ‹è¯• 3ï¼šå…¨å±€å˜é‡
_G.x = 1
benchmark("Global variable", function()
    local y = x + 1
end, N)
```

**å…¸å‹ç»“æœ**ï¼š

```
Local variable: 0.150 seconds
Upvalue: 0.230 seconds (1.5x slower)
Global variable: 0.680 seconds (4.5x slower)
```

---

## ğŸ”— ç›¸å…³æ–‡æ¡£

- [é€’å½’ä¸‹é™è§£æ](recursive_descent.md) - è§£æç®—æ³•åŸºç¡€
- [è¡¨è¾¾å¼è§£æ](expression_parsing.md) - è¡¨è¾¾å¼å¤„ç†
- [è¯­å¥è§£æ](statement_parsing.md) - è¯­å¥è§£æç»†èŠ‚
- [ä»£ç ç”Ÿæˆä¸ä¼˜åŒ–](code_generation.md) - å­—èŠ‚ç ç”Ÿæˆ
- [è™šæ‹Ÿæœºæ‰§è¡Œ](../vm/wiki_vm.md) - è¿è¡Œæ—¶æ‰§è¡Œ
- [åƒåœ¾å›æ”¶](../gc/wiki_gc.md) - Upvalue GC ç®¡ç†

---

*è¿”å›ï¼š[è§£æå™¨æ¨¡å—æ€»è§ˆ](wiki_parser.md)*
