# ğŸ“ è¯­å¥è§£æå®ç°ç»†èŠ‚

> **æŠ€æœ¯æ·±åº¦**ï¼šâ­â­â­â­  
> **é¢„è®¡é˜…è¯»æ—¶é—´**ï¼š30åˆ†é’Ÿ  
> **å‰ç½®çŸ¥è¯†**ï¼š[é€’å½’ä¸‹é™è§£æ](recursive_descent.md)ã€[è¡¨è¾¾å¼è§£æ](expression_parsing.md)

---

## ğŸ“‹ ç›®å½•

- [æ¦‚è¿°](#æ¦‚è¿°)
- [èµ‹å€¼è¯­å¥è§£æ](#èµ‹å€¼è¯­å¥è§£æ)
- [æ§åˆ¶æµè¯­å¥è§£æ](#æ§åˆ¶æµè¯­å¥è§£æ)
- [å‡½æ•°ç›¸å…³è¯­å¥](#å‡½æ•°ç›¸å…³è¯­å¥)
- [å—å’Œä½œç”¨åŸŸç®¡ç†](#å—å’Œä½œç”¨åŸŸç®¡ç†)
- [ç‰¹æ®Šè¯­å¥å¤„ç†](#ç‰¹æ®Šè¯­å¥å¤„ç†)
- [ä»£ç ç”Ÿæˆç¤ºä¾‹](#ä»£ç ç”Ÿæˆç¤ºä¾‹)
- [æ€§èƒ½ä¼˜åŒ–æŠ€å·§](#æ€§èƒ½ä¼˜åŒ–æŠ€å·§)
- [è°ƒè¯•ä¸å®è·µæŒ‡å—](#è°ƒè¯•ä¸å®è·µæŒ‡å—)

---

## ğŸ¯ æ¦‚è¿°

è¯­å¥è§£ææ˜¯ Lua ç¼–è¯‘å™¨çš„æ ¸å¿ƒéƒ¨åˆ†ï¼Œè´Ÿè´£å°†æºä»£ç ä¸­çš„å„ç§è¯­å¥è½¬æ¢ä¸ºå­—èŠ‚ç æŒ‡ä»¤ã€‚Lua æ”¯æŒä¸°å¯Œçš„è¯­å¥ç±»å‹ï¼Œæ¯ç§è¯­å¥éƒ½æœ‰å…¶ç‰¹å®šçš„è§£æé€»è¾‘å’Œä»£ç ç”Ÿæˆç­–ç•¥ã€‚

### Lua è¯­å¥åˆ†ç±»

Lua 5.1.5 æ”¯æŒä»¥ä¸‹è¯­å¥ç±»å‹ï¼š

```lua
-- 1. èµ‹å€¼è¯­å¥
local x = 10
a, b, c = 1, 2, 3
t.field = value

-- 2. æ§åˆ¶æµè¯­å¥
if condition then ... end
while condition do ... end
repeat ... until condition
for i = 1, 10 do ... end
for k, v in pairs(t) do ... end

-- 3. å‡½æ•°ç›¸å…³
function f(x) ... end
local function f(x) ... end
return x, y, z

-- 4. å—ç»“æ„
do ... end
break

-- 5. å…¶ä»–
; -- ç©ºè¯­å¥
func_call(args) -- å‡½æ•°è°ƒç”¨è¯­å¥
```

### è¯­å¥è§£ææ¶æ„

```mermaid
graph TD
    A[chunk] --> B[block]
    B --> C[statement]
    C --> D{è¯­å¥ç±»å‹}
    D --> E[ifstat]
    D --> F[whilestat]
    D --> G[forstat]
    D --> H[assignment]
    D --> I[funcstat]
    D --> J[localstat]
    D --> K[retstat]
    D --> L[breakstat]
    D --> M[exprstat]
    E --> N[ç”Ÿæˆå­—èŠ‚ç ]
    F --> N
    G --> N
    H --> N
    I --> N
    J --> N
    K --> N
    L --> N
    M --> N
```

### è§£æå…¥å£ï¼šstatement å‡½æ•°

```c
// æ¥è‡ª lparser.c
static void statement(LexState *ls) {
    int line = ls->linenumber;  // ä¿å­˜è¡Œå·ç”¨äºè°ƒè¯•ä¿¡æ¯
    
    switch (ls->t.token) {
        case TK_IF: {      // if ... then ... end
            ifstat(ls, line);
            return;
        }
        case TK_WHILE: {   // while ... do ... end
            whilestat(ls, line);
            return;
        }
        case TK_DO: {      // do ... end
            next(ls);
            block(ls);
            check_match(ls, TK_END, TK_DO, line);
            return;
        }
        case TK_FOR: {     // for ... do ... end
            forstat(ls, line);
            return;
        }
        case TK_REPEAT: {  // repeat ... until ...
            repeatstat(ls, line);
            return;
        }
        case TK_FUNCTION: {
            funcstat(ls, line);
            return;
        }
        case TK_LOCAL: {   // local ...
            next(ls);
            if (testnext(ls, TK_FUNCTION))  // local function
                localfunc(ls);
            else
                localstat(ls);
            return;
        }
        case TK_RETURN: {  // return ...
            retstat(ls);
            return;
        }
        case TK_BREAK: {   // break
            next(ls);
            breakstat(ls);
            return;
        }
        default: {
            exprstat(ls);  // èµ‹å€¼æˆ–å‡½æ•°è°ƒç”¨
            return;
        }
    }
}
```

### è¯­å¥ç±»å‹è¯¦è§£

| è¯­å¥ç±»å‹ | Token | è§£æå‡½æ•° | éš¾åº¦ | è¯´æ˜ |
|---------|-------|---------|------|------|
| **if è¯­å¥** | `TK_IF` | `ifstat()` | â­â­â­â­ | æ¡ä»¶åˆ†æ”¯ï¼Œéœ€å¤„ç†è·³è½¬é“¾è¡¨ |
| **while å¾ªç¯** | `TK_WHILE` | `whilestat()` | â­â­â­ | å¾ªç¯ç»“æ„ï¼Œéœ€å¤„ç† break |
| **repeat å¾ªç¯** | `TK_REPEAT` | `repeatstat()` | â­â­â­ | åæµ‹è¯•å¾ªç¯ |
| **for æ•°å€¼å‹** | `TK_FOR` | `fornum()` | â­â­â­â­ | æ•°å€¼å¾ªç¯ä¼˜åŒ– |
| **for æ³›å‹** | `TK_FOR` | `forlist()` | â­â­â­â­â­ | è¿­ä»£å™¨å¾ªç¯ |
| **å‡½æ•°å®šä¹‰** | `TK_FUNCTION` | `funcstat()` | â­â­â­â­â­ | å‡½æ•°ä½œç”¨åŸŸå’Œé—­åŒ… |
| **å±€éƒ¨å˜é‡** | `TK_LOCAL` | `localstat()` | â­â­â­ | ä½œç”¨åŸŸç®¡ç† |
| **return** | `TK_RETURN` | `retstat()` | â­â­â­ | å‡½æ•°è¿”å› |
| **break** | `TK_BREAK` | `breakstat()` | â­â­ | å¾ªç¯è·³å‡º |
| **èµ‹å€¼** | - | `assignment()` | â­â­â­â­ | å·¦å€¼è§£æï¼Œå¤šé‡èµ‹å€¼ |
| **å‡½æ•°è°ƒç”¨** | - | `exprstat()` | â­â­ | è¡¨è¾¾å¼è¯­å¥ |
| **do å—** | `TK_DO` | `block()` | â­â­ | ä½œç”¨åŸŸå— |

### block å’Œ chunk çš„å…³ç³»

```c
// chunk = æ–‡ä»¶é¡¶å±‚
static void chunk(LexState *ls) {
    block(ls);
}

// block = è¯­å¥åºåˆ— + ä½œç”¨åŸŸ
static void block(LexState *ls) {
    FuncState *fs = ls->fs;
    BlockCnt bl;
    
    enterblock(fs, &bl, 0);  // è¿›å…¥æ–°ä½œç”¨åŸŸ
    
    // è§£ææ‰€æœ‰è¯­å¥
    while (!block_follow(ls->t.token)) {
        statement(ls);
        testnext(ls, ';');  // å¯é€‰çš„åˆ†å·
    }
    
    leaveblock(fs);  // ç¦»å¼€ä½œç”¨åŸŸ
}

// å—ç»“æŸæ ‡å¿—
static int block_follow(int token) {
    switch (token) {
        case TK_ELSE: case TK_ELSEIF: case TK_END:
        case TK_UNTIL: case TK_EOS:
            return 1;
        default: return 0;
    }
}
```

### è¯­å¥è§£æçš„å…³é”®æ•°æ®ç»“æ„

**BlockCnt - å—æ§åˆ¶ç»“æ„**ï¼š

```c
typedef struct BlockCnt {
    struct BlockCnt *previous;  // å¤–å±‚å—
    int breaklist;              // break è¯­å¥è·³è½¬é“¾è¡¨
    lu_byte nactvar;            // å—å†…æ´»åŠ¨å±€éƒ¨å˜é‡æ•°
    lu_byte upval;              // å—å†…æ˜¯å¦æœ‰ upvalue
    lu_byte isbreakable;        // æ˜¯å¦å¯ä»¥ä½¿ç”¨ break
} BlockCnt;
```

**expdesc - è¡¨è¾¾å¼æè¿°ç¬¦**ï¼ˆç”¨äºå·¦å€¼å’Œå³å€¼ï¼‰ï¼š

```c
typedef struct expdesc {
    expkind k;              // è¡¨è¾¾å¼ç±»å‹
    union {
        struct { int info; int aux; } s;
        lua_Number nval;    // æ•°å­—å­—é¢é‡
    } u;
    int t;                  // true è·³è½¬é“¾è¡¨
    int f;                  // false è·³è½¬é“¾è¡¨
} expdesc;
```

### æ ¸å¿ƒæ¦‚å¿µï¼šè·³è½¬é“¾è¡¨

Lua ä½¿ç”¨**è·³è½¬é“¾è¡¨**ï¼ˆJump Listï¼‰å»¶è¿Ÿä¿®æ­£è·³è½¬ç›®æ ‡åœ°å€ï¼š

```c
// è·³è½¬æŒ‡ä»¤åˆå§‹æ—¶ç›®æ ‡åœ°å€æœªçŸ¥
JMP pc -> ???

// åç»­ä¿®æ­£ä¸ºå®é™…åœ°å€
JMP pc -> target_pc
```

**å·¥ä½œæµç¨‹**ï¼š

```mermaid
graph LR
    A[ç”Ÿæˆè·³è½¬æŒ‡ä»¤] --> B[è®°å½•PCåˆ°é“¾è¡¨]
    B --> C[ç»§ç»­è§£æ]
    C --> D[ç¡®å®šç›®æ ‡åœ°å€]
    D --> E[ä¿®æ­£æ‰€æœ‰é“¾è¡¨ä¸­çš„è·³è½¬]
```

**å…³é”®å‡½æ•°**ï¼š

```c
// ç”Ÿæˆè·³è½¬æŒ‡ä»¤å¹¶è¿”å›å…¶ PC
int luaK_jump(FuncState *fs);

// å°†è·³è½¬é“¾è¡¨ list ä¸­çš„æ‰€æœ‰è·³è½¬ä¿®æ­£åˆ° target
void luaK_patchlist(FuncState *fs, int list, int target);

// åˆå¹¶ä¸¤ä¸ªè·³è½¬é“¾è¡¨
void luaK_concat(FuncState *fs, int *l1, int l2);

// ä¿®æ­£è·³è½¬åˆ°å½“å‰ PC
void luaK_patchtohere(FuncState *fs, int list);
```

### è¯­å¥è§£æçš„é€šç”¨æµç¨‹

```
1. è¯†åˆ«è¯­å¥ç±»å‹ï¼ˆé€šè¿‡å½“å‰ Tokenï¼‰
2. æ£€æŸ¥è¯­æ³•ï¼ˆexpectã€check_match ç­‰ï¼‰
3. ç®¡ç†ä½œç”¨åŸŸï¼ˆenterblock/leaveblockï¼‰
4. è§£æå­è¡¨è¾¾å¼å’Œå­è¯­å¥
5. ç”Ÿæˆå­—èŠ‚ç æŒ‡ä»¤
6. ä¿®æ­£è·³è½¬åœ°å€ï¼ˆå¦‚æœ‰ï¼‰
7. æ›´æ–°è°ƒè¯•ä¿¡æ¯
```

---

## ğŸ’¾ èµ‹å€¼è¯­å¥è§£æ

èµ‹å€¼è¯­å¥æ˜¯ Lua ä¸­æœ€å¸¸è§çš„è¯­å¥ä¹‹ä¸€ï¼Œæ”¯æŒå¤šé‡èµ‹å€¼ã€è¡¨ç´¢å¼•èµ‹å€¼ç­‰å¤æ‚å½¢å¼ã€‚

### è¯­æ³•è§„åˆ™

```lua
-- ç®€å•èµ‹å€¼
x = 1

-- å¤šé‡èµ‹å€¼
a, b, c = 1, 2, 3

-- è¡¨ç´¢å¼•èµ‹å€¼
t[k] = v
t.field = value

-- å±€éƒ¨å˜é‡èµ‹å€¼
local x = 1
local a, b = 1, 2

-- æ··åˆèµ‹å€¼
local x, t[k], y = f(), g(), h()
```

### exprstat å‡½æ•°ï¼šèµ‹å€¼æˆ–å‡½æ•°è°ƒç”¨

```c
static void exprstat(LexState *ls) {
    FuncState *fs = ls->fs;
    struct LHS_assign v;
    
    primaryexp(ls, &v.v);  // è§£æç¬¬ä¸€ä¸ªè¡¨è¾¾å¼
    
    if (v.v.k == VCALL) {  // å‡½æ•°è°ƒç”¨è¯­å¥
        SETARG_C(getcode(fs, &v.v), 1);  // è°ƒæ•´è¿”å›å€¼æ•°é‡
    }
    else {  // èµ‹å€¼è¯­å¥
        v.prev = NULL;
        assignment(ls, &v, 1);
    }
}
```

### assignment å‡½æ•°ï¼šå¤šé‡èµ‹å€¼æ ¸å¿ƒ

```c
static void assignment(LexState *ls, struct LHS_assign *lh, int nvars) {
    expdesc e;
    
    check_condition(ls, VLOCAL <= lh->v.k && lh->v.k <= VINDEXED,
                    "syntax error");
    
    if (testnext(ls, ',')) {  // è¿˜æœ‰æ›´å¤šå·¦å€¼
        struct LHS_assign nv;
        nv.prev = lh;
        primaryexp(ls, &nv.v);
        
        if (nv.v.k == VLOCAL)
            check_conflict(ls, lh, &nv.v);
        
        assignment(ls, &nv, nvars + 1);
    }
    else {  // æ²¡æœ‰æ›´å¤šå·¦å€¼ï¼Œå¼€å§‹è§£æå³å€¼
        int nexps;
        checknext(ls, '=');
        nexps = explist1(ls, &e);
        
        if (nexps != nvars) {
            adjust_assign(ls, nvars, nexps, &e);
            if (nexps > nvars)
                ls->fs->freereg -= nexps - nvars;  // ç§»é™¤å¤šä½™å€¼
        }
        else {
            luaK_setoneret(ls->fs, &e);  // å…³é—­å¤šè¿”å›å€¼
            luaK_storevar(ls->fs, &lh->v, &e);
            return;  // é¿å…é»˜è®¤èµ‹å€¼
        }
    }
    
    init_exp(&e, VNONRELOC, ls->fs->freereg - 1);  // é»˜è®¤èµ‹å€¼
    luaK_storevar(ls->fs, &lh->v, &e);
}
```

### LHS_assign ç»“æ„ï¼šå·¦å€¼é“¾è¡¨

```c
struct LHS_assign {
    struct LHS_assign *prev;  // å‰ä¸€ä¸ªå·¦å€¼
    expdesc v;                // å½“å‰å·¦å€¼è¡¨è¾¾å¼
};
```

**ç¤ºä¾‹ï¼šè§£æ `a, b, c = 1, 2, 3`**

```
è°ƒç”¨æ ˆï¼š
assignment(lh={v=a, prev=NULL}, nvars=1)
  -> testnext(',') = true
  -> assignment(lh={v=b, prev=&{v=a}}, nvars=2)
    -> testnext(',') = true
    -> assignment(lh={v=c, prev=&{v=b, prev=&{v=a}}}, nvars=3)
      -> testnext(',') = false
      -> checknext('=')
      -> explist1() è§£æ 1, 2, 3ï¼Œè¿”å› nexps=3
      -> adjust_assign(nvars=3, nexps=3, ...)
      -> ç”Ÿæˆèµ‹å€¼ä»£ç ï¼š
         c = 3
         b = 2
         a = 1
```

### å·¦å€¼è§£æï¼šprimaryexp å’Œ suffixedexp

```c
static void primaryexp(LexState *ls, expdesc *v) {
    switch (ls->t.token) {
        case '(': {
            int line = ls->linenumber;
            next(ls);
            expr(ls, v);
            check_match(ls, ')', '(', line);
            luaK_dischargevars(ls->fs, v);
            return;
        }
        case TK_NAME: {
            singlevar(ls, v);
            return;
        }
        default: {
            luaX_syntaxerror(ls, "unexpected symbol");
            return;
        }
    }
}

static void suffixedexp(LexState *ls, expdesc *v) {
    FuncState *fs = ls->fs;
    int line = ls->linenumber;
    
    primaryexp(ls, v);
    
    for (;;) {
        switch (ls->t.token) {
            case '.': {  // t.field
                fieldsel(ls, v);
                break;
            }
            case '[': {  // t[exp]
                expdesc key;
                luaK_exp2anyreg(fs, v);
                yindex(ls, &key);
                luaK_indexed(fs, v, &key);
                break;
            }
            case ':': {  // t:method(args)
                expdesc key;
                next(ls);
                checkname(ls, &key);
                luaK_self(fs, v, &key);
                funcargs(ls, v);
                break;
            }
            case '(': case TK_STRING: case '{': {  // å‡½æ•°è°ƒç”¨
                luaK_exp2nextreg(fs, v);
                funcargs(ls, v);
                break;
            }
            default: return;
        }
    }
}
```

### å³å€¼è§£æï¼šexplist1

```c
static int explist1(LexState *ls, expdesc *v) {
    int n = 1;  // è‡³å°‘ä¸€ä¸ªè¡¨è¾¾å¼
    expr(ls, v);
    
    while (testnext(ls, ',')) {
        luaK_exp2nextreg(ls->fs, v);
        expr(ls, v);
        n++;
    }
    return n;
}
```

### adjust_assignï¼šè°ƒæ•´èµ‹å€¼æ•°é‡

```c
static void adjust_assign(LexState *ls, int nvars, int nexps, expdesc *e) {
    FuncState *fs = ls->fs;
    int extra = nvars - nexps;
    
    if (hasmultret(e->k)) {
        extra++;  // åŒ…æ‹¬å¤šè¿”å›å€¼è°ƒç”¨æœ¬èº«
        if (extra < 0) extra = 0;
        luaK_setreturns(fs, e, extra);  // è°ƒæ•´è¿”å›å€¼æ•°é‡
        if (extra > 1) luaK_reserveregs(fs, extra - 1);
    }
    else {
        if (e->k != VVOID) luaK_exp2nextreg(fs, e);  // å…³é—­æœ€åä¸€ä¸ªè¡¨è¾¾å¼
        if (extra > 0) {
            int reg = fs->freereg;
            luaK_reserveregs(fs, extra);
            luaK_nil(fs, reg, extra);  // å‰©ä½™å˜é‡èµ‹ nil
        }
    }
}
```

### ç¤ºä¾‹ï¼šä¸ç­‰é•¿èµ‹å€¼

**æƒ…å†µ 1ï¼šå³å€¼æ›´å¤š**

```lua
a, b = 1, 2, 3
```

```
nexps = 3, nvars = 2
extra = 2 - 3 = -1

ç”Ÿæˆä»£ç ï¼š
LOADK R0 1
LOADK R1 2
-- 3 è¢«ä¸¢å¼ƒ
```

**æƒ…å†µ 2ï¼šå³å€¼æ›´å°‘**

```lua
a, b, c = 1, 2
```

```
nexps = 2, nvars = 3
extra = 3 - 2 = 1

ç”Ÿæˆä»£ç ï¼š
LOADK R0 1
LOADK R1 2
LOADNIL R2 1    -- c = nil
```

**æƒ…å†µ 3ï¼šå¤šè¿”å›å€¼å‡½æ•°**

```lua
a, b, c = f()
```

```
nexps = 1ï¼ˆä½† f() å¯ä»¥è¿”å›å¤šä¸ªå€¼ï¼‰
nvars = 3
extra = 3 - 1 + 1 = 3

ç”Ÿæˆä»£ç ï¼š
CALL Rf 1 4     -- è°ƒç”¨ f()ï¼ŒæœŸæœ› 3 ä¸ªè¿”å›å€¼
MOVE R0 Rf
MOVE R1 Rf+1
MOVE R2 Rf+2
```

### luaK_storevarï¼šå­˜å‚¨åˆ°å·¦å€¼

```c
void luaK_storevar(FuncState *fs, expdesc *var, expdesc *ex) {
    switch (var->k) {
        case VLOCAL: {  // å±€éƒ¨å˜é‡
            freeexp(fs, ex);
            exp2reg(fs, ex, var->u.s.info);
            return;
        }
        case VUPVAL: {  // upvalue
            int e = luaK_exp2anyreg(fs, ex);
            luaK_codeABC(fs, OP_SETUPVAL, e, var->u.s.info, 0);
            break;
        }
        case VGLOBAL: {  // å…¨å±€å˜é‡
            int e = luaK_exp2anyreg(fs, ex);
            luaK_codeABx(fs, OP_SETGLOBAL, e, var->u.s.info);
            break;
        }
        case VINDEXED: {  // è¡¨ç´¢å¼•
            int e = luaK_exp2RK(fs, ex);
            luaK_codeABC(fs, OP_SETTABLE, var->u.s.info, var->u.s.aux, e);
            break;
        }
        default: {
            lua_assert(0);
            break;
        }
    }
    freeexp(fs, ex);
}
```

### å­—èŠ‚ç ç”Ÿæˆç¤ºä¾‹

**ç¤ºä¾‹ 1ï¼šç®€å•èµ‹å€¼**

```lua
local x = 10
```

```
LOADK R0 K0     ; K0 = 10
```

**ç¤ºä¾‹ 2ï¼šå¤šé‡èµ‹å€¼**

```lua
local a, b = 1, 2
```

```
LOADK R0 K0     ; K0 = 1
LOADK R1 K1     ; K1 = 2
```

**ç¤ºä¾‹ 3ï¼šè¡¨ç´¢å¼•èµ‹å€¼**

```lua
t[k] = v
```

```
GETGLOBAL R0 't'
GETGLOBAL R1 'k'
GETGLOBAL R2 'v'
SETTABLE R0 R1 R2
```

**ç¤ºä¾‹ 4ï¼šé“¾å¼èµ‹å€¼**

```lua
a = b = c = 1  -- Lua ä¸æ”¯æŒï¼å¿…é¡»å†™æˆ
c = 1
b = c
a = b
```

---

## ğŸ”€ æ§åˆ¶æµè¯­å¥è§£æ

æ§åˆ¶æµè¯­å¥æ˜¯ç¨‹åºé€»è¾‘çš„æ ¸å¿ƒï¼ŒLua æ”¯æŒ `if`ã€`while`ã€`repeat`ã€`for` ç­‰å¤šç§æ§åˆ¶ç»“æ„ã€‚

### if è¯­å¥è§£æ

**è¯­æ³•**ï¼š

```lua
if exp then block
elseif exp then block
else block
end
```

**ifstat å‡½æ•°**ï¼š

```c
static void ifstat(LexState *ls, int line) {
    FuncState *fs = ls->fs;
    int flist;
    int escapelist = NO_JUMP;
    
    flist = test_then_block(ls);  // IF æˆ– ELSEIF
    
    while (ls->t.token == TK_ELSEIF) {
        luaK_concat(fs, &escapelist, luaK_jump(fs));
        luaK_patchtohere(fs, flist);
        flist = test_then_block(ls);
    }
    
    if (ls->t.token == TK_ELSE) {
        luaK_concat(fs, &escapelist, luaK_jump(fs));
        luaK_patchtohere(fs, flist);
        next(ls);  // è·³è¿‡ ELSE
        block(ls);
    }
    else {
        luaK_concat(fs, &escapelist, flist);
    }
    
    luaK_patchtohere(fs, escapelist);
    check_match(ls, TK_END, TK_IF, line);
}
```

**test_then_blockï¼šè§£ææ¡ä»¶å’Œthenå—**

```c
static int test_then_block(LexState *ls) {
    int condexit;
    next(ls);  // è·³è¿‡ IF æˆ– ELSEIF
    
    expdesc v;
    expr(ls, &v);  // è§£ææ¡ä»¶è¡¨è¾¾å¼
    checknext(ls, TK_THEN);
    
    condexit = luaK_goiffalse(ls->fs, &v);  // æ¡ä»¶ä¸ºå‡æ—¶è·³è½¬
    block(ls);  // then å—
    
    return condexit;
}
```

**è·³è½¬é“¾è¡¨ç®¡ç†**ï¼š

```mermaid
graph TD
    A[if cond1 then] --> B{cond1}
    B -->|true| C[block1]
    B -->|false| D[elseif cond2]
    C --> E[escape jump]
    D --> F{cond2}
    F -->|true| G[block2]
    F -->|false| H[else]
    G --> I[escape jump]
    H --> J[block3]
    E --> K[END]
    I --> K
    J --> K
```

**å­—èŠ‚ç ç¤ºä¾‹**ï¼š

```lua
if x > 10 then
    print("big")
elseif x > 5 then
    print("medium")
else
    print("small")
end
```

```
GETGLOBAL R0 'x'
LT 0 K0 R0      ; K0 = 10, å¦‚æœ !(10 < x) åˆ™è·³è½¬
JMP [7]         ; è·³åˆ° elseif

; then block
GETGLOBAL R0 'print'
LOADK R1 K1     ; K1 = "big"
CALL R0 2 1
JMP [16]        ; è·³åˆ° END

; elseif
GETGLOBAL R0 'x'
LT 0 K2 R0      ; K2 = 5
JMP [14]        ; è·³åˆ° else

; elseif then block
GETGLOBAL R0 'print'
LOADK R1 K3     ; K3 = "medium"
CALL R0 2 1
JMP [16]

; else block
GETGLOBAL R0 'print'
LOADK R1 K4     ; K4 = "small"
CALL R0 2 1

; END
```

### while è¯­å¥è§£æ

**è¯­æ³•**ï¼š

```lua
while exp do block end
```

**whilestat å‡½æ•°**ï¼š

```c
static void whilestat(LexState *ls, int line) {
    FuncState *fs = ls->fs;
    int whileinit;
    int condexit;
    BlockCnt bl;
    
    next(ls);  // è·³è¿‡ WHILE
    whileinit = luaK_getlabel(fs);  // å¾ªç¯å¼€å§‹ä½ç½®
    
    expdesc v;
    expr(ls, &v);
    condexit = luaK_goiffalse(fs, &v);  // æ¡ä»¶ä¸ºå‡æ—¶è·³å‡º
    
    enterblock(fs, &bl, 1);  // å¯ break çš„å—
    checknext(ls, TK_DO);
    block(ls);
    
    luaK_patchlist(fs, luaK_jump(fs), whileinit);  // è·³å›å¾ªç¯å¼€å§‹
    check_match(ls, TK_END, TK_WHILE, line);
    leaveblock(fs);
    
    luaK_patchtohere(fs, condexit);  // ä¿®æ­£é€€å‡ºè·³è½¬
}
```

**å¾ªç¯ç»“æ„**ï¼š

```mermaid
graph LR
    A[whileinit] --> B{æ¡ä»¶æµ‹è¯•}
    B -->|true| C[block]
    C --> D[jump to whileinit]
    D --> A
    B -->|false| E[condexit]
```

**å­—èŠ‚ç ç¤ºä¾‹**ï¼š

```lua
local i = 1
while i <= 10 do
    print(i)
    i = i + 1
end
```

```
LOADK R0 K0     ; K0 = 1, i = 1

; whileinit
LE 1 R0 K1      ; K1 = 10, i <= 10?
JMP [9]         ; ä¸ºå‡åˆ™è·³å‡º

; block
GETGLOBAL R1 'print'
MOVE R2 R0
CALL R1 2 1
ADD R0 R0 K2    ; K2 = 1, i = i + 1
JMP [2]         ; è·³å› whileinit

; condexit
```

### repeat è¯­å¥è§£æ

**è¯­æ³•**ï¼š

```lua
repeat block until exp
```

**repeatstat å‡½æ•°**ï¼š

```c
static void repeatstat(LexState *ls, int line) {
    int condexit;
    FuncState *fs = ls->fs;
    int repeat_init = luaK_getlabel(fs);
    BlockCnt bl1, bl2;
    
    enterblock(fs, &bl1, 1);  // å¯ break çš„å—
    enterblock(fs, &bl2, 0);  // å†…å±‚å—ï¼ˆç”¨äº until ä¸­çš„å±€éƒ¨å˜é‡ï¼‰
    
    next(ls);  // è·³è¿‡ REPEAT
    chunk(ls);  // æ³¨æ„ï¼šè¿™é‡Œç”¨ chunk è€Œé block
    check_match(ls, TK_UNTIL, TK_REPEAT, line);
    
    expdesc v;
    expr(ls, &v);  // until æ¡ä»¶
    condexit = luaK_goiftrue(fs, &v);  // æ¡ä»¶ä¸ºçœŸæ—¶è·³å‡º
    
    leaveblock(fs);  // ç¦»å¼€å†…å±‚å—
    luaK_patchlist(fs, condexit, repeat_init);  // æ¡ä»¶ä¸ºå‡æ—¶å›åˆ°å¼€å§‹
    leaveblock(fs);  // ç¦»å¼€å¤–å±‚å—
}
```

**repeat vs while çš„åŒºåˆ«**ï¼š

| ç‰¹æ€§ | while | repeat |
|------|-------|--------|
| **æµ‹è¯•æ—¶æœº** | å‰æµ‹è¯•ï¼ˆpre-testï¼‰ | åæµ‹è¯•ï¼ˆpost-testï¼‰ |
| **æœ€å°‘æ‰§è¡Œ** | 0 æ¬¡ | 1 æ¬¡ |
| **ä½œç”¨åŸŸ** | block ç‹¬ç«‹ä½œç”¨åŸŸ | until å¯è®¿é—® block ä¸­çš„å˜é‡ |

**ç¤ºä¾‹ï¼šä½œç”¨åŸŸå·®å¼‚**

```lua
-- repeat å¯ä»¥ï¼š
repeat
    local x = get_input()
until x == "quit"  -- x å¯è§

-- while ä¸è¡Œï¼š
while true do
    local x = get_input()
    if x == "quit" then break end  -- å¿…é¡»è¿™æ ·å†™
end
```

**å­—èŠ‚ç ç¤ºä¾‹**ï¼š

```lua
local i = 1
repeat
    print(i)
    i = i + 1
until i > 10
```

```
LOADK R0 K0     ; K0 = 1

; repeat_init
GETGLOBAL R1 'print'
MOVE R2 R0
CALL R1 2 1
ADD R0 R0 K1    ; K1 = 1
LT 0 K2 R0      ; K2 = 10, i > 10?
JMP [2]         ; ä¸ºå‡åˆ™å›åˆ° repeat_init
```

### for æ•°å€¼å‹å¾ªç¯

**è¯­æ³•**ï¼š

```lua
for var = exp1, exp2, exp3 do block end
-- exp3 å¯é€‰ï¼Œé»˜è®¤ä¸º 1
```

**fornum å‡½æ•°**ï¼š

```c
static void fornum(LexState *ls, TString *varname, int line) {
    FuncState *fs = ls->fs;
    int base = fs->freereg;
    
    new_localvarliteral(ls, "(for index)", 0);
    new_localvarliteral(ls, "(for limit)", 1);
    new_localvarliteral(ls, "(for step)", 2);
    new_localvar(ls, varname, 3);  // å¾ªç¯å˜é‡
    
    checknext(ls, '=');
    exp1(ls);  // åˆå§‹å€¼
    checknext(ls, ',');
    exp1(ls);  // é™åˆ¶å€¼
    
    if (testnext(ls, ','))
        exp1(ls);  // æ­¥é•¿
    else {
        luaK_codeABx(fs, OP_LOADK, fs->freereg, luaK_numberK(fs, 1));
        luaK_reserveregs(fs, 1);
    }
    
    forbody(ls, base, line, 1, 1);
}
```

**forbody å‡½æ•°**ï¼š

```c
static void forbody(LexState *ls, int base, int line, int nvars, int isnum) {
    BlockCnt bl;
    FuncState *fs = ls->fs;
    int prep, endfor;
    
    adjustlocalvars(ls, 3);  // åˆå§‹åŒ–æ§åˆ¶å˜é‡
    checknext(ls, TK_DO);
    
    prep = isnum ? luaK_codeAsBx(fs, OP_FORPREP, base, NO_JUMP) : luaK_jump(fs);
    
    enterblock(fs, &bl, 0);
    adjustlocalvars(ls, nvars);
    luaK_reserveregs(fs, nvars);
    block(ls);
    leaveblock(fs);
    
    luaK_patchtohere(fs, prep);
    endfor = (isnum) ? luaK_codeAsBx(fs, OP_FORLOOP, base, NO_JUMP) :
                       luaK_codeABC(fs, OP_TFORLOOP, base, 0, nvars);
    luaK_fixline(fs, line);
    luaK_patchlist(fs, (isnum ? endfor : luaK_jump(fs)), prep + 1);
}
```

**for å¾ªç¯çš„å†…éƒ¨å˜é‡**ï¼š

```
å¯„å­˜å™¨å¸ƒå±€ï¼š
base + 0: (for index)  -- å½“å‰ç´¢å¼•
base + 1: (for limit)  -- é™åˆ¶å€¼
base + 2: (for step)   -- æ­¥é•¿
base + 3: var          -- ç”¨æˆ·å¯è§çš„å¾ªç¯å˜é‡
```

**FORPREP å’Œ FORLOOP æŒ‡ä»¤**ï¼š

```c
// FORPREP: åˆå§‹åŒ–å¾ªç¯
// R(A) -= R(A+2)  // index -= stepï¼ˆå› ä¸º FORLOOP ä¼šå…ˆåŠ ï¼‰
// pc += sBx       // è·³åˆ°å¾ªç¯ä½“

// FORLOOP: å¾ªç¯è¿­ä»£
// R(A) += R(A+2)  // index += step
// if R(A) <?= R(A+1) then {  // æ ¹æ® step ç¬¦å·åˆ¤æ–­
//     pc += sBx   // ç»§ç»­å¾ªç¯
//     R(A+3) = R(A)  // æ›´æ–°ç”¨æˆ·å˜é‡
// }
```

**å­—èŠ‚ç ç¤ºä¾‹**ï¼š

```lua
for i = 1, 10, 2 do
    print(i)
end
```

```
LOADK R0 K0     ; K0 = 1, (for index)
LOADK R1 K1     ; K1 = 10, (for limit)
LOADK R2 K2     ; K2 = 2, (for step)
FORPREP R0 [8]  ; è·³åˆ°å¾ªç¯ä½“

; loop body
GETGLOBAL R4 'print'
MOVE R5 R3      ; R3 = iï¼ˆç”¨æˆ·å˜é‡ï¼‰
CALL R4 2 1
FORLOOP R0 [4]  ; ç»§ç»­å¾ªç¯æˆ–é€€å‡º
```

### for æ³›å‹å¾ªç¯

**è¯­æ³•**ï¼š

```lua
for var1, var2, ... in explist do block end
```

**forlist å‡½æ•°**ï¼š

```c
static void forlist(LexState *ls, TString *indexname) {
    FuncState *fs = ls->fs;
    expdesc e;
    int nvars = 0;
    int line;
    int base = fs->freereg;
    
    // ä¸å¯è§çš„æ§åˆ¶å˜é‡
    new_localvarliteral(ls, "(for generator)", nvars++);
    new_localvarliteral(ls, "(for state)", nvars++);
    new_localvarliteral(ls, "(for control)", nvars++);
    
    // ç”¨æˆ·å˜é‡
    new_localvar(ls, indexname, nvars++);
    while (testnext(ls, ','))
        new_localvar(ls, str_checkname(ls), nvars++);
    
    checknext(ls, TK_IN);
    line = ls->linenumber;
    adjust_assign(ls, 3, explist1(ls, &e), &e);
    luaK_checkstack(fs, 3);  // é¢„ç•™ç©ºé—´
    
    forbody(ls, base, line, nvars - 3, 0);
}
```

**æ³›å‹ for çš„å†…éƒ¨å˜é‡**ï¼š

```
å¯„å­˜å™¨å¸ƒå±€ï¼š
base + 0: (for generator)  -- è¿­ä»£å™¨å‡½æ•°
base + 1: (for state)      -- çŠ¶æ€å˜é‡
base + 2: (for control)    -- æ§åˆ¶å˜é‡
base + 3: var1             -- ç”¨æˆ·å˜é‡ 1
base + 4: var2             -- ç”¨æˆ·å˜é‡ 2
...
```

**TFORLOOP æŒ‡ä»¤**ï¼š

```c
// TFORLOOP: æ³›å‹å¾ªç¯è¿­ä»£
// R(A+3), ..., R(A+2+C) = R(A)(R(A+1), R(A+2))  // è°ƒç”¨è¿­ä»£å™¨
// if R(A+3) ~= nil then {
//     R(A+2) = R(A+3)  // æ›´æ–°æ§åˆ¶å˜é‡
//     pc += sBx        // ç»§ç»­å¾ªç¯
// }
```

**å­—èŠ‚ç ç¤ºä¾‹**ï¼š

```lua
for k, v in pairs(t) do
    print(k, v)
end
```

```
GETGLOBAL R0 'pairs'
GETGLOBAL R1 't'
CALL R0 2 4     ; è°ƒç”¨ pairs(t)ï¼ŒæœŸæœ› 3 ä¸ªè¿”å›å€¼
; R0 = generator, R1 = state, R2 = control
JMP [8]         ; è·³åˆ°å¾ªç¯ä½“

; loop body
GETGLOBAL R5 'print'
MOVE R6 R3      ; R3 = k
MOVE R7 R4      ; R4 = v
CALL R5 3 1
TFORLOOP R0 2   ; ç»§ç»­è¿­ä»£
JMP [4]         ; å›åˆ°å¾ªç¯ä½“
```

---

## ğŸ”§ å‡½æ•°ç›¸å…³è¯­å¥

å‡½æ•°å®šä¹‰å’Œè°ƒç”¨æ˜¯ Lua çš„æ ¸å¿ƒç‰¹æ€§ï¼Œæ¶‰åŠä½œç”¨åŸŸã€é—­åŒ…ã€å‚æ•°ä¼ é€’ç­‰å¤æ‚æœºåˆ¶ã€‚

### å‡½æ•°å®šä¹‰è¯­å¥

**è¯­æ³•**ï¼š

```lua
function name(params) body end
function t.method(params) body end
function t:method(params) body end  -- éšå¼ self å‚æ•°
local function name(params) body end
```

**funcstat å‡½æ•°ï¼šå…¨å±€å‡½æ•°**

```c
static void funcstat(LexState *ls, int line) {
    expdesc v, b;
    
    next(ls);  // è·³è¿‡ FUNCTION
    
    int needself = funcname(ls, &v);  // è§£æå‡½æ•°å
    body(ls, &b, needself, line);     // è§£æå‡½æ•°ä½“
    luaK_storevar(ls->fs, &v, &b);    // å­˜å‚¨åˆ°å˜é‡
    luaK_fixline(ls->fs, line);
}
```

**funcname å‡½æ•°ï¼šè§£æå‡½æ•°å**

```c
static int funcname(LexState *ls, expdesc *v) {
    int needself = 0;
    
    singlevar(ls, v);  // ç¬¬ä¸€ä¸ªåå­—
    
    while (ls->t.token == '.') {
        fieldsel(ls, v);  // t.field
    }
    
    if (ls->t.token == ':') {
        needself = 1;
        fieldsel(ls, v);  // t:methodï¼ˆéœ€è¦éšå¼ selfï¼‰
    }
    
    return needself;
}
```

**ç¤ºä¾‹è§£æ**ï¼š

```lua
function math.add(a, b)
    return a + b
end
```

è§£æè¿‡ç¨‹ï¼š
1. `funcname()` è§£æ `math.add`ï¼Œè¿”å› `needself=0`
2. `body()` åˆ›å»ºæ–°çš„ `FuncState`ï¼Œè§£æå‚æ•°å’Œå‡½æ•°ä½“
3. `luaK_storevar()` ç”Ÿæˆ `SETTABLE` æŒ‡ä»¤

**å­—èŠ‚ç **ï¼š

```
GETGLOBAL R0 'math'
CLOSURE R1 <function>
SETTABLE R0 K0 R1   ; K0 = "add"

; <function> çš„åŸå‹ï¼š
function <math.add>:
    ADD R2 R0 R1    ; R0=a, R1=b
    RETURN R2 2
```

### body å‡½æ•°ï¼šè§£æå‡½æ•°ä½“

```c
static void body(LexState *ls, expdesc *e, int needself, int line) {
    FuncState new_fs;
    open_func(ls, &new_fs);
    new_fs.f->linedefined = line;
    
    checknext(ls, '(');
    
    if (needself) {
        new_localvarliteral(ls, "self", 0);
        adjustlocalvars(ls, 1);
    }
    
    parlist(ls);  // è§£æå‚æ•°åˆ—è¡¨
    checknext(ls, ')');
    chunk(ls);    // è§£æå‡½æ•°ä½“
    new_fs.f->lastlinedefined = ls->linenumber;
    check_match(ls, TK_END, TK_FUNCTION, line);
    
    close_func(ls);
    pushclosure(ls, &new_fs, e);
}
```

**open_func å’Œ close_func**ï¼š

```c
static void open_func(LexState *ls, FuncState *fs) {
    lua_State *L = ls->L;
    Proto *f = luaF_newproto(L);
    
    fs->f = f;
    fs->prev = ls->fs;  // é“¾æ¥åˆ°å¤–å±‚å‡½æ•°
    fs->ls = ls;
    fs->L = L;
    ls->fs = fs;
    
    fs->pc = 0;
    fs->lasttarget = -1;
    fs->jpc = NO_JUMP;
    fs->freereg = 0;
    fs->nk = 0;
    fs->np = 0;
    fs->nlocvars = 0;
    fs->nactvar = 0;
    fs->bl = NULL;
    f->source = ls->source;
    f->maxstacksize = 2;  // æœ€å°æ ˆå¤§å°
}

static void close_func(LexState *ls) {
    lua_State *L = ls->L;
    FuncState *fs = ls->fs;
    Proto *f = fs->f;
    
    removevars(ls, 0);  // ç§»é™¤æ‰€æœ‰å±€éƒ¨å˜é‡
    luaK_ret(fs, 0, 0);  // æ·»åŠ é»˜è®¤ return
    
    // è°ƒæ•´æ•°ç»„å¤§å°
    luaM_reallocvector(L, f->code, f->sizecode, fs->pc, Instruction);
    f->sizecode = fs->pc;
    luaM_reallocvector(L, f->lineinfo, f->sizelineinfo, fs->pc, int);
    f->sizelineinfo = fs->pc;
    luaM_reallocvector(L, f->k, f->sizek, fs->nk, TValue);
    f->sizek = fs->nk;
    luaM_reallocvector(L, f->p, f->sizep, fs->np, Proto *);
    f->sizep = fs->np;
    luaM_reallocvector(L, f->locvars, f->sizelocvars, fs->nlocvars, LocVar);
    f->sizelocvars = fs->nlocvars;
    luaM_reallocvector(L, f->upvalues, f->sizeupvalues, f->nups, TString *);
    f->sizeupvalues = f->nups;
    
    ls->fs = fs->prev;  // æ¢å¤å¤–å±‚å‡½æ•°
}
```

### parlist å‡½æ•°ï¼šå‚æ•°åˆ—è¡¨è§£æ

```c
static void parlist(LexState *ls) {
    FuncState *fs = ls->fs;
    Proto *f = fs->f;
    int nparams = 0;
    
    f->is_vararg = 0;
    
    if (ls->t.token != ')') {
        do {
            switch (ls->t.token) {
                case TK_NAME: {
                    new_localvar(ls, str_checkname(ls), nparams++);
                    break;
                }
                case TK_DOTS: {
                    next(ls);
                    f->is_vararg = VARARG_HASARG | VARARG_NEEDSARG;
                    break;
                }
                default: luaX_syntaxerror(ls, "<name> or " LUA_QL("...") " expected");
            }
        } while (!f->is_vararg && testnext(ls, ','));
    }
    
    adjustlocalvars(ls, nparams);
    f->numparams = cast_byte(fs->nactvar - (f->is_vararg & VARARG_HASARG));
    luaK_reserveregs(fs, fs->nactvar);  // ä¸ºå‚æ•°é¢„ç•™å¯„å­˜å™¨
}
```

**å¯å˜å‚æ•°å‡½æ•°**ï¼š

```lua
function f(a, b, ...)
    local args = {...}
    return a + b + #args
end
```

```c
// is_vararg æ ‡å¿—ä½ï¼š
#define VARARG_HASARG    1  // æœ‰ ... å‚æ•°
#define VARARG_ISVARARG  2  // æ˜¯ vararg å‡½æ•°ï¼ˆå…¼å®¹æ€§ï¼‰
#define VARARG_NEEDSARG  4  // éœ€è¦åˆ›å»º arg è¡¨ï¼ˆå·²åºŸå¼ƒï¼‰
```

### localfunc å‡½æ•°ï¼šå±€éƒ¨å‡½æ•°

```c
static void localfunc(LexState *ls) {
    expdesc v, b;
    FuncState *fs = ls->fs;
    
    new_localvar(ls, str_checkname(ls), 0);  // å…ˆå£°æ˜å˜é‡
    init_exp(&v, VLOCAL, fs->freereg);
    luaK_reserveregs(fs, 1);
    adjustlocalvars(ls, 1);  // ç«‹å³æ¿€æ´»ï¼ˆå…è®¸é€’å½’ï¼‰
    
    body(ls, &b, 0, ls->linenumber);
    luaK_storevar(fs, &v, &b);
    
    // ä¿®æ­£è°ƒè¯•ä¿¡æ¯ï¼ˆå˜é‡åœ¨å‡½æ•°ä½“å¼€å§‹å¤„æ‰çœŸæ­£å®šä¹‰ï¼‰
    getlocvar(fs, fs->nactvar - 1).startpc = fs->pc;
}
```

**å±€éƒ¨å‡½æ•° vs å…¨å±€å‡½æ•°**ï¼š

```lua
-- å±€éƒ¨å‡½æ•°ï¼šå¯ä»¥é€’å½’
local function fact(n)
    if n <= 1 then return 1
    else return n * fact(n - 1)  -- fact å·²ç»åœ¨ä½œç”¨åŸŸä¸­
    end
end

-- å…¨å±€å‡½æ•°ï¼šä¹Ÿå¯ä»¥é€’å½’ï¼ˆé€šè¿‡å…¨å±€åå­—ï¼‰
function fact2(n)
    if n <= 1 then return 1
    else return n * fact2(n - 1)
    end
end

-- é”™è¯¯ç¤ºä¾‹ï¼š
local fact3 = function(n)  -- fact3 è¿˜æœªå®šä¹‰
    if n <= 1 then return 1
    else return n * fact3(n - 1)  -- é”™è¯¯ï¼šfact3 æ˜¯ nil
    end
end
```

### return è¯­å¥

**è¯­æ³•**ï¼š

```lua
return
return exp
return exp1, exp2, ...
```

**retstat å‡½æ•°**ï¼š

```c
static void retstat(LexState *ls) {
    FuncState *fs = ls->fs;
    expdesc e;
    int first, nret;
    
    next(ls);  // è·³è¿‡ RETURN
    
    if (block_follow(ls->t.token) || ls->t.token == ';')
        first = nret = 0;  // returnï¼ˆæ— è¿”å›å€¼ï¼‰
    else {
        nret = explist1(ls, &e);  // è¿”å›å€¼åˆ—è¡¨
        
        if (hasmultret(e.k)) {
            luaK_setmultret(fs, &e);
            if (e.k == VCALL && nret == 1) {  // å°¾è°ƒç”¨ï¼Ÿ
                SET_OPCODE(getcode(fs, &e), OP_TAILCALL);
                lua_assert(GETARG_A(getcode(fs, &e)) == fs->nactvar);
            }
            first = fs->nactvar;
            nret = LUA_MULTRET;  // è¿”å›æ‰€æœ‰å€¼
        }
        else {
            if (nret == 1)
                first = luaK_exp2anyreg(fs, &e);
            else {
                luaK_exp2nextreg(fs, &e);
                first = fs->nactvar;
                lua_assert(nret == fs->freereg - first);
            }
        }
    }
    
    luaK_ret(fs, first, nret);
}
```

**luaK_ret å‡½æ•°**ï¼š

```c
void luaK_ret(FuncState *fs, int first, int nret) {
    luaK_codeABC(fs, OP_RETURN, first, nret + 1, 0);
}
```

**RETURN æŒ‡ä»¤**ï¼š

```c
// OP_RETURN A B
// return R(A), ..., R(A+B-2)
// B == 0: è¿”å›åˆ°æ ˆé¡¶
// B == 1: æ— è¿”å›å€¼
// B == 2: è¿”å› R(A)
// B > 2:  è¿”å› R(A) åˆ° R(A+B-2)
```

**å­—èŠ‚ç ç¤ºä¾‹**ï¼š

```lua
function f()
    return 1, 2, 3
end
```

```
LOADK R0 K0     ; K0 = 1
LOADK R1 K1     ; K1 = 2
LOADK R2 K2     ; K2 = 3
RETURN R0 4     ; è¿”å› 3 ä¸ªå€¼
```

### å°¾è°ƒç”¨ä¼˜åŒ–

**å°¾è°ƒç”¨æ¡ä»¶**ï¼š

```lua
-- æ˜¯å°¾è°ƒç”¨
return f()
return f(x)
return t:method(x)

-- ä¸æ˜¯å°¾è°ƒç”¨
return f() + 1       -- æœ‰é¢å¤–è¿ç®—
return f(), g()      -- å¤šä¸ªè¿”å›å€¼
return x, f()        -- f() ä¸æ˜¯å”¯ä¸€è¿”å›å€¼
local x = f(); return x  -- ä¸­é—´æœ‰å…¶ä»–è¯­å¥
```

**å®ç°**ï¼š

```c
if (e.k == VCALL && nret == 1) {
    SET_OPCODE(getcode(fs, &e), OP_TAILCALL);
    lua_assert(GETARG_A(getcode(fs, &e)) == fs->nactvar);
}
```

**TAILCALL vs CALL**ï¼š

| æŒ‡ä»¤ | æ ˆç®¡ç† | æ€§èƒ½ | ç”¨é€” |
|------|--------|------|------|
| `CALL` | ä¿ç•™è°ƒç”¨å¸§ | æ­£å¸¸ | æ™®é€šè°ƒç”¨ |
| `TAILCALL` | é‡ç”¨è°ƒç”¨å¸§ | ä¼˜åŒ– | å°¾é€’å½’ä¼˜åŒ– |

**ç¤ºä¾‹ï¼šå°¾é€’å½’**

```lua
local function sum(n, acc)
    acc = acc or 0
    if n == 0 then return acc
    else return sum(n - 1, acc + n)  -- å°¾è°ƒç”¨
    end
end
```

ç”Ÿæˆ `TAILCALL` è€Œé `CALL`ï¼Œé¿å…æ ˆæº¢å‡ºã€‚

---

## ğŸ“¦ å—å’Œä½œç”¨åŸŸç®¡ç†

å—ï¼ˆblockï¼‰æ˜¯ Lua ä½œç”¨åŸŸç®¡ç†çš„åŸºæœ¬å•ä½ï¼Œæ¯ä¸ªå—éƒ½æœ‰è‡ªå·±çš„å±€éƒ¨å˜é‡å’Œ upvalueã€‚

### enterblock å’Œ leaveblock

```c
static void enterblock(FuncState *fs, BlockCnt *bl, lu_byte isbreakable) {
    bl->breaklist = NO_JUMP;
    bl->isbreakable = isbreakable;
    bl->nactvar = fs->nactvar;
    bl->upval = 0;
    bl->previous = fs->bl;
    fs->bl = bl;
    lua_assert(fs->freereg == fs->nactvar);
}

static void leaveblock(FuncState *fs) {
    BlockCnt *bl = fs->bl;
    
    fs->bl = bl->previous;
    removevars(fs->ls, bl->nactvar);  // ç§»é™¤å—å†…å±€éƒ¨å˜é‡
    
    if (bl->upval)
        luaK_codeABC(fs, OP_CLOSE, bl->nactvar, 0, 0);
    
    fs->freereg = fs->nactvar;
    lua_assert(bl->nactvar == fs->nactvar);
    
    luaK_patchtohere(fs, bl->breaklist);  // ä¿®æ­£ break è·³è½¬
}
```

**BlockCnt å­—æ®µè¯´æ˜**ï¼š

| å­—æ®µ | ç±»å‹ | è¯´æ˜ |
|------|------|------|
| `previous` | `BlockCnt*` | å¤–å±‚å— |
| `breaklist` | `int` | break è¯­å¥è·³è½¬é“¾è¡¨ |
| `nactvar` | `lu_byte` | å—å¼€å§‹æ—¶çš„æ´»åŠ¨å˜é‡æ•° |
| `upval` | `lu_byte` | å—å†…æ˜¯å¦æœ‰ upvalue |
| `isbreakable` | `lu_byte` | æ˜¯å¦å¯ä»¥ä½¿ç”¨ break |

### å±€éƒ¨å˜é‡ç”Ÿå‘½å‘¨æœŸ

```c
static void new_localvar(LexState *ls, TString *name, int n) {
    FuncState *fs = ls->fs;
    luaX_checklimit(ls, fs->nactvar + n + 1, LUAI_MAXVARS, "local variables");
    fs->actvar[fs->nactvar + n] = cast(unsigned short, registerlocalvar(ls, name));
}

static int registerlocalvar(LexState *ls, TString *varname) {
    FuncState *fs = ls->fs;
    Proto *f = fs->f;
    int oldsize = f->sizelocvars;
    
    luaM_growvector(ls->L, f->locvars, fs->nlocvars, f->sizelocvars,
                    LocVar, SHRT_MAX, "too many local variables");
    
    while (oldsize < f->sizelocvars) f->locvars[oldsize++].varname = NULL;
    
    f->locvars[fs->nlocvars].varname = varname;
    luaC_objbarrier(ls->L, f, varname);
    return fs->nlocvars++;
}

static void adjustlocalvars(LexState *ls, int nvars) {
    FuncState *fs = ls->fs;
    fs->nactvar = cast_byte(fs->nactvar + nvars);
    for (; nvars; nvars--) {
        getlocvar(fs, fs->nactvar - nvars).startpc = fs->pc;
    }
}

static void removevars(LexState *ls, int tolevel) {
    FuncState *fs = ls->fs;
    while (fs->nactvar > tolevel)
        getlocvar(fs, --fs->nactvar).endpc = fs->pc;
}
```

**LocVar ç»“æ„**ï¼š

```c
typedef struct LocVar {
    TString *varname;  // å˜é‡å
    int startpc;       // ä½œç”¨åŸŸèµ·å§‹ PC
    int endpc;         // ä½œç”¨åŸŸç»“æŸ PC
} LocVar;
```

**ç¤ºä¾‹ï¼šä½œç”¨åŸŸåµŒå¥—**

```lua
do
    local x = 1  -- startpc = 0
    do
        local y = 2  -- startpc = 2
        print(x, y)
    end  -- y.endpc = 5
    print(x)
end  -- x.endpc = 7
```

### break è¯­å¥å¤„ç†

```c
static void breakstat(LexState *ls) {
    FuncState *fs = ls->fs;
    BlockCnt *bl = fs->bl;
    int upval = 0;
    
    while (bl && !bl->isbreakable) {
        upval |= bl->upval;
        bl = bl->previous;
    }
    
    if (!bl)
        luaX_syntaxerror(ls, "no loop to break");
    
    if (upval)
        luaK_codeABC(fs, OP_CLOSE, bl->nactvar, 0, 0);
    
    luaK_concat(fs, &bl->breaklist, luaK_jump(fs));
}
```

**break çš„é™åˆ¶**ï¼š

```lua
-- æ­£ç¡®
while condition do
    if x then break end
end

-- é”™è¯¯ï¼šä¸åœ¨å¾ªç¯ä¸­
if condition then
    break  -- syntax error: no loop to break
end

-- é”™è¯¯ï¼šLua 5.1 ä¸æ”¯æŒ continue
for i = 1, 10 do
    if i % 2 == 0 then
        continue  -- syntax errorï¼ˆLua 5.1ï¼‰
    end
    print(i)
end
```

### localstat å‡½æ•°ï¼šå±€éƒ¨å˜é‡å£°æ˜

```c
static void localstat(LexState *ls) {
    int nvars = 0;
    int nexps;
    expdesc e;
    
    do {
        new_localvar(ls, str_checkname(ls), nvars++);
    } while (testnext(ls, ','));
    
    if (testnext(ls, '='))
        nexps = explist1(ls, &e);
    else {
        e.k = VVOID;
        nexps = 0;
    }
    
    adjust_assign(ls, nvars, nexps, &e);
    adjustlocalvars(ls, nvars);
}
```

**ç¤ºä¾‹**ï¼š

```lua
local a, b, c = 1, 2
-- nvars = 3, nexps = 2
-- a = 1, b = 2, c = nil
```

---

## ğŸ”€ ç‰¹æ®Šè¯­å¥å¤„ç†

### do-end å—

**è¯­æ³•**ï¼š

```lua
do
    -- block
end
```

**å®ç°**ï¼ˆåœ¨ statement å‡½æ•°ä¸­ï¼‰ï¼š

```c
case TK_DO: {
    next(ls);
    block(ls);
    check_match(ls, TK_END, TK_DO, line);
    return;
}
```

**ç”¨é€”**ï¼š

```lua
-- é™åˆ¶å˜é‡ä½œç”¨åŸŸ
do
    local temp = expensive_calculation()
    result = process(temp)
end  -- temp è¢«å›æ”¶

-- æ¨¡æ‹Ÿ continue
for i = 1, 10 do
    if condition then
        -- ... code ...
    end
    ::continue::  -- Lua 5.2+
end
```

### å¤šè¿”å›å€¼å¤„ç†

**hasmultret å‡½æ•°**ï¼š

```c
static int hasmultret(expkind k) {
    return (k == VCALL || k == VVARARG);
}
```

**luaK_setmultret å‡½æ•°**ï¼š

```c
void luaK_setmultret(FuncState *fs, expdesc *e) {
    if (e->k == VCALL) {
        SETARG_C(getcode(fs, e), LUA_MULTRET);
    }
    else if (e->k == VVARARG) {
        SETARG_B(getcode(fs, e), LUA_MULTRET);
        SETARG_A(getcode(fs, e), fs->freereg);
        luaK_reserveregs(fs, 1);
    }
}
```

**ç¤ºä¾‹**ï¼š

```lua
-- æƒ…å†µ 1ï¼šèµ‹å€¼ç»™å¤šä¸ªå˜é‡
local a, b, c = f()
-- CALL Rf 1 0  (C=0 è¡¨ç¤ºå¤šè¿”å›å€¼)

-- æƒ…å†µ 2ï¼šä½œä¸ºæœ€åä¸€ä¸ªå‚æ•°
g(1, 2, f())
-- CALL Rf 1 0
-- CALL Rg 4 1  (ä¼ é€’ 1, 2, å’Œ f() çš„æ‰€æœ‰è¿”å›å€¼)

-- æƒ…å†µ 3ï¼šè¡¨æ„é€ å™¨
t = {1, 2, f()}
-- CALL Rf 1 0
-- SETLIST ...ï¼ˆåŒ…å« f() çš„æ‰€æœ‰è¿”å›å€¼ï¼‰

-- æƒ…å†µ 4ï¼šreturn è¯­å¥
return f()
-- TAILCALL Rf 1 0
-- RETURN Rf 0
```

### ç©ºè¯­å¥å’Œåˆ†å·

```c
static void statement(LexState *ls) {
    // ... è§£æè¯­å¥ ...
}

static void block(LexState *ls) {
    while (!block_follow(ls->t.token)) {
        statement(ls);
        testnext(ls, ';');  // å¯é€‰çš„åˆ†å·
    }
}
```

**ç¤ºä¾‹**ï¼š

```lua
local x = 1; local y = 2  -- åˆ†å·æ˜¯å¯é€‰çš„
;;; -- è¿ç»­åˆ†å·ï¼ˆç©ºè¯­å¥ï¼‰
```

### è°ƒè¯•ä¿¡æ¯ç”Ÿæˆ

**luaK_fixline å‡½æ•°**ï¼š

```c
void luaK_fixline(FuncState *fs, int line) {
    fs->f->lineinfo[fs->pc - 1] = line;
}
```

**lineinfo æ•°ç»„**ï¼š

```c
typedef struct Proto {
    // ...
    int *lineinfo;       // æ¯æ¡æŒ‡ä»¤å¯¹åº”çš„æºä»£ç è¡Œå·
    int sizelineinfo;
    // ...
} Proto;
```

**ç”¨é€”**ï¼šé”™è¯¯æ¶ˆæ¯å’Œè°ƒè¯•å™¨

```lua
-- test.lua:10
local x = nil
x.field = 1  -- é”™è¯¯

-- é”™è¯¯æ¶ˆæ¯ï¼š
-- test.lua:11: attempt to index local 'x' (a nil value)
--              ^^^^ é€šè¿‡ lineinfo ç¡®å®š
```

---

## ğŸ“Š ä»£ç ç”Ÿæˆç¤ºä¾‹

### ç¤ºä¾‹ 1ï¼šå¤æ‚ if è¯­å¥

**Lua ä»£ç **ï¼š

```lua
local x = 10
if x > 5 then
    print("big")
elseif x > 0 then
    print("small")
else
    print("zero or negative")
end
print("done")
```

**å­—èŠ‚ç **ï¼š

```
[1]  LOADK      R0 K0     ; K0 = 10
[2]  LT         0  K1 R0   ; K1 = 5, !(5 < x)?
[3]  JMP        [8]        ; è·³åˆ° elseif
[4]  GETGLOBAL  R1 'print'
[5]  LOADK      R2 K2      ; K2 = "big"
[6]  CALL       R1 2 1
[7]  JMP        [14]       ; è·³åˆ° END
[8]  LT         0  K3 R0   ; K3 = 0, !(0 < x)?
[9]  JMP        [13]       ; è·³åˆ° else
[10] GETGLOBAL  R1 'print'
[11] LOADK      R2 K4      ; K4 = "small"
[12] CALL       R1 2 1
[13] JMP        [17]       ; è·³åˆ° END
[14] GETGLOBAL  R1 'print'
[15] LOADK      R2 K5      ; K5 = "zero or negative"
[16] CALL       R1 2 1
[17] GETGLOBAL  R1 'print'
[18] LOADK      R2 K6      ; K6 = "done"
[19] CALL       R1 2 1
[20] RETURN     R0 1
```

### ç¤ºä¾‹ 2ï¼šåµŒå¥—å¾ªç¯

**Lua ä»£ç **ï¼š

```lua
for i = 1, 3 do
    for j = 1, 2 do
        print(i, j)
    end
end
```

**å­—èŠ‚ç **ï¼š

```
; å¤–å±‚å¾ªç¯
[1]  LOADK      R0 K0     ; K0 = 1, (for index)
[2]  LOADK      R1 K1     ; K1 = 3, (for limit)
[3]  LOADK      R2 K0     ; K0 = 1, (for step)
[4]  FORPREP    R0 [18]   ; è·³åˆ°å¤–å±‚ç»“æŸ

; å¤–å±‚å¾ªç¯ä½“
[5]  LOADK      R4 K0     ; å†…å±‚ (for index)
[6]  LOADK      R5 K2     ; K2 = 2, (for limit)
[7]  LOADK      R6 K0     ; (for step)
[8]  FORPREP    R4 [16]   ; è·³åˆ°å†…å±‚ç»“æŸ

; å†…å±‚å¾ªç¯ä½“
[9]  GETGLOBAL  R7 'print'
[10] MOVE       R8 R3     ; i
[11] MOVE       R9 R7     ; j
[12] CALL       R7 3 1
[13] FORLOOP    R4 [9]    ; å†…å±‚å¾ªç¯

; å¤–å±‚å¾ªç¯ç»§ç»­
[14] FORLOOP    R0 [5]    ; å¤–å±‚å¾ªç¯
[15] RETURN     R0 1
```

### ç¤ºä¾‹ 3ï¼šé—­åŒ…å’Œ upvalue

**Lua ä»£ç **ï¼š

```lua
local function make_counter()
    local count = 0
    return function()
        count = count + 1
        return count
    end
end

local c = make_counter()
print(c())  -- 1
print(c())  -- 2
```

**make_counter å­—èŠ‚ç **ï¼š

```
function <make_counter>:
[1] LOADK      R0 K0     ; K0 = 0, count = 0
[2] CLOSURE    R1 <inner>
[3] MOVE       R0 R0     ; å°† count æ ‡è®°ä¸º upvalue
[4] RETURN     R1 2
[5] RETURN     R0 1

function <inner>:  (1 upvalue)
[1] GETUPVAL   R0 U0     ; count
[2] ADD        R0 R0 K0  ; K0 = 1
[3] SETUPVAL   R0 U0     ; count = count + 1
[4] GETUPVAL   R0 U0
[5] RETURN     R0 2
[6] RETURN     R0 1
```

### ç¤ºä¾‹ 4ï¼šæ³›å‹ for å¾ªç¯

**Lua ä»£ç **ï¼š

```lua
local t = {10, 20, 30}
for i, v in ipairs(t) do
    print(i, v)
end
```

**å­—èŠ‚ç **ï¼š

```
[1]  NEWTABLE   R0 3 0
[2]  LOADK      R1 K0     ; K0 = 10
[3]  LOADK      R2 K1     ; K1 = 20
[4]  LOADK      R3 K2     ; K2 = 30
[5]  SETLIST    R0 3 1
[6]  GETGLOBAL  R1 'ipairs'
[7]  MOVE       R2 R0
[8]  CALL       R1 2 4    ; æœŸæœ› 3 ä¸ªè¿”å›å€¼ï¼ˆgenerator, state, controlï¼‰
[9]  JMP        [15]      ; è·³åˆ°å¾ªç¯ä½“

; å¾ªç¯ä½“
[10] GETGLOBAL  R5 'print'
[11] MOVE       R6 R4     ; i
[12] MOVE       R7 R5     ; v
[13] CALL       R5 3 1
[14] TFORLOOP   R1 2      ; è°ƒç”¨è¿­ä»£å™¨
[15] JMP        [10]      ; ç»§ç»­å¾ªç¯
[16] RETURN     R0 1
```

---

## âš¡ æ€§èƒ½ä¼˜åŒ–æŠ€å·§

### 1. å¸¸é‡ä¼ æ’­

ç¼–è¯‘æ—¶è®¡ç®—å¸¸é‡è¡¨è¾¾å¼ï¼š

```lua
local x = 2 + 3  -- ç¼–è¯‘ä¸º LOADK R0 K0 (K0 = 5)
```

**å®ç°**ï¼ˆåœ¨è¡¨è¾¾å¼è§£æä¸­ï¼‰ï¼š

```c
if (tonumeral(e1, &nb) && tonumeral(e2, &nc)) {
    e1->u.nval = luai_numadd(nb, nc);  // ç¼–è¯‘æ—¶è®¡ç®—
    return;
}
```

### 2. æ­»ä»£ç æ¶ˆé™¤

```lua
if true then
    print("always")
else
    print("never")  -- ä¸ç”Ÿæˆå­—èŠ‚ç 
end
```

**å®ç°**ï¼š

```c
static int test_then_block(LexState *ls) {
    expdesc v;
    expr(ls, &v);
    
    if (v.k == VTRUE) {
        // æ¡ä»¶æ’çœŸï¼Œä¸ç”Ÿæˆè·³è½¬
        block(ls);
        return NO_JUMP;
    }
    // ...
}
```

### 3. å±€éƒ¨å˜é‡å¯„å­˜å™¨å¤ç”¨

```lua
do
    local a = 1
    print(a)
end  -- a å ç”¨çš„å¯„å­˜å™¨è¢«é‡Šæ”¾

do
    local b = 2  -- å¤ç”¨ä¹‹å‰ a çš„å¯„å­˜å™¨
    print(b)
end
```

### 4. çŸ­è·¯æ±‚å€¼ä¼˜åŒ–

```lua
local x = expensive_function() or default_value
-- å¦‚æœ expensive_function() è¿”å›éå‡å€¼ï¼Œä¸ä¼šè®¡ç®— default_value
```

**å­—èŠ‚ç **ï¼š

```
CALL Rf 1 2         ; è°ƒç”¨å‡½æ•°
TEST Rf 0 1         ; æµ‹è¯•ç»“æœ
JMP [next]          ; ä¸ºçœŸåˆ™è·³è¿‡é»˜è®¤å€¼
LOADK Rf K0         ; åŠ è½½é»˜è®¤å€¼
; next:
```

### 5. å°¾è°ƒç”¨ä¼˜åŒ–

```lua
local function sum(n, acc)
    if n == 0 then return acc
    else return sum(n - 1, acc + n)  -- TAILCALL
    end
end
```

é¿å…æ ˆå¢é•¿ï¼Œæ”¯æŒæ— é™é€’å½’æ·±åº¦ã€‚

### 6. for å¾ªç¯ä¼˜åŒ–

**æ•°å€¼å‹ for ä½¿ç”¨ä¸“ç”¨æŒ‡ä»¤**ï¼š

```lua
for i = 1, 1000000 do
    -- FORLOOP æŒ‡ä»¤é«˜æ•ˆè¿­ä»£
end
```

æ¯” while å¾ªç¯å¿«çº¦ 20-30%ã€‚

### 7. è¡¨æ„é€ å™¨ä¼˜åŒ–

```lua
local t = {1, 2, 3, 4, 5}
-- ç”Ÿæˆ NEWTABLE + SETLISTï¼ˆæ‰¹é‡è®¾ç½®ï¼‰

local t2 = {}
t2[1] = 1
t2[2] = 2
-- ç”Ÿæˆå¤šä¸ª SETTABLEï¼ˆè¾ƒæ…¢ï¼‰
```

---

## ğŸ› ï¸ è°ƒè¯•ä¸å®è·µæŒ‡å—

### GDB è°ƒè¯•è¯­å¥è§£æ

```bash
$ gdb ./lua
(gdb) break statement
(gdb) run test.lua
```

**æŸ¥çœ‹è§£æçŠ¶æ€**ï¼š

```gdb
# å½“å‰ Token
(gdb) print ls->t.token
$1 = TK_IF

# å½“å‰å‡½æ•°çŠ¶æ€
(gdb) print ls->fs->f->source
$2 = "test.lua"

# æ´»åŠ¨å±€éƒ¨å˜é‡æ•°
(gdb) print ls->fs->nactvar
$3 = 2

# å½“å‰ PC
(gdb) print ls->fs->pc
$4 = 15

# å½“å‰å—
(gdb) print ls->fs->bl->isbreakable
$5 = 1
```

### æ·»åŠ è°ƒè¯•è¾“å‡º

```c
#define DEBUG_STMT 1

#ifdef DEBUG_STMT
static void print_token(int token) {
    switch (token) {
        case TK_IF: printf("IF\n"); break;
        case TK_WHILE: printf("WHILE\n"); break;
        case TK_FOR: printf("FOR\n"); break;
        // ...
        default: printf("token=%d\n", token); break;
    }
}

#define PRINT_TOKEN(t) print_token(t)
#else
#define PRINT_TOKEN(t)
#endif

static void statement(LexState *ls) {
    PRINT_TOKEN(ls->t.token);
    // ... åŸä»£ç  ...
}
```

### æ·»åŠ æ–°è¯­å¥ç±»å‹

**ç¤ºä¾‹ï¼šæ·»åŠ  switch è¯­å¥ï¼ˆLua 5.1 ä¸æ”¯æŒï¼‰**

**1. æ·»åŠ  Token**ï¼š

```c
// llex.h
#define TK_SWITCH  290
#define TK_CASE    291
#define TK_DEFAULT 292

// llex.c
static const char *const luaX_tokens[] = {
    // ... ç°æœ‰ Token ...
    "switch", "case", "default"
};
```

**2. è¯æ³•åˆ†æå™¨è¯†åˆ«å…³é”®å­—**ï¼š

```c
// llex.c
static int reserved_word(TString *ts) {
    // ... ç°æœ‰ä»£ç  ...
    if (strcmp(getstr(ts), "switch") == 0) return TK_SWITCH;
    if (strcmp(getstr(ts), "case") == 0) return TK_CASE;
    if (strcmp(getstr(ts), "default") == 0) return TK_DEFAULT;
    return TK_NAME;
}
```

**3. è§£æå‡½æ•°**ï¼š

```c
// lparser.c
static void switchstat(LexState *ls, int line) {
    FuncState *fs = ls->fs;
    expdesc v;
    int escape = NO_JUMP;
    BlockCnt bl;
    
    next(ls);  // è·³è¿‡ SWITCH
    expr(ls, &v);  // è§£æ switch è¡¨è¾¾å¼
    int switchreg = luaK_exp2anyreg(fs, &v);
    
    enterblock(fs, &bl, 1);
    
    while (ls->t.token == TK_CASE) {
        next(ls);
        expdesc caseval;
        expr(ls, &caseval);  // case å€¼
        
        // ç”Ÿæˆæ¯”è¾ƒï¼šif switchval == caseval then
        expdesc cmp;
        luaK_codeABC(fs, OP_EQ, 1, switchreg, luaK_exp2RK(fs, &caseval));
        luaK_concat(fs, &escape, luaK_jump(fs));
        
        checknext(ls, ':');
        statement(ls);
    }
    
    if (testnext(ls, TK_DEFAULT)) {
        checknext(ls, ':');
        statement(ls);
    }
    
    leaveblock(fs);
    check_match(ls, TK_END, TK_SWITCH, line);
    luaK_patchtohere(fs, escape);
}

// åœ¨ statement() ä¸­æ·»åŠ 
case TK_SWITCH: {
    switchstat(ls, line);
    return;
}
```

### å¸¸è§é”™è¯¯å¤„ç†

**1. "chunk has too many syntax levels"**ï¼š

```lua
-- åµŒå¥—è¿‡æ·±ï¼ˆè¶…è¿‡ 200 å±‚ï¼‰
(((((((...))))))
```

**è§£å†³**ï¼šé‡æ„ä»£ç ï¼Œå‡å°‘åµŒå¥—ã€‚

**2. "no loop to break"**ï¼š

```lua
if condition then
    break  -- é”™è¯¯
end
```

**è§£å†³**ï¼šç¡®ä¿ break åœ¨å¾ªç¯å†…ã€‚

**3. "attempt to index local 'x' (a nil value)"**ï¼š

```lua
local x
x.field = 1  -- x æ˜¯ nil
```

**è§£å†³**ï¼šåˆå§‹åŒ–å˜é‡ã€‚

### æµ‹è¯•ç”¨ä¾‹

```lua
-- test_statements.lua

-- æµ‹è¯• 1ï¼šif è¯­å¥
local function test_if()
    local x = 10
    if x > 5 then
        return "big"
    elseif x > 0 then
        return "small"
    else
        return "zero"
    end
end
assert(test_if() == "big")

-- æµ‹è¯• 2ï¼šwhile å¾ªç¯
local function test_while()
    local sum = 0
    local i = 1
    while i <= 10 do
        sum = sum + i
        i = i + 1
    end
    return sum
end
assert(test_while() == 55)

-- æµ‹è¯• 3ï¼šfor æ•°å€¼å‹
local function test_for_num()
    local sum = 0
    for i = 1, 10, 2 do
        sum = sum + i
    end
    return sum
end
assert(test_for_num() == 25)

-- æµ‹è¯• 4ï¼šfor æ³›å‹
local function test_for_list()
    local t = {10, 20, 30}
    local sum = 0
    for i, v in ipairs(t) do
        sum = sum + v
    end
    return sum
end
assert(test_for_list() == 60)

-- æµ‹è¯• 5ï¼šå±€éƒ¨å‡½æ•°é€’å½’
local function test_recursive()
    local function fact(n)
        if n <= 1 then return 1
        else return n * fact(n - 1)
        end
    end
    return fact(5)
end
assert(test_recursive() == 120)

-- æµ‹è¯• 6ï¼šå°¾è°ƒç”¨
local function test_tailcall()
    local function sum(n, acc)
        acc = acc or 0
        if n == 0 then return acc
        else return sum(n - 1, acc + n)
        end
    end
    return sum(10000)  -- å¤§æ•°ä¸ä¼šæ ˆæº¢å‡º
end
assert(test_tailcall() == 50005000)

print("All tests passed!")
```

---

## ğŸ”— ç›¸å…³æ–‡æ¡£

- [é€’å½’ä¸‹é™è§£æ](recursive_descent.md) - è§£æç®—æ³•åŸºç¡€
- [è¡¨è¾¾å¼è§£æ](expression_parsing.md) - è¡¨è¾¾å¼å¤„ç†ç»†èŠ‚
- [ä½œç”¨åŸŸä¸ upvalue](scope_management.md) - ä½œç”¨åŸŸç®¡ç†è¯¦è§£
- [ä»£ç ç”Ÿæˆä¸ä¼˜åŒ–](code_generation.md) - å­—èŠ‚ç ç”Ÿæˆç­–ç•¥
- [è™šæ‹ŸæœºæŒ‡ä»¤é›†](../vm/instruction_set.md) - æŒ‡ä»¤è¯¦ç»†è¯´æ˜

---

*è¿”å›ï¼š[è§£æå™¨æ¨¡å—æ€»è§ˆ](wiki_parser.md)*
