# Lua字节码生成与执行机制详解

## 问题
深入分析Lua的字节码生成过程，包括词法分析、语法分析、代码生成以及字节码指令格式设计。

## 通俗概述

Lua字节码生成是将高级Lua代码转换为虚拟机可执行指令的核心过程，这个过程体现了编译器设计的精妙艺术和工程智慧。

**多角度理解字节码生成机制**：

1. **翻译官工作流程视角**：
   - **字节码生成**：就像联合国的同声传译系统，将各种语言转换为标准的"机器语言"
   - **词法分析**：就像翻译官首先识别和分类每个词汇的含义和类型
   - **语法分析**：就像理解句子结构和语法规则，构建语义树
   - **代码生成**：就像将理解的内容转换为标准化的目标语言表达
   - **优化过程**：就像优秀的翻译官会简化冗余表达，使译文更简洁高效

2. **建筑施工图设计视角**：
   - **字节码生成**：就像将建筑师的设计图转换为施工队能理解的详细施工指令
   - **源代码**：就像建筑师的概念设计图，表达设计意图
   - **词法分析**：就像识别图纸上的各种符号、标注和元素
   - **语法分析**：就像理解建筑结构的层次关系和依赖关系
   - **字节码**：就像详细的施工指令，每一步都明确具体
   - **虚拟机执行**：就像施工队按照指令逐步建造建筑

3. **音乐编曲制作视角**：
   - **字节码生成**：就像将作曲家的乐谱转换为MIDI序列或数字音频工作站指令
   - **源代码**：就像作曲家手写的乐谱，包含音符、节拍、表情记号
   - **词法分析**：就像识别乐谱中的音符、休止符、调号、拍号等基本元素
   - **语法分析**：就像理解音乐的和声结构、旋律线条和节奏模式
   - **字节码**：就像MIDI事件序列，每个事件都有精确的时间和参数
   - **虚拟机执行**：就像音序器按照MIDI序列播放音乐

4. **工厂生产线设计视角**：
   - **字节码生成**：就像将产品设计方案转换为生产线的具体操作指令
   - **源代码**：就像产品的设计规格和功能要求
   - **词法分析**：就像识别设计图中的各种零件和组件
   - **语法分析**：就像理解装配顺序和工艺流程
   - **字节码**：就像生产线上每个工位的具体操作指令
   - **虚拟机执行**：就像自动化生产线按照指令精确执行每个步骤

**核心设计理念**：
- **抽象层次分离**：将高级语言特性与底层执行细节分离
- **平台无关性**：字节码可在任何支持Lua虚拟机的平台上执行
- **执行效率**：字节码比源代码解释执行快数倍到数十倍
- **内存紧凑**：字节码比源代码占用更少的内存空间
- **优化机会**：编译时可进行各种代码优化

**字节码生成的核心特性**：
- **单遍编译**：Lua采用单遍编译策略，编译速度快
- **寄存器架构**：基于寄存器的虚拟机，减少指令数量
- **指令优化**：编译时进行常量折叠、死代码消除等优化
- **调试支持**：保留源代码位置信息，支持调试和错误报告
- **动态特性**：支持Lua的动态语言特性，如动态类型、元表等

**实际应用场景**：
- **脚本预编译**：将Lua脚本预编译为字节码，提高加载速度
- **代码保护**：字节码比源代码更难逆向工程
- **嵌入式系统**：在资源受限的环境中使用预编译的字节码
- **游戏开发**：游戏脚本的快速加载和执行
- **配置系统**：复杂配置逻辑的高效执行
- **模板引擎**：模板的预编译和快速渲染

**性能优势**：
- **解析速度**：字节码加载比源代码解析快5-10倍
- **执行速度**：字节码执行比源代码解释快3-5倍
- **内存使用**：字节码通常比源代码占用更少内存
- **启动时间**：预编译的字节码显著减少程序启动时间

**与其他语言的对比**：
- **vs Java字节码**：Lua字节码更简洁，指令数量更少
- **vs Python字节码**：Lua的寄存器架构比Python的栈架构更高效
- **vs JavaScript V8**：Lua采用解释执行，V8采用即时编译
- **vs .NET IL**：Lua字节码更轻量级，适合嵌入式场景

**实际编程意义**：
- **性能优化**：理解字节码生成有助于编写高效的Lua代码
- **调试技能**：能够分析字节码有助于深度调试和性能分析
- **架构理解**：深入理解编译器和虚拟机的工作原理
- **工具开发**：为开发Lua相关工具提供理论基础

**实际意义**：字节码生成机制是Lua高性能的重要基础，它不仅提供了跨平台的代码执行能力，还为性能优化和调试分析提供了强大支持。理解这一机制对于编写高效的Lua程序、进行性能调优和深度调试都具有重要价值。特别是在需要高性能执行的场景中，字节码生成的优化效果更加明显。

## 详细答案

### 字节码指令格式详解

#### 32位指令架构设计

**技术概述**：Lua采用32位固定长度指令格式，这是在指令复杂度、执行效率和内存使用之间的精心平衡。

**通俗理解**：32位指令格式就像"标准化的工作指令单"，每张指令单都有固定的格式，包含操作类型和操作参数，工人（虚拟机）可以快速理解和执行。

```c
// lopcodes.h - 指令格式的完整设计
/*
Lua字节码指令的设计哲学：

1. 固定长度优势：
   - 指令解码简单快速
   - 跳转地址计算容易
   - 内存访问模式规律

2. 寄存器架构：
   - 减少栈操作开销
   - 指令数量更少
   - 更接近现代CPU架构

3. 多种寻址模式：
   - A: 目标寄存器（8位）
   - B, C: 源操作数（9位）
   - Bx: 扩展操作数（18位）
   - sBx: 有符号扩展操作数（18位）

4. 指令编码格式：
   31    22    13     5     0
   +------+-----+-----+-----+
   |  Bx  |  C  |  B  |  A  | iABC
   +------+-----+-----+-----+
   |      Bx     |     A     | iABx
   +------+-----+-----+-----+
   |     sBx     |     A     | iAsBx
   +------+-----+-----+-----+
*/

/* 指令格式类型定义 */
typedef enum {
  iABC,   /* A:8 B:9 C:9 */
  iABx,   /* A:8 Bx:18 */
  iAsBx,  /* A:8 sBx:18 (signed) */
  iAx     /* Ax:26 */
} OpMode;

/* 指令操作码完整定义 */
typedef enum {
/*----------------------------------------------------------------------
name		args	description
------------------------------------------------------------------------*/

/* === 数据移动和加载指令 === */
OP_MOVE,/*	A B	R(A) := R(B)					*/
OP_LOADK,/*	A Bx	R(A) := Kst(Bx)				*/
OP_LOADKX,/*	A 	R(A) := Kst(extra arg)			*/
OP_LOADBOOL,/*	A B C	R(A) := (Bool)B; if (C) pc++		*/
OP_LOADNIL,/*	A B	R(A), R(A+1), ..., R(A+B) := nil	*/

/* === Upvalue操作指令 === */
OP_GETUPVAL,/*	A B	R(A) := UpValue[B]			*/
OP_GETTABUP,/*	A B C	R(A) := UpValue[B][RK(C)]		*/
OP_GETTABLE,/*	A B C	R(A) := R(B)[RK(C)]			*/

OP_SETTABUP,/*	A B C	UpValue[A][RK(B)] := RK(C)		*/
OP_SETUPVAL,/*	A B	UpValue[B] := R(A)			*/
OP_SETTABLE,/*	A B C	R(A)[RK(B)] := RK(C)			*/

/* === 表操作指令 === */
OP_NEWTABLE,/*	A B C	R(A) := {} (size = B,C)			*/
OP_SELF,/*	A B C	R(A+1) := R(B); R(A) := R(B)[RK(C)]	*/

/* === 算术运算指令 === */
OP_ADD,/*	A B C	R(A) := RK(B) + RK(C)			*/
OP_SUB,/*	A B C	R(A) := RK(B) - RK(C)			*/
OP_MUL,/*	A B C	R(A) := RK(B) * RK(C)			*/
OP_MOD,/*	A B C	R(A) := RK(B) % RK(C)			*/
OP_POW,/*	A B C	R(A) := RK(B) ^ RK(C)			*/
OP_DIV,/*	A B C	R(A) := RK(B) / RK(C)			*/
OP_IDIV,/*	A B C	R(A) := RK(B) // RK(C)			*/
OP_BAND,/*	A B C	R(A) := RK(B) & RK(C)			*/
OP_BOR,/*	A B C	R(A) := RK(B) | RK(C)			*/
OP_BXOR,/*	A B C	R(A) := RK(B) ~ RK(C)			*/
OP_SHL,/*	A B C	R(A) := RK(B) << RK(C)			*/
OP_SHR,/*	A B C	R(A) := RK(B) >> RK(C)			*/
OP_UNM,/*	A B	R(A) := -R(B)				*/
OP_BNOT,/*	A B	R(A) := ~R(B)				*/
OP_NOT,/*	A B	R(A) := not R(B)			*/
OP_LEN,/*	A B	R(A) := length of R(B)			*/

/* === 字符串连接指令 === */
OP_CONCAT,/*	A B C	R(A) := R(B).. ... ..R(C)		*/

/* === 跳转和比较指令 === */
OP_JMP,/*	A sBx	pc+=sBx; if (A) close all upvalues >= R(A - 1)	*/
OP_EQ,/*	A B C	if ((RK(B) == RK(C)) ~= A) then pc++	*/
OP_LT,/*	A B C	if ((RK(B) <  RK(C)) ~= A) then pc++	*/
OP_LE,/*	A B C	if ((RK(B) <= RK(C)) ~= A) then pc++	*/

/* === 逻辑测试指令 === */
OP_TEST,/*	A C	if not (R(A) <=> C) then pc++		*/
OP_TESTSET,/*	A B C	if (R(B) <=> C) then R(A) := R(B) else pc++	*/

/* === 函数调用指令 === */
OP_CALL,/*	A B C	R(A), ... ,R(A+C-2) := R(A)(R(A+1), ... ,R(A+B-1)) */
OP_TAILCALL,/*	A B C	return R(A)(R(A+1), ... ,R(A+B-1))	*/
OP_RETURN,/*	A B	return R(A), ... ,R(A+B-2)		*/

/* === 循环控制指令 === */
OP_FORLOOP,/*	A sBx	R(A)+=R(A+2); if R(A) <?= R(A+1) then { pc+=sBx; R(A+3)=R(A) }*/
OP_FORPREP,/*	A sBx	R(A)-=R(A+2); pc+=sBx			*/
OP_TFORCALL,/*	A C	R(A+3), ... ,R(A+2+C) := R(A)(R(A+1), R(A+2));	*/
OP_TFORLOOP,/*	A sBx	if R(A+1) ~= nil then { R(A)=R(A+1); pc += sBx }*/

/* === 表列表构造指令 === */
OP_SETLIST,/*	A B C	R(A)[(C-1)*FPF+i] := R(A+i), 1 <= i <= B	*/

/* === 闭包和Upvalue指令 === */
OP_CLOSURE,/*	A Bx	R(A) := closure(KPROTO[Bx])		*/
OP_VARARG,/*	A B	R(A), R(A+1), ..., R(A+B-2) = vararg	*/

/* === 扩展指令 === */
OP_EXTRAARG/*	Ax	extra (larger) argument for previous opcode	*/
} OpCode;

/* 指令字段提取宏 */
#define GETARG_A(i)	(cast(int, ((i)>>POS_A) & MASK1(SIZE_A,0)))
#define GETARG_B(i)	(cast(int, ((i)>>POS_B) & MASK1(SIZE_B,0)))
#define GETARG_C(i)	(cast(int, ((i)>>POS_C) & MASK1(SIZE_C,0)))
#define GETARG_Bx(i)	(cast(int, ((i)>>POS_Bx) & MASK1(SIZE_Bx,0)))
#define GETARG_sBx(i)	(GETARG_Bx(i)-MAXARG_sBx)
#define GETARG_Ax(i)	(cast(int, ((i)>>POS_Ax) & MASK1(SIZE_Ax,0)))

/* 指令构造宏 */
#define CREATE_ABC(o,a,b,c)	((cast(Instruction, o)<<POS_OP) \
			| (cast(Instruction, a)<<POS_A) \
			| (cast(Instruction, b)<<POS_B) \
			| (cast(Instruction, c)<<POS_C))

#define CREATE_ABx(o,a,bc)	((cast(Instruction, o)<<POS_OP) \
			| (cast(Instruction, a)<<POS_A) \
			| (cast(Instruction, bc)<<POS_Bx))

#define CREATE_Ax(o,a)		((cast(Instruction, o)<<POS_OP) \
			| (cast(Instruction, a)<<POS_Ax))
```

#### 寄存器vs常量的寻址机制

```c
// lvm.c - RK寻址机制的实现
/*
RK寻址机制的设计巧思：

1. 统一寻址：
   - RK(x): 如果x < 256，则为寄存器R(x)
   - RK(x): 如果x >= 256，则为常量K(x-256)
   - 一个操作数字段可以表示寄存器或常量

2. 编码优化：
   - 9位操作数字段可表示512个值
   - 256个寄存器 + 256个常量
   - 最大化指令的表达能力

3. 执行效率：
   - 运行时通过简单位测试区分类型
   - 避免额外的指令来区分寄存器和常量
   - 减少指令数量和执行开销
*/

/* RK寻址的实现 */
#define ISK(x)		((x) & BITRK)  /* 测试是否为常量 */
#define INDEXK(r)	((int)(r) & ~BITRK)  /* 获取常量索引 */
#define MAXINDEXRK	(BITRK - 1)  /* 最大RK索引 */
#define RKASK(x)	((x) | BITRK)  /* 标记为常量 */

/* 获取RK值的宏 */
#define RKB(i)	check_exp(getBMode(GET_OPCODE(i)) == OpArgRK, \
		ISK(GETARG_B(i)) ? k+INDEXK(GETARG_B(i)) : base+GETARG_B(i))

#define RKC(i)	check_exp(getCMode(GET_OPCODE(i)) == OpArgRK, \
		ISK(GETARG_C(i)) ? k+INDEXK(GETARG_C(i)) : base+GETARG_C(i))
```

OP_ADD,/*	A B C	R(A) := RK(B) + RK(C)				*/
OP_SUB,/*	A B C	R(A) := RK(B) - RK(C)				*/
OP_MUL,/*	A B C	R(A) := RK(B) * RK(C)				*/
OP_MOD,/*	A B C	R(A) := RK(B) % RK(C)				*/
OP_POW,/*	A B C	R(A) := RK(B) ^ RK(C)				*/
OP_DIV,/*	A B C	R(A) := RK(B) / RK(C)				*/
OP_IDIV,/*	A B C	R(A) := RK(B) // RK(C)				*/
OP_BAND,/*	A B C	R(A) := RK(B) & RK(C)				*/
OP_BOR,/*	A B C	R(A) := RK(B) | RK(C)				*/
OP_BXOR,/*	A B C	R(A) := RK(B) ~ RK(C)				*/
OP_SHL,/*	A B C	R(A) := RK(B) << RK(C)				*/
OP_SHR,/*	A B C	R(A) := RK(B) >> RK(C)				*/
OP_UNM,/*	A B	R(A) := -R(B)					*/
OP_BNOT,/*	A B	R(A) := ~R(B)					*/
OP_NOT,/*	A B	R(A) := not R(B)				*/
OP_LEN,/*	A B	R(A) := length of R(B)				*/

OP_CONCAT,/*	A B C	R(A) := R(B).. ... ..R(C)			*/

OP_JMP,/*	A sBx	pc+=sBx; if (A) close all upvalues >= R(A - 1)	*/
OP_EQ,/*	A B C	if ((RK(B) == RK(C)) ~= A) then pc++		*/
OP_LT,/*	A B C	if ((RK(B) <  RK(C)) ~= A) then pc++		*/
OP_LE,/*	A B C	if ((RK(B) <= RK(C)) ~= A) then pc++		*/

OP_TEST,/*	A C	if not (R(A) <=> C) then pc++			*/
OP_TESTSET,/*	A B C	if (R(B) <=> C) then R(A) := R(B) else pc++	*/

OP_CALL,/*	A B C	R(A), ... ,R(A+C-2) := R(A)(R(A+1), ... ,R(A+B-1)) */
OP_TAILCALL,/*	A B C	return R(A)(R(A+1), ... ,R(A+B-1))		*/
OP_RETURN,/*	A B	return R(A), ... ,R(A+B-2)	(see note)	*/

OP_FORLOOP,/*	A sBx	R(A)+=R(A+2);
			if R(A) <?= R(A+1) then { pc+=sBx; R(A+3)=R(A) }*/
OP_FORPREP,/*	A sBx	R(A)-=R(A+2); pc+=sBx				*/

OP_TFORCALL,/*	A C	R(A+3), ... ,R(A+2+C) := R(A)(R(A+1), R(A+2));	*/
OP_TFORLOOP,/*	A sBx	if R(A+1) ~= nil then { R(A)=R(A+1); pc += sBx }*/

OP_SETLIST,/*	A B C	R(A)[(C-1)*FPF+i] := R(A+i), 1 <= i <= B	*/

OP_CLOSURE,/*	A Bx	R(A) := closure(KPROTO[Bx])			*/

OP_VARARG,/*	A B	R(A), R(A+1), ..., R(A+B-2) = vararg		*/

OP_EXTRAARG/*	Ax	extra (larger) argument for previous opcode	*/
} OpCode;

// 指令参数提取宏
#define GETARG_A(i)	(cast(int, ((i)>>POS_A) & MASK1(SIZE_A,0)))
#define GETARG_B(i)	(cast(int, ((i)>>POS_B) & MASK1(SIZE_B,0)))
#define GETARG_C(i)	(cast(int, ((i)>>POS_C) & MASK1(SIZE_C,0)))
#define GETARG_Bx(i)	(cast(int, ((i)>>POS_Bx) & MASK1(SIZE_Bx,0)))
#define GETARG_Ax(i)	(cast(int, ((i)>>POS_Ax) & MASK1(SIZE_Ax,0)))
#define GETARG_sBx(i)	(GETARG_Bx(i)-MAXARG_sBx)
```

### 词法分析器详解

#### 词法分析的核心机制

**技术概述**：Lua的词法分析器采用有限状态自动机设计，将源代码字符流转换为标记（Token）流。

**通俗理解**：词法分析器就像"文本识别专家"，能够识别代码中的每个"词汇"，就像人类阅读时能区分单词、标点符号和数字一样。

```c
// llex.c - 词法分析器的完整实现
/*
Lua词法分析器的设计特点：

1. 单遍扫描：
   - 从左到右逐字符扫描
   - 不需要回溯
   - 高效的线性时间复杂度

2. 状态驱动：
   - 基于当前字符决定状态转换
   - 支持复杂的词法规则
   - 处理嵌套结构（如长字符串）

3. 错误恢复：
   - 精确的错误位置报告
   - 友好的错误消息
   - 继续分析能力

4. 内存高效：
   - 流式处理，不需要全部加载到内存
   - 缓冲区重用
   - 最小化内存分配
*/

/* 词法分析器状态结构 */
typedef struct LexState {
  int current;                /* 当前字符 */
  int linenumber;             /* 当前行号 */
  int lastline;               /* 最后一个标记的行号 */
  Token t;                    /* 当前标记 */
  Token lookahead;            /* 前瞻标记 */
  struct FuncState *fs;       /* 当前函数状态 */
  struct lua_State *L;        /* Lua状态 */
  ZIO *z;                     /* 输入流 */
  Mbuffer *buff;              /* 标记缓冲区 */
  Table *h;                   /* 避免收集/重用字符串 */
  struct Dyndata *dyd;        /* 动态结构（用于解析） */
  TString *source;            /* 当前源名 */
  TString *envn;              /* 环境变量名 */
} LexState;

/* 标记类型定义 */
typedef enum {
  /* 终端符号，由相应的字符表示 */
  TK_AND = FIRST_RESERVED, TK_BREAK,
  TK_DO, TK_ELSE, TK_ELSEIF, TK_END, TK_FALSE, TK_FOR,
  TK_FUNCTION, TK_GOTO, TK_IF, TK_IN, TK_LOCAL, TK_NIL, TK_NOT,
  TK_OR, TK_REPEAT, TK_RETURN, TK_THEN, TK_TRUE, TK_UNTIL, TK_WHILE,
  /* 其他终端符号 */
  TK_IDIV, TK_CONCAT, TK_DOTS, TK_EQ, TK_GE, TK_LE, TK_NE,
  TK_SHL, TK_SHR,
  TK_DBCOLON, TK_EOS,
  TK_FLT, TK_INT, TK_NAME, TK_STRING
} RESERVED;

/* 词法分析的主函数 */
static int llex (LexState *ls, SemInfo *seminfo) {
  luaZ_resetbuffer(ls->buff);  /* 重置缓冲区 */

  for (;;) {  /* 主循环：跳过空白和注释 */
    switch (ls->current) {

      /* === 空白字符处理 === */
      case '\n': case '\r': {  /* 行结束符 */
        inclinenumber(ls);  /* 增加行号并跳过 */
        break;
      }
      case ' ': case '\f': case '\t': case '\v': {  /* 空白字符 */
        next(ls);  /* 跳过空白字符 */
        break;
      }

      /* === 注释处理 === */
      case '-': {  /* '-' 或 '--' (注释) */
        next(ls);
        if (ls->current != '-') return '-';  /* 单独的减号 */

        /* 处理注释 */
        next(ls);
        if (ls->current == '[') {  /* 长注释？ */
          int sep = skip_sep(ls);  /* 检查分隔符 */
          luaZ_resetbuffer(ls->buff);  /* 清理缓冲区 */
          if (sep >= 0) {
            read_long_string(ls, NULL, sep);  /* 跳过长注释 */
            luaZ_resetbuffer(ls->buff);
            break;
          }
        }
        /* 短注释：跳到行尾 */
        while (!currIsNewline(ls) && ls->current != EOZ)
          next(ls);
        break;
      }

      /* === 字符串字面量 === */
      case '[': {  /* 长字符串或简单'[' */
        int sep = skip_sep(ls);
        if (sep >= 0) {
          read_long_string(ls, seminfo, sep);  /* 读取长字符串 */
          return TK_STRING;
        }
        else if (sep != -1)  /* '[=...' 缺少第二个'[' */
          lexerror(ls, "invalid long string delimiter", TK_STRING);
        return '[';  /* 普通的左方括号 */
      }
      case '"': case '\'': {  /* 短字符串 */
        read_string(ls, ls->current, seminfo);
        return TK_STRING;
      }

      /* === 运算符和分隔符 === */
      case '=': {
        next(ls);
        if (check_next1(ls, '=')) return TK_EQ;  /* == */
        else return '=';  /* = */
      }
      case '<': {
        next(ls);
        if (check_next1(ls, '=')) return TK_LE;      /* <= */
        else if (check_next1(ls, '<')) return TK_SHL; /* << */
        else return '<';  /* < */
      }
      case '>': {
        next(ls);
        if (check_next1(ls, '=')) return TK_GE;      /* >= */
        else if (check_next1(ls, '>')) return TK_SHR; /* >> */
        else return '>';  /* > */
      }
      case '/': {
        next(ls);
        if (check_next1(ls, '/')) return TK_IDIV;  /* // */
        else return '/';  /* / */
      }
      case '~': {
        next(ls);
        if (check_next1(ls, '=')) return TK_NE;  /* ~= */
        else return '~';  /* ~ */
      }
      case ':': {
        next(ls);
        if (check_next1(ls, ':')) return TK_DBCOLON;  /* :: */
        else return ':';  /* : */
      }
      case '.': {  /* '.', '..', '...', 或数字 */
        save_and_next(ls);
        if (check_next1(ls, '.')) {
          if (check_next1(ls, '.'))
            return TK_DOTS;   /* ... */
          else return TK_CONCAT;  /* .. */
        }
        else if (!lisdigit(ls->current)) return '.';  /* . */
        else return read_numeral(ls, seminfo);  /* 小数 */
      }

      /* === 数字字面量 === */
      case '0': case '1': case '2': case '3': case '4':
      case '5': case '6': case '7': case '8': case '9': {
        return read_numeral(ls, seminfo);
      }

      /* === 文件结束 === */
      case EOZ: {
        return TK_EOS;  /* 文件结束标记 */
      }

      /* === 标识符和关键字 === */
      default: {
        if (lislalpha(ls->current)) {  /* 标识符或保留字？ */
          TString *ts;
          do {
            save_and_next(ls);  /* 保存字符并前进 */
          } while (lislalnum(ls->current));  /* 读取完整标识符 */

          ts = luaX_newstring(ls, luaZ_buffer(ls->buff),
                                  luaZ_bufflen(ls->buff));
          seminfo->ts = ts;

          /* 检查是否为保留字 */
          if (isreserved(ts))  /* 保留字？ */
            return ts->extra - 1 + FIRST_RESERVED;
          else {
            return TK_NAME;  /* 普通标识符 */
          }
        }
        else {  /* 单字符标记（运算符、分隔符等） */
          int c = ls->current;
          next(ls);
          return c;  /* 返回字符本身作为标记 */
        }
      }
    }
  }
}
```

#### 数字字面量的解析

```c
// llex.c - 数字解析的精细实现
/*
Lua数字解析的特点：

1. 多进制支持：
   - 十进制：123, 3.14159
   - 十六进制：0x1A, 0x1.Ap+3
   - 科学计数法：1e10, 3.14e-2

2. 类型推断：
   - 整数：没有小数点和指数
   - 浮点数：有小数点或指数
   - 自动选择最合适的表示

3. 精度处理：
   - 整数范围检查
   - 浮点数精度保持
   - 溢出检测

4. 错误处理：
   - 格式错误检测
   - 精确的错误位置
   - 友好的错误消息
*/

static int read_numeral (LexState *ls, SemInfo *seminfo) {
  TValue obj;
  const char *expo = "Ee";  /* 十进制指数标记 */
  int first = ls->current;

  lua_assert(lisdigit(ls->current));
  save_and_next(ls);  /* 保存第一个数字 */

  /* 检查十六进制前缀 */
  if (first == '0' && check_next2(ls, "xX"))  /* 十六进制？ */
    expo = "Pp";  /* 十六进制指数标记 */

  /* 读取数字部分 */
  for (;;) {
    if (check_next2(ls, expo))  /* 指数部分？ */
      check_next2(ls, "-+");  /* 可选的符号 */
    if (lisxdigit(ls->current))  /* 十六进制数字 */
      save_and_next(ls);
    else if (ls->current == '.')  /* 小数点 */
      save_and_next(ls);
    else break;
  }

  /* 检查数字后是否跟着字母（错误情况） */
  if (lislalpha(ls->current))
    save_and_next(ls);  /* 保存错误字符用于错误报告 */

  /* 转换字符串为数字 */
  if (luaO_str2num(luaZ_buffer(ls->buff), &obj) == 0)  /* 格式错误？ */
    lexerror(ls, "malformed number", TK_FLT);

  /* 根据数字类型设置语义信息 */
  if (ttisinteger(&obj)) {
    seminfo->i = ivalue(&obj);
    return TK_INT;  /* 整数标记 */
  }
  else {
    lua_assert(ttisfloat(&obj));
    seminfo->r = fltvalue(&obj);
    return TK_FLT;  /* 浮点数标记 */
  }
}
```
      case ':': {
        next(ls);
        if (check_next1(ls, ':')) return TK_DBCOLON;
        else return ':';
      }
      case '"': case '\'': {  /* 短字符串 */
        read_string(ls, ls->current, seminfo);
        return TK_STRING;
      }
      case '.': {  /* '.', '..', '...', 或数字 */
        save_and_next(ls);
        if (check_next1(ls, '.')) {
          if (check_next1(ls, '.'))
            return TK_DOTS;   /* '...' */
          else return TK_CONCAT;   /* '..' */
        }
        else if (!lisdigit(ls->current)) return '.';
        else return read_numeral(ls, seminfo);
      }
      case '0': case '1': case '2': case '3': case '4':
      case '5': case '6': case '7': case '8': case '9': {
        return read_numeral(ls, seminfo);
      }
      case EOZ: {
        return TK_EOS;
      }
      default: {
        if (lislalpha(ls->current)) {  /* 标识符或保留字？ */
          TString *ts;
          do {
            save_and_next(ls);
          } while (lislalnum(ls->current));
          ts = luaX_newstring(ls, luaZ_buffer(ls->buff),
                                  luaZ_bufflen(ls->buff));
          seminfo->ts = ts;
          if (isreserved(ts))  /* 保留字？ */
            return ts->extra - 1 + FIRST_RESERVED;
          else {
            return TK_NAME;
          }
        }
        else {  /* 单字符标记(+ - / ...) */
          int c = ls->current;
          next(ls);
          return c;
        }
      }
    }
  }
}
```

### 语法分析器

```c
// lparser.c - 表达式解析
static void expr (LexState *ls, expdesc *v) {
  subexpr(ls, v, 0);
}

static BinOpr subexpr (LexState *ls, expdesc *v, int limit) {
  BinOpr op;
  UnOpr uop;
  enterlevel(ls);
  uop = getunopr(ls->t.token);
  if (uop != OPR_NOUNOPR) {
    int line = ls->linenumber;
    luaX_next(ls);
    subexpr(ls, v, UNARY_PRIORITY);
    luaK_prefix(ls->fs, uop, v, line);
  }
  else simpleexp(ls, v);
  /* 展开二元运算符 */
  op = getbinopr(ls->t.token);
  while (op != OPR_NOBINOPR && priority[op].left > limit) {
    expdesc v2;
    BinOpr nextop;
    int line = ls->linenumber;
    luaX_next(ls);
    /* 读取子表达式，优先级更高 */
    nextop = subexpr(ls, &v2, priority[op].right);
    luaK_infix(ls->fs, op, v);
    luaK_posfix(ls->fs, op, v, &v2, line);
    op = nextop;
  }
  leavelevel(ls);
  return op;  /* 返回第一个未处理的运算符 */
}
```

### 代码生成器

```c
// lcode.c - 指令生成
int luaK_code (FuncState *fs, Instruction i) {
  Proto *f = fs->f;
  dischargejpc(fs);  /* 'pc'将改变 */
  /* 将新指令放在数组中 */
  luaM_growvector(fs->ls->L, f->code, fs->pc, f->sizecode, Instruction,
                  MAX_INT, "opcodes");
  f->code[fs->pc] = i;
  /* 保存对应的行信息 */
  luaM_growvector(fs->ls->L, f->lineinfo, fs->pc, f->sizelineinfo, int,
                  MAX_INT, "opcodes");
  f->lineinfo[fs->pc] = fs->ls->lastline;
  return fs->pc++;
}

// 生成二元运算指令
void luaK_posfix (FuncState *fs, BinOpr op,
                  expdesc *e1, expdesc *e2, int line) {
  switch (op) {
    case OPR_AND: {
      lua_assert(e1->t == NO_JUMP);  /* 列表必须关闭 */
      luaK_dischargevars(fs, e2);
      luaK_concat(fs, &e2->f, e1->f);
      *e1 = *e2;
      break;
    }
    case OPR_OR: {
      lua_assert(e1->f == NO_JUMP);  /* 列表必须关闭 */
      luaK_dischargevars(fs, e2);
      luaK_concat(fs, &e2->t, e1->t);
      *e1 = *e2;
      break;
    }
    case OPR_CONCAT: {
      luaK_exp2nextreg(fs, e2);  /* 操作数必须在'栈'中 */
      codearith(fs, OP_CONCAT, e1, e2, line);
      break;
    }
    case OPR_ADD: case OPR_SUB: case OPR_MUL: case OPR_DIV:
    case OPR_IDIV: case OPR_MOD: case OPR_POW:
    case OPR_BAND: case OPR_BOR: case OPR_BXOR:
    case OPR_SHL: case OPR_SHR: {
      codearith(fs, cast(OpCode, (op - OPR_ADD) + OP_ADD), e1, e2, line);
      break;
    }
    case OPR_EQ: case OPR_LT: case OPR_LE: {
      codecomp(fs, cast(OpCode, (op - OPR_EQ) + OP_EQ), 1, e1, e2);
      break;
    }
    case OPR_NE: case OPR_GT: case OPR_GE: {
      codecomp(fs, cast(OpCode, (op - OPR_NE) + OP_EQ), 0, e1, e2);
      break;
    }
    default: lua_assert(0);
  }
}
```

### 函数原型结构

```c
// lobject.h - 函数原型定义
typedef struct Proto {
  CommonHeader;
  lu_byte numparams;  /* 固定参数数量 */
  lu_byte is_vararg;  /* 2: 声明为vararg; 1: 使用vararg */
  lu_byte maxstacksize;  /* 此函数使用的寄存器数量 */
  int sizeupvalues;  /* upvalue数量 */
  int sizek;  /* 'k'的大小 */
  int sizecode;  /* 'code'的大小 */
  int sizelineinfo;  /* 'lineinfo'的大小 */
  int sizep;  /* 'p'的大小 */
  int sizelocvars;  /* 'locvars'的大小 */
  int linedefined;  /* 调试信息 */
  int lastlinedefined;  /* 调试信息 */
  TValue *k;  /* 函数使用的常量 */
  Instruction *code;  /* 操作码 */
  struct Proto **p;  /* 函数内定义的函数 */
  int *lineinfo;  /* 每个指令的行信息映射 */
  LocVar *locvars;  /* 局部变量信息(调试信息) */
  Upvaldesc *upvalues;  /* upvalue信息 */
  struct LClosure *cache;  /* 最后创建的闭包，带有此原型 */
  TString  *source;  /* 用于调试信息 */
  GCObject *gclist;
} Proto;
```

## 面试官关注要点

1. **编译流程**：从源码到字节码的完整过程
2. **指令设计**：32位指令格式的优势和限制
3. **优化策略**：常量折叠、跳转优化等
4. **调试信息**：行号映射、局部变量信息

## 常见后续问题详解

### 1. Lua为什么选择基于寄存器的虚拟机架构？

**技术原理**：
Lua选择基于寄存器的虚拟机架构是经过深思熟虑的设计决策，主要考虑执行效率和指令简洁性。

**寄存器架构vs栈架构的详细对比**：
```c
// 寄存器架构vs栈架构的设计对比
/*
寄存器架构的优势：

1. 指令数量更少：
   - 栈架构：LOAD a; LOAD b; ADD; STORE c (4条指令)
   - 寄存器架构：ADD c, a, b (1条指令)
   - 减少指令解码和执行开销

2. 内存访问更少：
   - 栈架构需要频繁的栈操作
   - 寄存器架构直接操作寄存器
   - 减少内存带宽需求

3. 更接近现代CPU：
   - 现代CPU都是寄存器架构
   - 更容易进行JIT编译优化
   - 指令映射更直接

4. 编译器优化空间更大：
   - 寄存器分配优化
   - 死代码消除
   - 常量传播
*/

/* 寄存器架构的实际效果演示 */
static void demonstrate_register_vs_stack() {
  /*
  示例：计算 (a + b) * (c - d)

  栈架构需要的指令：
  1. LOAD a      ; 栈: [a]
  2. LOAD b      ; 栈: [a, b]
  3. ADD         ; 栈: [a+b]
  4. LOAD c      ; 栈: [a+b, c]
  5. LOAD d      ; 栈: [a+b, c, d]
  6. SUB         ; 栈: [a+b, c-d]
  7. MUL         ; 栈: [(a+b)*(c-d)]
  8. STORE result; 栈: []
  总计：8条指令

  寄存器架构需要的指令：
  1. ADD R1, Ra, Rb    ; R1 = a + b
  2. SUB R2, Rc, Rd    ; R2 = c - d
  3. MUL Rresult, R1, R2 ; result = R1 * R2
  总计：3条指令

  性能提升：
  - 指令数量减少62.5%
  - 内存访问减少约50%
  - 执行时间减少40-60%
  */
}

/* 寄存器分配的优化策略 */
static void register_allocation_optimization() {
  /*
  Lua寄存器分配的智能策略：

  1. 局部变量优先：
     - 局部变量直接分配寄存器
     - 减少内存访问
     - 提高访问速度

  2. 临时值管理：
     - 表达式计算的中间结果
     - 及时释放不需要的寄存器
     - 最小化寄存器使用

  3. 生命周期分析：
     - 分析变量的使用范围
     - 重用不冲突的寄存器
     - 优化寄存器分配

  4. 函数调用优化：
     - 参数直接传递到目标寄存器
     - 减少数据移动
     - 优化调用约定
  */
}
```

### 2. 字节码的优化策略有哪些？

**技术原理**：
Lua在字节码生成过程中实施多种优化策略，在编译速度和执行效率之间取得平衡。

**编译时优化策略详解**：
```c
// lcode.c - 字节码优化策略的实现
/*
Lua字节码优化的层次结构：

1. 词法层优化：
   - 数字字面量的预处理
   - 字符串驻留
   - 标识符规范化

2. 语法层优化：
   - 常量表达式折叠
   - 死代码消除
   - 控制流简化

3. 代码生成优化：
   - 窥孔优化
   - 跳转链合并
   - 寄存器重用

4. 指令级优化：
   - 指令合并
   - 寻址模式优化
   - 立即数优化
*/

/* 常量折叠优化的实现 */
static int constfolding (FuncState *fs, int op, expdesc *e1, expdesc *e2) {
  TValue v1, v2, res;

  /* 检查是否为可折叠的常量表达式 */
  if (!tonumeral(e1, &v1) || !tonumeral(e2, &v2) || !validop(op, &v1, &v2))
    return 0;  /* 不能折叠 */

  /* 编译时计算结果 */
  luaO_arith(fs->ls->L, op, &v1, &v2, &res);

  if (ttisinteger(&res)) {
    e1->k = VKINT;
    e1->u.ival = ivalue(&res);
  }
  else {
    lua_Number n = fltvalue(&res);
    if (luai_numisnan(n) || n == 0.0)
      return 0;  /* 避免特殊值的折叠 */
    e1->k = VKFLT;
    e1->u.nval = n;
  }

  return 1;  /* 成功折叠 */
}

/* 跳转优化的实现 */
static void optimize_jumps(FuncState *fs) {
  /*
  跳转优化策略：

  1. 跳转链合并：
     - 将多个连续跳转合并为一个
     - 减少跳转指令数量
     - 提高分支预测效率

  2. 条件跳转优化：
     - 优化布尔表达式的跳转
     - 短路求值的实现
     - 减少不必要的比较

  3. 死代码消除：
     - 移除永远不会执行的代码
     - 简化控制流图
     - 减少代码大小

  示例优化：
  原始代码：
    if true then
      print("always")
    else
      print("never")  -- 死代码
    end

  优化后：
    print("always")
  */
}

/* 窥孔优化的实现 */
static void peephole_optimization(FuncState *fs) {
  /*
  窥孔优化模式：

  1. 冗余MOVE消除：
     MOVE R1, R2
     MOVE R3, R1  =>  MOVE R3, R2

  2. 常量加载优化：
     LOADK R1, K1
     ADD R2, R1, K2  =>  ADD R2, K1, K2 (如果可能)

  3. 跳转目标优化：
     JMP L1
     L1: JMP L2  =>  JMP L2

  4. 布尔值优化：
     LOADBOOL R1, 1, 0
     TEST R1, 0  =>  JMP (无条件跳转)
  */
}
```

### 3. 如何理解Lua的单遍编译过程？

**技术原理**：
Lua采用单遍编译策略，在语法分析的同时直接生成字节码，这种设计简化了编译器结构并提高了编译速度。

**单遍编译的实现机制**：
```c
// lparser.c - 单遍编译的实现
/*
单遍编译的设计优势：

1. 内存效率：
   - 不需要构建完整的AST
   - 减少内存分配和回收
   - 适合嵌入式环境

2. 编译速度：
   - 避免多次遍历源代码
   - 减少中间表示的转换
   - 快速的编译过程

3. 实现简洁：
   - 语法分析和代码生成紧密结合
   - 减少编译器的复杂性
   - 易于维护和调试

4. 错误处理：
   - 及时发现语法错误
   - 精确的错误位置报告
   - 友好的错误消息
*/

/* 单遍编译的核心流程 */
static void single_pass_compilation_flow() {
  /*
  单遍编译的处理流程：

  1. 词法分析 -> 立即处理标记
  2. 语法分析 -> 立即生成代码
  3. 语义分析 -> 嵌入在语法分析中
  4. 代码优化 -> 局部优化，即时应用

  示例：解析赋值语句 "a = b + c"

  步骤1：词法分析识别 "a", "=", "b", "+", "c"
  步骤2：语法分析识别赋值模式
  步骤3：立即生成指令：
    ADD R_temp, R_b, R_c
    MOVE R_a, R_temp
  步骤4：应用窥孔优化（如果可能）

  整个过程在一次遍历中完成，无需中间表示。
  */
}

/* 前向引用的处理 */
static void handle_forward_references(FuncState *fs) {
  /*
  单遍编译中前向引用的挑战：

  1. 函数前向声明：
     - 使用占位符处理
     - 后续填充实际地址
     - 维护引用列表

  2. 跳转目标：
     - 使用跳转链表
     - 延迟地址解析
     - 回填机制

  3. 局部变量作用域：
     - 作用域栈管理
     - 变量生命周期跟踪
     - 寄存器分配优化

  解决方案：
  - 使用待定列表（pending list）
  - 两阶段地址解析
  - 智能的回填算法
  */
}
```

### 4. 字节码指令的设计考虑了哪些因素？

**技术原理**：
Lua字节码指令的设计综合考虑了执行效率、编码密度、解码复杂度和扩展性等多个因素。

**指令设计的综合考虑**：
```c
// lopcodes.h - 指令设计的考虑因素
/*
字节码指令设计的关键因素：

1. 执行频率：
   - 常用指令优化编码
   - 减少解码开销
   - 提高执行效率

2. 操作数类型：
   - 寄存器vs常量的统一寻址
   - 立即数的支持
   - 地址模式的选择

3. 指令长度：
   - 固定32位长度
   - 简化指令解码
   - 便于跳转计算

4. 扩展性：
   - 预留操作码空间
   - 支持未来扩展
   - 版本兼容性

5. 调试支持：
   - 行号信息保留
   - 变量名映射
   - 调试器集成
*/

/* 指令编码效率的分析 */
static void instruction_encoding_efficiency() {
  /*
  指令编码效率的优化：

  1. 操作码分配：
     - 常用指令使用较小的操作码
     - 减少指令解码的分支
     - 提高指令缓存效率

  2. 操作数编码：
     - RK寻址模式的创新
     - 一个字段表示寄存器或常量
     - 最大化指令的表达能力

  3. 特殊指令优化：
     - LOADBOOL的条件跳转集成
     - SELF指令的方法调用优化
     - SETLIST的批量赋值优化

  4. 指令组合：
     - 相关操作的指令组合
     - 减少指令间的依赖
     - 提高流水线效率
  */
}

/* 跨平台兼容性的保证 */
static void cross_platform_compatibility() {
  /*
  跨平台字节码的设计：

  1. 字节序无关：
     - 使用标准的字节序
     - 序列化时统一格式
     - 反序列化时自动转换

  2. 数据类型统一：
     - 标准的数值表示
     - 字符串编码统一
     - 指针大小无关

  3. 对齐要求：
     - 避免严格的对齐要求
     - 使用字节流格式
     - 支持不同架构

  4. 版本兼容：
     - 版本号标识
     - 向后兼容机制
     - 优雅的降级处理
  */
}
```

### 5. Lua字节码与其他语言字节码的区别是什么？

**技术原理**：
Lua字节码在设计理念、架构选择和优化策略上与其他语言的字节码有显著区别。

**与其他语言字节码的详细对比**：
```c
// 不同语言字节码的对比分析
/*
Lua vs Java字节码：

1. 虚拟机架构：
   - Lua：基于寄存器
   - Java：基于栈
   - 影响：Lua指令更少，执行更快

2. 类型系统：
   - Lua：动态类型，运行时检查
   - Java：静态类型，编译时检查
   - 影响：Lua更灵活，Java更安全

3. 内存管理：
   - Lua：垃圾回收，简单标记清除
   - Java：复杂的分代GC
   - 影响：Lua更轻量，Java更优化

4. 指令复杂度：
   - Lua：简单指令，固定格式
   - Java：复杂指令，变长格式
   - 影响：Lua解码快，Java功能丰富
*/

static void lua_vs_python_bytecode() {
  /*
  Lua vs Python字节码：

  1. 执行模型：
     - Lua：寄存器机器
     - Python：栈机器
     - 性能：Lua通常更快

  2. 优化程度：
     - Lua：编译时优化
     - Python：运行时优化（PyPy）
     - 策略：不同的优化时机

  3. 可移植性：
     - Lua：高度可移植
     - Python：平台相关性更强
     - 应用：Lua更适合嵌入

  4. 调试支持：
     - Lua：基本调试信息
     - Python：丰富的调试功能
     - 权衡：简洁vs功能
  */
}

static void lua_vs_javascript_v8() {
  /*
  Lua vs JavaScript V8：

  1. 编译策略：
     - Lua：解释执行字节码
     - V8：即时编译到机器码
     - 性能：V8峰值更高，Lua启动更快

  2. 内存使用：
     - Lua：内存占用小
     - V8：内存占用大
     - 适用：不同的应用场景

  3. 复杂度：
     - Lua：简单直接
     - V8：高度复杂
     - 维护：Lua更易维护

  4. 生态系统：
     - Lua：专注核心功能
     - V8：丰富的运行时
     - 定位：不同的设计目标
  */
}

/* Lua字节码的独特优势 */
static void lua_bytecode_advantages() {
  /*
  Lua字节码的独特优势：

  1. 简洁性：
     - 指令集小而精
     - 易于理解和实现
     - 减少维护成本

  2. 效率：
     - 寄存器架构的性能优势
     - 编译时优化
     - 快速的执行速度

  3. 可嵌入性：
     - 小巧的虚拟机
     - 最小的依赖
     - 易于集成

  4. 可移植性：
     - 纯C实现
     - 跨平台兼容
     - 标准化的字节码格式

  5. 调试友好：
     - 保留源码信息
     - 清晰的指令映射
     - 支持调试器
  */
}
```

## 实践应用指南

### 1. 字节码分析和调试技巧

**字节码反汇编工具**：
```lua
-- 字节码分析的实用工具

-- 1. 简单的字节码查看器
local function dump_bytecode(func)
  if type(func) ~= "function" then
    error("Expected function, got " .. type(func))
  end

  print("=== 字节码分析 ===")
  print("函数信息:")

  -- 使用debug库获取函数信息
  local info = debug.getinfo(func, "S")
  print("  源文件:", info.source)
  print("  定义行:", info.linedefined, "-", info.lastlinedefined)

  -- 分析upvalue
  local upvalue_count = 0
  while debug.getupvalue(func, upvalue_count + 1) do
    upvalue_count = upvalue_count + 1
  end
  print("  Upvalue数量:", upvalue_count)

  -- 分析局部变量（需要在函数内部调用）
  print("  参数信息:", info.nparams or "未知")
  print("  是否可变参数:", info.isvararg and "是" or "否")

  print("\n注意：详细的字节码查看需要使用luac -l命令")
end

-- 2. 性能分析工具
local function profile_compilation()
  local start_time = os.clock()
  local test_code = [[
    local function fibonacci(n)
      if n <= 1 then
        return n
      else
        return fibonacci(n-1) + fibonacci(n-2)
      end
    end
    return fibonacci
  ]]

  -- 编译代码
  local func, err = load(test_code)
  local compile_time = os.clock() - start_time

  if func then
    print("编译成功")
    print("编译时间:", string.format("%.6f秒", compile_time))

    -- 测试执行
    start_time = os.clock()
    local fib = func()
    local result = fib(10)
    local exec_time = os.clock() - start_time

    print("执行时间:", string.format("%.6f秒", exec_time))
    print("结果:", result)
  else
    print("编译失败:", err)
  end
end

-- 3. 字节码优化验证
local function verify_optimizations()
  -- 测试常量折叠
  local code1 = "return 2 + 3 * 4"
  local code2 = "return 14"

  local func1 = load(code1)
  local func2 = load(code2)

  print("常量折叠测试:")
  print("  原始表达式:", code1)
  print("  优化后应该等价于:", code2)
  print("  结果1:", func1())
  print("  结果2:", func2())
  print("  优化验证:", func1() == func2() and "成功" or "失败")
end
```

### 2. 性能优化技巧

**编写字节码友好的Lua代码**：
```lua
-- 字节码性能优化的编程技巧

-- 1. 局部变量优化
local function optimize_local_variables()
  -- 好的做法：使用局部变量
  local function good_practice()
    local math_sin = math.sin  -- 缓存全局函数
    local result = 0
    for i = 1, 1000 do
      result = result + math_sin(i)  -- 快速的局部变量访问
    end
    return result
  end

  -- 不好的做法：频繁访问全局变量
  local function bad_practice()
    local result = 0
    for i = 1, 1000 do
      result = result + math.sin(i)  -- 每次都查找全局变量
    end
    return result
  end

  -- 性能测试
  local start_time = os.clock()
  good_practice()
  local good_time = os.clock() - start_time

  start_time = os.clock()
  bad_practice()
  local bad_time = os.clock() - start_time

  print("局部变量优化效果:")
  print("  优化版本:", string.format("%.6f秒", good_time))
  print("  未优化版本:", string.format("%.6f秒", bad_time))
  print("  性能提升:", string.format("%.1f倍", bad_time / good_time))
end

-- 2. 表访问优化
local function optimize_table_access()
  local data = {x = 1, y = 2, z = 3}

  -- 好的做法：缓存表字段
  local function good_table_access()
    local x, y, z = data.x, data.y, data.z  -- 一次性提取
    local result = 0
    for i = 1, 1000 do
      result = result + x + y + z
    end
    return result
  end

  -- 不好的做法：重复表查找
  local function bad_table_access()
    local result = 0
    for i = 1, 1000 do
      result = result + data.x + data.y + data.z  -- 每次都查找表
    end
    return result
  end

  print("表访问优化测试:")
  print("  优化版本生成更少的GETTABLE指令")
  print("  未优化版本每次循环都有表查找开销")
end

-- 3. 函数调用优化
local function optimize_function_calls()
  -- 尾调用优化
  local function tail_call_optimized(n, acc)
    if n <= 0 then
      return acc or 0
    end
    return tail_call_optimized(n - 1, (acc or 0) + n)  -- 尾调用
  end

  -- 非尾调用版本
  local function non_tail_call(n)
    if n <= 0 then
      return 0
    end
    return n + non_tail_call(n - 1)  -- 非尾调用
  end

  print("尾调用优化:")
  print("  尾调用版本使用TAILCALL指令，不增加栈深度")
  print("  非尾调用版本使用CALL指令，可能导致栈溢出")

  -- 测试大数值（注意：可能导致栈溢出）
  local safe_n = 100
  print("  尾调用结果:", tail_call_optimized(safe_n))
  print("  非尾调用结果:", non_tail_call(safe_n))
end
```

### 3. 字节码生成的调试和分析

**深度调试技巧**：
```lua
-- 字节码调试的高级技巧

-- 1. 函数复杂度分析
local function analyze_function_complexity(func)
  if type(func) ~= "function" then
    error("Expected function")
  end

  local info = debug.getinfo(func, "S")
  print("函数复杂度分析:")
  print("  源文件:", info.source)
  print("  代码行数:", (info.lastlinedefined or 0) - (info.linedefined or 0) + 1)

  -- 分析upvalue复杂度
  local upvalue_count = 0
  local upvalue_names = {}
  while true do
    local name = debug.getupvalue(func, upvalue_count + 1)
    if not name then break end
    upvalue_count = upvalue_count + 1
    table.insert(upvalue_names, name)
  end

  print("  Upvalue数量:", upvalue_count)
  if upvalue_count > 0 then
    print("  Upvalue列表:", table.concat(upvalue_names, ", "))
  end

  -- 估算字节码复杂度
  local estimated_instructions = (info.lastlinedefined - info.linedefined) * 2
  print("  估算指令数:", estimated_instructions, "(粗略估计)")

  if upvalue_count > 10 then
    print("  警告：Upvalue数量较多，可能影响性能")
  end

  if estimated_instructions > 1000 then
    print("  建议：考虑拆分大函数以提高可维护性")
  end
end

-- 2. 编译错误诊断
local function diagnose_compilation_errors()
  local test_cases = {
    {
      name = "语法错误",
      code = "local a = 1 + ",
      expected_error = "语法错误"
    },
    {
      name = "未定义变量",
      code = "return undefined_variable",
      expected_error = "可能的运行时错误"
    },
    {
      name = "类型错误",
      code = "return 'string' + 123",
      expected_error = "可能的类型错误"
    }
  }

  print("编译错误诊断:")
  for _, test in ipairs(test_cases) do
    print("\n测试:", test.name)
    print("代码:", test.code)

    local func, err = load(test.code)
    if func then
      print("编译:", "成功")
      -- 尝试执行以检测运行时错误
      local ok, result = pcall(func)
      if ok then
        print("执行:", "成功，结果:", result)
      else
        print("执行:", "失败，错误:", result)
      end
    else
      print("编译:", "失败，错误:", err)
    end
  end
end

-- 3. 性能基准测试
local function benchmark_bytecode_performance()
  local test_functions = {
    {
      name = "简单算术",
      func = function() return 1 + 2 * 3 end
    },
    {
      name = "局部变量操作",
      func = function()
        local a, b, c = 1, 2, 3
        return a + b * c
      end
    },
    {
      name = "表操作",
      func = function()
        local t = {x = 1, y = 2}
        return t.x + t.y
      end
    },
    {
      name = "函数调用",
      func = function()
        local function add(a, b) return a + b end
        return add(1, 2)
      end
    }
  }

  print("字节码性能基准测试:")
  for _, test in ipairs(test_functions) do
    local iterations = 100000
    local start_time = os.clock()

    for i = 1, iterations do
      test.func()
    end

    local elapsed = os.clock() - start_time
    local per_call = elapsed / iterations * 1000000  -- 微秒

    print(string.format("  %s: %.6f秒 (%.2f微秒/调用)",
          test.name, elapsed, per_call))
  end
end
```

## 相关源文件

### 核心文件
- `llex.c/llex.h` - 词法分析器实现和标记定义
- `lparser.c/lparser.h` - 语法分析器和递归下降解析
- `lcode.c/lcode.h` - 代码生成器和指令优化

### 支撑文件
- `lopcodes.c/lopcodes.h` - 指令集定义和操作码
- `lundump.c/lundump.h` - 字节码序列化和反序列化
- `ldump.c` - 字节码转储和保存

### 相关组件
- `lvm.c` - 虚拟机执行引擎和指令解释
- `lfunc.c` - 函数对象和原型管理
- `lstring.c` - 字符串处理和常量管理

### 工具和辅助
- `luac.c` - Lua编译器工具
- `ldo.c` - 执行控制和错误处理
- `lgc.c` - 垃圾回收和内存管理

理解这些文件的关系和作用，有助于深入掌握Lua字节码生成的完整流程和优化机制。字节码生成作为连接高级语言和虚拟机执行的桥梁，其设计思想和实现技巧对于理解现代编程语言的编译技术具有重要参考价值。
