# ğŸ“ Lua 5.1.5 å‡½æ•°è°ƒç”¨æœºåˆ¶å®Œå…¨è§£æ

> **æŠ€æœ¯å±‚çº§æ–‡æ¡£** - æ·±å…¥å‰–æ Lua å‡½æ•°è°ƒç”¨çš„å®Œæ•´æµç¨‹å’Œå®ç°ç»†èŠ‚

---

## ğŸ“‘ å¯¼èˆªç›®å½•

<details open>
<summary><b>ç‚¹å‡»å±•å¼€/æŠ˜å ç›®å½•</b></summary>

### æ ¸å¿ƒç« èŠ‚
1. [æ¦‚è¿°](#1-æ¦‚è¿°)
2. [è°ƒç”¨æµç¨‹æ€»è§ˆ](#2-è°ƒç”¨æµç¨‹æ€»è§ˆ)
3. [OP_CALL æŒ‡ä»¤è¯¦è§£](#3-op_call-æŒ‡ä»¤è¯¦è§£)
4. [luaD_precall å‰ç½®å¤„ç†](#4-luad_precall-å‰ç½®å¤„ç†)
5. [Luaå‡½æ•°è°ƒç”¨](#5-luaå‡½æ•°è°ƒç”¨)
6. [Cå‡½æ•°è°ƒç”¨](#6-cå‡½æ•°è°ƒç”¨)
7. [luaD_poscall åç½®å¤„ç†](#7-luad_poscall-åç½®å¤„ç†)
8. [å°¾è°ƒç”¨ä¼˜åŒ–](#8-å°¾è°ƒç”¨ä¼˜åŒ–)
9. [å¯å˜å‚æ•°å¤„ç†](#9-å¯å˜å‚æ•°å¤„ç†)
10. [å®æˆ˜æ¡ˆä¾‹åˆ†æ](#10-å®æˆ˜æ¡ˆä¾‹åˆ†æ)

### é™„å½•
- [å…³é”®æ•°æ®ç»“æ„](#å…³é”®æ•°æ®ç»“æ„)
- [è°ƒç”¨æ ˆç¤ºæ„å›¾](#è°ƒç”¨æ ˆç¤ºæ„å›¾)
- [æ€§èƒ½åˆ†æ](#æ€§èƒ½åˆ†æ)
- [ç›¸å…³æ–‡æ¡£](#ç›¸å…³æ–‡æ¡£)

</details>

---

## 1. æ¦‚è¿°

### 1.1 å‡½æ•°è°ƒç”¨çš„é‡è¦æ€§

å‡½æ•°è°ƒç”¨æ˜¯ç¼–ç¨‹è¯­è¨€çš„æ ¸å¿ƒæœºåˆ¶ä¹‹ä¸€ï¼ŒLua çš„å‡½æ•°è°ƒç”¨ç³»ç»Ÿå…·æœ‰ä»¥ä¸‹ç‰¹ç‚¹ï¼š

- **ç»Ÿä¸€çš„è°ƒç”¨çº¦å®š**ï¼šLua å‡½æ•°å’Œ C å‡½æ•°ä½¿ç”¨ç›¸åŒçš„è°ƒç”¨æœºåˆ¶
- **é€æ˜çš„äº’æ“ä½œ**ï¼šLua å¯ä»¥æ— ç¼è°ƒç”¨ C å‡½æ•°ï¼Œåä¹‹äº¦ç„¶
- **å°¾è°ƒç”¨ä¼˜åŒ–**ï¼šè‡ªåŠ¨ä¼˜åŒ–å°¾é€’å½’ï¼Œé¿å…æ ˆæº¢å‡º
- **å¯å˜å‚æ•°æ”¯æŒ**ï¼šçµæ´»çš„å‚æ•°ä¼ é€’æœºåˆ¶
- **å¤šè¿”å›å€¼**ï¼šæ”¯æŒå‡½æ•°è¿”å›å¤šä¸ªå€¼

### 1.2 æ¶‰åŠçš„æ ¸å¿ƒæ–‡ä»¶

| æ–‡ä»¶ | èŒè´£ | æ ¸å¿ƒå‡½æ•° |
|------|------|---------|
| `lvm.c` | è™šæ‹Ÿæœºæ‰§è¡Œå¼•æ“ | `OP_CALL`, `OP_TAILCALL`, `OP_RETURN` |
| `ldo.c` | æ‰§è¡Œæ§åˆ¶ | `luaD_precall()`, `luaD_poscall()`, `luaD_call()` |
| `lfunc.c` | å‡½æ•°å¯¹è±¡ç®¡ç† | é—­åŒ…åˆ›å»ºå’Œç®¡ç† |
| `lapi.c` | C API | `lua_call()`, `lua_pcall()` |

### 1.3 å…³é”®æ¦‚å¿µ

```mermaid
graph LR
    A[å‡½æ•°è°ƒç”¨] --> B[è°ƒç”¨å‰å‡†å¤‡]
    A --> C[å‚æ•°ä¼ é€’]
    A --> D[æ ˆå¸§åˆ›å»º]
    A --> E[å‡½æ•°æ‰§è¡Œ]
    A --> F[è¿”å›å€¼å¤„ç†]
    A --> G[æ ˆå¸§æ¸…ç†]
    
    B --> B1[æ£€æŸ¥å‡½æ•°ç±»å‹]
    B --> B2[å‡†å¤‡æ ˆç©ºé—´]
    
    C --> C1[å›ºå®šå‚æ•°]
    C --> C2[å¯å˜å‚æ•°]
    
    D --> D1[åˆ›å»ºCallInfo]
    D --> D2[è®¾ç½®base/top]
    
    style A fill:#ff6b6b
    style E fill:#51cf66
    style F fill:#ffd43b
```

---

## 2. è°ƒç”¨æµç¨‹æ€»è§ˆ

### 2.1 å®Œæ•´è°ƒç”¨æµç¨‹

```mermaid
sequenceDiagram
    participant Caller as è°ƒç”¨è€…
    participant VM as è™šæ‹Ÿæœº(lvm.c)
    participant DO as æ‰§è¡Œæ§åˆ¶(ldo.c)
    participant Stack as æ ˆ
    participant Callee as è¢«è°ƒç”¨å‡½æ•°
    
    Caller->>Stack: 1. å‹å…¥å‡½æ•°å¯¹è±¡
    Caller->>Stack: 2. å‹å…¥å‚æ•°
    Caller->>VM: 3. æ‰§è¡ŒOP_CALLæŒ‡ä»¤
    
    VM->>VM: 4. ä¿å­˜PC
    VM->>Stack: 5. è°ƒæ•´æ ˆé¡¶
    VM->>DO: 6. è°ƒç”¨luaD_precall()
    
    DO->>DO: 7. æ£€æŸ¥å‡½æ•°ç±»å‹
    
    alt Luaå‡½æ•°
        DO->>Stack: 8a. åˆ›å»ºCallInfo
        DO->>Stack: 9a. è°ƒæ•´å‚æ•°
        DO->>Stack: 10a. è®¾ç½®æ–°æ ˆå¸§
        DO->>VM: 11a. è¿”å›PCRLUA
        VM->>VM: 12a. goto reentry
        VM->>Callee: 13a. æ‰§è¡Œå­—èŠ‚ç 
        Callee->>VM: 14a. OP_RETURN
        VM->>DO: 15a. è°ƒç”¨luaD_poscall()
    else Cå‡½æ•°
        DO->>Callee: 8b. ç›´æ¥è°ƒç”¨Cå‡½æ•°
        Callee->>DO: 9b. è¿”å›ç»“æœ
        DO->>Stack: 10b. å¤„ç†è¿”å›å€¼
        DO->>VM: 11b. è¿”å›PCRC
    end
    
    DO->>Stack: 16. å¤åˆ¶è¿”å›å€¼
    DO->>Stack: 17. æ¢å¤è°ƒç”¨è€…æ ˆå¸§
    DO->>Caller: 18. è¿”å›
```

### 2.2 è°ƒç”¨é˜¶æ®µåˆ’åˆ†

| é˜¶æ®µ | å‡½æ•° | ä¸»è¦ä»»åŠ¡ |
|------|------|---------|
| **å‡†å¤‡é˜¶æ®µ** | `OP_CALL` | ä¿å­˜PCã€è®¾ç½®æ ˆé¡¶ |
| **å‰ç½®å¤„ç†** | `luaD_precall()` | ç±»å‹æ£€æŸ¥ã€æ ˆå¸§åˆ›å»ºã€å‚æ•°è°ƒæ•´ |
| **æ‰§è¡Œé˜¶æ®µ** | `luaV_execute()` / Cå‡½æ•° | æ‰§è¡Œå‡½æ•°ä½“ |
| **åç½®å¤„ç†** | `luaD_poscall()` | å¤åˆ¶è¿”å›å€¼ã€æ¢å¤æ ˆå¸§ |

### 2.3 æ ˆçŠ¶æ€è½¬æ¢

**è°ƒç”¨å‰**ï¼ˆè°ƒç”¨è€…è§†è§’ï¼‰ï¼š
```
â”Œâ”€â”€â”€â”€â”€â”€â”€â”€â”€â”€â”€â”€â”€â”€â”€â”€â”€â”€â”
â”‚ è°ƒç”¨è€…æ•°æ®       â”‚
â”œâ”€â”€â”€â”€â”€â”€â”€â”€â”€â”€â”€â”€â”€â”€â”€â”€â”€â”€â”¤
â”‚ R(n) = å‡½æ•°å¯¹è±¡  â”‚ â† func
â”‚ R(n+1) = å‚æ•°1   â”‚
â”‚ R(n+2) = å‚æ•°2   â”‚
â”‚ ...              â”‚
â”œâ”€â”€â”€â”€â”€â”€â”€â”€â”€â”€â”€â”€â”€â”€â”€â”€â”€â”€â”¤ â† topï¼ˆè°ƒç”¨å‰ï¼‰
â”‚ æœªä½¿ç”¨ç©ºé—´       â”‚
â””â”€â”€â”€â”€â”€â”€â”€â”€â”€â”€â”€â”€â”€â”€â”€â”€â”€â”€â”˜
```

**è°ƒç”¨æ—¶**ï¼ˆè¢«è°ƒç”¨å‡½æ•°è§†è§’ï¼‰ï¼š
```
â”Œâ”€â”€â”€â”€â”€â”€â”€â”€â”€â”€â”€â”€â”€â”€â”€â”€â”€â”€â”
â”‚ è°ƒç”¨è€…æ•°æ®       â”‚
â”œâ”€â”€â”€â”€â”€â”€â”€â”€â”€â”€â”€â”€â”€â”€â”€â”€â”€â”€â”¤
â”‚ å‡½æ•°å¯¹è±¡         â”‚ â† ci->func
â”œâ”€â”€â”€â”€â”€â”€â”€â”€â”€â”€â”€â”€â”€â”€â”€â”€â”€â”€â”¤
â”‚ R(0) = å‚æ•°1     â”‚ â† base = ci->base
â”‚ R(1) = å‚æ•°2     â”‚
â”‚ R(2) = å±€éƒ¨å˜é‡1 â”‚
â”‚ R(3) = å±€éƒ¨å˜é‡2 â”‚
â”‚ ...              â”‚
â”œâ”€â”€â”€â”€â”€â”€â”€â”€â”€â”€â”€â”€â”€â”€â”€â”€â”€â”€â”¤ â† topï¼ˆå‡½æ•°å†…ï¼‰
â”‚ æœªä½¿ç”¨ç©ºé—´       â”‚
â””â”€â”€â”€â”€â”€â”€â”€â”€â”€â”€â”€â”€â”€â”€â”€â”€â”€â”€â”˜
```

**è¿”å›å**ï¼ˆè°ƒç”¨è€…è§†è§’ï¼‰ï¼š
```
â”Œâ”€â”€â”€â”€â”€â”€â”€â”€â”€â”€â”€â”€â”€â”€â”€â”€â”€â”€â”
â”‚ è°ƒç”¨è€…æ•°æ®       â”‚
â”œâ”€â”€â”€â”€â”€â”€â”€â”€â”€â”€â”€â”€â”€â”€â”€â”€â”€â”€â”¤
â”‚ R(n) = è¿”å›å€¼1   â”‚ â† resï¼ˆè¦†ç›–å‡½æ•°å¯¹è±¡ï¼‰
â”‚ R(n+1) = è¿”å›å€¼2 â”‚
â”‚ ...              â”‚
â”œâ”€â”€â”€â”€â”€â”€â”€â”€â”€â”€â”€â”€â”€â”€â”€â”€â”€â”€â”¤ â† topï¼ˆè¿”å›åï¼‰
â”‚ æœªä½¿ç”¨ç©ºé—´       â”‚
â””â”€â”€â”€â”€â”€â”€â”€â”€â”€â”€â”€â”€â”€â”€â”€â”€â”€â”€â”˜
```

---

## 3. OP_CALL æŒ‡ä»¤è¯¦è§£

### 3.1 æŒ‡ä»¤æ ¼å¼

```c
OP_CALL,  /*  A B C   R(A), ... ,R(A+C-2) := R(A)(R(A+1), ... ,R(A+B-1)) */
```

**å‚æ•°è¯´æ˜**ï¼š
- **A**: å‡½æ•°æ‰€åœ¨çš„å¯„å­˜å™¨
- **B**: å‚æ•°æ•°é‡ + 1
  - `B = 0`: å‚æ•°æ•°é‡åˆ°æ ˆé¡¶ `top - (A + 1)`
  - `B > 0`: å‚æ•°æ•°é‡ = `B - 1`
- **C**: æœŸæœ›è¿”å›å€¼æ•°é‡ + 1
  - `C = 0`: ä¿ç•™æ‰€æœ‰è¿”å›å€¼åˆ°æ ˆé¡¶
  - `C = 1`: ä¸éœ€è¦è¿”å›å€¼
  - `C > 1`: æœŸæœ›è¿”å›å€¼æ•°é‡ = `C - 1`

### 3.2 æŒ‡ä»¤å®ç°

```c
case OP_CALL: {
    int b = GETARG_B(i);          // å‚æ•°æ•°é‡ + 1
    int nresults = GETARG_C(i) - 1; // æœŸæœ›è¿”å›å€¼æ•°é‡
    
    // è®¾ç½®æ ˆé¡¶ï¼ˆç¡®å®šå‚æ•°èŒƒå›´ï¼‰
    if (b != 0) {
        L->top = ra + b;  // ra + b = å‡½æ•° + å‚æ•°
    }
    // å¦‚æœ b == 0ï¼Œæ ˆé¡¶å·²ç»åœ¨ä¹‹å‰çš„æŒ‡ä»¤ä¸­è®¾ç½®å¥½
    
    // ä¿å­˜ç¨‹åºè®¡æ•°å™¨ï¼ˆç”¨äºè¿”å›å’Œé”™è¯¯å¤„ç†ï¼‰
    L->savedpc = pc;
    
    // è°ƒç”¨å‰ç½®å¤„ç†å‡½æ•°
    switch (luaD_precall(L, ra, nresults)) {
        case PCRLUA: {
            // Luaå‡½æ•°ï¼šéœ€è¦æ‰§è¡Œå­—èŠ‚ç 
            nexeccalls++;
            goto reentry;  // é‡å…¥æ‰§è¡Œå¾ªç¯
        }
        
        case PCRC: {
            // Cå‡½æ•°ï¼šå·²æ‰§è¡Œå®Œæ¯•
            if (nresults >= 0) {
                L->top = L->ci->top;  // æ¢å¤æ ˆé¡¶
            }
            base = L->base;  // é‡æ–°åŠ è½½base
            continue;  // ç»§ç»­æ‰§è¡Œä¸‹ä¸€æ¡æŒ‡ä»¤
        }
        
        default: {
            // åç¨‹æŒ‚èµ·æˆ–é”™è¯¯
            return;
        }
    }
}
```

### 3.3 å‚æ•°ä¼ é€’ç¤ºä¾‹

**Lua ä»£ç **ï¼š
```lua
local function test(a, b, c)
    return a + b + c
end

local result = test(10, 20, 30)
```

**å­—èŠ‚ç **ï¼š
```
; å‡½æ•°å®šä¹‰
function <test:1,3> (4 instructions)
3 params, 4 slots, 0 upvalues, 3 locals, 0 constants
    1  [2]  ADD      3 0 1    ; R(3) = R(0) + R(1)
    2  [2]  ADD      3 3 2    ; R(3) = R(3) + R(2)
    3  [2]  RETURN   3 2      ; return R(3)
    4  [3]  RETURN   0 1      ;

; è°ƒç”¨ä»£ç 
MOVE     1 0      ; å‡½æ•°ç§»åˆ°R(1)
LOADK    2 -1     ; R(2) = 10
LOADK    3 -2     ; R(3) = 20
LOADK    4 -3     ; R(4) = 30
CALL     1 4 2    ; R(1) = test(R(2), R(3), R(4))
                  ; A=1, B=4 (3å‚æ•°+å‡½æ•°), C=2 (1è¿”å›å€¼+1)
```

**æ‰§è¡Œè¿‡ç¨‹**ï¼š

| æ­¥éª¤ | æ“ä½œ | æ ˆçŠ¶æ€ |
|------|------|--------|
| 1 | MOVE 1 0 | R(1) = testå‡½æ•° |
| 2 | LOADK 2 -1 | R(2) = 10 |
| 3 | LOADK 3 -2 | R(3) = 20 |
| 4 | LOADK 4 -3 | R(4) = 30 |
| 5 | CALL 1 4 2 | top = R(1) + 4 = R(5) |
| 6 | luaD_precall | åˆ›å»ºæ–°æ ˆå¸§ |
| 7 | æ‰§è¡Œtest | R(0)=10, R(1)=20, R(2)=30 |
| 8 | RETURN | è¿”å›60 |
| 9 | luaD_poscall | R(1) = 60 |

---

## 4. luaD_precall å‰ç½®å¤„ç†

### 4.1 å‡½æ•°ç­¾å

```c
int luaD_precall (lua_State *L, StkId func, int nresults)
```

**å‚æ•°**ï¼š
- `L`: Lua çŠ¶æ€æœº
- `func`: å‡½æ•°å¯¹è±¡åœ¨æ ˆä¸­çš„ä½ç½®
- `nresults`: æœŸæœ›çš„è¿”å›å€¼æ•°é‡

**è¿”å›å€¼**ï¼š
- `PCRLUA`: Lua å‡½æ•°ï¼Œéœ€è¦æ‰§è¡Œå­—èŠ‚ç 
- `PCRC`: C å‡½æ•°ï¼Œå·²æ‰§è¡Œå®Œæ¯•
- `PCRYIELD`: åç¨‹æŒ‚èµ·

### 4.2 å®Œæ•´å®ç°æµç¨‹

```mermaid
flowchart TD
    Start([luaD_precallå¼€å§‹]) --> CheckFunc{æ˜¯å‡½æ•°?}
    
    CheckFunc -->|å¦| TryMeta[å°è¯•__callå…ƒæ–¹æ³•]
    TryMeta --> CheckFunc2{è·å–åˆ°å‡½æ•°?}
    CheckFunc2 -->|å¦| Error[æŠ¥é”™: éå‡½æ•°]
    CheckFunc2 -->|æ˜¯| CheckType
    
    CheckFunc -->|æ˜¯| CheckType{å‡½æ•°ç±»å‹?}
    
    CheckType -->|Luaå‡½æ•°| LuaFunc[å¤„ç†Luaå‡½æ•°]
    CheckType -->|Cå‡½æ•°| CFunc[å¤„ç†Cå‡½æ•°]
    
    LuaFunc --> CheckStack[æ£€æŸ¥æ ˆç©ºé—´]
    CheckStack --> AdjustArgs[è°ƒæ•´å‚æ•°]
    AdjustArgs --> VarArg{å¯å˜å‚æ•°?}
    
    VarArg -->|æ˜¯| AdjustVarArg[adjust_varargs]
    VarArg -->|å¦| SetBase[è®¾ç½®æ ˆåŸºå€]
    AdjustVarArg --> SetBase
    
    SetBase --> CreateCI[åˆ›å»ºCallInfo]
    CreateCI --> InitLocals[åˆå§‹åŒ–å±€éƒ¨å˜é‡ä¸ºnil]
    InitLocals --> CallHook[è°ƒç”¨é’©å­]
    CallHook --> ReturnPCRLUA[è¿”å›PCRLUA]
    
    CFunc --> CheckCStack[æ£€æŸ¥Cæ ˆç©ºé—´]
    CheckCStack --> SetupCCall[è®¾ç½®Cè°ƒç”¨]
    SetupCCall --> CallCFunc[æ‰§è¡ŒCå‡½æ•°]
    CallCFunc --> ProcessRet[å¤„ç†è¿”å›å€¼]
    ProcessRet --> CallHook2[è°ƒç”¨é’©å­]
    CallHook2 --> ReturnPCRC[è¿”å›PCRC]
    
    style Start fill:#81c784
    style LuaFunc fill:#64b5f6
    style CFunc fill:#ffd54f
    style ReturnPCRLUA fill:#ba68c8
    style ReturnPCRC fill:#ba68c8
    style Error fill:#ef5350
```

### 4.3 æºä»£ç å®ç°

```c
int luaD_precall (lua_State *L, StkId func, int nresults) {
    LClosure *cl;
    ptrdiff_t funcr;
    
    // 1. æ£€æŸ¥æ˜¯å¦æ˜¯å‡½æ•°ï¼Œå¦åˆ™å°è¯•å…ƒæ–¹æ³•
    if (!ttisfunction(func)) {
        func = tryfuncTM(L, func);  // å°è¯• __call å…ƒæ–¹æ³•
    }
    
    funcr = savestack(L, func);  // ä¿å­˜funcä½ç½®ï¼ˆé˜²æ­¢GCç§»åŠ¨ï¼‰
    cl = &clvalue(func)->l;
    L->ci->savedpc = L->savedpc;  // ä¿å­˜è°ƒç”¨è€…çš„PC
    
    // 2. åŒºåˆ†Luaå‡½æ•°å’ŒCå‡½æ•°
    if (!cl->isC) {  
        // ==================== Lua å‡½æ•°å¤„ç† ====================
        CallInfo *ci;
        StkId st, base;
        Proto *p = cl->p;
        
        // 2.1 æ£€æŸ¥æ ˆç©ºé—´
        luaD_checkstack(L, p->maxstacksize);
        func = restorestack(L, funcr);  // æ¢å¤funcï¼ˆå¯èƒ½è¢«GCç§»åŠ¨ï¼‰
        
        // 2.2 è®¡ç®—å®é™…å‚æ•°æ•°é‡
        int n = cast_int(L->top - func) - 1;  // å®é™…å‚æ•°æ•°
        
        // 2.3 è°ƒæ•´å‚æ•°æ•°é‡ï¼ˆå¡«å……nilæˆ–æˆªæ–­ï¼‰
        for (; n < p->numparams; n++)
            setnilvalue(L->top++);  // å¡«å……ç¼ºå¤±å‚æ•°ä¸ºnil
        
        // 2.4 è®¾ç½®æ ˆåŸºå€
        if (!p->is_vararg) {
            // å›ºå®šå‚æ•°ï¼šbaseç›´æ¥åœ¨å‡½æ•°å
            base = func + 1;
            L->top = base + p->maxstacksize;
        } else {
            // å¯å˜å‚æ•°ï¼šéœ€è¦ç‰¹æ®Šå¤„ç†
            base = adjust_varargs(L, p, n);
        }
        
        // 2.5 åˆ›å»ºæ–°çš„CallInfo
        ci = inc_ci(L);
        ci->func = func;
        L->base = ci->base = base;
        ci->top = L->base + p->maxstacksize;
        lua_assert(ci->top <= L->stack_last);
        L->savedpc = p->code;  // è®¾ç½®PCä¸ºå‡½æ•°ç¬¬ä¸€æ¡æŒ‡ä»¤
        ci->tailcalls = 0;
        ci->nresults = nresults;
        
        // 2.6 åˆå§‹åŒ–å±€éƒ¨å˜é‡ä¸ºnil
        for (st = L->top; st < ci->top; st++)
            setnilvalue(st);
        L->top = ci->top;
        
        // 2.7 è°ƒç”¨é’©å­
        if (L->hookmask & LUA_MASKCALL)
            luaD_callhook(L, LUA_HOOKCALL, -1);
        
        return PCRLUA;  // éœ€è¦æ‰§è¡ŒLuaå­—èŠ‚ç 
        
    } else {  
        // ==================== C å‡½æ•°å¤„ç† ====================
        CallInfo *ci;
        int n;
        
        // 2.1 æ£€æŸ¥Cè°ƒç”¨æ ˆæ·±åº¦
        luaD_checkstack(L, LUA_MINSTACK);
        ci = inc_ci(L);
        ci->func = restorestack(L, funcr);
        L->base = ci->base = ci->func + 1;
        ci->top = L->top + LUA_MINSTACK;
        lua_assert(ci->top <= L->stack_last);
        ci->nresults = nresults;
        
        // 2.2 è°ƒç”¨é’©å­
        if (L->hookmask & LUA_MASKCALL)
            luaD_callhook(L, LUA_HOOKCALL, -1);
        
        lua_unlock(L);
        
        // 2.3 æ‰§è¡ŒCå‡½æ•°
        n = (*curr_func(L)->c.f)(L);  // è°ƒç”¨Cå‡½æ•°
        
        lua_lock(L);
        
        // 2.4 å¤„ç†è¿”å›å€¼
        luaD_poscall(L, L->top - n);
        
        return PCRC;  // Cå‡½æ•°å·²æ‰§è¡Œå®Œæ¯•
    }
}
```

### 4.4 å…³é”®æ­¥éª¤è§£æ

#### 4.4.1 å…ƒæ–¹æ³•å°è¯•

```c
static StkId tryfuncTM (lua_State *L, StkId func) {
    const TValue *tm = luaT_gettmbyobj(L, func, TM_CALL);
    StkId p;
    ptrdiff_t funcr = savestack(L, func);
    
    if (!ttisfunction(tm))
        luaG_typeerror(L, func, "call");
    
    // å°†åŸå¯¹è±¡ä½œä¸ºç¬¬ä¸€ä¸ªå‚æ•°
    for (p = L->top; p > func; p--)
        setobjs2s(L, p, p-1);
    incr_top(L);
    
    func = restorestack(L, funcr);
    setobj2s(L, func, tm);  // æ›¿æ¢ä¸ºå…ƒæ–¹æ³•
    return func;
}
```

**ç¤ºä¾‹**ï¼š
```lua
local t = {}
setmetatable(t, {
    __call = function(self, x, y)
        return x + y
    end
})

print(t(10, 20))  -- è°ƒç”¨__callå…ƒæ–¹æ³•
-- å†…éƒ¨ä¼šå°† t(10, 20) è½¬æ¢ä¸º __call(t, 10, 20)
```

#### 4.4.2 å‚æ•°è°ƒæ•´

```c
// å¡«å……ç¼ºå¤±å‚æ•°
for (; n < p->numparams; n++)
    setnilvalue(L->top++);
```

**ç¤ºä¾‹**ï¼š
```lua
function test(a, b, c)
    print(a, b, c)
end

test(1)        -- a=1, b=nil, c=nilï¼ˆè‡ªåŠ¨å¡«å……ï¼‰
test(1, 2)     -- a=1, b=2, c=nil
test(1, 2, 3)  -- a=1, b=2, c=3
test(1, 2, 3, 4)  -- a=1, b=2, c=3ï¼ˆç¬¬4ä¸ªå‚æ•°è¢«å¿½ç•¥ï¼‰
```

---

## 5. Luaå‡½æ•°è°ƒç”¨

### 5.1 Luaå‡½æ•°æ‰§è¡Œæµç¨‹

å½“ `luaD_precall()` è¿”å› `PCRLUA` æ—¶ï¼Œè™šæ‹Ÿæœºé€šè¿‡ `goto reentry` é‡æ–°è¿›å…¥æ‰§è¡Œå¾ªç¯ï¼š

```c
case OP_CALL: {
    // ... å‰é¢çš„ä»£ç  ...
    
    switch (luaD_precall(L, ra, nresults)) {
        case PCRLUA: {
            nexeccalls++;
            goto reentry;  // â† é‡æ–°è¿›å…¥æ‰§è¡Œå¾ªç¯
        }
        // ...
    }
}

reentry:  /* entry point */
    lua_assert(isLua(L->ci));
    pc = L->savedpc;
    cl = &clvalue(L->ci->func)->l;
    base = L->base;
    k = cl->p->k;
    
    /* main loop of interpreter */
    for (;;) {
        const Instruction i = *pc++;
        StkId ra;
        // ... æ‰§è¡ŒæŒ‡ä»¤ ...
    }
```

### 5.2 æ ˆå¸§ç»“æ„è¯¦è§£

**CallInfo ç»“æ„**ï¼š
```c
typedef struct CallInfo {
    StkId base;        /* å‡½æ•°æ ˆåŸºå€ = func + 1 */
    StkId func;        /* å‡½æ•°å¯¹è±¡åœ¨æ ˆä¸­çš„ä½ç½® */
    StkId top;         /* å‡½æ•°æ ˆé¡¶ï¼ˆbase + maxstacksizeï¼‰ */
    const Instruction *savedpc;  /* ç¨‹åºè®¡æ•°å™¨ */
    int nresults;      /* æœŸæœ›è¿”å›å€¼æ•°é‡ */
    int tailcalls;     /* å°¾è°ƒç”¨è®¡æ•°å™¨ */
} CallInfo;
```

**æ ˆå¸§å¸ƒå±€**ï¼š
```
                        è°ƒç”¨è€…æ ˆå¸§
â”Œâ”€â”€â”€â”€â”€â”€â”€â”€â”€â”€â”€â”€â”€â”€â”€â”€â”€â”€â”€â”€â”€â”€â”€â”€â”€â”€â”€â”€â”€â”€â”€â”€â”€â”€â”€â”€â”
â”‚ ... è°ƒç”¨è€…çš„å±€éƒ¨å˜é‡ ...           â”‚
â”œâ”€â”€â”€â”€â”€â”€â”€â”€â”€â”€â”€â”€â”€â”€â”€â”€â”€â”€â”€â”€â”€â”€â”€â”€â”€â”€â”€â”€â”€â”€â”€â”€â”€â”€â”€â”€â”¤ â† è°ƒç”¨è€…çš„ top
â”‚                                    â”‚
â”‚        ç©ºé—²ç©ºé—´                    â”‚
â”‚                                    â”‚
â””â”€â”€â”€â”€â”€â”€â”€â”€â”€â”€â”€â”€â”€â”€â”€â”€â”€â”€â”€â”€â”€â”€â”€â”€â”€â”€â”€â”€â”€â”€â”€â”€â”€â”€â”€â”€â”˜

                        è¢«è°ƒç”¨å‡½æ•°æ ˆå¸§
â”Œâ”€â”€â”€â”€â”€â”€â”€â”€â”€â”€â”€â”€â”€â”€â”€â”€â”€â”€â”€â”€â”€â”€â”€â”€â”€â”€â”€â”€â”€â”€â”€â”€â”€â”€â”€â”€â”
â”‚ å‡½æ•°å¯¹è±¡ (é—­åŒ…)                    â”‚ â† ci->func
â”œâ”€â”€â”€â”€â”€â”€â”€â”€â”€â”€â”€â”€â”€â”€â”€â”€â”€â”€â”€â”€â”€â”€â”€â”€â”€â”€â”€â”€â”€â”€â”€â”€â”€â”€â”€â”€â”¤
â”‚ R(0) = å‚æ•° 1 æˆ–å±€éƒ¨å˜é‡ 1         â”‚ â† ci->base = L->base
â”‚ R(1) = å‚æ•° 2 æˆ–å±€éƒ¨å˜é‡ 2         â”‚
â”‚ R(2) = å‚æ•° 3 æˆ–å±€éƒ¨å˜é‡ 3         â”‚
â”‚ ...                                â”‚
â”‚ R(n) = å±€éƒ¨å˜é‡ n                  â”‚
â”œâ”€â”€â”€â”€â”€â”€â”€â”€â”€â”€â”€â”€â”€â”€â”€â”€â”€â”€â”€â”€â”€â”€â”€â”€â”€â”€â”€â”€â”€â”€â”€â”€â”€â”€â”€â”€â”¤ â† L->top
â”‚                                    â”‚
â”‚        ç©ºé—²ç©ºé—´                    â”‚
â”‚                                    â”‚
â”œâ”€â”€â”€â”€â”€â”€â”€â”€â”€â”€â”€â”€â”€â”€â”€â”€â”€â”€â”€â”€â”€â”€â”€â”€â”€â”€â”€â”€â”€â”€â”€â”€â”€â”€â”€â”€â”¤ â† ci->top
â”‚                                    â”‚
â””â”€â”€â”€â”€â”€â”€â”€â”€â”€â”€â”€â”€â”€â”€â”€â”€â”€â”€â”€â”€â”€â”€â”€â”€â”€â”€â”€â”€â”€â”€â”€â”€â”€â”€â”€â”€â”˜
```

### 5.3 å¯„å­˜å™¨åˆ°æ ˆçš„æ˜ å°„

åœ¨ `luaV_execute()` ä¸­ï¼š
```c
#define RA(i)   (base+GETARG_A(i))
#define RB(i)   check_exp(getBMode(GET_OPCODE(i)) == OpArgR, base+GETARG_B(i))
#define RC(i)   check_exp(getCMode(GET_OPCODE(i)) == OpArgR, base+GETARG_C(i))
```

**ç¤ºä¾‹**ï¼š
```lua
local function test(a, b)
    local c = a + b
    return c
end
```

**å­—èŠ‚ç å’Œæ ˆæ˜ å°„**ï¼š
```
function <test:1,4> (3 instructions, 3 slots)
    å‚æ•°: a(R0), b(R1)
    å±€éƒ¨å˜é‡: c(R2)

    1  [3]  ADD      2 0 1    ; R(2) = R(0) + R(1)
                               ; base[2] = base[0] + base[1]
                               ; c = a + b
    
    2  [3]  RETURN   2 2      ; return R(2)
                               ; è¿”å› base[2]
    
    3  [4]  RETURN   0 1      ; return (å‡½æ•°ç»“æŸ)
```

**æ ˆçŠ¶æ€å˜åŒ–**ï¼š

| æ—¶é—´ç‚¹ | æ ˆå¸ƒå±€ | è¯´æ˜ |
|--------|--------|------|
| è°ƒç”¨å‰ | `[func][10][20]` | func=test, å‚æ•°10, 20 |
| precallå | `baseâ†’[10][20][nil]` | R(0)=10, R(1)=20, R(2)=nil |
| æ‰§è¡ŒADDå | `baseâ†’[10][20][30]` | R(2) = 10 + 20 = 30 |
| RETURNå‰ | `baseâ†’[10][20][30]` | å‡†å¤‡è¿”å›R(2) |

### 5.4 å‡½æ•°è¿”å› (OP_RETURN)

```c
case OP_RETURN: {
    int b;
    
    // A: ç¬¬ä¸€ä¸ªè¿”å›å€¼çš„å¯„å­˜å™¨
    // B: è¿”å›å€¼æ•°é‡ + 1 (0è¡¨ç¤ºåˆ°æ ˆé¡¶)
    
    if (L->hookmask & LUA_MASKRET)
        luaD_callhook(L, LUA_HOOKRET, -1);
    
    b = GETARG_B(i);
    if (b != 0) {
        L->top = ra + b - 1;  // è®¾ç½®æ ˆé¡¶åˆ°æœ€åä¸€ä¸ªè¿”å›å€¼
    }
    // b == 0 æ—¶ï¼Œæ ˆé¡¶å·²ç»æ­£ç¡®è®¾ç½®
    
    if (L->openupval) 
        luaF_close(L, base);  // å…³é—­upvalue
    
    L->savedpc = pc;
    b = luaD_poscall(L, ra);  // åç½®å¤„ç†
    
    if (--nexeccalls == 0)  // æœ€å¤–å±‚å‡½æ•°ï¼Ÿ
        return;
    else {  // å†…å±‚å‡½æ•°ï¼Œç»§ç»­æ‰§è¡Œ
        if (b) L->top = L->ci->top;
        lua_assert(isLua(L->ci));
        lua_assert(GET_OPCODE(*((L->ci)->savedpc - 1)) == OP_CALL);
        goto reentry;  // è¿”å›åˆ°è°ƒç”¨è€…
    }
}
```

**è¿”å›å€¼å¤„ç†ç¤ºä¾‹**ï¼š

```lua
-- ç¤ºä¾‹1ï¼šå•è¿”å›å€¼
function f1()
    return 42
end
-- å­—èŠ‚ç : RETURN 0 2  (è¿”å›R(0), 1ä¸ªè¿”å›å€¼)

-- ç¤ºä¾‹2ï¼šå¤šè¿”å›å€¼
function f2()
    return 10, 20, 30
end
-- å­—èŠ‚ç :
--   LOADK 0 -1  ; R(0) = 10
--   LOADK 1 -2  ; R(1) = 20
--   LOADK 2 -3  ; R(2) = 30
--   RETURN 0 4  ; è¿”å›R(0)åˆ°R(2), 3ä¸ªè¿”å›å€¼

-- ç¤ºä¾‹3ï¼šè¿”å›æ‰€æœ‰æ ˆé¡¶å€¼
function f3(...)
    return ...
end
-- å­—èŠ‚ç : RETURN 0 0  (è¿”å›æ‰€æœ‰å¯å˜å‚æ•°)
```

### 5.5 å®Œæ•´ç¤ºä¾‹ï¼šé€’å½’è°ƒç”¨

**Lua ä»£ç **ï¼š
```lua
local function factorial(n)
    if n <= 1 then
        return 1
    else
        return n * factorial(n - 1)
    end
end

local result = factorial(5)
```

**è°ƒç”¨æ ˆæ¼”å˜**ï¼š

```mermaid
sequenceDiagram
    participant Main as ä¸»å‡½æ•°
    participant F5 as factorial(5)
    participant F4 as factorial(4)
    participant F3 as factorial(3)
    participant F2 as factorial(2)
    participant F1 as factorial(1)
    
    Main->>F5: CALL (n=5)
    activate F5
    Note over F5: n > 1, éœ€è¦é€’å½’
    
    F5->>F4: CALL (n=4)
    activate F4
    Note over F4: n > 1, éœ€è¦é€’å½’
    
    F4->>F3: CALL (n=3)
    activate F3
    Note over F3: n > 1, éœ€è¦é€’å½’
    
    F3->>F2: CALL (n=2)
    activate F2
    Note over F2: n > 1, éœ€è¦é€’å½’
    
    F2->>F1: CALL (n=1)
    activate F1
    Note over F1: n <= 1, è¿”å›1
    F1-->>F2: RETURN 1
    deactivate F1
    
    Note over F2: 2 * 1 = 2
    F2-->>F3: RETURN 2
    deactivate F2
    
    Note over F3: 3 * 2 = 6
    F3-->>F4: RETURN 6
    deactivate F3
    
    Note over F4: 4 * 6 = 24
    F4-->>F5: RETURN 24
    deactivate F4
    
    Note over F5: 5 * 24 = 120
    F5-->>Main: RETURN 120
    deactivate F5
```

**æ ˆæ·±åº¦å˜åŒ–**ï¼ˆCallInfo é“¾ï¼‰ï¼š

```
æ—¶é—´ â†’ â†’ â†’ â†’ â†’ â†’ â†’ â†’
     â”Œâ”€â”€â”€â”
     â”‚ 5 â”‚ factorial(5)
     â”œâ”€â”€â”€â”¤
     â”‚ 4 â”‚ factorial(4)
     â”œâ”€â”€â”€â”¤
     â”‚ 3 â”‚ factorial(3)
     â”œâ”€â”€â”€â”¤
     â”‚ 2 â”‚ factorial(2)
     â”œâ”€â”€â”€â”¤
     â”‚ 1 â”‚ factorial(1)  â† æœ€æ·±ç‚¹
     â”œâ”€â”€â”€â”¤
     â”‚ 2 â”‚ è¿”å›2
     â”œâ”€â”€â”€â”¤
     â”‚ 6 â”‚ è¿”å›6
     â”œâ”€â”€â”€â”¤
     â”‚ 24â”‚ è¿”å›24
     â”œâ”€â”€â”€â”¤
     â”‚120â”‚ è¿”å›120
     â””â”€â”€â”€â”˜
```

---

## 6. Cå‡½æ•°è°ƒç”¨

### 6.1 Cå‡½æ•°æ¥å£

**æ ‡å‡† C å‡½æ•°ç­¾å**ï¼š
```c
typedef int (*lua_CFunction) (lua_State *L);
```

**è°ƒç”¨çº¦å®š**ï¼š
- å‚æ•°ï¼šä»æ ˆä¸­è¯»å–ï¼ˆ`lua_to*` ç³»åˆ—å‡½æ•°ï¼‰
- è¿”å›å€¼ï¼šå‹å…¥æ ˆï¼Œè¿”å›å€¼æ•°é‡ä½œä¸ºå‡½æ•°è¿”å›å€¼

### 6.2 Cå‡½æ•°æ‰§è¡Œæµç¨‹

åœ¨ `luaD_precall()` ä¸­ç›´æ¥æ‰§è¡Œï¼š

```c
// C å‡½æ•°åˆ†æ”¯
if (cl->isC) {
    CallInfo *ci;
    int n;
    
    // 1. æ£€æŸ¥æ ˆç©ºé—´
    luaD_checkstack(L, LUA_MINSTACK);
    
    // 2. åˆ›å»ºCallInfo
    ci = inc_ci(L);
    ci->func = restorestack(L, funcr);
    L->base = ci->base = ci->func + 1;
    ci->top = L->top + LUA_MINSTACK;
    ci->nresults = nresults;
    
    // 3. è°ƒç”¨é’©å­
    if (L->hookmask & LUA_MASKCALL)
        luaD_callhook(L, LUA_HOOKCALL, -1);
    
    lua_unlock(L);
    
    // 4. æ‰§è¡ŒCå‡½æ•°
    n = (*curr_func(L)->c.f)(L);  // â† å®é™…è°ƒç”¨
    
    lua_lock(L);
    
    // 5. å¤„ç†è¿”å›å€¼
    luaD_poscall(L, L->top - n);
    
    return PCRC;  // ç«‹å³è¿”å›
}
```

### 6.3 Cå‡½æ•°ç¤ºä¾‹

**ç¤ºä¾‹1ï¼šåŸºç¡€åŠ æ³•å‡½æ•°**

```c
// C ä»£ç 
static int l_add(lua_State *L) {
    // 1. è·å–å‚æ•°
    double a = luaL_checknumber(L, 1);  // ç¬¬ä¸€ä¸ªå‚æ•°
    double b = luaL_checknumber(L, 2);  // ç¬¬äºŒä¸ªå‚æ•°
    
    // 2. è®¡ç®—ç»“æœ
    double result = a + b;
    
    // 3. å‹å…¥è¿”å›å€¼
    lua_pushnumber(L, result);
    
    // 4. è¿”å›å€¼æ•°é‡
    return 1;
}

// æ³¨å†Œå‡½æ•°
lua_register(L, "add", l_add);
```

```lua
-- Lua è°ƒç”¨
local sum = add(10, 20)  -- sum = 30
```

**æ ˆçŠ¶æ€å˜åŒ–**ï¼š

| é˜¶æ®µ | æ ˆå†…å®¹ | è¯´æ˜ |
|------|--------|------|
| è°ƒç”¨å‰ | `[addå‡½æ•°][10][20]` | func + 2å‚æ•° |
| Cå‡½æ•°å†…ï¼ˆå¼€å§‹ï¼‰ | `baseâ†’[10][20]` | base = func + 1 |
| pushnumberå | `baseâ†’[10][20][30]` | å‹å…¥ç»“æœ |
| è¿”å›æ—¶ | `top = base + 1` | æŒ‡å‘ç»“æœ |
| poscallå | `[30]` | åªä¿ç•™è¿”å›å€¼ |

**ç¤ºä¾‹2ï¼šå¤šè¿”å›å€¼å‡½æ•°**

```c
static int l_divmod(lua_State *L) {
    int a = luaL_checkint(L, 1);
    int b = luaL_checkint(L, 2);
    
    if (b == 0) {
        return luaL_error(L, "division by zero");
    }
    
    lua_pushinteger(L, a / b);  // å•†
    lua_pushinteger(L, a % b);  // ä½™æ•°
    return 2;  // è¿”å›2ä¸ªå€¼
}
```

```lua
local quot, rem = divmod(17, 5)  -- quot=3, rem=2
```

**ç¤ºä¾‹3ï¼šå¯å˜å‚æ•°å‡½æ•°**

```c
static int l_sum(lua_State *L) {
    int n = lua_gettop(L);  // è·å–å‚æ•°æ•°é‡
    double sum = 0.0;
    
    for (int i = 1; i <= n; i++) {
        if (!lua_isnumber(L, i)) {
            return luaL_error(L, "argument %d is not a number", i);
        }
        sum += lua_tonumber(L, i);
    }
    
    lua_pushnumber(L, sum);
    return 1;
}
```

```lua
print(sum(1, 2, 3, 4, 5))  -- 15
```

### 6.4 C API æ ˆæ“ä½œ

**å¸¸ç”¨å‡½æ•°**ï¼š

| å‡½æ•° | ä½œç”¨ |
|------|------|
| `lua_gettop(L)` | è·å–æ ˆé¡¶ç´¢å¼•ï¼ˆå‚æ•°æ•°é‡ï¼‰ |
| `lua_settop(L, n)` | è®¾ç½®æ ˆé¡¶åˆ°ç´¢å¼• n |
| `lua_pushvalue(L, i)` | å¤åˆ¶ç´¢å¼• i çš„å€¼åˆ°æ ˆé¡¶ |
| `lua_remove(L, i)` | ç§»é™¤ç´¢å¼• i çš„å€¼ |
| `lua_insert(L, i)` | å°†æ ˆé¡¶å€¼æ’å…¥åˆ°ç´¢å¼• i |
| `lua_replace(L, i)` | ç”¨æ ˆé¡¶å€¼æ›¿æ¢ç´¢å¼• i |

**ç±»å‹æ£€æŸ¥**ï¼š

| å‡½æ•° | ä½œç”¨ |
|------|------|
| `luaL_checktype(L, i, t)` | æ£€æŸ¥ç±»å‹ï¼Œé”™è¯¯æ—¶æŠ›å‡ºå¼‚å¸¸ |
| `luaL_checkany(L, i)` | æ£€æŸ¥å‚æ•°å­˜åœ¨ |
| `luaL_checknumber(L, i)` | æ£€æŸ¥å¹¶è·å–æ•°å­— |
| `luaL_checkstring(L, i)` | æ£€æŸ¥å¹¶è·å–å­—ç¬¦ä¸² |

### 6.5 é”™è¯¯å¤„ç†

**æ–¹æ³•1ï¼šä½¿ç”¨ `luaL_error`**
```c
static int l_sqrt(lua_State *L) {
    double n = luaL_checknumber(L, 1);
    if (n < 0) {
        return luaL_error(L, "negative number");
    }
    lua_pushnumber(L, sqrt(n));
    return 1;
}
```

**æ–¹æ³•2ï¼šä½¿ç”¨ `lua_error`**
```c
static int l_custom_error(lua_State *L) {
    lua_pushstring(L, "custom error message");
    return lua_error(L);  // æ°¸ä¸è¿”å›
}
```

**é”™è¯¯ä¼ æ’­**ï¼š
```lua
local ok, err = pcall(function()
    sqrt(-1)  -- è§¦å‘é”™è¯¯
end)

if not ok then
    print("Error:", err)  -- Error: negative number
end
```

### 6.6 Cé—­åŒ…

**åˆ›å»ºå¸¦ upvalue çš„ C å‡½æ•°**ï¼š

```c
static int counter_inc(lua_State *L) {
    // è·å–upvalue
    int val = lua_tointeger(L, lua_upvalueindex(1));
    val++;
    
    // æ›´æ–°upvalue
    lua_pushinteger(L, val);
    lua_replace(L, lua_upvalueindex(1));
    
    // è¿”å›æ–°å€¼
    lua_pushinteger(L, val);
    return 1;
}

// åˆ›å»ºé—­åŒ…
lua_pushinteger(L, 0);  // åˆå§‹å€¼
lua_pushcclosure(L, counter_inc, 1);  // 1ä¸ªupvalue
lua_setglobal(L, "counter");
```

```lua
print(counter())  -- 1
print(counter())  -- 2
print(counter())  -- 3
```

---

## 7. luaD_poscall åç½®å¤„ç†

### 7.1 å‡½æ•°ç­¾å

```c
int luaD_poscall (lua_State *L, StkId firstResult)
```

**å‚æ•°**ï¼š
- `L`: Lua çŠ¶æ€æœº
- `firstResult`: ç¬¬ä¸€ä¸ªè¿”å›å€¼åœ¨æ ˆä¸­çš„ä½ç½®

**è¿”å›å€¼**ï¼š
- `1`: è°ƒç”¨è€…éœ€è¦è°ƒæ•´æ ˆé¡¶
- `0`: æ ˆé¡¶å·²ç»æ­£ç¡®

### 7.2 å®Œæ•´å®ç°

```c
int luaD_poscall (lua_State *L, StkId firstResult) {
    StkId res;
    int wanted, i;
    CallInfo *ci;
    
    // 1. è°ƒç”¨è¿”å›é’©å­
    if (L->hookmask & LUA_MASKRET)
        firstResult = callrethooks(L, firstResult);
    
    // 2. è·å–å½“å‰CallInfo
    ci = L->ci--;  // å¼¹å‡ºCallInfo
    res = ci->func;  // ä¿å­˜å‡½æ•°ä½ç½®ï¼ˆè¿”å›å€¼å°†æ”¾åœ¨è¿™é‡Œï¼‰
    wanted = ci->nresults;  // æœŸæœ›çš„è¿”å›å€¼æ•°é‡
    
    // 3. æ¢å¤è°ƒç”¨è€…çš„çŠ¶æ€
    L->base = (ci - 1)->base;  // æ¢å¤base
    L->savedpc = (ci - 1)->savedpc;  // æ¢å¤PC
    
    // 4. å¤åˆ¶è¿”å›å€¼åˆ°æ­£ç¡®ä½ç½®
    // ä» firstResult å¤åˆ¶åˆ° res
    for (i = wanted; i != 0 && firstResult < L->top; i--)
        setobjs2s(L, res++, firstResult++);
    
    // 5. å¤„ç†è¿”å›å€¼æ•°é‡ä¸åŒ¹é…
    while (i-- > 0)
        setnilvalue(res++);  // å¡«å……nil
    
    // 6. è®¾ç½®æ ˆé¡¶
    L->top = res;
    
    return (wanted - LUA_MULTRET);  // è¿”å›æ˜¯å¦éœ€è¦è°ƒæ•´
}
```

### 7.3 è¿”å›å€¼å¤åˆ¶è¯¦è§£

**åœºæ™¯1ï¼šè¿”å›å€¼æ•°é‡åŒ¹é…**

```lua
function f()
    return 10, 20, 30
end

local a, b, c = f()  -- wanted=3, å®é™…è¿”å›3ä¸ª
```

**æ ˆå˜åŒ–**ï¼š
```
è°ƒç”¨å‰:
â”Œâ”€â”€â”€â”€â”€â”€â”€â”€â”€â”€â”€â”€â”
â”‚ è°ƒç”¨è€…æ•°æ® â”‚
â”œâ”€â”€â”€â”€â”€â”€â”€â”€â”€â”€â”€â”€â”¤
â”‚ [func]     â”‚ â† res
â”‚ ...        â”‚
â””â”€â”€â”€â”€â”€â”€â”€â”€â”€â”€â”€â”€â”˜

è¿”å›æ—¶:
â”Œâ”€â”€â”€â”€â”€â”€â”€â”€â”€â”€â”€â”€â”
â”‚ è°ƒç”¨è€…æ•°æ® â”‚
â”œâ”€â”€â”€â”€â”€â”€â”€â”€â”€â”€â”€â”€â”¤
â”‚ [10]       â”‚ â† res (è¦†ç›–func)
â”‚ [20]       â”‚
â”‚ [30]       â”‚ â† L->top
â””â”€â”€â”€â”€â”€â”€â”€â”€â”€â”€â”€â”€â”˜
```

**åœºæ™¯2ï¼šè¿”å›å€¼è¿‡å¤š**

```lua
function f()
    return 10, 20, 30, 40
end

local a, b = f()  -- wanted=2, å®é™…è¿”å›4ä¸ª
```

**å¤„ç†**ï¼š
```c
// åªå¤åˆ¶wantedä¸ª
for (i = wanted; i != 0 && firstResult < L->top; i--)
    setobjs2s(L, res++, firstResult++);
// ç»“æœï¼ša=10, b=20 (30å’Œ40è¢«ä¸¢å¼ƒ)
```

**åœºæ™¯3ï¼šè¿”å›å€¼ä¸è¶³**

```lua
function f()
    return 10
end

local a, b, c = f()  -- wanted=3, å®é™…è¿”å›1ä¸ª
```

**å¤„ç†**ï¼š
```c
// å¤åˆ¶å®é™…è¿”å›å€¼
setobjs2s(L, res++, firstResult++);  // a = 10

// å¡«å……nil
while (i-- > 0)
    setnilvalue(res++);  // b=nil, c=nil
```

**åœºæ™¯4ï¼šå¤šè¿”å›å€¼ä¼ é€’**

```lua
function f()
    return 10, 20, 30
end

print(f())  -- wanted=LUA_MULTRET (ä¿ç•™æ‰€æœ‰)
```

**å¤„ç†**ï¼š
```c
// wanted = LUA_MULTRET = -1
// å¾ªç¯ä¼šå¤åˆ¶æ‰€æœ‰è¿”å›å€¼ï¼Œä¸å¡«å……nil
for (i = wanted; i != 0 && firstResult < L->top; i--)
    // iä»-1å¼€å§‹ï¼Œæ°¸è¿œä¸ä¼šå˜æˆ0
    // ç›´åˆ° firstResult >= L->top
```

### 7.4 CallInfo æ ˆç®¡ç†

**CallInfo é“¾ç»“æ„**ï¼š
```c
struct lua_State {
    // ...
    CallInfo *ci;        /* å½“å‰CallInfo */
    CallInfo *base_ci;   /* CallInfoæ•°ç»„åŸºå€ */
    CallInfo *end_ci;    /* CallInfoæ•°ç»„æœ«å°¾ */
    // ...
};
```

**å…¥æ ˆ (inc_ci)**ï¼š
```c
static CallInfo *inc_ci (lua_State *L) {
    CallInfo *ci = ++L->ci;
    if (ci == L->end_ci)
        return growCI(L);  // æ‰©å±•æ•°ç»„
    return ci;
}
```

**å‡ºæ ˆ (åœ¨poscallä¸­)**ï¼š
```c
ci = L->ci--;  // ç®€å•é€’å‡æŒ‡é’ˆ
```

**ç¤ºä¾‹æ¼”å˜**ï¼š

```
åˆå§‹çŠ¶æ€:
base_ci[0] â† ci (ä¸»å‡½æ•°)

è°ƒç”¨f1:
base_ci[0]
base_ci[1] â† ci (f1)

f1è°ƒç”¨f2:
base_ci[0]
base_ci[1]
base_ci[2] â† ci (f2)

f2è¿”å›:
base_ci[0]
base_ci[1] â† ci (å›åˆ°f1)

f1è¿”å›:
base_ci[0] â† ci (å›åˆ°ä¸»å‡½æ•°)
```

### 7.5 å®Œæ•´è°ƒç”¨ç¤ºä¾‹

**ä»£ç **ï¼š
```lua
function add(a, b)
    return a + b
end

function test()
    local x = add(10, 20)
    return x * 2
end

local result = test()
```

**è¯¦ç»†æµç¨‹**ï¼š

| æ­¥éª¤ | å‡½æ•° | æ“ä½œ | æ ˆçŠ¶æ€ |
|------|------|------|--------|
| 1 | test | CALL add | `[add][10][20]` |
| 2 | add | precall | `baseâ†’[10][20]` |
| 3 | add | æ‰§è¡ŒADD | `baseâ†’[10][20][30]` |
| 4 | add | RETURN | firstResultâ†’`[30]` |
| 5 | add | poscall | `[30]` (è¦†ç›–add) |
| 6 | test | ç»§ç»­æ‰§è¡Œ | `x=30` |
| 7 | test | è®¡ç®—x*2 | `[60]` |
| 8 | test | RETURN | firstResultâ†’`[60]` |
| 9 | test | poscall | `[60]` |
| 10 | main | èµ‹å€¼ | `result=60` |

---

## 8. å°¾è°ƒç”¨ä¼˜åŒ–

### 8.1 å°¾è°ƒç”¨å®šä¹‰

**å°¾è°ƒç”¨**æ˜¯æŒ‡å‡½æ•°çš„æœ€åä¸€ä¸ªæ“ä½œæ˜¯è°ƒç”¨å¦ä¸€ä¸ªå‡½æ•°å¹¶ç›´æ¥è¿”å›å…¶ç»“æœï¼š

```lua
-- å°¾è°ƒç”¨
function f(x)
    return g(x)  -- â† å°¾è°ƒç”¨
end

-- éå°¾è°ƒç”¨
function f(x)
    return g(x) + 1  -- éœ€è¦å¯¹gçš„ç»“æœè¿›è¡Œé¢å¤–æ“ä½œ
end

function f(x)
    g(x)  -- æ²¡æœ‰return
    return 1
end
```

### 8.2 OP_TAILCALL æŒ‡ä»¤

```c
case OP_TAILCALL: {
    int b;
    
    b = GETARG_B(i);
    if (b != 0) L->top = ra + b;
    
    lua_assert(GETARG_C(i) - 1 == LUA_MULTRET);
    L->savedpc = pc;
    
    lua_assert(GET_OPCODE(*((ci->func)+ci->funcr)) == OP_CALL);
    
    switch (luaD_precall(L, ra, LUA_MULTRET)) {
        case PCRLUA: {
            // Luaå‡½æ•°ï¼šç›´æ¥å¤ç”¨å½“å‰æ ˆå¸§
            CallInfo *ci = L->ci - 1;
            int aux;
            
            // 1. å…³é—­å½“å‰å‡½æ•°çš„upvalue
            if (L->openupval) luaF_close(L, ci->base);
            
            // 2. å¤åˆ¶è¢«è°ƒç”¨å‡½æ•°å’Œå‚æ•°åˆ°å½“å‰æ ˆå¸§
            for (aux = 0; ra + aux < L->top; aux++)
                setobjs2s(L, ci->func + aux, ra + aux);
            
            // 3. è°ƒæ•´CallInfo
            L->top = ci->func + aux;
            lua_assert(L->top == L->base + clvalue(ci->func)->l.p->maxstacksize);
            ci->savedpc = L->savedpc;
            ci->tailcalls++;  // å°¾è°ƒç”¨è®¡æ•°å™¨
            L->ci--;  // å¼¹å‡ºè¢«è°ƒç”¨å‡½æ•°çš„CallInfo
            
            goto reentry;
        }
        
        case PCRC: {
            // Cå‡½æ•°ï¼šæ— æ³•ä¼˜åŒ–ï¼Œå½“ä½œæ™®é€šè°ƒç”¨
            if (--nexeccalls == 0)
                return;
            else {
                L->top = L->ci->top;
                goto reentry;
            }
        }
        
        default: {
            return;
        }
    }
}
```

### 8.3 å°¾è°ƒç”¨ä¼˜åŒ–åŸç†

**å…³é”®æ€æƒ³**ï¼šå¤ç”¨å½“å‰æ ˆå¸§ï¼Œè€Œä¸æ˜¯åˆ›å»ºæ–°æ ˆå¸§

**æ™®é€šè°ƒç”¨**ï¼š
```
è°ƒç”¨å‰:              è°ƒç”¨å:
â”Œâ”€â”€â”€â”€â”€â”€â”€â”€â”€â”         â”Œâ”€â”€â”€â”€â”€â”€â”€â”€â”€â”
â”‚  fçš„å¸§  â”‚         â”‚  fçš„å¸§  â”‚
â”œâ”€â”€â”€â”€â”€â”€â”€â”€â”€â”¤         â”œâ”€â”€â”€â”€â”€â”€â”€â”€â”€â”¤
â”‚  ç©ºé—´   â”‚    â†’    â”‚  gçš„å¸§  â”‚ â† æ–°æ ˆå¸§
â””â”€â”€â”€â”€â”€â”€â”€â”€â”€â”˜         â””â”€â”€â”€â”€â”€â”€â”€â”€â”€â”˜
```

**å°¾è°ƒç”¨ä¼˜åŒ–**ï¼š
```
è°ƒç”¨å‰:              è°ƒç”¨å:
â”Œâ”€â”€â”€â”€â”€â”€â”€â”€â”€â”         â”Œâ”€â”€â”€â”€â”€â”€â”€â”€â”€â”
â”‚  fçš„å¸§  â”‚    â†’    â”‚  gçš„å¸§  â”‚ â† å¤ç”¨fçš„æ ˆå¸§
â””â”€â”€â”€â”€â”€â”€â”€â”€â”€â”˜         â””â”€â”€â”€â”€â”€â”€â”€â”€â”€â”˜
```

### 8.4 å°¾è°ƒç”¨ç¤ºä¾‹

**ç¤ºä¾‹1ï¼šå°¾é€’å½’ä¼˜åŒ–**

```lua
-- æœªä¼˜åŒ–çš„é€’å½’ï¼ˆä¼šæ ˆæº¢å‡ºï¼‰
function sum(n, acc)
    if n == 0 then
        return acc
    end
    return sum(n - 1, acc + n)  -- å°¾è°ƒç”¨
end

print(sum(100000, 0))  -- åœ¨å°¾è°ƒç”¨ä¼˜åŒ–ä¸‹å¯ä»¥æˆåŠŸ
```

**å­—èŠ‚ç **ï¼š
```
function <sum:1,5> (10 instructions)
    1  [2]  EQ       1 0 -1   ; n == 0?
    2  [2]  JMP      2        ; è·³åˆ°5
    3  [3]  RETURN   1 2      ; return acc
    4  [3]  JMP      4        ; è·³åˆ°9
    5  [5]  GETGLOBAL 2 -2    ; sum
    6  [5]  SUB      3 0 -3   ; n - 1
    7  [5]  ADD      4 1 0    ; acc + n
    8  [5]  TAILCALL 2 3 0    ; â† å°¾è°ƒç”¨
    9  [5]  RETURN   2 0
   10  [6]  RETURN   0 1
```

**æ ˆå¸§å¤ç”¨è¿‡ç¨‹**ï¼š

```
sum(5, 0):
â”Œâ”€â”€â”€â”€â”€â”€â”€â”€â”€â”€â”
â”‚ n=5      â”‚
â”‚ acc=0    â”‚
â””â”€â”€â”€â”€â”€â”€â”€â”€â”€â”€â”˜

å°¾è°ƒç”¨ sum(4, 5): (å¤ç”¨æ ˆå¸§)
â”Œâ”€â”€â”€â”€â”€â”€â”€â”€â”€â”€â”
â”‚ n=4      â”‚ â† ç›´æ¥è¦†ç›–
â”‚ acc=5    â”‚
â””â”€â”€â”€â”€â”€â”€â”€â”€â”€â”€â”˜

å°¾è°ƒç”¨ sum(3, 9):
â”Œâ”€â”€â”€â”€â”€â”€â”€â”€â”€â”€â”
â”‚ n=3      â”‚
â”‚ acc=9    â”‚
â””â”€â”€â”€â”€â”€â”€â”€â”€â”€â”€â”˜

... (æ ˆæ·±åº¦ä¸å˜)

å°¾è°ƒç”¨ sum(0, 15):
â”Œâ”€â”€â”€â”€â”€â”€â”€â”€â”€â”€â”
â”‚ n=0      â”‚
â”‚ acc=15   â”‚
â””â”€â”€â”€â”€â”€â”€â”€â”€â”€â”€â”˜
â†“
return 15
```

**å¯¹æ¯”ï¼šæ— å°¾è°ƒç”¨ä¼˜åŒ–**

```lua
-- éå°¾è°ƒç”¨ç‰ˆæœ¬
function sum(n, acc)
    if n == 0 then
        return acc
    end
    local result = sum(n - 1, acc + n)  -- éå°¾è°ƒç”¨
    return result  -- éœ€è¦é¢å¤–çš„return
end
```

**æ ˆå¢é•¿**ï¼š
```
sum(5, 0)
  â”œâ”€ sum(4, 5)
  â”‚   â”œâ”€ sum(3, 9)
  â”‚   â”‚   â”œâ”€ sum(2, 12)
  â”‚   â”‚   â”‚   â”œâ”€ sum(1, 14)
  â”‚   â”‚   â”‚   â”‚   â””â”€ sum(0, 15) â†’ 15
  â”‚   â”‚   â”‚   â””â”€ return 15
  â”‚   â”‚   â””â”€ return 15
  â”‚   â””â”€ return 15
  â””â”€ return 15
```

### 8.5 å°¾è°ƒç”¨è®¡æ•°å™¨

```c
typedef struct CallInfo {
    // ...
    int tailcalls;  /* è¿ç»­å°¾è°ƒç”¨æ¬¡æ•° */
} CallInfo;
```

**ä½œç”¨**ï¼š
1. **è°ƒè¯•ä¿¡æ¯**ï¼š`debug.traceback()` ä¼šæ˜¾ç¤ºå°¾è°ƒç”¨æ¬¡æ•°
2. **é’©å­é™åˆ¶**ï¼šé¿å…é’©å­è¢«è§¦å‘å¤ªå¤šæ¬¡

**ç¤ºä¾‹**ï¼š
```lua
function f() return g() end
function g() return h() end
function h() return 42 end

f()
-- è°ƒç”¨é“¾: f â†’ g â†’ h
-- tailcalls: fè°ƒç”¨gæ—¶+1, gè°ƒç”¨hæ—¶+1
```

### 8.6 å°¾è°ƒç”¨çš„é™åˆ¶

**Cå‡½æ•°ä¸èƒ½è¢«å°¾è°ƒç”¨ä¼˜åŒ–**ï¼š
```lua
-- æ— æ³•ä¼˜åŒ–ï¼ˆmath.sqrtæ˜¯Cå‡½æ•°ï¼‰
function f(x)
    return math.sqrt(x)  -- å½“ä½œæ™®é€šè°ƒç”¨
end
```

**åŸå› **ï¼šCå‡½æ•°ä½¿ç”¨Cè°ƒç”¨æ ˆï¼Œæ— æ³•å¤ç”¨Luaæ ˆå¸§

**è¿”å›è¡¨è¾¾å¼ä¸èƒ½æ˜¯å°¾è°ƒç”¨**ï¼š
```lua
-- éå°¾è°ƒç”¨
function f(x)
    return g(x) + 1  -- éœ€è¦å¯¹ç»“æœè¿›è¡Œæ“ä½œ
end

-- éå°¾è°ƒç”¨
function f(x, y)
    return x, g(y)  -- å¤šè¿”å›å€¼çš„ç¬¬äºŒä¸ª
end
```

---

## 9. å¯å˜å‚æ•°å¤„ç†

### 9.1 å¯å˜å‚æ•°å‡½æ•°

```lua
function test(a, b, ...)
    print(a, b)
    print(...)
end

test(1, 2, 3, 4, 5)
-- a=1, b=2
-- ... = 3, 4, 5
```

### 9.2 adjust_varargs å‡½æ•°

```c
static StkId adjust_varargs (lua_State *L, Proto *p, int actual) {
    int i;
    int nfixargs = p->numparams;  // å›ºå®šå‚æ•°æ•°é‡
    Table *htab = NULL;
    StkId base, fixed;
    
    // 1. åˆ›å»º arg è¡¨ï¼ˆå¦‚æœéœ€è¦ï¼‰
    if (p->is_vararg & VARARG_NEEDSARG) {
        int nvar = actual - nfixargs;  // å¯å˜å‚æ•°æ•°é‡
        if (nvar < 0) nvar = 0;
        
        htab = luaH_new(L, nvar, 1);  // åˆ›å»ºè¡¨
        // ... å¡«å……argè¡¨ ...
    }
    
    // 2. ç§»åŠ¨å›ºå®šå‚æ•°
    fixed = L->top - actual;  // å‚æ•°èµ·å§‹ä½ç½®
    base = L->top;  // æ–°æ ˆåŸºå€ï¼ˆåœ¨å¯å˜å‚æ•°ä¹‹åï¼‰
    
    for (i = 0; i < nfixargs; i++) {
        setobjs2s(L, L->top++, fixed + i);
        setnilvalue(fixed + i);  // æ¸…ç©ºåŸä½ç½®
    }
    
    // 3. è®¾ç½®argè¡¨ï¼ˆå¦‚æœæœ‰ï¼‰
    if (htab) {
        sethvalue(L, L->top++, htab);
    }
    
    return base;
}
```

### 9.3 å¯å˜å‚æ•°æ ˆå¸ƒå±€

**è°ƒç”¨å‰**ï¼š
```
â”Œâ”€â”€â”€â”€â”€â”€â”€â”€â”€â”€â”€â”€â”
â”‚ å‡½æ•°å¯¹è±¡   â”‚ â† func
â”‚ å‚æ•°1 (a)  â”‚
â”‚ å‚æ•°2 (b)  â”‚
â”‚ å‚æ•°3      â”‚ â† å¯å˜å‚æ•°å¼€å§‹
â”‚ å‚æ•°4      â”‚
â”‚ å‚æ•°5      â”‚
â”œâ”€â”€â”€â”€â”€â”€â”€â”€â”€â”€â”€â”€â”¤ â† top
```

**adjust_varargs å**ï¼š
```
â”Œâ”€â”€â”€â”€â”€â”€â”€â”€â”€â”€â”€â”€â”
â”‚ å‡½æ•°å¯¹è±¡   â”‚ â† func
â”‚ nil        â”‚ â† åŸå‚æ•°ä½ç½®è¢«æ¸…ç©º
â”‚ nil        â”‚
â”‚ å‚æ•°3      â”‚ â† å¯å˜å‚æ•°ä¿ç•™
â”‚ å‚æ•°4      â”‚
â”‚ å‚æ•°5      â”‚
â”œâ”€â”€â”€â”€â”€â”€â”€â”€â”€â”€â”€â”€â”¤
â”‚ å‚æ•°1 (a)  â”‚ â† base (æ–°æ ˆåŸºå€)
â”‚ å‚æ•°2 (b)  â”‚
â”‚ å±€éƒ¨å˜é‡1  â”‚
â”‚ ...        â”‚
â”œâ”€â”€â”€â”€â”€â”€â”€â”€â”€â”€â”€â”€â”¤ â† top
```

### 9.4 è®¿é—®å¯å˜å‚æ•°

**æ–¹æ³•1ï¼šç›´æ¥ä½¿ç”¨ ...**
```lua
function test(...)
    print(...)  -- ç›´æ¥ä¼ é€’
    local args = {...}  -- æ‰“åŒ…æˆè¡¨
end
```

**å­—èŠ‚ç **ï¼š
```
function <test:1,4> (3 instructions)
    1  [2]  GETGLOBAL 0 -1  ; print
    2  [2]  VARARG    1 0   ; å±•å¼€å¯å˜å‚æ•°
    3  [2]  CALL      0 0 1
    4  [3]  NEWTABLE  0 0 0
    5  [3]  VARARG    1 0   ; å†æ¬¡å±•å¼€
    6  [3]  SETLIST   0 0 1
```

**æ–¹æ³•2ï¼šé€šè¿‡ select**
```lua
function test(...)
    local n = select('#', ...)  -- å‚æ•°æ•°é‡
    local first = select(1, ...)  -- ç¬¬1ä¸ªå‚æ•°
end
```

**æ–¹æ³•3ï¼šæ—§å¼ arg è¡¨ï¼ˆä¸æ¨èï¼‰**
```lua
function test(...)
    -- Lua 5.0 é£æ ¼
    print(arg.n)  -- å‚æ•°æ•°é‡
    print(arg[1]) -- ç¬¬1ä¸ªå‚æ•°
end
```

### 9.5 VARARG æŒ‡ä»¤

```c
case OP_VARARG: {
    int b;
    int j;
    CallInfo *ci = L->ci;
    int n = cast_int(ci->base - ci->func) - cl->p->numparams - 1;
    
    b = GETARG_B(i) - 1;
    
    if (b == LUA_MULTRET) {
        // å±•å¼€æ‰€æœ‰å¯å˜å‚æ•°
        luaD_checkstack(L, n);
        ra = RA(i);
        for (j = 0; j < n; j++)
            setobjs2s(L, ra + j, ci->base - n + j);
        L->top = ra + n;
    } else {
        // å±•å¼€æŒ‡å®šæ•°é‡
        for (j = 0; j < b && j < n; j++)
            setobjs2s(L, ra + j, ci->base - n + j);
        for (; j < b; j++)  // ä¸è¶³çš„å¡«nil
            setnilvalue(ra + j);
    }
    continue;
}
```

### 9.6 å®Œæ•´ç¤ºä¾‹

**ä»£ç **ï¼š
```lua
function printf(fmt, ...)
    local args = {...}
    io.write(string.format(fmt, unpack(args)))
end

printf("x=%d, y=%d\n", 10, 20)
```

**æ‰§è¡Œæµç¨‹**ï¼š

| æ­¥éª¤ | æ“ä½œ | æ ˆçŠ¶æ€ |
|------|------|--------|
| 1 | CALL printf | `[printf]["x=%d, y=%d\n"][10][20]` |
| 2 | precall | è°ƒæ•´æ ˆï¼Œfmtåœ¨R(0) |
| 3 | VARARG | å±•å¼€10, 20åˆ°ä¸´æ—¶è¡¨ |
| 4 | GETGLOBAL io.write | å‡†å¤‡è°ƒç”¨io.write |
| 5 | CALL string.format | ç”Ÿæˆæ ¼å¼åŒ–å­—ç¬¦ä¸² |
| 6 | CALL io.write | è¾“å‡ºç»“æœ |

---

## 10. å®æˆ˜æ¡ˆä¾‹åˆ†æ

### 10.1 æ¡ˆä¾‹1ï¼šç®€å•è°ƒç”¨é“¾

**Lua ä»£ç **ï¼š
```lua
local function add(a, b)
    return a + b
end

local function multiply(x, y)
    local sum = add(x, y)
    return sum * 2
end

local result = multiply(5, 3)
print(result)  -- 16
```

**å­—èŠ‚ç åˆ†æ**ï¼š

```
; add å‡½æ•°
function <add:1,3> (2 instructions)
    1  [2]  ADD      2 0 1    ; R(2) = R(0) + R(1)
    2  [2]  RETURN   2 2      ; return R(2)
    3  [3]  RETURN   0 1

; multiply å‡½æ•°
function <multiply:5,9> (7 instructions)
    1  [6]  GETGLOBAL 2 -1    ; add
    2  [6]  MOVE     3 0      ; x
    3  [6]  MOVE     4 1      ; y
    4  [6]  CALL     2 3 2    ; sum = add(x, y)
    5  [7]  MUL      2 2 -2   ; R(2) = sum * 2
    6  [7]  RETURN   2 2      ; return R(2)
    7  [8]  RETURN   0 1

; ä¸»å‡½æ•°
    1  [11] GETGLOBAL 0 -1    ; multiply
    2  [11] LOADK    1 -2     ; 5
    3  [11] LOADK    2 -3     ; 3
    4  [11] CALL     0 3 2    ; result = multiply(5, 3)
    5  [12] GETGLOBAL 1 -4    ; print
    6  [12] MOVE     2 0      ; result
    7  [12] CALL     1 2 1
```

**è°ƒç”¨æ ˆæ¼”å˜**ï¼š

```mermaid
graph TD
    A[ä¸»å‡½æ•°] -->|CALL multiply| B[multiply]
    B -->|CALL add| C[add]
    C -->|RETURN 8| B
    B -->|RETURN 16| A
    A -->|CALL print| D[print]
    D -->|RETURN| A
    
    style A fill:#e1f5fe
    style B fill:#fff9c4
    style C fill:#f8bbd0
    style D fill:#c8e6c9
```

**è¯¦ç»†æ ˆçŠ¶æ€**ï¼š

```
t=0 (ä¸»å‡½æ•°è°ƒç”¨multiply):
â”Œâ”€â”€â”€â”€â”€â”€â”€â”€â”€â”€â”€â”€â”€â”€â”€â”€â”
â”‚ [multiply]     â”‚ â† func
â”‚ [5]            â”‚
â”‚ [3]            â”‚
â”œâ”€â”€â”€â”€â”€â”€â”€â”€â”€â”€â”€â”€â”€â”€â”€â”€â”¤ â† top

t=1 (multiplyå†…éƒ¨):
â”Œâ”€â”€â”€â”€â”€â”€â”€â”€â”€â”€â”€â”€â”€â”€â”€â”€â”
â”‚ R(0) = 5       â”‚ â† base
â”‚ R(1) = 3       â”‚
â”‚ R(2) = add     â”‚ â† å‡†å¤‡è°ƒç”¨add
â”‚ R(3) = 5       â”‚
â”‚ R(4) = 3       â”‚
â”œâ”€â”€â”€â”€â”€â”€â”€â”€â”€â”€â”€â”€â”€â”€â”€â”€â”¤ â† top

t=2 (addæ‰§è¡Œ):
â”Œâ”€â”€â”€â”€â”€â”€â”€â”€â”€â”€â”€â”€â”€â”€â”€â”€â”
â”‚ ... multiplyæ ˆ â”‚
â”œâ”€â”€â”€â”€â”€â”€â”€â”€â”€â”€â”€â”€â”€â”€â”€â”€â”¤
â”‚ R(0) = 5       â”‚ â† addçš„base
â”‚ R(1) = 3       â”‚
â”‚ R(2) = 8       â”‚ â† è®¡ç®—ç»“æœ
â”œâ”€â”€â”€â”€â”€â”€â”€â”€â”€â”€â”€â”€â”€â”€â”€â”€â”¤ â† top

t=3 (addè¿”å›å):
â”Œâ”€â”€â”€â”€â”€â”€â”€â”€â”€â”€â”€â”€â”€â”€â”€â”€â”
â”‚ R(0) = 5       â”‚ â† multiplyçš„base
â”‚ R(1) = 3       â”‚
â”‚ R(2) = 8       â”‚ â† sum (è¦†ç›–addå‡½æ•°ä½ç½®)
â”œâ”€â”€â”€â”€â”€â”€â”€â”€â”€â”€â”€â”€â”€â”€â”€â”€â”¤ â† top

t=4 (multiplyè¿”å›):
â”Œâ”€â”€â”€â”€â”€â”€â”€â”€â”€â”€â”€â”€â”€â”€â”€â”€â”
â”‚ [16]           â”‚ â† result (è¦†ç›–multiply)
â”œâ”€â”€â”€â”€â”€â”€â”€â”€â”€â”€â”€â”€â”€â”€â”€â”€â”¤ â† top
```

### 10.2 æ¡ˆä¾‹2ï¼šå°¾é€’å½’ä¼˜åŒ–

**ä»£ç **ï¼š
```lua
local function factorial_tail(n, acc)
    if n <= 1 then
        return acc
    else
        return factorial_tail(n - 1, n * acc)  -- å°¾è°ƒç”¨
    end
end

local result = factorial_tail(5, 1)
print(result)  -- 120
```

**å­—èŠ‚ç **ï¼š
```
function <factorial_tail:1,7> (13 instructions)
    1  [2]  LE       1 0 -1   ; n <= 1?
    2  [2]  JMP      2
    3  [3]  RETURN   1 2      ; return acc
    4  [3]  JMP      7
    5  [5]  GETGLOBAL 2 -2    ; factorial_tail
    6  [5]  SUB      3 0 -3   ; n - 1
    7  [5]  MUL      4 0 1    ; n * acc
    8  [5]  TAILCALL 2 3 0    ; å°¾è°ƒç”¨
    9  [5]  RETURN   2 0
   10  [6]  JMP      -10
   11  [7]  RETURN   0 1
```

**æ ˆæ·±åº¦ä¿æŒä¸å˜**ï¼š

```
åˆå§‹: factorial_tail(5, 1)
â”Œâ”€â”€â”€â”€â”€â”€â”€â”€â”€â”€â”€â”€â”
â”‚ n=5        â”‚
â”‚ acc=1      â”‚
â””â”€â”€â”€â”€â”€â”€â”€â”€â”€â”€â”€â”€â”˜

å°¾è°ƒç”¨å: factorial_tail(4, 5)  â† å¤ç”¨æ ˆå¸§
â”Œâ”€â”€â”€â”€â”€â”€â”€â”€â”€â”€â”€â”€â”
â”‚ n=4        â”‚
â”‚ acc=5      â”‚
â””â”€â”€â”€â”€â”€â”€â”€â”€â”€â”€â”€â”€â”˜

å°¾è°ƒç”¨å: factorial_tail(3, 20)
â”Œâ”€â”€â”€â”€â”€â”€â”€â”€â”€â”€â”€â”€â”
â”‚ n=3        â”‚
â”‚ acc=20     â”‚
â””â”€â”€â”€â”€â”€â”€â”€â”€â”€â”€â”€â”€â”˜

å°¾è°ƒç”¨å: factorial_tail(2, 60)
â”Œâ”€â”€â”€â”€â”€â”€â”€â”€â”€â”€â”€â”€â”
â”‚ n=2        â”‚
â”‚ acc=60     â”‚
â””â”€â”€â”€â”€â”€â”€â”€â”€â”€â”€â”€â”€â”˜

å°¾è°ƒç”¨å: factorial_tail(1, 120)
â”Œâ”€â”€â”€â”€â”€â”€â”€â”€â”€â”€â”€â”€â”
â”‚ n=1        â”‚
â”‚ acc=120    â”‚
â””â”€â”€â”€â”€â”€â”€â”€â”€â”€â”€â”€â”€â”˜
â†“ return 120

æ ˆæ·±åº¦å§‹ç»ˆä¸º1ï¼
```

### 10.3 æ¡ˆä¾‹3ï¼šCå‡½æ•°è°ƒç”¨

**C ä»£ç **ï¼š
```c
// è‡ªå®šä¹‰mathåº“å‡½æ•°
static int l_quadratic(lua_State *L) {
    double a = luaL_checknumber(L, 1);
    double b = luaL_checknumber(L, 2);
    double c = luaL_checknumber(L, 3);
    
    double discriminant = b*b - 4*a*c;
    
    if (discriminant < 0) {
        lua_pushnil(L);
        lua_pushstring(L, "no real roots");
        return 2;
    }
    
    double sqrt_d = sqrt(discriminant);
    double x1 = (-b + sqrt_d) / (2*a);
    double x2 = (-b - sqrt_d) / (2*a);
    
    lua_pushnumber(L, x1);
    lua_pushnumber(L, x2);
    return 2;
}

// æ³¨å†Œå‡½æ•°
lua_register(L, "quadratic", l_quadratic);
```

**Lua è°ƒç”¨**ï¼š
```lua
local x1, x2 = quadratic(1, -3, 2)
print(x1, x2)  -- 2, 1 (æ±‚è§£ x^2 - 3x + 2 = 0)
```

**æ ˆçŠ¶æ€å˜åŒ–**ï¼š

| é˜¶æ®µ | æ ˆå†…å®¹ | è¯´æ˜ |
|------|--------|------|
| è°ƒç”¨å‰ | `[quadratic][1][-3][2]` | å‡†å¤‡è°ƒç”¨ |
| Cå‡½æ•°å¼€å§‹ | `baseâ†’[1][-3][2]` | è¿›å…¥Cå‡½æ•° |
| æ£€æŸ¥å‚æ•° | è·å–a=1, b=-3, c=2 | luaL_checknumber |
| è®¡ç®— | discriminant = 1 | bÂ² - 4ac |
| å‹å…¥ç»“æœ | `[1][-3][2][2][1]` | x1=2, x2=1 |
| è¿”å› | n=2 | è¿”å›2ä¸ªå€¼ |
| poscallå | `[2][1]` | ä¿ç•™è¿”å›å€¼ |

### 10.4 æ¡ˆä¾‹4ï¼šé«˜é˜¶å‡½æ•°

**ä»£ç **ï¼š
```lua
local function map(func, list)
    local result = {}
    for i, v in ipairs(list) do
        result[i] = func(v)
    end
    return result
end

local function square(x)
    return x * x
end

local numbers = {1, 2, 3, 4, 5}
local squares = map(square, numbers)
-- {1, 4, 9, 16, 25}
```

**è°ƒç”¨åˆ†æ**ï¼š

```
map å‡½æ•°è¢«è°ƒç”¨:
    â†’ func = square é—­åŒ…
    â†’ list = {1, 2, 3, 4, 5}
    
    å¾ªç¯è¿­ä»£ i=1:
        â†’ CALL func(1)
            â†’ square(1)
            â†’ RETURN 1
        â†’ result[1] = 1
    
    å¾ªç¯è¿­ä»£ i=2:
        â†’ CALL func(2)
            â†’ square(2)
            â†’ RETURN 4
        â†’ result[2] = 4
    
    ... (ç»§ç»­)
    
    è¿”å› result
```

### 10.5 æ¡ˆä¾‹5ï¼šåç¨‹è°ƒç”¨

**ä»£ç **ï¼š
```lua
local function producer()
    for i = 1, 5 do
        coroutine.yield(i)
    end
end

local co = coroutine.create(producer)

while true do
    local ok, value = coroutine.resume(co)
    if not ok or value == nil then break end
    print(value)
end
```

**è°ƒç”¨æµç¨‹**ï¼š

```mermaid
sequenceDiagram
    participant Main as ä¸»åç¨‹
    participant CO as produceråç¨‹
    
    Main->>CO: resume()
    activate CO
    CO->>CO: i=1
    CO-->>Main: yield(1)
    deactivate CO
    Main->>Main: print(1)
    
    Main->>CO: resume()
    activate CO
    CO->>CO: i=2
    CO-->>Main: yield(2)
    deactivate CO
    Main->>Main: print(2)
    
    Note over Main,CO: ... (ç»§ç»­)
    
    Main->>CO: resume()
    activate CO
    CO->>CO: å¾ªç¯ç»“æŸ
    CO-->>Main: return nil
    deactivate CO
    Main->>Main: é€€å‡ºå¾ªç¯
```

---

## å…³é”®æ•°æ®ç»“æ„

### CallInfo ç»“æ„

```c
typedef struct CallInfo {
    StkId base;              /* æ ˆåŸºå€ï¼ˆå‡½æ•°ç¬¬ä¸€ä¸ªå‚æ•°ï¼‰ */
    StkId func;              /* å‡½æ•°å¯¹è±¡ä½ç½® */
    StkId top;               /* æ ˆé¡¶ï¼ˆbase + maxstacksizeï¼‰ */
    const Instruction *savedpc;  /* ä¿å­˜çš„ç¨‹åºè®¡æ•°å™¨ */
    int nresults;            /* æœŸæœ›çš„è¿”å›å€¼æ•°é‡ */
    int tailcalls;           /* å°¾è°ƒç”¨è®¡æ•°å™¨ */
} CallInfo;
```

**å­—æ®µè¯´æ˜**ï¼š
- `base`: æŒ‡å‘å‡½æ•°çš„ç¬¬ä¸€ä¸ªå¯„å­˜å™¨ï¼ˆR(0)ï¼‰
- `func`: æŒ‡å‘å‡½æ•°å¯¹è±¡ï¼ˆåœ¨baseä¹‹å‰ï¼‰
- `top`: å‡½æ•°å¯ç”¨çš„æœ€å¤§æ ˆç©ºé—´
- `savedpc`: è°ƒç”¨ç‚¹çš„PCï¼Œç”¨äºè¿”å›
- `nresults`: è°ƒç”¨è€…æœŸæœ›çš„è¿”å›å€¼æ•°é‡ï¼ˆ-1è¡¨ç¤ºå…¨éƒ¨ï¼‰
- `tailcalls`: è¿ç»­å°¾è°ƒç”¨æ¬¡æ•°ï¼Œç”¨äºè°ƒè¯•

### Proto ç»“æ„ï¼ˆå‡½æ•°åŸå‹ï¼‰

```c
typedef struct Proto {
    TValue *k;               /* å¸¸é‡æ•°ç»„ */
    Instruction *code;       /* å­—èŠ‚ç æ•°ç»„ */
    struct Proto **p;        /* åµŒå¥—å‡½æ•°åŸå‹ */
    int *lineinfo;           /* è¡Œå·ä¿¡æ¯ */
    struct LocVar *locvars;  /* å±€éƒ¨å˜é‡ä¿¡æ¯ */
    TString **upvalues;      /* upvalueåç§° */
    TString *source;         /* æºæ–‡ä»¶å */
    int sizeupvalues;        /* upvalueæ•°é‡ */
    int sizek;               /* å¸¸é‡æ•°é‡ */
    int sizecode;            /* æŒ‡ä»¤æ•°é‡ */
    int sizelineinfo;
    int sizep;               /* åµŒå¥—å‡½æ•°æ•°é‡ */
    int sizelocvars;         /* å±€éƒ¨å˜é‡æ•°é‡ */
    int linedefined;         /* å‡½æ•°å®šä¹‰èµ·å§‹è¡Œ */
    int lastlinedefined;     /* å‡½æ•°å®šä¹‰ç»“æŸè¡Œ */
    GCObject *gclist;
    lu_byte nups;            /* upvalueæ•°é‡ */
    lu_byte numparams;       /* å‚æ•°æ•°é‡ */
    lu_byte is_vararg;       /* å¯å˜å‚æ•°æ ‡å¿— */
    lu_byte maxstacksize;    /* æœ€å¤§æ ˆå¤§å° */
} Proto;
```

### Closure ç»“æ„ï¼ˆé—­åŒ…ï¼‰

```c
/* Luaé—­åŒ… */
typedef struct LClosure {
    ClosureHeader;
    struct Proto *p;         /* å‡½æ•°åŸå‹ */
    UpVal *upvals[1];        /* upvalueæ•°ç»„ */
} LClosure;

/* Cé—­åŒ… */
typedef struct CClosure {
    ClosureHeader;
    lua_CFunction f;         /* Cå‡½æ•°æŒ‡é’ˆ */
    TValue upvalue[1];       /* upvalueæ•°ç»„ */
} CClosure;

/* é€šç”¨é—­åŒ… */
typedef union Closure {
    LClosure l;
    CClosure c;
} Closure;
```

---

## è°ƒç”¨æ ˆç¤ºæ„å›¾

### å®Œæ•´è°ƒç”¨æ ˆç»“æ„

```
â”â”â”â”â”â”â”â”â”â”â”â”â”â”â”â”â”â”â”â”â”â”â”â”â”â”â”â”â”â”â”â”â”â”â”â”â”â”
         Lua è°ƒç”¨æ ˆ (lua_State)
â”â”â”â”â”â”â”â”â”â”â”â”â”â”â”â”â”â”â”â”â”â”â”â”â”â”â”â”â”â”â”â”â”â”â”â”â”â”

â”Œâ”€â”€â”€â”€â”€â”€â”€â”€â”€â”€â”€â”€â”€â”€â”€â”€â”€â”€â”€â”€â”€â”€â”€â”€â”€â”€â”€â”€â”€â”€â”€â”€â”€â”€â”€â”€â”
â”‚          C è°ƒç”¨æ ˆï¼ˆæ“ä½œç³»ç»Ÿï¼‰        â”‚
â”œâ”€â”€â”€â”€â”€â”€â”€â”€â”€â”€â”€â”€â”€â”€â”€â”€â”€â”€â”€â”€â”€â”€â”€â”€â”€â”€â”€â”€â”€â”€â”€â”€â”€â”€â”€â”€â”¤
â”‚  lua_pcall(L, ...)                 â”‚
â”‚    â””â”€ luaD_call()                  â”‚
â”‚         â””â”€ luaD_precall()          â”‚
â”‚              â””â”€ luaV_execute()     â”‚
â””â”€â”€â”€â”€â”€â”€â”€â”€â”€â”€â”€â”€â”€â”€â”€â”€â”€â”€â”€â”€â”€â”€â”€â”€â”€â”€â”€â”€â”€â”€â”€â”€â”€â”€â”€â”€â”˜
                  â†“
â”Œâ”€â”€â”€â”€â”€â”€â”€â”€â”€â”€â”€â”€â”€â”€â”€â”€â”€â”€â”€â”€â”€â”€â”€â”€â”€â”€â”€â”€â”€â”€â”€â”€â”€â”€â”€â”€â”
â”‚      CallInfo é“¾ (L->ci)           â”‚
â”œâ”€â”€â”€â”€â”€â”€â”€â”€â”€â”€â”€â”€â”€â”€â”€â”€â”€â”€â”€â”€â”€â”€â”€â”€â”€â”€â”€â”€â”€â”€â”€â”€â”€â”€â”€â”€â”¤
â”‚  CallInfo[0]  â† base_ci            â”‚
â”‚    func: ä¸»å‡½æ•°                    â”‚
â”‚    base: stack_init                â”‚
â”‚    top:  stack_init + size         â”‚
â”œâ”€â”€â”€â”€â”€â”€â”€â”€â”€â”€â”€â”€â”€â”€â”€â”€â”€â”€â”€â”€â”€â”€â”€â”€â”€â”€â”€â”€â”€â”€â”€â”€â”€â”€â”€â”€â”¤
â”‚  CallInfo[1]                       â”‚
â”‚    func: function f()              â”‚
â”‚    base: ...                       â”‚
â”‚    savedpc: ...                    â”‚
â”œâ”€â”€â”€â”€â”€â”€â”€â”€â”€â”€â”€â”€â”€â”€â”€â”€â”€â”€â”€â”€â”€â”€â”€â”€â”€â”€â”€â”€â”€â”€â”€â”€â”€â”€â”€â”€â”¤
â”‚  CallInfo[2]  â† L->ci (å½“å‰)       â”‚
â”‚    func: function g()              â”‚
â”‚    base: ...                       â”‚
â”‚    savedpc: ...                    â”‚
â””â”€â”€â”€â”€â”€â”€â”€â”€â”€â”€â”€â”€â”€â”€â”€â”€â”€â”€â”€â”€â”€â”€â”€â”€â”€â”€â”€â”€â”€â”€â”€â”€â”€â”€â”€â”€â”˜
                  â†“
â”Œâ”€â”€â”€â”€â”€â”€â”€â”€â”€â”€â”€â”€â”€â”€â”€â”€â”€â”€â”€â”€â”€â”€â”€â”€â”€â”€â”€â”€â”€â”€â”€â”€â”€â”€â”€â”€â”
â”‚      æ ˆå†…å­˜ (L->stack)             â”‚
â”œâ”€â”€â”€â”€â”€â”€â”€â”€â”€â”€â”€â”€â”€â”€â”€â”€â”€â”€â”€â”€â”€â”€â”€â”€â”€â”€â”€â”€â”€â”€â”€â”€â”€â”€â”€â”€â”¤
â”‚  [ä¸»å‡½æ•°æ•°æ®]                      â”‚
â”‚  [ä¸»å‡½æ•°å±€éƒ¨å˜é‡]                  â”‚
â”œâ”€â”€â”€â”€â”€â”€â”€â”€â”€â”€â”€â”€â”€â”€â”€â”€â”€â”€â”€â”€â”€â”€â”€â”€â”€â”€â”€â”€â”€â”€â”€â”€â”€â”€â”€â”€â”¤
â”‚  [få‡½æ•°å¯¹è±¡]   â† CallInfo[1].func  â”‚
â”‚  [fçš„å‚æ•°]     â† CallInfo[1].base  â”‚
â”‚  [fçš„å±€éƒ¨å˜é‡]                     â”‚
â”œâ”€â”€â”€â”€â”€â”€â”€â”€â”€â”€â”€â”€â”€â”€â”€â”€â”€â”€â”€â”€â”€â”€â”€â”€â”€â”€â”€â”€â”€â”€â”€â”€â”€â”€â”€â”€â”¤
â”‚  [gå‡½æ•°å¯¹è±¡]   â† CallInfo[2].func  â”‚
â”‚  [gçš„å‚æ•°]     â† CallInfo[2].base  â”‚
â”‚  [gçš„å±€éƒ¨å˜é‡] â† L->base           â”‚
â”‚  [ä¸´æ—¶å€¼]      â† L->top            â”‚
â”œâ”€â”€â”€â”€â”€â”€â”€â”€â”€â”€â”€â”€â”€â”€â”€â”€â”€â”€â”€â”€â”€â”€â”€â”€â”€â”€â”€â”€â”€â”€â”€â”€â”€â”€â”€â”€â”¤
â”‚  [ç©ºé—²ç©ºé—´]                        â”‚
â”œâ”€â”€â”€â”€â”€â”€â”€â”€â”€â”€â”€â”€â”€â”€â”€â”€â”€â”€â”€â”€â”€â”€â”€â”€â”€â”€â”€â”€â”€â”€â”€â”€â”€â”€â”€â”€â”¤ â† L->stack_last
â”‚  [é¢å¤–ç©ºé—´]                        â”‚
â””â”€â”€â”€â”€â”€â”€â”€â”€â”€â”€â”€â”€â”€â”€â”€â”€â”€â”€â”€â”€â”€â”€â”€â”€â”€â”€â”€â”€â”€â”€â”€â”€â”€â”€â”€â”€â”˜ â† L->stack + L->stacksize
```

### è°ƒç”¨æ ˆå¢é•¿ç¤ºä¾‹

**ä»£ç **ï¼š
```lua
function a()
    return b()
end

function b()
    return c()
end

function c()
    return 42
end

a()
```

**CallInfoé“¾æ¼”å˜**ï¼š

```
åˆå§‹:
base_ci[0] â† ci (ä¸»å‡½æ•°)

è°ƒç”¨a():
base_ci[0]
base_ci[1] â† ci (a)

a()è°ƒç”¨b():
base_ci[0]
base_ci[1] (a)
base_ci[2] â† ci (b)

b()è°ƒç”¨c():
base_ci[0]
base_ci[1] (a)
base_ci[2] (b)
base_ci[3] â† ci (c)

c()è¿”å›42:
base_ci[0]
base_ci[1] (a)
base_ci[2] â† ci (b, è·å¾—è¿”å›å€¼42)

b()è¿”å›42:
base_ci[0]
base_ci[1] â† ci (a, è·å¾—è¿”å›å€¼42)

a()è¿”å›42:
base_ci[0] â† ci (ä¸»å‡½æ•°, è·å¾—è¿”å›å€¼42)
```

---

## æ€§èƒ½åˆ†æ

### è°ƒç”¨å¼€é”€å¯¹æ¯”

| è°ƒç”¨ç±»å‹ | ç›¸å¯¹å¼€é”€ | ä¸»è¦æˆæœ¬ |
|---------|---------|---------|
| **å±€éƒ¨å‡½æ•°è°ƒç”¨** | 1x | æ ˆå¸§åˆ›å»º + PCè·³è½¬ |
| **å…¨å±€å‡½æ•°è°ƒç”¨** | 1.2x | + å…¨å±€æŸ¥æ‰¾ |
| **è¡¨æ–¹æ³•è°ƒç”¨** | 1.5x | + è¡¨æŸ¥æ‰¾ + å…ƒè¡¨æŸ¥æ‰¾ |
| **Cå‡½æ•°è°ƒç”¨** | 0.8x | æ— å­—èŠ‚ç æ‰§è¡Œ |
| **å°¾è°ƒç”¨ï¼ˆä¼˜åŒ–ï¼‰** | 0.5x | æ ˆå¸§å¤ç”¨ |

### ä¼˜åŒ–å»ºè®®

**1. ä½¿ç”¨å±€éƒ¨å‡½æ•°**
```lua
-- æ…¢
for i = 1, 1000000 do
    math.sin(i)  -- æ¯æ¬¡æŸ¥æ‰¾å…¨å±€mathè¡¨
end

-- å¿«
local sin = math.sin
for i = 1, 1000000 do
    sin(i)  -- ç›´æ¥è°ƒç”¨
end
```

**2. åˆ©ç”¨å°¾è°ƒç”¨ä¼˜åŒ–**
```lua
-- å¯èƒ½æ ˆæº¢å‡º
function sum(n, acc)
    if n == 0 then return acc end
    acc = acc + n
    return sum(n - 1, acc)  -- ç¡®ä¿æ˜¯å°¾è°ƒç”¨
end
```

**3. å‡å°‘Cè°ƒç”¨å¼€é”€**
```lua
-- æ‰¹é‡è°ƒç”¨
local t = {}
for i = 1, 1000 do
    t[i] = i
end
table.sort(t)  -- ä¸€æ¬¡Cè°ƒç”¨

-- é¿å…é¢‘ç¹Cè°ƒç”¨
-- for i = 1, 1000 do
--     table.insert(t, i)  -- 1000æ¬¡Cè°ƒç”¨
-- end
```

### å†…å­˜ä½¿ç”¨

**CallInfo ç»“æ„å¤§å°**ï¼š
- çº¦ 48 å­—èŠ‚ï¼ˆ64ä½ç³»ç»Ÿï¼‰
- é»˜è®¤é¢„åˆ†é… 20 ä¸ª CallInfo

**æ ˆç©ºé—´**ï¼š
- é»˜è®¤ 20 KB
- æŒ‰éœ€å¢é•¿
- æ¯ä¸ªå‡½æ•°æ ˆå¸§å¤§å° = `maxstacksize * sizeof(TValue)`

---

## ç›¸å…³æ–‡æ¡£

### æ¨èé˜…è¯»é¡ºåº

1. **åŸºç¡€ç†è§£**
   - [`execution_loop.md`](./execution_loop.md) - è™šæ‹Ÿæœºæ‰§è¡Œå¾ªç¯
   - [`register_management.md`](./register_management.md) - å¯„å­˜å™¨åˆ†é…

2. **æœ¬æ–‡æ¡£**
   - `function_call.md` - å‡½æ•°è°ƒç”¨æœºåˆ¶ï¼ˆå½“å‰ï¼‰

3. **æ·±å…¥ä¸»é¢˜**
   - [`../gc/gc_principles.md`](../gc/gc_principles.md) - åƒåœ¾å›æ”¶ï¼ˆæ¶‰åŠé—­åŒ…å’Œupvalueï¼‰
   - [`../object/closure.md`](../object/closure.md) - é—­åŒ…å®ç°
   - [`../runtime/coroutine.md`](../runtime/coroutine.md) - åç¨‹æœºåˆ¶

### æºç å‚è€ƒ

| æ–‡ä»¶ | é‡ç‚¹å‡½æ•° |
|------|---------|
| `ldo.c` | `luaD_precall`, `luaD_poscall`, `luaD_call`, `luaD_callhook` |
| `lvm.c` | `OP_CALL`, `OP_TAILCALL`, `OP_RETURN`, `luaV_execute` |
| `lapi.c` | `lua_call`, `lua_pcall`, `lua_cpcall` |
| `lfunc.c` | `luaF_newLclosure`, `luaF_newCclosure`, `luaF_close` |
| `lobject.h` | `CallInfo`, `Closure`, `Proto` ç»“æ„å®šä¹‰ |

### ç›¸å…³é—®ç­”

- **Q1**: ä¸ºä»€ä¹ˆéœ€è¦ CallInfo ç»“æ„ï¼Ÿ
  - **A**: ä¿å­˜æ¯ä¸ªå‡½æ•°è°ƒç”¨çš„ä¸Šä¸‹æ–‡ï¼Œæ”¯æŒå¤šå±‚åµŒå¥—è°ƒç”¨å’Œåç¨‹åˆ‡æ¢

- **Q2**: å°¾è°ƒç”¨ä¼˜åŒ–çš„é™åˆ¶ï¼Ÿ
  - **A**: åªèƒ½ä¼˜åŒ– Lua å‡½æ•°ï¼ŒC å‡½æ•°æ— æ³•ä¼˜åŒ–ï¼›å¿…é¡»æ˜¯æœ€åä¸€ä¸ªæ“ä½œ

- **Q3**: å¤šè¿”å›å€¼å¦‚ä½•å®ç°ï¼Ÿ
  - **A**: é€šè¿‡æ ˆé¡¶æŒ‡é’ˆå’Œ `nresults` å‚æ•°æ§åˆ¶

- **Q4**: C å‡½æ•°å’Œ Lua å‡½æ•°è°ƒç”¨çš„åŒºåˆ«ï¼Ÿ
  - **A**: C å‡½æ•°ç›´æ¥æ‰§è¡Œè¿”å›ï¼ŒLua å‡½æ•°éœ€è¦å­—èŠ‚ç è§£é‡Š

---

## æ€»ç»“

### æ ¸å¿ƒè¦ç‚¹

1. **è°ƒç”¨æµç¨‹**ï¼š`OP_CALL` â†’ `luaD_precall` â†’ æ‰§è¡Œ â†’ `luaD_poscall`
2. **æ ˆå¸§ç®¡ç†**ï¼šé€šè¿‡ CallInfo é“¾ç»´æŠ¤è°ƒç”¨æ ˆ
3. **å°¾è°ƒç”¨ä¼˜åŒ–**ï¼šå¤ç”¨æ ˆå¸§ï¼Œé¿å…æ ˆæº¢å‡º
4. **ç»Ÿä¸€æ¥å£**ï¼šLua å’Œ C å‡½æ•°ä½¿ç”¨ç›¸åŒçš„è°ƒç”¨æœºåˆ¶
5. **å¯å˜å‚æ•°**ï¼šé€šè¿‡ `adjust_varargs` å’Œ `VARARG` æŒ‡ä»¤å¤„ç†

### è®¾è®¡äº®ç‚¹

- **é«˜æ•ˆ**ï¼šæœ€å°åŒ–æ ˆæ“ä½œå’Œå†…å­˜åˆ†é…
- **çµæ´»**ï¼šæ”¯æŒå¤šè¿”å›å€¼ã€å¯å˜å‚æ•°ã€å°¾è°ƒç”¨
- **ç»Ÿä¸€**ï¼šLua/C å‡½æ•°é€æ˜äº’æ“ä½œ
- **å®‰å…¨**ï¼šæ ˆæº¢å‡ºæ£€æŸ¥ã€é”™è¯¯ä¼ æ’­

### åº”ç”¨ä»·å€¼

ç†è§£å‡½æ•°è°ƒç”¨æœºåˆ¶å¯¹ä»¥ä¸‹åœºæ™¯è‡³å…³é‡è¦ï¼š
- ç¼–å†™é«˜æ€§èƒ½ Lua ä»£ç 
- å¼€å‘ C æ‰©å±•æ¨¡å—
- è°ƒè¯•å¤æ‚è°ƒç”¨é“¾
- ä¼˜åŒ–é€’å½’ç®—æ³•
- å®ç°åç¨‹åŠŸèƒ½

---

<div align="center">

**ğŸ“š æ·±å…¥ç ”ç©¶æ¨è**

[è™šæ‹ŸæœºåŸç†](../vm/) | [åƒåœ¾å›æ”¶](../gc/) | [é—­åŒ…å®ç°](../object/) | [åç¨‹æœºåˆ¶](../runtime/)

---

**ğŸ“ æ–‡æ¡£ä¿¡æ¯**

- **ä½œè€…**: DeepWiki è‡ªåŠ¨ç”Ÿæˆ
- **ç‰ˆæœ¬**: v1.0
- **æ—¥æœŸ**: 2025-01-17
- **Luaç‰ˆæœ¬**: 5.1.5

---

*æœ¬æ–‡æ¡£åŸºäº Lua 5.1.5 æºç åˆ†æï¼Œç»“åˆå®è·µç»éªŒç¼–å†™*

</div>
