# Lua 5.1 指令集深度解析

## 概述

Lua 5.1 虚拟机是基于寄存器的虚拟机，使用字节码指令执行。本文档详细分析了 Lua 5.1 的所有指令集，包括指令格式、操作语义和实现细节。

## 指令格式

Lua 5.1 的指令是32位无符号整数，包含以下字段：

```
指令格式 (32位):
+-------+-------+-------+-------+
| OP(6) | A(8)  |   B(9)   |  C(9)  |  iABC格式
+-------+-------+-------+-------+
| OP(6) | A(8)  |     Bx(18)     |  iABx格式  
+-------+-------+-------+-------+
| OP(6) | A(8)  |    sBx(18)     |  iAsBx格式
+-------+-------+-------+-------+
```

### 字段说明
- **OP**: 操作码 (6位，支持64种指令)
- **A**: 目标寄存器 (8位，0-255)
- **B**: 源寄存器/立即数 (9位，0-511)
- **C**: 源寄存器/立即数 (9位，0-511)
- **Bx**: 大立即数 (18位，无符号)
- **sBx**: 有符号立即数 (18位，有符号，偏移编码)

### 寄存器/常量编码 (RK)
- 如果参数的最高位为1，表示常量表索引
- 如果参数的最高位为0，表示寄存器索引
- `BITRK = 256` (第9位)，用于区分寄存器和常量

## 指令分类

### 1. 数据移动指令

#### OP_MOVE (0)
```
格式: MOVE A B     (iABC)
操作: R(A) := R(B)
描述: 将寄存器B的值复制到寄存器A
```

#### OP_LOADK (1)
```
格式: LOADK A Bx   (iABx)
操作: R(A) := Kst(Bx)
描述: 将常量表中索引为Bx的常量加载到寄存器A
```

#### OP_LOADBOOL (2)
```
格式: LOADBOOL A B C  (iABC)
操作: R(A) := (Bool)B; if (C) pc++
描述: 将布尔值B加载到寄存器A，如果C非零则跳过下一条指令
应用: 实现短路逻辑运算
```

#### OP_LOADNIL (3)
```
格式: LOADNIL A B  (iABC)
操作: R(A) := ... := R(B) := nil
描述: 将寄存器A到B（包含）设置为nil
```

### 2. Upvalue操作指令

#### OP_GETUPVAL (4)
```
格式: GETUPVAL A B  (iABC)
操作: R(A) := UpValue[B]
描述: 获取第B个upvalue的值到寄存器A
```

#### OP_SETUPVAL (8)
```
格式: SETUPVAL A B  (iABC)
操作: UpValue[B] := R(A)
描述: 设置第B个upvalue为寄存器A的值
```

### 3. 全局变量操作指令

#### OP_GETGLOBAL (5)
```
格式: GETGLOBAL A Bx  (iABx)
操作: R(A) := Gbl[Kst(Bx)]
描述: 从全局表中获取名为Kst(Bx)的变量到寄存器A
实现: 实际上是 R(A) := _ENV[Kst(Bx)]
```

#### OP_SETGLOBAL (7)
```
格式: SETGLOBAL A Bx  (iABx)
操作: Gbl[Kst(Bx)] := R(A)
描述: 将寄存器A的值设置到全局变量Kst(Bx)
实现: 实际上是 _ENV[Kst(Bx)] := R(A)
```

### 4. 表操作指令

#### OP_GETTABLE (6)
```
格式: GETTABLE A B C  (iABC)
操作: R(A) := R(B)[RK(C)]
描述: 获取表R(B)中键为RK(C)的值到寄存器A
元方法: 支持__index元方法
```

#### OP_SETTABLE (9)
```
格式: SETTABLE A B C  (iABC)
操作: R(A)[RK(B)] := RK(C)
描述: 设置表R(A)中键为RK(B)的值为RK(C)
元方法: 支持__newindex元方法
```

#### OP_NEWTABLE (10)
```
格式: NEWTABLE A B C  (iABC)
操作: R(A) := {} (size = B,C)
描述: 创建新表，数组部分大小为B，散列部分大小为C
实现: B和C使用浮点字节编码(floating point byte)
```

#### OP_SETLIST (33)
```
格式: SETLIST A B C  (iABC)
操作: R(A)[(C-1)*FPF+i] := R(A+i), 1 <= i <= B
描述: 批量设置表的数组部分
FPF: LFIELDS_PER_FLUSH = 50
注意: 如果C=0，则真实的C值在下一条指令中
```

### 5. 算术运算指令

#### OP_ADD (12)
```
格式: ADD A B C  (iABC)
操作: R(A) := RK(B) + RK(C)
描述: 加法运算
元方法: 支持__add元方法
```

#### OP_SUB (13)
```
格式: SUB A B C  (iABC)
操作: R(A) := RK(B) - RK(C)
描述: 减法运算
元方法: 支持__sub元方法
```

#### OP_MUL (14)
```
格式: MUL A B C  (iABC)
操作: R(A) := RK(B) * RK(C)
描述: 乘法运算
元方法: 支持__mul元方法
```

#### OP_DIV (15)
```
格式: DIV A B C  (iABC)
操作: R(A) := RK(B) / RK(C)
描述: 除法运算
元方法: 支持__div元方法
```

#### OP_MOD (16)
```
格式: MOD A B C  (iABC)
操作: R(A) := RK(B) % RK(C)
描述: 取模运算
元方法: 支持__mod元方法
```

#### OP_POW (17)
```
格式: POW A B C  (iABC)
操作: R(A) := RK(B) ^ RK(C)
描述: 幂运算
元方法: 支持__pow元方法
```

#### OP_UNM (18)
```
格式: UNM A B  (iABC)
操作: R(A) := -R(B)
描述: 一元取负运算
元方法: 支持__unm元方法
```

### 6. 逻辑运算指令

#### OP_NOT (19)
```
格式: NOT A B  (iABC)
操作: R(A) := not R(B)
描述: 逻辑非运算
实现: 只有nil和false为假，其他都为真
```

#### OP_LEN (20)
```
格式: LEN A B  (iABC)
操作: R(A) := length of R(B)
描述: 获取长度
支持类型: 字符串、表
元方法: 支持__len元方法
```

### 7. 字符串操作指令

#### OP_CONCAT (21)
```
格式: CONCAT A B C  (iABC)
操作: R(A) := R(B).. ... ..R(C)
描述: 字符串连接，连接寄存器B到C（包含）的所有值
元方法: 支持__concat元方法
```

### 8. 跳转指令

#### OP_JMP (22)
```
格式: JMP sBx  (iAsBx)
操作: pc += sBx
描述: 无条件跳转
范围: sBx为有符号18位，支持±131071的跳转距离
```

### 9. 比较指令

#### OP_EQ (23)
```
格式: EQ A B C  (iABC)
操作: if ((RK(B) == RK(C)) ~= A) then pc++
描述: 相等比较，如果比较结果与A不同则跳过下一条指令
元方法: 支持__eq元方法
```

#### OP_LT (24)
```
格式: LT A B C  (iABC)
操作: if ((RK(B) < RK(C)) ~= A) then pc++
描述: 小于比较
元方法: 支持__lt元方法
```

#### OP_LE (25)
```
格式: LE A B C  (iABC)
操作: if ((RK(B) <= RK(C)) ~= A) then pc++
描述: 小于等于比较
元方法: 支持__le元方法，如果没有则尝试使用__lt
```

### 10. 测试指令

#### OP_TEST (26)
```
格式: TEST A C  (iABC)
操作: if not (R(A) <=> C) then pc++
描述: 测试寄存器A的真假性，如果与C不符则跳过下一条指令
应用: 实现条件跳转和短路逻辑
```

#### OP_TESTSET (27)
```
格式: TESTSET A B C  (iABC)
操作: if (R(B) <=> C) then R(A) := R(B) else pc++
描述: 测试寄存器B，如果与C相符则赋值给A，否则跳过下一条指令
应用: 实现逻辑运算符 and 和 or 的短路特性
```

### 11. 函数调用指令

#### OP_CALL (28)
```
格式: CALL A B C  (iABC)
操作: R(A), ... ,R(A+C-2) := R(A)(R(A+1), ... ,R(A+B-1))
描述: 函数调用
参数:
  - A: 函数所在寄存器
  - B: 参数个数+1 (0表示使用top)
  - C: 返回值个数+1 (0表示使用LUA_MULTRET)
```

#### OP_TAILCALL (29)
```
格式: TAILCALL A B C  (iABC)
操作: return R(A)(R(A+1), ... ,R(A+B-1))
描述: 尾调用，复用当前栈帧
优化: 避免栈溢出，实现真正的尾递归
```

#### OP_RETURN (30)
```
格式: RETURN A B  (iABC)
操作: return R(A), ... ,R(A+B-2)
描述: 函数返回
参数:
  - A: 第一个返回值所在寄存器
  - B: 返回值个数+1 (0表示返回到top)
```

### 12. 方法调用指令

#### OP_SELF (11)
```
格式: SELF A B C  (iABC)
操作: R(A+1) := R(B); R(A) := R(B)[RK(C)]
描述: 为方法调用准备self参数
实现: table:method() 语法糖的底层实现
```

### 13. 循环指令

#### OP_FORLOOP (31)
```
格式: FORLOOP A sBx  (iAsBx)
操作: R(A) += R(A+2); if R(A) <?= R(A+1) then { pc += sBx; R(A+3) = R(A) }
描述: 数值for循环的循环体
寄存器布局:
  - R(A): 当前值 (index)
  - R(A+1): 限制值 (limit)
  - R(A+2): 步长 (step)
  - R(A+3): 循环变量
```

#### OP_FORPREP (32)
```
格式: FORPREP A sBx  (iAsBx)
操作: R(A) -= R(A+2); pc += sBx
描述: 数值for循环的初始化
作用: 预减步长，为第一次FORLOOP做准备
```

#### OP_TFORLOOP (33)
```
格式: TFORLOOP A C  (iABC)
操作: R(A+3), ... ,R(A+2+C) := R(A)(R(A+1), R(A+2));
      if R(A+3) ~= nil then R(A+2) = R(A+3) else pc++
描述: 通用for循环 (for k,v in pairs(t))
寄存器布局:
  - R(A): 迭代器函数
  - R(A+1): 状态
  - R(A+2): 控制变量
  - R(A+3+): 循环变量
```

### 14. 闭包相关指令

#### OP_CLOSURE (35)
```
格式: CLOSURE A Bx  (iABx)
操作: R(A) := closure(KPROTO[Bx], R(A), ... ,R(A+n))
描述: 创建闭包
实现: 后续指令指定upvalue的来源（GETUPVAL或MOVE）
```

#### OP_CLOSE (34)
```
格式: CLOSE A  (iABC)
操作: close all variables in the stack up to (>=) R(A)
描述: 关闭局部变量，将其转换为upvalue
触发: 离开作用域时自动插入
```

### 15. 可变参数指令

#### OP_VARARG (36)
```
格式: VARARG A B  (iABC)
操作: R(A), R(A+1), ..., R(A+B-1) = vararg
描述: 展开可变参数
参数:
  - A: 目标寄存器起始位置
  - B: 展开的参数个数+1 (0表示展开所有)
```

## 指令模式和属性

每个指令都有相关的模式信息，存储在 `luaP_opmodes` 数组中：

```c
// 位域定义
bits 0-1: 指令格式 (iABC, iABx, iAsBx)
bits 2-3: C参数模式 (OpArgN, OpArgU, OpArgR, OpArgK)
bits 4-5: B参数模式 (OpArgN, OpArgU, OpArgR, OpArgK)
bit 6:    是否设置寄存器A
bit 7:    是否为测试指令
```

### 参数模式说明
- **OpArgN**: 参数未使用
- **OpArgU**: 参数被使用但不是寄存器/常量
- **OpArgR**: 参数是寄存器或跳转偏移
- **OpArgK**: 参数是常量或寄存器/常量(RK)

## 虚拟机执行流程

### 主循环结构
```c
void luaV_execute(lua_State *L, int nexeccalls) {
  // 初始化执行环境
  LClosure *cl = &clvalue(L->ci->func)->l;
  StkId base = L->base;           // 当前栈基址
  TValue *k = cl->p->k;           // 常量表
  const Instruction *pc = L->savedpc; // 程序计数器
  
  // 主执行循环
  for (;;) {
    const Instruction i = *pc++;   // 取指令并递增PC
    StkId ra = RA(i);             // 计算寄存器A的地址
    
    switch (GET_OPCODE(i)) {
      case OP_MOVE: /* ... */ break;
      // ... 其他指令处理
    }
  }
}
```

### 关键宏定义
```c
#define RA(i)   (base+GETARG_A(i))        // 寄存器A地址
#define RB(i)   (base+GETARG_B(i))        // 寄存器B地址  
#define RC(i)   (base+GETARG_C(i))        // 寄存器C地址
#define RKB(i)  (ISK(B) ? k+INDEXK(B) : base+B)  // B参数(寄存器或常量)
#define RKC(i)  (ISK(C) ? k+INDEXK(C) : base+C)  // C参数(寄存器或常量)
#define KBx(i)  (k+GETARG_Bx(i))          // 常量表索引Bx
```

## 指令优化技术

### 1. 常量折叠
编译器在生成字节码时会进行常量折叠优化，将编译时可确定的表达式直接计算为常量。

### 2. 跳转优化
- 使用有符号偏移量，支持向前和向后跳转
- 条件跳转指令通常与无条件跳转配合使用

### 3. 寄存器重用
Lua编译器会尽可能重用寄存器，减少栈空间占用。

### 4. 尾调用优化
`OP_TAILCALL` 指令实现真正的尾调用优化，避免栈溢出。

## 元方法支持

许多指令支持元方法机制：

### 算术运算元方法
- `__add`, `__sub`, `__mul`, `__div`, `__mod`, `__pow`, `__unm`

### 比较运算元方法  
- `__eq`, `__lt`, `__le`

### 表操作元方法
- `__index`, `__newindex`, `__len`

### 字符串操作元方法
- `__concat`

## 指令执行的错误处理

许多指令使用 `Protect` 宏来处理可能的错误：

```c
#define Protect(x) { L->savedpc = pc; {x;}; base = L->base; }
```

这个宏确保：
1. 保存当前PC位置
2. 执行可能抛出错误的操作
3. 恢复栈基址（因为错误处理可能改变栈）

## 性能考虑

### 1. 寄存器访问
基于寄存器的虚拟机比基于栈的虚拟机减少了数据移动，提高了性能。

### 2. 指令密度
32位指令格式在空间和功能之间达到了良好平衡。

### 3. 分支预测
测试指令的设计考虑了现代CPU的分支预测特性。

## 总结

Lua 5.1的指令集设计简洁而高效，包含37条指令，涵盖了：
- 数据移动和常量加载
- 算术和逻辑运算  
- 表和字符串操作
- 函数调用和控制流
- 循环和迭代
- 闭包和upvalue管理
- 可变参数处理

每条指令都经过精心设计，在功能性、性能和实现复杂度之间达到了最佳平衡。这个指令集是Lua语言高性能的重要基础。
