# ğŸš€ Luaè¯­å¥æ‰§è¡Œæµç¨‹æ·±åº¦è§£æ - DeepWikiç‰ˆæœ¬

> **å­¦ä¹ æŒ‡å—**: æœ¬æ–‡æ¡£æ·±å…¥åˆ†æLuaè¯­å¥ä»æºä»£ç åˆ°æœ€ç»ˆæ‰§è¡Œçš„å®Œæ•´åº•å±‚æµç¨‹ï¼Œé€šè¿‡å®é™…ç¤ºä¾‹æ­ç¤ºè¯æ³•åˆ†æã€è¯­æ³•åˆ†æã€ä»£ç ç”Ÿæˆã€è™šæ‹Ÿæœºæ‰§è¡Œçš„æŠ€æœ¯ç»†èŠ‚å’Œä¼˜åŒ–ç­–ç•¥ã€‚

---

## ğŸ¯ å­¦ä¹ ç›®æ ‡ä¸è·¯å¾„

### ğŸ“– é€‚åˆè¯»è€…ç¾¤ä½“
- **åˆçº§å¼€å‘è€…**: å…·å¤‡ç¼–ç¨‹åŸºç¡€ï¼Œå¸Œæœ›äº†è§£ç¼–ç¨‹è¯­è¨€æ‰§è¡ŒåŸç†
- **ä¸­çº§å¼€å‘è€…**: ç†Ÿæ‚‰Luaè¯­æ³•ï¼Œæƒ³æ·±å…¥ç†è§£ç¼–è¯‘å’Œæ‰§è¡Œæœºåˆ¶
- **é«˜çº§å¼€å‘è€…**: ç ”ç©¶è™šæ‹Ÿæœºè®¾è®¡ï¼Œå¯»æ±‚æ€§èƒ½ä¼˜åŒ–å’Œè°ƒè¯•æŠ€å·§
- **ç¼–è¯‘å™¨å¼€å‘è€…**: å­¦ä¹ ç¼–è¯‘å™¨è®¾è®¡ï¼Œç†è§£ç°ä»£è¯­è¨€å®ç°æŠ€æœ¯

### ğŸ›¤ï¸ å­¦ä¹ è·¯å¾„è§„åˆ’
```mermaid
graph TB
    A[ğŸ å¼€å§‹å­¦ä¹ ] --> B[ğŸ“ ç†è§£æ‰§è¡Œæµç¨‹æ¦‚è§ˆ]
    B --> C[ğŸ” æŒæ¡è¯æ³•åˆ†ææœºåˆ¶]
    C --> D[ğŸŒ³ å­¦ä¹ è¯­æ³•åˆ†æåŸç†]
    D --> E[ğŸ”§ ç†è§£ä»£ç ç”ŸæˆæŠ€æœ¯]
    E --> F[âš™ï¸ æŒæ¡è™šæ‹Ÿæœºæ‰§è¡Œ]
    F --> G[ğŸ“ å­¦ä¹ å‡½æ•°è°ƒç”¨æœºåˆ¶]
    G --> H[ğŸš€ æŒæ¡æ€§èƒ½ä¼˜åŒ–æŠ€æœ¯]
    H --> I[ğŸ‰ å®Œæˆæ·±åº¦ç†è§£]
    
    style A fill:#e1f5fe
    style I fill:#c8e6c9
    style B fill:#fff3e0
    style C fill:#fce4ec
    style D fill:#f3e5f5
    style E fill:#e8f5e8
    style F fill:#fff8e1
    style G fill:#f1f8e9
    style H fill:#ffebee
```

### â±ï¸ å­¦ä¹ æ—¶é—´ä¼°ç®—
- **å¿«é€Ÿæµè§ˆ**: 30-40åˆ†é’Ÿ - ç†è§£åŸºæœ¬æ‰§è¡Œæµç¨‹
- **æ·±åº¦å­¦ä¹ **: 2-3å°æ—¶ - æŒæ¡å„é˜¶æ®µæŠ€æœ¯ç»†èŠ‚
- **å®è·µåº”ç”¨**: 4-6å°æ—¶ - å­¦ä¹ è°ƒè¯•å’Œä¼˜åŒ–æŠ€æœ¯
- **ä¸“å®¶çº§**: 10-15å°æ—¶ - æ·±å…¥ç ”ç©¶è™šæ‹Ÿæœºå®ç°

---

## ğŸ§­ æ–‡æ¡£å¯¼èˆª

### ğŸ“‘ æ ¸å¿ƒç« èŠ‚å¯¼è§ˆ
| ç« èŠ‚ | å†…å®¹æ¦‚è¦ | éš¾åº¦ç­‰çº§ | é‡è¦ç¨‹åº¦ | å­¦ä¹ æ—¶é—´ |
|------|----------|----------|----------|----------|
| [ğŸ¯ æ‰§è¡Œæµç¨‹æ¦‚è§ˆ](#-æ‰§è¡Œæµç¨‹æ¦‚è§ˆ) | äº”å¤§æ‰§è¡Œé˜¶æ®µæ€»è§ˆ | â­â­ | ğŸ”¥ğŸ”¥ğŸ”¥ | 8åˆ†é’Ÿ |
| [ğŸ” è¯æ³•åˆ†æé˜¶æ®µ](#-è¯æ³•åˆ†æé˜¶æ®µ) | TokenåŒ–å’Œè¯æ³•çŠ¶æ€ | â­â­â­ | ğŸ”¥ğŸ”¥ğŸ”¥ | 15åˆ†é’Ÿ |
| [ğŸŒ³ è¯­æ³•åˆ†æé˜¶æ®µ](#-è¯­æ³•åˆ†æé˜¶æ®µ) | ASTæ„å»ºå’Œè¯­ä¹‰åˆ†æ | â­â­â­â­ | ğŸ”¥ğŸ”¥ğŸ”¥ | 25åˆ†é’Ÿ |
| [ğŸ”§ ä»£ç ç”Ÿæˆé˜¶æ®µ](#-ä»£ç ç”Ÿæˆé˜¶æ®µ) | å­—èŠ‚ç ç”Ÿæˆå’Œä¼˜åŒ– | â­â­â­â­ | ğŸ”¥ğŸ”¥ğŸ”¥ | 20åˆ†é’Ÿ |
| [âš™ï¸ è™šæ‹Ÿæœºæ‰§è¡Œ](#-è™šæ‹Ÿæœºæ‰§è¡Œé˜¶æ®µ) | å­—èŠ‚ç æ‰§è¡Œå’Œå¯„å­˜å™¨ç®¡ç† | â­â­â­â­â­ | ğŸ”¥ğŸ”¥ğŸ”¥ | 30åˆ†é’Ÿ |
| [ğŸ“ å‡½æ•°è°ƒç”¨æœºåˆ¶](#-å‡½æ•°è°ƒç”¨æœºåˆ¶) | å‡½æ•°è°ƒç”¨å’Œå‚æ•°ä¼ é€’ | â­â­â­ | ğŸ”¥ğŸ”¥ | 15åˆ†é’Ÿ |
| [ğŸš€ æ€§èƒ½ä¼˜åŒ–æŠ€æœ¯](#-æ€§èƒ½ä¼˜åŒ–æŠ€æœ¯) | ç¼–è¯‘å’Œæ‰§è¡Œä¼˜åŒ–ç­–ç•¥ | â­â­â­â­â­ | ğŸ”¥ğŸ”¥ | 20åˆ†é’Ÿ |

### ğŸ”— ç›¸å…³æ–‡æ¡£é“¾æ¥
- ğŸ“– [Luaè¯æ³•åˆ†æå™¨è¯¦è§£](./wiki_lexer.md) - æ·±å…¥è¯æ³•åˆ†æå®ç°
- ğŸŒ³ [Luaè¯­æ³•åˆ†æå™¨å®ç°](./wiki_parser.md) - å®Œæ•´è¯­æ³•åˆ†ææŠ€æœ¯
- ğŸ”§ [Luaå­—èŠ‚ç ç”Ÿæˆæœºåˆ¶](./wiki_code.md) - ä»£ç ç”Ÿæˆå’Œä¼˜åŒ–
- âš™ï¸ [Luaè™šæ‹Ÿæœºæ¶æ„](./wiki_vm.md) - è™šæ‹Ÿæœºè®¾è®¡å’Œå®ç°
- ğŸ“Š [Luaæ“ä½œç ç³»ç»Ÿ](./wiki_opcodes.md) - æŒ‡ä»¤é›†å’Œæ‰§è¡Œè¯­ä¹‰
- ğŸ›ï¸ [Luaå‡½æ•°æ‰§è¡Œå™¨](./wiki_do.md) - å‡½æ•°è°ƒç”¨å’Œå¼‚å¸¸å¤„ç†

### ğŸ“š å­¦ä¹ å‰ç½®è¦æ±‚
- âœ… **Luaè¯­æ³•åŸºç¡€**: å‡½æ•°ã€å˜é‡ã€è¡¨è¾¾å¼çš„åŸºæœ¬æ¦‚å¿µ
- âœ… **ç¼–ç¨‹è¯­è¨€åŸç†**: ç¼–è¯‘å™¨åŸºç¡€æ¦‚å¿µå’Œæ‰§è¡Œæ¨¡å‹
- âœ… **Cè¯­è¨€åŸºç¡€**: ç†è§£æŒ‡é’ˆã€ç»“æ„ä½“ã€å‡½æ•°è°ƒç”¨
- âœ… **æ•°æ®ç»“æ„**: æ ‘ã€å“ˆå¸Œè¡¨ã€æ ˆçš„åŸºæœ¬æ“ä½œ

---

## ğŸ¯ æ‰§è¡Œæµç¨‹æ¦‚è§ˆ

### ğŸ” Luaæ‰§è¡Œæ¨¡å‹æ€»è§ˆ

Luaè¯­å¥çš„æ‰§è¡Œæ˜¯ä¸€ä¸ªå¤šé˜¶æ®µçš„å¤æ‚è¿‡ç¨‹ï¼Œæ¯ä¸ªé˜¶æ®µéƒ½æœ‰æ˜ç¡®çš„èŒè´£å’Œè¾“å…¥è¾“å‡ºï¼š

```mermaid
graph TB
    subgraph "ğŸš€ Luaè¯­å¥æ‰§è¡Œå®Œæ•´æµç¨‹"
        A["ğŸ“„ æºä»£ç : print('Hello')"] --> B["ğŸ” è¯æ³•åˆ†æ: llex.c"]
        B --> C["ğŸŒ³ è¯­æ³•åˆ†æ: lparser.c"]
        C --> D["ğŸ”§ ä»£ç ç”Ÿæˆ: lcode.c"]
        D --> E["âš™ï¸ è™šæ‹Ÿæœºæ‰§è¡Œ: lvm.c"]
        E --> F["ğŸ“ å‡½æ•°è°ƒç”¨: lbaselib.c"]
        
        G[Tokenæµ] -.-> B
        H[ASTè¯­æ³•æ ‘] -.-> C
        I[å­—èŠ‚ç æŒ‡ä»¤] -.-> D
        J[æ‰§è¡Œç»“æœ] -.-> E
        K[å‡½æ•°è¾“å‡º] -.-> F
    end
    
    style A fill:#e3f2fd
    style B fill:#f3e5f5
    style C fill:#e8f5e8
    style D fill:#fff8e1
    style E fill:#fff3e0
    style F fill:#ffebee
```

### ğŸ“Š å„é˜¶æ®µèŒè´£åˆ†å·¥

#### ğŸ¯ **é˜¶æ®µé—´æ•°æ®æµè½¬**
```mermaid
graph LR
    subgraph "ğŸ“Š æ•°æ®æµè½¬é“¾æ¡"
        A["ğŸ“ æºç å­—ç¬¦ä¸²: print('Hello')"] --> B["ğŸ”– Tokenåºåˆ—: TK_NAME LPAREN TK_STRING RPAREN"]
        B --> C["ğŸŒ³ æŠ½è±¡è¯­æ³•æ ‘: FunctionCallèŠ‚ç‚¹"]
        C --> D["ğŸ’¾ å­—èŠ‚ç æŒ‡ä»¤: GETGLOBAL, LOADK, CALL"]
        D --> E["ğŸ¯ æ‰§è¡Œç»“æœ: æ§åˆ¶å°è¾“å‡º"]
    end
    
    style A fill:#4caf50
    style B fill:#ff9800
    style C fill:#2196f3
    style D fill:#9c27b0
    style E fill:#f44336
```

#### ğŸ—ï¸ **æ ¸å¿ƒç»„ä»¶æ¶æ„**
| é˜¶æ®µ | æ ¸å¿ƒæ¨¡å— | ä¸»è¦åŠŸèƒ½ | è¾“å…¥ | è¾“å‡º | å…³é”®æ•°æ®ç»“æ„ |
|------|----------|----------|------|------|-------------|
| **ğŸ” è¯æ³•åˆ†æ** | llex.c | TokenåŒ–æºç  | å­—ç¬¦æµ | Tokenæµ | LexState, Token |
| **ğŸŒ³ è¯­æ³•åˆ†æ** | lparser.c | æ„å»ºAST | Tokenæµ | è¯­æ³•æ ‘ | FuncState, expdesc |
| **ğŸ”§ ä»£ç ç”Ÿæˆ** | lcode.c | ç”Ÿæˆå­—èŠ‚ç  | è¯­æ³•æ ‘ | å­—èŠ‚ç  | Instruction |
| **âš™ï¸ è™šæ‹Ÿæœºæ‰§è¡Œ** | lvm.c | æ‰§è¡ŒæŒ‡ä»¤ | å­—èŠ‚ç  | è¿è¡Œæ—¶å€¼ | lua_State, StkId |
| **ğŸ“ å‡½æ•°è°ƒç”¨** | lbaselib.c | è°ƒç”¨å‡½æ•° | å‚æ•° | ç»“æœ | CallInfo |

### ğŸ’¡ è®¾è®¡ç†å¿µ

#### âœ… **åˆ†å±‚æ¶æ„ä¼˜åŠ¿**
- **ğŸ”„ èŒè´£åˆ†ç¦»**: æ¯ä¸ªé˜¶æ®µä¸“æ³¨ç‰¹å®šä»»åŠ¡ï¼Œä¾¿äºç»´æŠ¤å’Œæ‰©å±•
- **ğŸ“Š æ•°æ®æ ‡å‡†åŒ–**: é˜¶æ®µé—´æœ‰æ˜ç¡®çš„æ•°æ®æ¥å£ï¼Œé™ä½è€¦åˆåº¦
- **âš¡ æ€§èƒ½ä¼˜åŒ–**: æ¯ä¸ªé˜¶æ®µå¯ç‹¬ç«‹ä¼˜åŒ–ï¼Œæé«˜æ•´ä½“æ€§èƒ½
- **ğŸ› ï¸ è°ƒè¯•å‹å¥½**: å¯åœ¨ä»»æ„é˜¶æ®µæ’å…¥è°ƒè¯•å’Œåˆ†æå·¥å…·

#### ğŸ¯ **æ‰§è¡Œæ•ˆç‡ä¿è¯**
```mermaid
graph TB
    subgraph "âš¡ æ€§èƒ½ä¼˜åŒ–ç­–ç•¥"
        A[ğŸ“Š ç¼–è¯‘æ—¶ä¼˜åŒ–] --> B[å¸¸é‡æŠ˜å ]
        A --> C[æ­»ä»£ç æ¶ˆé™¤]
        A --> D[è·³è½¬ä¼˜åŒ–]
        
        E[ğŸƒâ€â™‚ï¸ è¿è¡Œæ—¶ä¼˜åŒ–] --> F[å¯„å­˜å™¨åˆ†é…]
        E --> G[æŒ‡ä»¤ç¼“å­˜]
        E --> H[å‡½æ•°å†…è”]
        
        I[ğŸ§  æ™ºèƒ½ä¼˜åŒ–] --> J[çƒ­ç‚¹æ£€æµ‹]
        I --> K[è‡ªé€‚åº”ä¼˜åŒ–]
        I --> L[å†…å­˜å±€éƒ¨æ€§]
    end
    
    style A fill:#4caf50
    style E fill:#ff9800
    style I fill:#2196f3
```

---

## ğŸ” è¯æ³•åˆ†æé˜¶æ®µ

### ğŸ¯ è¯æ³•åˆ†æå™¨æ ¸å¿ƒåŠŸèƒ½

è¯æ³•åˆ†æå™¨æ˜¯ç¼–è¯‘è¿‡ç¨‹çš„ç¬¬ä¸€æ­¥ï¼Œè´Ÿè´£å°†æºä»£ç å­—ç¬¦æµè½¬æ¢ä¸ºæœ‰æ„ä¹‰çš„Tokenåºåˆ—ï¼š

#### ğŸ“‹ Tokenç±»å‹ä½“ç³»
```mermaid
graph TB
    subgraph "ğŸ”– Lua Tokenåˆ†ç±»ä½“ç³»"
        A[ğŸ¯ Tokenç±»å‹] --> B["ğŸ“ ä¿ç•™å­—: TK_IF, TK_WHILE..."]
        A --> C["ğŸ”¢ å­—é¢é‡: TK_NUMBER, TK_STRING"]
        A --> D["ğŸ·ï¸ æ ‡è¯†ç¬¦: TK_NAME"]
        A --> E["âš™ï¸ æ“ä½œç¬¦: åŠ å‡ä¹˜é™¤"]
        A --> F["ğŸ”— åˆ†éš”ç¬¦: æ‹¬å·å’ŒèŠ±æ‹¬å·"]
        A --> G["ğŸª ç‰¹æ®ŠToken: TK_EOS, TK_CONCAT"]
        
        B --> H[ğŸ›ï¸ æ§åˆ¶ç»“æ„å…³é”®å­—]
        C --> I[ğŸ“Š æ•°å€¼å’Œå­—ç¬¦ä¸²å¸¸é‡]
        D --> J[ğŸŒ å˜é‡å’Œå‡½æ•°å]
    end
    
    style A fill:#ffeb3b
    style B fill:#4caf50
    style C fill:#ff9800
    style D fill:#2196f3
```

#### ğŸ—ï¸ æ ¸å¿ƒæ•°æ®ç»“æ„è¯¦è§£
```c
// è¯æ³•çŠ¶æ€ç®¡ç†çš„å®Œæ•´ç»“æ„
typedef struct LexState {
  int current;          // ğŸ” å½“å‰å¤„ç†çš„å­—ç¬¦
  int linenumber;       // ğŸ“ å½“å‰è¡Œå·ï¼ˆé”™è¯¯æŠ¥å‘Šç”¨ï¼‰
  int lastline;         // ğŸ“ æœ€åå¤„ç†çš„Tokenè¡Œå·
  Token t;              // ğŸ¯ å½“å‰Token
  Token lookahead;      // ğŸ‘€ å‰ç»Tokenï¼ˆè¯­æ³•åˆ†æç”¨ï¼‰
  struct FuncState *fs; // ğŸ”— å…³è”çš„å‡½æ•°çŠ¶æ€
  struct lua_State *L;  // ğŸŒ Luaè™šæ‹ŸæœºçŠ¶æ€
  ZIO *z;               // ğŸ“„ è¾“å…¥å­—ç¬¦æµ
  Mbuffer *buff;        // ğŸ“¦ Tokenæ„å»ºç¼“å†²åŒº
  TString *source;      // ğŸ“ æºæ–‡ä»¶å
  char decpoint;        // ğŸ”¢ æœ¬åœ°åŒ–å°æ•°ç‚¹å­—ç¬¦
} LexState;
```

### ğŸ“Š å®ä¾‹åˆ†æï¼š`print("Hello, World")`

#### ğŸ”„ TokenåŒ–è¿‡ç¨‹è¯¦è§£
```mermaid
graph LR
    subgraph "ğŸ” è¯æ³•åˆ†æè¯¦ç»†æµç¨‹"
        A["ğŸ“ æºç : print('Hello, World')"] --> B["ğŸ¯ è¯†åˆ«æ ‡è¯†ç¬¦: print"]
        B --> C["ğŸ”— è¯†åˆ«åˆ†éš”ç¬¦: å·¦æ‹¬å·"]
        C --> D["ğŸ“ è¯†åˆ«å­—ç¬¦ä¸²: 'Hello, World'"]
        D --> E["ğŸ”— è¯†åˆ«åˆ†éš”ç¬¦: å³æ‹¬å·"]
        E --> F[âœ… å®ŒæˆTokenåŒ–]
    end
    
    style A fill:#e3f2fd
    style F fill:#c8e6c9
```

#### ğŸ“‹ Tokenåºåˆ—ç”Ÿæˆè¡¨
| ä½ç½® | å­—ç¬¦åºåˆ— | Tokenç±»å‹ | Tokenå€¼ | å±æ€§ä¿¡æ¯ |
|------|----------|-----------|---------|----------|
| 1 | `print` | `TK_NAME` | "print" | æ ‡è¯†ç¬¦ï¼Œ5å­—ç¬¦ |
| 2 | `(` | `'('` | 40 (ASCII) | å·¦æ‹¬å·åˆ†éš”ç¬¦ |  
| 3 | `"Hello, World"` | `TK_STRING` | "Hello, World" | å­—ç¬¦ä¸²å­—é¢é‡ï¼Œ13å­—ç¬¦ |
| 4 | `)` | `')'` | 41 (ASCII) | å³æ‹¬å·åˆ†éš”ç¬¦ |
| 5 | EOF | `TK_EOS` | - | è¾“å…¥ç»“æŸæ ‡è®° |

#### âš™ï¸ å…³é”®ç®—æ³•å®ç°
```c
/* æ ¸å¿ƒè¯æ³•åˆ†æå‡½æ•° */
static int llex (LexState *ls, SemInfo *seminfo) {
  /*
  è¯æ³•åˆ†æçš„æ ¸å¿ƒæµç¨‹ï¼š
  
  1. ğŸ” è·³è¿‡ç©ºç™½å­—ç¬¦å’Œæ³¨é‡Š
  2. ğŸ¯ è¯†åˆ«Tokenèµ·å§‹å­—ç¬¦
  3. ğŸ“Š æ ¹æ®å­—ç¬¦ç±»å‹åˆ†æ´¾å¤„ç†
  4. ğŸ“¦ æ„å»ºTokenå¹¶è¿”å›ç±»å‹
  */
  
  luaZ_resetbuffer(ls->buff);  /* é‡ç½®ç¼“å†²åŒº */
  
  for (;;) {
    switch (ls->current) {
      case '\n': case '\r':      /* ğŸ”„ å¤„ç†æ¢è¡Œç¬¦ */
        inclinenumber(ls);
        break;
        
      case ' ': case '\f': case '\t': case '\v':  /* â­ï¸ è·³è¿‡ç©ºç™½ */
        next(ls);
        break;
        
      case '-': {                /* ğŸ” å¤„ç†å‡å·æˆ–æ³¨é‡Š */
        next(ls);
        if (ls->current != '-') return '-';
        /* å¤„ç†æ³¨é‡Šé€»è¾‘ */
        break;
      }
      
      case '"': case '\'':       /* ğŸ“ å¤„ç†å­—ç¬¦ä¸² */
        read_string(ls, ls->current, seminfo);
        return TK_STRING;
        
      case '0': case '1': case '2': case '3': case '4':
      case '5': case '6': case '7': case '8': case '9': {  /* ğŸ”¢ å¤„ç†æ•°å­— */
        read_numeral(ls, seminfo);
        return TK_NUMBER;
      }
      
      default: {
        if (lislalpha(ls->current)) {  /* ğŸ·ï¸ å¤„ç†æ ‡è¯†ç¬¦ */
          /* è¯»å–æ ‡è¯†ç¬¦æˆ–ä¿ç•™å­— */
          TString *ts;
          do {
            save_and_next(ls);
          } while (lislalnum(ls->current));
          ts = luaX_newstring(ls, luaZ_buffer(ls->buff), luaZ_bufflen(ls->buff));
          seminfo->ts = ts;
          if (ts->tsv.reserved > 0)  /* ğŸ¯ æ£€æŸ¥ä¿ç•™å­— */
            return ts->tsv.reserved - 1 + FIRST_RESERVED;
          else
            return TK_NAME;
        }
      }
    }
  }
}
```

### ğŸ› ï¸ é«˜çº§ç‰¹æ€§è§£æ

#### ğŸ”¢ æ•°å€¼å¤„ç†æŠ€æœ¯
```mermaid
graph TB
    subgraph "ğŸ”¢ æ•°å€¼Tokenå¤„ç†æµç¨‹"
        A[ğŸ¯ æ£€æµ‹æ•°å­—èµ·å§‹] --> B{ğŸ“Š æ•°å­—ç±»å‹åˆ¤æ–­}
        B -->|ğŸ”Ÿ åè¿›åˆ¶| C[ğŸ“Š è¯»å–åè¿›åˆ¶æ•°å­—]
        B -->|ğŸ”£ åå…­è¿›åˆ¶| D[ğŸ“Š è¯»å–0xå¼€å¤´æ•°å­—]
        C --> E[ğŸ” æ£€æŸ¥å°æ•°ç‚¹]
        D --> E
        E --> F[ğŸ”¬ æ£€æŸ¥ç§‘å­¦è®°æ•°æ³•]
        F --> G[ğŸ“¦ æ„å»ºæ•°å€¼Token]
        G --> H[âœ… è¿”å›TK_NUMBER]
    end
    
    style A fill:#4caf50
    style H fill:#ffeb3b
```

#### ğŸ“ å­—ç¬¦ä¸²å¤„ç†ç­–ç•¥
```c
/* å­—ç¬¦ä¸²è¯»å–çš„å®Œæ•´å®ç° */
static void read_string (LexState *ls, int del, SemInfo *seminfo) {
  /*
  å­—ç¬¦ä¸²å¤„ç†çš„æ ¸å¿ƒåŠŸèƒ½ï¼š
  
  1. ğŸ” å¤„ç†è½¬ä¹‰å­—ç¬¦åºåˆ—
  2. ğŸ“ æ”¯æŒå¤šè¡Œå­—ç¬¦ä¸²
  3. ğŸ›¡ï¸ æ£€æµ‹æœªç»ˆæ­¢å­—ç¬¦ä¸²
  4. ğŸ”„ Unicodeå’Œå­—ç¬¦ç¼–ç æ”¯æŒ
  */
  
  save_and_next(ls);  /* è·³è¿‡èµ·å§‹å¼•å· */
  
  while (ls->current != del) {
    switch (ls->current) {
      case EOZ:
        lexerror(ls, "unfinished string", TK_EOS);
        break;
        
      case '\n':
      case '\r':
        lexerror(ls, "unfinished string", TK_STRING);
        break;
        
      case '\\': {  /* ğŸ”„ å¤„ç†è½¬ä¹‰åºåˆ— */
        int c;  /* è½¬ä¹‰åçš„å­—ç¬¦ */
        next(ls);  /* è·³è¿‡ '\' */
        switch (ls->current) {
          case 'a': c = '\a'; break;
          case 'b': c = '\b'; break;
          case 'f': c = '\f'; break;
          case 'n': c = '\n'; break;
          case 'r': c = '\r'; break;
          case 't': c = '\t'; break;
          case 'v': c = '\v'; break;
          case '\\': c = '\\'; break;
          case '"': c = '"'; break;
          case '\'': c = '\''; break;
          /* æ•°å­—è½¬ä¹‰åºåˆ—å¤„ç† */
          default: {
            if (!lisdigit(ls->current))
              escerror(ls, &ls->current, 1, "invalid escape sequence");
            /* è¯»å–æ•°å­—è½¬ä¹‰åºåˆ— */
          }
        }
        save(ls, c);
        next(ls);
        break;
      }
      
      default:
        save_and_next(ls);
    }
  }
  
  save_and_next(ls);  /* è·³è¿‡ç»“æŸå¼•å· */
  seminfo->ts = luaX_newstring(ls, luaZ_buffer(ls->buff) + 1,
                                   luaZ_bufflen(ls->buff) - 2);
}
```

---

## ğŸŒ³ è¯­æ³•åˆ†æé˜¶æ®µ

### ğŸ¯ è¯­æ³•åˆ†æå™¨æ ¸å¿ƒæ¶æ„

è¯­æ³•åˆ†æå™¨æ˜¯ç¼–è¯‘è¿‡ç¨‹çš„å…³é”®é˜¶æ®µï¼Œè´Ÿè´£å°†Tokenæµè½¬æ¢ä¸ºæŠ½è±¡è¯­æ³•æ ‘(AST)ï¼ŒåŒæ—¶è¿›è¡Œè¯­ä¹‰åˆ†æå’Œä»£ç ç”Ÿæˆï¼š

#### ğŸ—ï¸ è¯­æ³•åˆ†æçš„åŒé‡èŒè´£
```mermaid
graph TB
    subgraph "ğŸŒ³ è¯­æ³•åˆ†æå™¨æ¶æ„è®¾è®¡"
        A[ğŸ”– Tokenæµè¾“å…¥] --> B[ğŸ“‹ è¯­æ³•è§„åˆ™åŒ¹é…]
        B --> C[ğŸŒ³ ASTæ„å»º]
        B --> D[ğŸ”§ ä»£ç ç”Ÿæˆ]
        
        E[ğŸ“Š è¯­æ³•åˆ¶å¯¼ç¿»è¯‘] --> F[ğŸ¯ è¾¹è§£æè¾¹ç”Ÿæˆ]
        F --> G[âš¡ ä¸€éå¼å¤„ç†]
        
        H[ğŸ“ è¯­ä¹‰åˆ†æ] --> I[ğŸ” ç±»å‹æ£€æŸ¥]
        I --> J[ğŸ·ï¸ ä½œç”¨åŸŸç®¡ç†]
        J --> K[ğŸ”— ç¬¦å·è¡¨ç»´æŠ¤]
    end
    
    style B fill:#4caf50
    style E fill:#ff9800
    style H fill:#2196f3
```

#### ğŸ“Š è¡¨è¾¾å¼æè¿°ç¬¦ç³»ç»Ÿ
```c
// è¡¨è¾¾å¼çŠ¶æ€çš„å®Œæ•´åˆ†ç±»ç³»ç»Ÿ
typedef enum {
  VVOID,      // âŒ æ— å€¼è¡¨è¾¾å¼ï¼ˆè¯­å¥ï¼‰
  VNIL,       // ğŸ”˜ nilå¸¸é‡
  VTRUE,      // âœ… trueå¸¸é‡  
  VFALSE,     // âŒ falseå¸¸é‡
  VK,         // ğŸ“Š å¸¸é‡è¡¨ä¸­çš„å€¼
  VKNUM,      // ğŸ”¢ æ•°å€¼å¸¸é‡
  VLOCAL,     // ğŸ“ å±€éƒ¨å˜é‡
  VUPVAL,     // â¬†ï¸ ä¸Šå€¼å˜é‡
  VGLOBAL,    // ğŸŒ å…¨å±€å˜é‡
  VINDEXED,   // ğŸ“‹ è¡¨ç´¢å¼•è®¿é—®
  VJMP,       // ğŸ”„ è·³è½¬è¡¨è¾¾å¼
  VRELOCABLE, // ğŸ¯ å¯é‡å®šä½æŒ‡ä»¤ç»“æœ
  VNONRELOC,  // ğŸ“Œ å›ºå®šå¯„å­˜å™¨ç»“æœ
  VCALL,      // ğŸ“ å‡½æ•°è°ƒç”¨
  VVARARG     // ğŸ“‹ å¯å˜å‚æ•°
} expkind;

typedef struct expdesc {
  expkind k;                    // ğŸ·ï¸ è¡¨è¾¾å¼ç±»å‹
  union {
    struct { int info, aux; } s; // ğŸ“Š å¯„å­˜å™¨ä¿¡æ¯æˆ–è·³è½¬ä¿¡æ¯
    lua_Number nval;            // ğŸ”¢ æ•°å€¼å¸¸é‡å€¼
  } u;
  int t;  // âœ… "ä¸ºçœŸæ—¶"è·³è½¬é“¾è¡¨  
  int f;  // âŒ "ä¸ºå‡æ—¶"è·³è½¬é“¾è¡¨
} expdesc;
```

### ğŸ“Š å®ä¾‹åˆ†æï¼š`print("Hello, World")`

#### ğŸŒ³ ASTæ„å»ºè¿‡ç¨‹
```mermaid
graph TB
    subgraph "ğŸŒ³ æŠ½è±¡è¯­æ³•æ ‘æ„å»ºæµç¨‹"
        A["ğŸ¯ chunk(): ä»£ç å—è§£æ"] --> B["ğŸ“ statement(): è¯­å¥è¯†åˆ«"]
        B --> C["ğŸ“ exprstat(): è¡¨è¾¾å¼è¯­å¥"]
        C --> D["ğŸ” primaryexp(): ä¸»è¡¨è¾¾å¼è§£æ"]
        D --> E["ğŸ·ï¸ singlevar(): è¯†åˆ«'print'"]
        E --> F["ğŸ“ funcargs(): å‚æ•°åˆ—è¡¨è§£æ"]
        F --> G["ğŸ“ str_checkname(): å­—ç¬¦ä¸²å‚æ•°"]
        G --> H["ğŸ”§ luaK_exp2nextreg(): ä»£ç ç”Ÿæˆ"]
        H --> I[âœ… å®ŒæˆASTæ„å»º]
    end
    
    style A fill:#4caf50
    style I fill:#ffeb3b
```

#### ğŸ›ï¸ å‡½æ•°çŠ¶æ€ç®¡ç†
```c
// è¯­æ³•åˆ†æè¿‡ç¨‹ä¸­çš„å‡½æ•°ç¼–è¯‘çŠ¶æ€
typedef struct FuncState {
  Proto *f;                    // ğŸ¯ å½“å‰ç¼–è¯‘çš„å‡½æ•°åŸå‹
  Table *h;                    // ğŸ—‚ï¸ å¸¸é‡è¡¨å“ˆå¸Œæ˜ å°„
  struct FuncState *prev;      // ğŸ”™ å¤–å±‚å‡½æ•°çŠ¶æ€ï¼ˆé—­åŒ…é“¾ï¼‰
  struct LexState *ls;         // ğŸ”— è¯æ³•åˆ†æå™¨çŠ¶æ€
  struct lua_State *L;         // ğŸŒ Luaè™šæ‹ŸæœºçŠ¶æ€
  struct BlockCnt *bl;         // ğŸ“¦ å½“å‰ä½œç”¨åŸŸå—
  int pc;                      // ğŸ“ ä¸‹ä¸€æ¡æŒ‡ä»¤çš„ä½ç½®
  int lasttarget;              // ğŸ¯ æœ€åè·³è½¬ç›®æ ‡
  int jpc;                     // ğŸ”„ å¾…å¤„ç†è·³è½¬é“¾è¡¨
  int freereg;                 // ğŸ†“ ç¬¬ä¸€ä¸ªç©ºé—²å¯„å­˜å™¨
  int nk;                      // ğŸ“Š å¸¸é‡è¡¨å¤§å°
  int np;                      // ğŸ”¢ å­å‡½æ•°æ•°é‡
  short nlocvars;              // ğŸ“ å±€éƒ¨å˜é‡æ€»æ•°
  lu_byte nactvar;             // ğŸ¯ å½“å‰æ´»è·ƒå±€éƒ¨å˜é‡æ•°
  upvaldesc upvalues[LUAI_MAXUPVALUES];  // â¬†ï¸ ä¸Šå€¼æè¿°æ•°ç»„
  unsigned short actvar[LUAI_MAXVARS];   // ğŸ“‹ æ´»è·ƒå˜é‡æ ˆ
} FuncState;
```

### âš™ï¸ å…³é”®è§£æç®—æ³•

#### ğŸ” ä¸»è¡¨è¾¾å¼è§£æ
```c
/* ä¸»è¡¨è¾¾å¼è§£æçš„æ ¸å¿ƒé€»è¾‘ */
static void primaryexp (LexState *ls, expdesc *v) {
  /*
  ä¸»è¡¨è¾¾å¼è§£æçš„å®Œæ•´æµç¨‹ï¼š
  
  1. ğŸ¯ æ ¹æ®å½“å‰Tokenç¡®å®šè¡¨è¾¾å¼ç±»å‹
  2. ğŸ“Š å¤„ç†åŸºæœ¬å­—é¢é‡ï¼ˆnil, true, false, number, stringï¼‰
  3. ğŸ·ï¸ å¤„ç†æ ‡è¯†ç¬¦ï¼ˆå˜é‡ã€å‡½æ•°åï¼‰
  4. ğŸ”„ å¤„ç†å¤æ‚è¡¨è¾¾å¼ï¼ˆè¡¨æ„é€ å™¨ã€å‡½æ•°å®šä¹‰ï¼‰
  5. ğŸ“ å¤„ç†åç¼€è¡¨è¾¾å¼ï¼ˆå‡½æ•°è°ƒç”¨ã€ç´¢å¼•è®¿é—®ï¼‰
  */
  
  FuncState *fs = ls->fs;
  switch (ls->t.token) {
    case '(': {  /* ğŸ”„ æ‹¬å·è¡¨è¾¾å¼ */
      int line = ls->linenumber;
      luaX_next(ls);  /* è·³è¿‡ '(' */
      expr(ls, v);    /* è§£æå†…éƒ¨è¡¨è¾¾å¼ */
      check_match(ls, ')', '(', line);  /* æ£€æŸ¥åŒ¹é…çš„ ')' */
      luaK_dischargevars(fs, v);  /* å¤„ç†å˜é‡è§£å¼•ç”¨ */
      return;
    }
    
    case TK_NIL: {   /* ğŸ”˜ nilå­—é¢é‡ */
      init_exp(v, VNIL, 0);
      break;
    }
    
    case TK_TRUE: {  /* âœ… trueå­—é¢é‡ */
      init_exp(v, VTRUE, 0);
      break;
    }
    
    case TK_FALSE: { /* âŒ falseå­—é¢é‡ */
      init_exp(v, VFALSE, 0);
      break;
    }
    
    case TK_NUMBER: { /* ğŸ”¢ æ•°å€¼å­—é¢é‡ */
      init_exp(v, VKNUM, 0);
      v->u.nval = ls->t.seminfo.r;
      break;
    }
    
    case TK_STRING: { /* ğŸ“ å­—ç¬¦ä¸²å­—é¢é‡ */
      codestring(ls, v, ls->t.seminfo.ts);
      break;
    }
    
    case TK_NAME: {   /* ğŸ·ï¸ æ ‡è¯†ç¬¦ */
      singlevar(ls, v);
      return;
    }
    
    default: {
      luaX_syntaxerror(ls, "unexpected symbol");
      return;
    }
  }
  luaX_next(ls);  /* æ¶ˆè´¹å½“å‰Token */
}
```

#### ğŸ“ å‡½æ•°è°ƒç”¨è§£æ
```c
/* å‡½æ•°å‚æ•°åˆ—è¡¨è§£æ */
static void funcargs (LexState *ls, expdesc *f) {
  /*
  å‡½æ•°å‚æ•°è§£æçš„å¤„ç†ç­–ç•¥ï¼š
  
  1. ğŸ“‹ æ”¯æŒå¤šç§å‚æ•°å½¢å¼ï¼š
     - (expr, expr, ...) æ ‡å‡†å‚æ•°åˆ—è¡¨
     - "string" å•ä¸ªå­—ç¬¦ä¸²å‚æ•°
     - {field=value, ...} è¡¨æ„é€ å™¨å‚æ•°
  
  2. ğŸ”§ è¾¹è§£æè¾¹ç”Ÿæˆä»£ç ï¼š
     - å‚æ•°è¡¨è¾¾å¼ç›´æ¥ç”Ÿæˆåˆ°è¿ç»­å¯„å­˜å™¨
     - ä¼˜åŒ–å‡½æ•°è°ƒç”¨çš„å‚æ•°ä¼ é€’
  */
  
  FuncState *fs = ls->fs;
  expdesc args;
  int base, nparams;
  int line = ls->linenumber;
  
  switch (ls->t.token) {
    case '(': {  /* ğŸ“‹ æ ‡å‡†å‚æ•°åˆ—è¡¨ */
      if (line != ls->lastline)
        luaX_syntaxerror(ls, "ambiguous syntax (function call x new statement)");
      luaX_next(ls);
      if (ls->t.token == ')')  /* ğŸ”„ ç©ºå‚æ•°åˆ—è¡¨ï¼Ÿ */
        args.k = VVOID;
      else {
        explist1(ls, &args);   /* è§£æå‚æ•°è¡¨è¾¾å¼åˆ—è¡¨ */
        luaK_setmultret(fs, &args);  /* å¤„ç†å¤šè¿”å›å€¼ */
      }
      check_match(ls, ')', '(', line);
      break;
    }
    
    case '{': {  /* ğŸ“Š è¡¨æ„é€ å™¨ä½œä¸ºå‚æ•° */
      constructor(ls, &args);
      break;
    }
    
    case TK_STRING: {  /* ğŸ“ å­—ç¬¦ä¸²å­—é¢é‡ä½œä¸ºå‚æ•° */
      codestring(ls, &args, ls->t.seminfo.ts);
      luaX_next(ls);  /* å¿…é¡»ç«‹å³æ¶ˆè´¹å­—ç¬¦ä¸²token */
      break;
    }
    
    default: {
      luaX_syntaxerror(ls, "function arguments expected");
      return;
    }
  }
  
  lua_assert(f->k == VNONRELOC);
  base = f->u.s.info;  /* å‡½æ•°åœ¨å¯„å­˜å™¨ä¸­çš„ä½ç½® */
  if (hasmultret(args.k))
    nparams = LUA_MULTRET;  /* å¤šè¿”å›å€¼å‚æ•° */
  else {
    if (args.k != VVOID)
      luaK_exp2nextreg(fs, &args);  /* å…³é—­å‚æ•°åˆ—è¡¨ */
    nparams = fs->freereg - (base+1);
  }
  init_exp(f, VCALL, luaK_codeABC(fs, OP_CALL, base, nparams+1, 2));
  luaK_fixline(fs, line);
  fs->freereg = base+1;  /* è°ƒç”¨åæ¸…ç†å¯„å­˜å™¨ */
}
```

---

## ğŸ”§ ä»£ç ç”Ÿæˆé˜¶æ®µ

### ğŸ¯ å­—èŠ‚ç ç”Ÿæˆæ ¸å¿ƒæœºåˆ¶

ä»£ç ç”Ÿæˆé˜¶æ®µå°†è¯­æ³•åˆ†æçš„ç»“æœè½¬æ¢ä¸ºLuaè™šæ‹Ÿæœºå¯æ‰§è¡Œçš„å­—èŠ‚ç æŒ‡ä»¤ï¼š

#### âš¡ æŒ‡ä»¤ç”Ÿæˆç­–ç•¥
```mermaid
graph TB
    subgraph "ğŸ”§ å­—èŠ‚ç ç”Ÿæˆæ¶æ„"
        A[ğŸŒ³ ASTèŠ‚ç‚¹] --> B[ğŸ¯ æŒ‡ä»¤é€‰æ‹©]
        B --> C[ğŸ“Š å¯„å­˜å™¨åˆ†é…]
        C --> D[ğŸ”§ æŒ‡ä»¤ç¼–ç ]
        D --> E[ğŸ“¦ æŒ‡ä»¤ä¼˜åŒ–]
        E --> F[ğŸ’¾ å­—èŠ‚ç è¾“å‡º]
        
        G[ğŸ“‹ ä¼˜åŒ–æŠ€æœ¯] --> H[ğŸ“Š å¸¸é‡æŠ˜å ]
        G --> I[ğŸ”„ è·³è½¬ä¼˜åŒ–]
        G --> J[ğŸ¯ å¯„å­˜å™¨å¤ç”¨]
        
        H --> E
        I --> E
        J --> E
    end
    
    style B fill:#4caf50
    style E fill:#ff9800
    style F fill:#2196f3
```

#### ğŸ›ï¸ æ ¸å¿ƒç”Ÿæˆå‡½æ•°
```c
// ä¸»è¦çš„å­—èŠ‚ç ç”Ÿæˆå‡½æ•°æ—
/* ABCæ ¼å¼æŒ‡ä»¤ç”Ÿæˆ */
int luaK_codeABC (FuncState *fs, OpCode o, int a, int b, int c) {
  /*
  ABCæŒ‡ä»¤æ ¼å¼çš„ç¼–ç è¿‡ç¨‹ï¼š
  
  1. ğŸ” éªŒè¯æŒ‡ä»¤æ ¼å¼å’Œå‚æ•°èŒƒå›´
  2. ğŸ”§ æ„é€ 32ä½æŒ‡ä»¤å­—
  3. ğŸ“ å†™å…¥æŒ‡ä»¤æµ
  4. ğŸ“ è¿”å›æŒ‡ä»¤ä½ç½®
  */
  Instruction i;
  lua_assert(getOpMode(o) == iABC);
  lua_assert(getBMode(o) != OpArgN || b == 0);
  lua_assert(getCMode(o) != OpArgN || c == 0);
  i = CREATE_ABC(o, a, b, c);
  return luaK_code(fs, i, fs->ls->lastline);
}

/* ABxæ ¼å¼æŒ‡ä»¤ç”Ÿæˆ */  
int luaK_codeABx (FuncState *fs, OpCode o, int a, unsigned int bc) {
  /*
  ABxæŒ‡ä»¤æ ¼å¼ç”¨äºï¼š
  - ğŸ“Š LOADKæŒ‡ä»¤ï¼ˆåŠ è½½å¸¸é‡ï¼‰
  - ğŸŒ GETGLOBALæŒ‡ä»¤ï¼ˆè·å–å…¨å±€å˜é‡ï¼‰
  - ğŸ“ CLOSUREæŒ‡ä»¤ï¼ˆåˆ›å»ºé—­åŒ…ï¼‰
  */
  Instruction i;
  lua_assert(getOpMode(o) == iABx || getOpMode(o) == iAsBx);
  lua_assert(getCMode(o) == OpArgN);
  i = CREATE_ABx(o, a, bc);
  return luaK_code(fs, i, fs->ls->lastline);
}
```

### ğŸ“Š å®ä¾‹åˆ†æï¼šå­—èŠ‚ç ç”Ÿæˆè¿‡ç¨‹

#### ğŸ”„ `print("Hello, World")`çš„å®Œæ•´ç”Ÿæˆæµç¨‹
```mermaid
graph TB
    subgraph "ğŸ”§ å­—èŠ‚ç ç”Ÿæˆè¯¦ç»†è¿‡ç¨‹"
        A[ğŸ·ï¸ è¯†åˆ«æ ‡è¯†ç¬¦'print'] --> B[ğŸŒ ç”ŸæˆGETGLOBALæŒ‡ä»¤]
        B --> C[ğŸ“ å¤„ç†å­—ç¬¦ä¸²å‚æ•°] --> D[ğŸ“Š ç”ŸæˆLOADKæŒ‡ä»¤]
        D --> E[ğŸ“ å¤„ç†å‡½æ•°è°ƒç”¨] --> F[ğŸ“ ç”ŸæˆCALLæŒ‡ä»¤]
        
        G[ğŸ¯ å¯„å­˜å™¨åˆ†é…] --> H["R0: printå‡½æ•°; R1: å­—ç¬¦ä¸²å‚æ•°"]
        
        I[ğŸ’¾ æœ€ç»ˆå­—èŠ‚ç ] --> J["GETGLOBAL R0 'print'; LOADK R1 'Hello, World'; CALL R0 2 1"]
    end
    
    style B fill:#4caf50
    style D fill:#ff9800  
    style F fill:#2196f3
    style J fill:#9c27b0
```

#### ğŸ“‹ æŒ‡ä»¤ç”Ÿæˆåºåˆ—è¡¨
| æ­¥éª¤ | è¯­æ³•å…ƒç´  | ç”ŸæˆæŒ‡ä»¤ | å¯„å­˜å™¨ä½¿ç”¨ | è¯´æ˜ |
|------|----------|----------|-----------|------|
| 1 | `print` | `GETGLOBAL R0 "print"` | R0=å‡½æ•° | ä»å…¨å±€ç¯å¢ƒè·å–printå‡½æ•° |
| 2 | `"Hello, World"` | `LOADK R1 "Hello, World"` | R1=å­—ç¬¦ä¸² | åŠ è½½å­—ç¬¦ä¸²å¸¸é‡åˆ°å¯„å­˜å™¨ |
| 3 | `print(...)` | `CALL R0 2 1` | R0+å‚æ•° | è°ƒç”¨å‡½æ•°ï¼Œ2ä¸ªslotï¼Œ1ä¸ªè¿”å›å€¼ |

### ğŸ¯ é«˜çº§ä¼˜åŒ–æŠ€æœ¯

#### ğŸ“Š å¸¸é‡æŠ˜å å®ç°
```c
/* ç¼–è¯‘æ—¶å¸¸é‡è®¡ç®—ä¼˜åŒ– */
static int constfolding (OpCode op, expdesc *e1, expdesc *e2) {
  /*
  å¸¸é‡æŠ˜å çš„ä¼˜åŒ–åœºæ™¯ï¼š
  
  1. ğŸ§® ç®—æœ¯è¿ç®—ï¼š2 + 3 â†’ 5
  2. ğŸ”¤ å­—ç¬¦ä¸²è¿æ¥ï¼š"a" .. "b" â†’ "ab"  
  3. ğŸ” æ¯”è¾ƒè¿ç®—ï¼š1 < 2 â†’ true
  4. ğŸ” é€»è¾‘è¿ç®—ï¼štrue and false â†’ false
  */
  
  lua_Number v1, v2, r;
  if (!isnumeral(e1) || !isnumeral(e2)) return 0;
  v1 = e1->u.nval;
  v2 = e2->u.nval;
  
  switch (op) {
    case OP_ADD: r = luai_numadd(v1, v2); break;
    case OP_SUB: r = luai_numsub(v1, v2); break;
    case OP_MUL: r = luai_nummul(v1, v2); break;
    case OP_DIV:
      if (v2 == 0) return 0;  /* ğŸš¨ é¿å…é™¤é›¶ */
      r = luai_numdiv(v1, v2); break;
    case OP_MOD: r = luai_nummod(v1, v2); break;
    case OP_POW: r = luai_numpow(v1, v2); break;
    case OP_UNM: r = luai_numunm(v1); break;
    case OP_LEN: return 0;  /* ğŸ“ é•¿åº¦è¿ç®—æ— æ³•æŠ˜å  */
    default: lua_assert(0); return 0;
  }
  
  if (luai_numisnan(r)) return 0;  /* ğŸš« é¿å…NaNç»“æœ */
  e1->u.nval = r;
  return 1;  /* âœ… æŠ˜å æˆåŠŸ */
}
```

#### ğŸ”„ è·³è½¬ä¼˜åŒ–æœºåˆ¶
```mermaid
graph LR
    subgraph "ğŸ”„ è·³è½¬æŒ‡ä»¤ä¼˜åŒ–æµç¨‹"
        A[ğŸ¯ ç”Ÿæˆæ¡ä»¶è·³è½¬] --> B[ğŸ“‹ åŠ å…¥è·³è½¬é“¾è¡¨]
        B --> C[ğŸ”„ å»¶è¿Ÿåœ°å€è®¡ç®—]
        C --> D[ğŸ“Š è·³è½¬é“¾åˆå¹¶]
        D --> E[ğŸ¯ ç»Ÿä¸€åœ°å€ä¿®è¡¥]
        E --> F[âœ… ä¼˜åŒ–å®Œæˆ]
    end
    
    style A fill:#4caf50
    style D fill:#ff9800
    style F fill:#2196f3
```

## âš¡ è™šæ‹Ÿæœºæ‰§è¡Œé˜¶æ®µ

### ğŸ¯ Luaè™šæ‹Ÿæœºæ ¸å¿ƒæ¶æ„

Luaè™šæ‹Ÿæœºæ˜¯ä¸€ä¸ªåŸºäºå¯„å­˜å™¨çš„æ ˆå¼è™šæ‹Ÿæœºï¼Œè´Ÿè´£æ‰§è¡Œç¼–è¯‘ç”Ÿæˆçš„å­—èŠ‚ç ï¼š

#### ğŸ—ï¸ è™šæ‹Ÿæœºè®¾è®¡ç†å¿µ
```mermaid
graph TB
    subgraph "âš¡ Luaè™šæ‹Ÿæœºæ‰§è¡Œæ¶æ„"
        A[ğŸ’¾ å­—èŠ‚ç æŒ‡ä»¤æµ] --> B[ğŸ”„ æ‰§è¡Œå¾ªç¯å¼•æ“]
        B --> C[ğŸ›ï¸ æŒ‡ä»¤è§£ç å™¨]
        C --> D[ğŸ“Š å¯„å­˜å™¨æ ˆæ“ä½œ]
        D --> E[ğŸ”§ æŒ‡ä»¤æ‰§è¡Œå•å…ƒ]
        
        F[ğŸ—‚ï¸ æ‰§è¡ŒçŠ¶æ€ç®¡ç†] --> G[ğŸ“‹ è°ƒç”¨æ ˆ]
        G --> H[ğŸ¯ å¯„å­˜å™¨çª—å£]
        H --> I[ğŸŒ ç¯å¢ƒç®¡ç†]
        
        J[âš¡ æ€§èƒ½ä¼˜åŒ–] --> K[ğŸ”„ æŒ‡ä»¤åˆ†æ´¾ä¼˜åŒ–]
        J --> L[ğŸ“Š å¯„å­˜å™¨åˆ†é…ä¼˜åŒ–]
        J --> M[ğŸ¯ çƒ­ç‚¹ä»£ç è¯†åˆ«]
    end
    
    style B fill:#4caf50
    style E fill:#ff9800
    style J fill:#2196f3
```

#### ğŸ›ï¸ æ ¸å¿ƒæ‰§è¡Œå¾ªç¯
```c
/* Luaè™šæ‹Ÿæœºçš„å¿ƒè„ï¼šä¸»æ‰§è¡Œå¾ªç¯ */
void luaV_execute (lua_State *L, int nexeccalls) {
  /*
  è™šæ‹Ÿæœºæ‰§è¡Œå¾ªç¯çš„æ ¸å¿ƒè®¾è®¡ï¼š
  
  1. ğŸ”„ æ— é™å¾ªç¯æ‰§è¡ŒæŒ‡ä»¤
  2. ğŸ¯ åŸºäºgotoçš„åˆ†æ´¾è¡¨ä¼˜åŒ–
  3. ğŸ“Š ç›´æ¥æ“ä½œå¯„å­˜å™¨æ ˆ
  4. âš¡ æœ€å°åŒ–å‡½æ•°è°ƒç”¨å¼€é”€
  */
  
  LClosure *cl;
  StkId base;
  TValue *k;
  const Instruction *pc;
  
reentry:  /* ğŸ”„ é‡å…¥ç‚¹ï¼Œç”¨äºå‡½æ•°è°ƒç”¨è¿”å› */
  lua_assert(isLua(L->ci));
  pc = L->savedpc;
  cl = &clvalue(L->ci->func)->l;
  base = L->base;
  k = cl->p->k;  /* ğŸ—‚ï¸ å¸¸é‡è¡¨ */
  
  /* ğŸš€ ä¸»æ‰§è¡Œå¾ªç¯ */
  for (;;) {
    const Instruction i = *pc++;
    StkId ra;
    
    /* ğŸ“Š å¿«é€Ÿè§£ç æŒ‡ä»¤çš„Aå­—æ®µ */
    if ((L->hookmask & (LUA_MASKLINE | LUA_MASKCOUNT)) &&
        (--L->hookcount == 0 || L->hookmask & LUA_MASKLINE)) {
      traceexec(L, pc);  /* ğŸ” è°ƒè¯•é’©å­å¤„ç† */
      if (L->status == LUA_YIELD) {  /* ğŸ”„ åç¨‹è®©æ­¥æ£€æŸ¥ */
        L->savedpc = pc - 1;
        return;
      }
      base = L->base;  /* ğŸ”„ é’©å­å¯èƒ½æ”¹å˜æ ˆ */
    }
    
    ra = RA(i);  /* ğŸ¯ è·å–ç›®æ ‡å¯„å­˜å™¨åœ°å€ */
    lua_assert(base == L->base && L->base == L->ci->base);
    lua_assert(base <= L->top && L->top <= L->stack + L->stacksize);
    lua_assert(L->top == L->ci->top || luaG_checkopenop(i));
    
    /* ğŸ”„ æŒ‡ä»¤åˆ†æ´¾ï¼šä½¿ç”¨è®¡ç®—è·³è½¬è¡¨ä¼˜åŒ– */
    switch (GET_OPCODE(i)) {
      
      case OP_MOVE: {  /* ğŸ“‹ å¯„å­˜å™¨é—´ç§»åŠ¨ */
        setobjs2s(L, ra, RB(i));
        continue;
      }
      
      case OP_LOADK: {  /* ğŸ“Š åŠ è½½å¸¸é‡ */
        setobj2s(L, ra, KBx(i));
        continue;
      }
      
      case OP_GETGLOBAL: {  /* ğŸŒ è·å–å…¨å±€å˜é‡ */
        TValue g;
        TValue *rb = KBx(i);
        sethvalue(L, &g, cl->env);  /* ğŸŒ è·å–ç¯å¢ƒè¡¨ */
        lua_assert(ttisstring(rb));
        Protect(luaV_gettable(L, &g, rb, ra));  /* ğŸ” è¡¨æŸ¥æ‰¾ */
        continue;
      }
      
      case OP_CALL: {  /* ğŸ“ å‡½æ•°è°ƒç”¨ */
        int b = GETARG_B(i);  /* ğŸ”¢ å‚æ•°ä¸ªæ•° */
        int nresults = GETARG_C(i) - 1;  /* ğŸ“‹ è¿”å›å€¼ä¸ªæ•° */
        if (b != 0) L->top = ra+b;  /* ğŸ¯ è®¾ç½®è°ƒç”¨æ ˆé¡¶ */
        L->savedpc = pc;  /* ğŸ’¾ ä¿å­˜ç¨‹åºè®¡æ•°å™¨ */
        switch (luaD_precall(L, ra, nresults)) {
          case PCRLUA: {  /* ğŸ¯ Luaå‡½æ•°è°ƒç”¨ */
            nexeccalls++;
            goto reentry;  /* ğŸ”„ é‡æ–°è¿›å…¥æ‰§è¡Œå¾ªç¯ */
          }
          case PCRJ: {  /* ğŸ“ Cå‡½æ•°è°ƒç”¨å®Œæˆ */
            /* ç»“æœå·²ç»åœ¨æ ˆä¸Š */
            if (nresults >= 0) L->top = L->ci->top;
            continue;
          }
          default: {
            return;  /* ğŸ”„ è®©æ­¥æˆ–é”™è¯¯ */
          }
        }
      }
      
      /* ... å…¶ä»–æŒ‡ä»¤çš„å®ç° ... */
    }
  }
}
```

### ğŸ“Š å®ä¾‹åˆ†æï¼šæŒ‡ä»¤æ‰§è¡Œæµç¨‹

#### ğŸ”„ `print("Hello, World")`çš„è™šæ‹Ÿæœºæ‰§è¡Œ
```mermaid
graph TB
    subgraph "âš¡ è™šæ‹Ÿæœºæ‰§è¡Œè¯¦ç»†æµç¨‹"
        A[ğŸ¯ PCæŒ‡å‘GETGLOBAL] --> B[ğŸ” è§£ç æŒ‡ä»¤å‚æ•°]
        B --> C[ğŸŒ è®¿é—®å…¨å±€ç¯å¢ƒè¡¨] --> D[ğŸ” æŸ¥æ‰¾'print'æ ‡è¯†ç¬¦]
        D --> E[ğŸ“‹ å°†å‡½æ•°å­˜å…¥R0]
        
        E --> F[ğŸ“ PCæŒ‡å‘LOADK] --> G[ğŸ“Š ä»å¸¸é‡è¡¨è·å–å­—ç¬¦ä¸²]
        G --> H[ğŸ“‹ å°†å­—ç¬¦ä¸²å­˜å…¥R1]
        
        H --> I[ğŸ“ PCæŒ‡å‘CALL] --> J[ğŸ”§ è®¾ç½®è°ƒç”¨å‚æ•°]
        J --> K[ğŸ“ æ‰§è¡Œå‡½æ•°è°ƒç”¨] --> L[ğŸ“¤ å¤„ç†è¿”å›å€¼]
        L --> M[âœ… æ‰§è¡Œå®Œæˆ]
    end
    
    style A fill:#4caf50
    style K fill:#ff9800
    style M fill:#2196f3
```

#### ğŸ“‹ å¯„å­˜å™¨çŠ¶æ€å˜åŒ–è¡¨
| æ‰§è¡Œé˜¶æ®µ | PC | æŒ‡ä»¤ | R0çŠ¶æ€ | R1çŠ¶æ€ | æ ˆé¡¶ä½ç½® |
|----------|----|----|-------|-------|---------|
| åˆå§‹ | 0 | - | `nil` | `nil` | base |
| GETGLOBAL | 1 | `GETGLOBAL R0 "print"` | `function: print` | `nil` | base |
| LOADK | 2 | `LOADK R1 "Hello, World"` | `function: print` | `"Hello, World"` | base |
| CALL | 3 | `CALL R0 2 1` | `nil` (è°ƒç”¨å) | `nil` (è°ƒç”¨å) | base+1 |

### ğŸ›ï¸ å…³é”®æ‰§è¡Œæœºåˆ¶

#### ğŸ” æŒ‡ä»¤è§£ç ä¸å‚æ•°æå–
```c
/* æŒ‡ä»¤æ ¼å¼è§£ç çš„é«˜æ•ˆå®ç° */
#define GET_OPCODE(i)    (cast(OpCode, ((i)>>POS_OP) & MASK1(SIZE_OP,0)))
#define GETARG_A(i)      (cast(int, ((i)>>POS_A) & MASK1(SIZE_A,0)))
#define GETARG_B(i)      (cast(int, ((i)>>POS_B) & MASK1(SIZE_B,0)))
#define GETARG_C(i)      (cast(int, ((i)>>POS_C) & MASK1(SIZE_C,0)))
#define GETARG_Bx(i)     (cast(int, ((i)>>POS_Bx) & MASK1(SIZE_Bx,0)))
#define GETARG_sBx(i)    (GETARG_Bx(i)-MAXARG_sBx)

/* å¯„å­˜å™¨åœ°å€è®¡ç®—çš„å®å®šä¹‰ */
#define RA(i)    (base+GETARG_A(i))       /* ğŸ¯ ç›®æ ‡å¯„å­˜å™¨ */
#define RB(i)    check_exp(getBMode(GET_OPCODE(i)) == OpArgR, base+GETARG_B(i))
#define RC(i)    check_exp(getCMode(GET_OPCODE(i)) == OpArgR, base+GETARG_C(i))
#define RKB(i)   check_exp(getBMode(GET_OPCODE(i)) == OpArgK, \
        ISK(GETARG_B(i)) ? k+INDEXK(GETARG_B(i)) : base+GETARG_B(i))
#define RKC(i)   check_exp(getCMode(GET_OPCODE(i)) == OpArgK, \
        ISK(GETARG_C(i)) ? k+INDEXK(GETARG_C(i)) : base+GETARG_C(i))
#define KBx(i)   check_exp(getBMode(GET_OPCODE(i)) == OpArgK, k+GETARG_Bx(i))
```

#### ğŸŒ å…¨å±€å˜é‡è®¿é—®ä¼˜åŒ–
```c
/* å…¨å±€å˜é‡è®¿é—®çš„é«˜æ•ˆå®ç° */
case OP_GETGLOBAL: {
  /*
  å…¨å±€å˜é‡è®¿é—®çš„ä¼˜åŒ–ç­–ç•¥ï¼š
  
  1. ğŸ¯ ç›´æ¥è®¿é—®ç¯å¢ƒè¡¨ï¼Œé¿å…å­—ç¬¦ä¸²å“ˆå¸Œé‡å¤è®¡ç®—
  2. ğŸ“Š åˆ©ç”¨å…ƒè¡¨æœºåˆ¶æ”¯æŒ _ENV è‡ªå®šä¹‰
  3. ğŸ” å†…è”å¸¸è§çš„è¡¨æŸ¥æ‰¾æ“ä½œ
  4. âš¡ é¿å…åˆ›å»ºä¸´æ—¶Luaå¯¹è±¡
  */
  
  TValue g;
  TValue *rb = KBx(i);  /* ğŸ·ï¸ å…¨å±€å˜é‡åï¼ˆå¸¸é‡ï¼‰ */
  
  /* ğŸŒ è·å–å½“å‰ç¯å¢ƒè¡¨ */
  sethvalue(L, &g, cl->env);
  lua_assert(ttisstring(rb));
  
  /* ğŸ” æ‰§è¡Œè¡¨æŸ¥æ‰¾æ“ä½œ */
  Protect(luaV_gettable(L, &g, rb, ra));
  continue;
}

/* è¡¨æŸ¥æ‰¾çš„æ ¸å¿ƒå®ç° */
void luaV_gettable (lua_State *L, const TValue *t, TValue *key, StkId val) {
  /*
  è¡¨æŸ¥æ‰¾æ“ä½œçš„å®Œæ•´æµç¨‹ï¼š
  
  1. ğŸ” æ£€æŸ¥å¯¹è±¡ç±»å‹ï¼ˆè¡¨ã€ç”¨æˆ·æ•°æ®ç­‰ï¼‰
  2. ğŸ“Š å°è¯•ç›´æ¥å“ˆå¸Œè¡¨æŸ¥æ‰¾
  3. ğŸ”„ å¤„ç†å…ƒæ–¹æ³• __index
  4. ğŸ¯ é€’å½’æŸ¥æ‰¾åŸå‹é“¾
  */
  
  int loop;
  for (loop = 0; loop < MAXTAGLOOP; loop++) {
    const TValue *tm;
    if (ttistable(t)) {  /* ğŸ“Š æ ‡å‡†è¡¨æŸ¥æ‰¾ */
      Table *h = hvalue(t);
      const TValue *res = luaH_get(h, key);  /* ğŸ” å“ˆå¸Œè¡¨æŸ¥æ‰¾ */
      if (!ttisnil(res) ||  /* ğŸ¯ æ‰¾åˆ°ç»“æœ */
          (tm = fasttm(L, h->metatable, TM_INDEX)) == NULL) { /* ğŸš« æ— __indexå…ƒæ–¹æ³• */
        setobj2s(L, val, res);
        return;
      }
      /* ğŸ”„ å°è¯•__indexå…ƒæ–¹æ³• */
    }
    else if (ttisnil(tm = luaT_gettmbyobj(L, t, TM_INDEX)))
      luaG_typeerror(L, t, "index");  /* ğŸš¨ ç±»å‹é”™è¯¯ */
    
    if (ttisfunction(tm)) {  /* ğŸ“ __indexæ˜¯å‡½æ•° */
      callTMres(L, val, tm, t, key);
      return;
    }
    t = tm;  /* ğŸ”„ __indexæ˜¯è¡¨ï¼Œç»§ç»­æŸ¥æ‰¾ */
  }
  luaG_runerror(L, "loop in gettable");  /* ğŸ”„ å¾ªç¯è¿‡æ·±é”™è¯¯ */
}
```

---

## ğŸ“ å‡½æ•°è°ƒç”¨ä¸è¿”å›æœºåˆ¶

### ğŸ¯ å‡½æ•°è°ƒç”¨çš„å®Œæ•´ç”Ÿå‘½å‘¨æœŸ

å‡½æ•°è°ƒç”¨æ˜¯Luaæ‰§è¡Œçš„æ ¸å¿ƒæœºåˆ¶ï¼Œæ¶‰åŠå‚æ•°ä¼ é€’ã€æ ˆå¸§ç®¡ç†ã€è¿”å›å€¼å¤„ç†ç­‰å¤šä¸ªæ–¹é¢ï¼š

#### ğŸ—ï¸ è°ƒç”¨æ ˆç®¡ç†æ¶æ„
```mermaid
graph TB
    subgraph "ğŸ“ å‡½æ•°è°ƒç”¨æ ˆç®¡ç†"
        A[ğŸ“‹ è°ƒç”¨å‡†å¤‡é˜¶æ®µ] --> B[ğŸ¯ å‚æ•°æ ˆå¸ƒå±€]
        B --> C[ğŸ“¦ æ–°æ ˆå¸§åˆ›å»º]
        C --> D[ğŸ”§ æ‰§è¡Œä¸Šä¸‹æ–‡åˆ‡æ¢]
        D --> E[âš¡ å‡½æ•°ä½“æ‰§è¡Œ]
        E --> F[ğŸ“¤ è¿”å›å€¼å¤„ç†]
        F --> G[ğŸ”„ æ ˆå¸§æ¢å¤]
        
        H[ğŸ—‚ï¸ è°ƒç”¨ä¿¡æ¯ç®¡ç†] --> I[ğŸ’¾ CallInfoç»“æ„]
        I --> J[ğŸ“ è¿”å›åœ°å€ä¿å­˜]
        J --> K[ğŸ¯ åŸºå€æŒ‡é’ˆç®¡ç†]
        
        L[âš¡ æ€§èƒ½ä¼˜åŒ–] --> M[ğŸ”„ å°¾è°ƒç”¨ä¼˜åŒ–]
        L --> N[ğŸ“Š å‚æ•°ä¼ é€’ä¼˜åŒ–]
        L --> O[ğŸ¯ æ ˆç©ºé—´å¤ç”¨]
    end
    
    style A fill:#4caf50
    style E fill:#ff9800
    style L fill:#2196f3
```

#### ğŸ“Š CallInfoç»“æ„è¯¦è§£
```c
/* å‡½æ•°è°ƒç”¨ä¿¡æ¯çš„å®Œæ•´æ•°æ®ç»“æ„ */
typedef struct CallInfo {
  StkId base;              /* ğŸ¯ å‡½æ•°çš„åŸºå€æŒ‡é’ˆ */
  StkId func;              /* ğŸ“ å‡½æ•°å¯¹è±¡åœ¨æ ˆä¸­çš„ä½ç½® */
  StkId top;               /* ğŸ“Š å‡½æ•°å¯ç”¨æ ˆç©ºé—´çš„é¡¶éƒ¨ */
  const Instruction *savedpc;  /* ğŸ’¾ ä¿å­˜çš„ç¨‹åºè®¡æ•°å™¨ */
  int nresults;            /* ğŸ“‹ æœŸæœ›çš„è¿”å›å€¼æ•°é‡ */
  int tailcalls;           /* ğŸ”„ å°¾è°ƒç”¨è®¡æ•°å™¨ */
} CallInfo;

/* è°ƒç”¨æ ˆçš„åŠ¨æ€ç®¡ç† */
typedef struct lua_State {
  /* ... å…¶ä»–å­—æ®µ ... */
  StkId top;               /* ğŸ“Š å½“å‰æ ˆé¡¶ */
  StkId base;              /* ğŸ¯ å½“å‰å‡½æ•°åŸºå€ */
  CallInfo *ci;            /* ğŸ“‹ å½“å‰è°ƒç”¨ä¿¡æ¯ */
  CallInfo *end_ci;        /* ğŸ”š è°ƒç”¨æ ˆç»“æŸä½ç½® */
  CallInfo base_ci[LUAI_MAXCALLS];  /* ğŸ“¦ è°ƒç”¨ä¿¡æ¯æ•°ç»„ */
  /* ... */
} lua_State;
```

### ğŸ”§ `print("Hello, World")`çš„å®Œæ•´è°ƒç”¨è¿‡ç¨‹

#### ğŸ“‹ è°ƒç”¨é¢„å¤„ç†é˜¶æ®µ
```c
/* å‡½æ•°è°ƒç”¨çš„é¢„å¤„ç†ï¼šluaD_precall */
int luaD_precall (lua_State *L, StkId func, int nresults) {
  /*
  å‡½æ•°è°ƒç”¨é¢„å¤„ç†çš„å…³é”®æ­¥éª¤ï¼š
  
  1. ğŸ” è¯†åˆ«å‡½æ•°ç±»å‹ï¼ˆLuaå‡½æ•° vs Cå‡½æ•°ï¼‰
  2. ğŸ“Š éªŒè¯å‚æ•°æ•°é‡å’Œç±»å‹
  3. ğŸ¯ è®¾ç½®æ–°çš„æ‰§è¡Œç¯å¢ƒ
  4. ğŸ’¾ ä¿å­˜å½“å‰æ‰§è¡ŒçŠ¶æ€
  */
  
  LClosure *cl;
  ptrdiff_t funcr;
  
  if (!ttisfunction(func))  /* ğŸš¨ éå‡½æ•°å¯¹è±¡é”™è¯¯ */
    func = tryfuncTM(L, func);  /* å°è¯• __call å…ƒæ–¹æ³• */
  
  funcr = savestack(L, func);  /* ğŸ’¾ ä¿å­˜å‡½æ•°ä½ç½® */
  cl = &clvalue(func)->l;
  
  /* ğŸ“Š æ£€æŸ¥æ ˆç©ºé—´æ˜¯å¦è¶³å¤Ÿ */
  if (!cl->isC) {  /* ğŸ¯ Luaå‡½æ•°è°ƒç”¨ */
    CallInfo *ci;
    StkId st, base;
    Proto *p = cl->p;
    
    /* ğŸ“ å‚æ•°æ•°é‡æ£€æŸ¥å’Œè°ƒæ•´ */
    luaD_checkstack(L, p->maxstacksize);
    func = restorestack(L, funcr);
    
    if (!p->is_vararg) {  /* ğŸ¯ å›ºå®šå‚æ•°å‡½æ•° */
      for (st = L->top; st < func + 1 + p->numparams; st++)
        setnilvalue(st);  /* ğŸ”˜ ç¼ºå¤±å‚æ•°è¡¥nil */
      L->top = func + 1 + p->numparams;
    }
    else {  /* ğŸ“‹ å¯å˜å‚æ•°å‡½æ•° */
      int nargs = cast_int(L->top - func) - 1;  /* ğŸ”¢ å®é™…å‚æ•°æ•°é‡ */
      base = adjust_varargs(L, p, nargs);  /* ğŸ”§ è°ƒæ•´å¯å˜å‚æ•° */
      func = restorestack(L, funcr);  /* ğŸ”„ æ¢å¤å‡½æ•°ä½ç½® */
    }
    
    /* ğŸ“¦ åˆ›å»ºæ–°çš„è°ƒç”¨ä¿¡æ¯ */
    ci = ++L->ci;  /* ğŸ” æ¨è¿›è°ƒç”¨æ ˆ */
    L->base = (ci-1)->top = base;  /* ğŸ¯ è®¾ç½®åŸºå€ */
    ci->func = func;
    ci->base = base;
    ci->top = base + p->maxstacksize;  /* ğŸ“Š è®¾ç½®æ ˆé¡¶ */
    lua_assert(ci->top <= L->stack_last);
    L->savedpc = p->code;  /* ğŸ’¾ è®¾ç½®ç¨‹åºè®¡æ•°å™¨ */
    ci->savedpc = p->code;
    ci->tailcalls = 0;
    ci->nresults = nresults;  /* ğŸ“‹ æœŸæœ›è¿”å›å€¼æ•°é‡ */
    
    /* ğŸ”˜ åˆå§‹åŒ–å±€éƒ¨å˜é‡ä¸ºnil */
    for (st = L->top; st < ci->top; st++)
      setnilvalue(st);
    L->top = ci->top;
    
    return PCRLUA;  /* ğŸ¯ è¿”å›Luaå‡½æ•°è°ƒç”¨æ ‡å¿— */
  }
  else {  /* ğŸ“ Cå‡½æ•°è°ƒç”¨ */
    CallInfo *ci;
    int n;
    
    /* ğŸ“¦ Cå‡½æ•°è°ƒç”¨ä¿¡æ¯è®¾ç½® */
    luaD_checkstack(L, LUA_MINSTACK);
    ci = ++L->ci;
    L->base = (ci-1)->top = func + 1;
    ci->func = func;
    ci->base = func + 1;
    ci->top = L->top + LUA_MINSTACK;
    lua_assert(ci->top <= L->stack_last);
    ci->nresults = nresults;
    ci->tailcalls = 0;
    
    /* ğŸ“ æ‰§è¡ŒCå‡½æ•° */
    n = (*clvalue(func)->c.f)(L);  /* ğŸ”§ è°ƒç”¨Cå‡½æ•°æŒ‡é’ˆ */
    
    /* ğŸ“¤ å¤„ç†Cå‡½æ•°è¿”å›å€¼ */
    if (n < 0)  /* ğŸ”„ è®©æ­¥æ ‡å¿— */
      return PCRYIELD;
    else {
      luaD_poscall(L, L->top - n);  /* ğŸ“‹ å¤„ç†è¿”å›å€¼ */
      return PCRJ;  /* ğŸ“ Cå‡½æ•°è°ƒç”¨å®Œæˆ */
    }
  }
}
```

#### ğŸ“¤ å‡½æ•°è¿”å›å¤„ç†
```c
/* å‡½æ•°è¿”å›çš„åå¤„ç†ï¼šluaD_poscall */
int luaD_poscall (lua_State *L, StkId firstResult) {
  /*
  å‡½æ•°è¿”å›å¤„ç†çš„æ ¸å¿ƒä»»åŠ¡ï¼š
  
  1. ğŸ“‹ æ•´ç†è¿”å›å€¼åˆ°æ­£ç¡®ä½ç½®
  2. ğŸ”„ æ¢å¤è°ƒç”¨è€…çš„æ‰§è¡ŒçŠ¶æ€
  3. ğŸ“Š è°ƒæ•´æ ˆé¡¶æŒ‡é’ˆ
  4. ğŸ¯ è¿”å›è°ƒç”¨ç»“æœ
  */
  
  StkId res;
  int wanted, i;
  CallInfo *ci;
  
  ci = L->ci--;  /* ğŸ”™ å¼¹å‡ºè°ƒç”¨ä¿¡æ¯ */
  res = ci->func;  /* ğŸ¯ è¿”å›å€¼å­˜å‚¨ä½ç½® */
  wanted = ci->nresults;  /* ğŸ“‹ æœŸæœ›è¿”å›å€¼æ•°é‡ */
  L->base = (ci-1)->base;  /* ğŸ”„ æ¢å¤åŸºå€æŒ‡é’ˆ */
  L->savedpc = (ci-1)->savedpc;  /* ğŸ’¾ æ¢å¤ç¨‹åºè®¡æ•°å™¨ */
  
  /* ğŸ“‹ ç§»åŠ¨è¿”å›å€¼åˆ°æ­£ç¡®ä½ç½® */
  for (i = wanted; i != 0 && firstResult < L->top; i--)
    setobjs2s(L, res++, firstResult++);  /* ğŸ“Š å¤åˆ¶è¿”å›å€¼ */
  
  while (i-- > 0)
    setnilvalue(res++);  /* ğŸ”˜ å¤šä½™ä½ç½®å¡«nil */
  
  L->top = res;  /* ğŸ“Š è°ƒæ•´æ ˆé¡¶ */
  return (wanted - LUA_MULTRET);  /* ğŸ”¢ è¿”å›å®é™…è¿”å›å€¼æ•°é‡ */
}
```

### âš¡ æ€§èƒ½ä¼˜åŒ–ï¼šå°¾è°ƒç”¨å¤„ç†

#### ğŸ”„ å°¾è°ƒç”¨ä¼˜åŒ–çš„æ ¸å¿ƒæœºåˆ¶
```mermaid
graph LR
    subgraph "ğŸ”„ å°¾è°ƒç”¨ä¼˜åŒ–æµç¨‹"
        A[ğŸ¯ è¯†åˆ«å°¾è°ƒç”¨æ¨¡å¼] --> B[ğŸ“Š å¤ç”¨å½“å‰æ ˆå¸§]
        B --> C[ğŸ”§ å‚æ•°å°±åœ°æ›¿æ¢]
        C --> D[ğŸ’¾ æ›´æ–°æ‰§è¡Œä¸Šä¸‹æ–‡]
        D --> E[âš¡ ç›´æ¥è·³è½¬æ‰§è¡Œ]
        
        F[ğŸš« å¸¸è§„è°ƒç”¨] --> G[ğŸ“¦ åˆ›å»ºæ–°æ ˆå¸§]
        G --> H[ğŸ“‹ è°ƒç”¨æ ˆå¢é•¿]
        
        I[âœ… å°¾è°ƒç”¨] --> B
        I --> J[ğŸ“‰ æ ˆç©ºé—´èŠ‚çœ]
        J --> K[â™»ï¸ é¿å…æ ˆæº¢å‡º]
    end
    
    style A fill:#4caf50
    style E fill:#ff9800
    style K fill:#2196f3
```

```c
/* å°¾è°ƒç”¨ä¼˜åŒ–çš„å®ç° */
case OP_TAILCALL: {
  /*
  å°¾è°ƒç”¨ä¼˜åŒ–çš„å…³é”®ç­–ç•¥ï¼š
  
  1. ğŸ”„ å¤ç”¨å½“å‰å‡½æ•°çš„æ ˆå¸§
  2. ğŸ“Š é¿å…è°ƒç”¨æ ˆæ— é™å¢é•¿  
  3. âš¡ å‡å°‘å‡½æ•°è°ƒç”¨å¼€é”€
  4. ğŸ¯ æ”¯æŒçœŸæ­£çš„å°¾é€’å½’
  */
  
  int b = GETARG_B(i);  /* ğŸ”¢ å‚æ•°æ•°é‡ */
  if (b != 0) L->top = ra+b;  /* ğŸ“Š è°ƒæ•´æ ˆé¡¶ */
  
  lua_assert(GETARG_C(i) - 1 == LUA_MULTRET);
  if (luaD_precall(L, ra, LUA_MULTRET) == PCRLUA) {  /* ğŸ¯ Luaå‡½æ•°ï¼Ÿ */
    /* ğŸ”„ å°¾è°ƒç”¨ä¼˜åŒ–ï¼šå¤ç”¨æ ˆå¸§ */
    CallInfo *ci = L->ci - 1;  /* ğŸ”™ è·å–è°ƒç”¨è€…ä¿¡æ¯ */
    CallInfo *lim = L->ci;     /* ğŸ“Š å½“å‰è°ƒç”¨ä¿¡æ¯ */
    StkId tb = ci->top;        /* ğŸ¯ è°ƒç”¨è€…æ ˆé¡¶ */
    
    /* ğŸ“‹ ç§»åŠ¨å‚æ•°åˆ°è°ƒç”¨è€…æ ˆå¸§ */
    while (lim->base < L->top)
      setobjs2s(L, tb++, lim->base++);
    
    ci->top = tb;              /* ğŸ“Š æ›´æ–°è°ƒç”¨è€…æ ˆé¡¶ */
    lua_assert(ci->top <= L->stack_last);
    
    ci->savedpc = L->savedpc;  /* ğŸ’¾ æ›´æ–°è¿”å›åœ°å€ */
    ci->tailcalls++;           /* ğŸ”¢ å¢åŠ å°¾è°ƒç”¨è®¡æ•° */
    L->ci--;                   /* ğŸ”™ å¼¹å‡ºå½“å‰æ ˆå¸§ */
    L->base = L->ci->base;     /* ğŸ¯ æ¢å¤åŸºå€ */
    goto reentry;              /* ğŸ”„ é‡æ–°è¿›å…¥æ‰§è¡Œå¾ªç¯ */
  }
  continue;
}
```

## ğŸš€ é«˜çº§ä¼˜åŒ–æŠ€æœ¯ä¸æ€§èƒ½åˆ†æ

### âš¡ æ‰§è¡Œå¼•æ“çš„æ·±åº¦ä¼˜åŒ–

Luaè™šæ‹Ÿæœºé€šè¿‡å¤šå±‚æ¬¡çš„ä¼˜åŒ–æŠ€æœ¯å®ç°é«˜æ€§èƒ½æ‰§è¡Œï¼š

#### ğŸ¯ æŒ‡ä»¤çº§ä¼˜åŒ–ç­–ç•¥
```mermaid
graph TB
    subgraph "ğŸš€ è™šæ‹Ÿæœºæ€§èƒ½ä¼˜åŒ–ä½“ç³»"
        A[ğŸ”„ æŒ‡ä»¤åˆ†æ´¾ä¼˜åŒ–] --> B[ğŸ“Š è®¡ç®—è·³è½¬è¡¨]
        A --> C[ğŸ¯ åˆ†æ”¯é¢„æµ‹å‹å¥½]
        
        D[ğŸ“‹ å¯„å­˜å™¨ä¼˜åŒ–] --> E[ğŸ”„ å¯„å­˜å™¨å¤ç”¨]
        D --> F[ğŸ“Š æ•°æ®å±€éƒ¨æ€§ä¼˜åŒ–]
        
        G[ğŸ›ï¸ å†…å­˜ç®¡ç†ä¼˜åŒ–] --> H[ğŸ“¦ æ ˆåˆ†é…ç­–ç•¥]
        G --> I[â™»ï¸ åƒåœ¾å›æ”¶åä½œ]
        
        J[âš¡ çƒ­ç‚¹ä¼˜åŒ–] --> K[ğŸ” æŒ‡ä»¤ç»Ÿè®¡]
        J --> L[ğŸ¯ å…³é”®è·¯å¾„ä¼˜åŒ–]
    end
    
    style A fill:#4caf50
    style D fill:#ff9800
    style G fill:#2196f3
    style J fill:#9c27b0
```

#### ğŸ”„ è®¡ç®—è·³è½¬è¡¨å®ç°
```c
/* é«˜æ•ˆçš„æŒ‡ä»¤åˆ†æ´¾æœºåˆ¶ */
#ifdef LUA_USE_JUMPTABLE

/* ğŸ“Š é¢„è®¡ç®—è·³è½¬è¡¨ï¼Œé¿å…è¿è¡Œæ—¶switchå¼€é”€ */
static const void* const dispatch_table[] = {
  &&L_OP_MOVE,     &&L_OP_LOADK,    &&L_OP_LOADBOOL,
  &&L_OP_LOADNIL,  &&L_OP_GETUPVAL, &&L_OP_GETGLOBAL,
  &&L_OP_GETTABLE, &&L_OP_SETGLOBAL,&&L_OP_SETUPVAL,
  /* ... æ‰€æœ‰æ“ä½œç çš„æ ‡ç­¾ ... */
};

#define DISPATCH_GOTO(op) goto *dispatch_table[op]

/* ğŸš€ ä¼˜åŒ–çš„æ‰§è¡Œå¾ªç¯ */
void luaV_execute_optimized (lua_State *L, int nexeccalls) {
  /* ... åˆå§‹åŒ–ä»£ç  ... */
  
  DISPATCH_GOTO(GET_OPCODE(*pc++));  /* ğŸ¯ é¦–æ¬¡åˆ†æ´¾ */

L_OP_MOVE: {  /* ğŸ“‹ å¯„å­˜å™¨ç§»åŠ¨ä¼˜åŒ– */
  /*
  å¯„å­˜å™¨ç§»åŠ¨çš„å¾®ä¼˜åŒ–ï¼š
  1. ğŸ¯ é¿å…ä¸å¿…è¦çš„ç±»å‹æ£€æŸ¥
  2. ğŸ“Š åˆ©ç”¨å†…å­˜å¯¹é½ä¼˜åŒ–å¤åˆ¶
  3. ğŸ”„ æ‰¹é‡ç§»åŠ¨æ£€æµ‹
  */
  setobjs2s(L, ra, RB(i));
  DISPATCH_GOTO(GET_OPCODE(*pc++));  /* ğŸ”„ ç›´æ¥è·³è½¬åˆ°ä¸‹ä¸€æŒ‡ä»¤ */
}

L_OP_LOADK: {  /* ğŸ“Š å¸¸é‡åŠ è½½ä¼˜åŒ– */
  /*
  å¸¸é‡åŠ è½½çš„æ€§èƒ½ä¼˜åŒ–ï¼š
  1. ğŸ¯ å¸¸é‡è¡¨ç¼“å­˜é¢„å–
  2. ğŸ“Š å‡å°‘é—´æ¥å¯»å€
  3. ğŸ”„ æ‰¹é‡å¸¸é‡åŠ è½½
  */
  TValue *k_val = KBx(i);
  setobj2s(L, ra, k_val);  /* ğŸš€ ç›´æ¥å¤åˆ¶ï¼Œé¿å…å‡½æ•°è°ƒç”¨ */
  DISPATCH_GOTO(GET_OPCODE(*pc++));
}

  /* ... å…¶ä»–ä¼˜åŒ–æŒ‡ä»¤å®ç° ... */
}

#endif /* LUA_USE_JUMPTABLE */
```

#### ğŸ“Š å†…å­˜è®¿é—®ä¼˜åŒ–
```c
/* å¯„å­˜å™¨è®¿é—®çš„ç¼“å­˜ä¼˜åŒ–ç­–ç•¥ */
static inline void optimized_setobj(TValue *obj1, const TValue *obj2) {
  /*
  å†…å­˜å¤åˆ¶çš„å¤šçº§ä¼˜åŒ–ï¼š
  
  1. ğŸ¯ åˆ©ç”¨CPUç¼“å­˜è¡Œå¯¹é½
  2. ğŸ“Š å‡å°‘å†…å­˜å±éšœæŒ‡ä»¤
  3. ğŸ”„ å‘é‡åŒ–æ•°æ®ç§»åŠ¨
  4. âš¡ é¢„å–ä¸‹æ¬¡è®¿é—®æ•°æ®
  */
  
  /* ğŸš€ ä½¿ç”¨ç¼–è¯‘å™¨å†…å»ºå‡½æ•°ä¼˜åŒ– */
  #ifdef LUA_USE_BUILTIN_MEMCPY
    __builtin_memcpy(obj1, obj2, sizeof(TValue));
  #else
    obj1->value = obj2->value;
    obj1->tt = obj2->tt;
  #endif
  
  /* ğŸ“Š å¯é€‰çš„é¢„å–ä¼˜åŒ– */
  #ifdef LUA_USE_PREFETCH
    __builtin_prefetch(obj1 + 1, 1, 3);  /* é¢„å–ä¸‹ä¸€ä¸ªTValue */
  #endif
}
```

### ğŸ” æ€§èƒ½ç“¶é¢ˆåˆ†æä¸ç›‘æ§

#### ğŸ“ˆ æ‰§è¡Œç»Ÿè®¡ä¸åˆ†æ
```c
/* è¿è¡Œæ—¶æ€§èƒ½ç»Ÿè®¡ç»“æ„ */
typedef struct ExecutionStats {
  /* ğŸ“Š æŒ‡ä»¤æ‰§è¡Œç»Ÿè®¡ */
  unsigned long opcode_counts[NUM_OPCODES];    /* ğŸ”¢ å„æŒ‡ä»¤æ‰§è¡Œæ¬¡æ•° */
  unsigned long opcode_cycles[NUM_OPCODES];    /* â±ï¸ å„æŒ‡ä»¤æ¶ˆè€—å‘¨æœŸ */
  
  /* ğŸ“‹ å‡½æ•°è°ƒç”¨ç»Ÿè®¡ */
  unsigned long function_calls;                /* ğŸ“ å‡½æ•°è°ƒç”¨æ€»æ•° */
  unsigned long c_function_calls;              /* ğŸ“ Cå‡½æ•°è°ƒç”¨æ•° */
  unsigned long tail_calls;                    /* ğŸ”„ å°¾è°ƒç”¨æ¬¡æ•° */
  
  /* ğŸ¯ å†…å­˜è®¿é—®ç»Ÿè®¡ */
  unsigned long global_accesses;               /* ğŸŒ å…¨å±€å˜é‡è®¿é—® */
  unsigned long table_accesses;                /* ğŸ“Š è¡¨è®¿é—®æ¬¡æ•° */
  unsigned long upvalue_accesses;              /* â¬†ï¸ ä¸Šå€¼è®¿é—®æ¬¡æ•° */
  
  /* âš¡ æ€§èƒ½å…³é”®æŒ‡æ ‡ */
  unsigned long cache_misses;                  /* ğŸ“‰ ç¼“å­˜æœªå‘½ä¸­ */
  unsigned long gc_triggers;                   /* â™»ï¸ GCè§¦å‘æ¬¡æ•° */
} ExecutionStats;

/* ğŸ” æ€§èƒ½åˆ†æå·¥å…·å‡½æ•° */
void luaV_profile_instruction(lua_State *L, Instruction i) {
  ExecutionStats *stats = L->stats;
  OpCode op = GET_OPCODE(i);
  
  /* ğŸ“Š æ›´æ–°æŒ‡ä»¤è®¡æ•° */
  stats->opcode_counts[op]++;
  
  /* â±ï¸ é«˜ç²¾åº¦è®¡æ—¶ï¼ˆå¯é€‰ï¼‰ */
  #ifdef LUA_ENABLE_PROFILING
    uint64_t start_cycles = __rdtsc();  /* ğŸ”„ è¯»å–CPUå‘¨æœŸè®¡æ•°å™¨ */
    /* æŒ‡ä»¤æ‰§è¡Œ... */
    uint64_t end_cycles = __rdtsc();
    stats->opcode_cycles[op] += (end_cycles - start_cycles);
  #endif
  
  /* ğŸ” çƒ­ç‚¹æ£€æµ‹ */
  if (stats->opcode_counts[op] % 1000 == 0) {
    luaV_check_hotspot(L, L->savedpc - 1);  /* ğŸ“ˆ æ£€æŸ¥çƒ­ç‚¹ä»£ç  */
  }
}
```

#### ğŸ¯ çƒ­ç‚¹ä»£ç è¯†åˆ«
```mermaid
graph LR
    subgraph "ğŸ” çƒ­ç‚¹ä»£ç åˆ†ææµç¨‹"
        A[ğŸ“Š æŒ‡ä»¤è®¡æ•°ç»Ÿè®¡] --> B[ğŸ¯ é˜ˆå€¼æ£€æµ‹]
        B --> C[ğŸ“ˆ é¢‘ç‡åˆ†æ]
        C --> D[ğŸ” æ¨¡å¼è¯†åˆ«]
        D --> E[âš¡ ä¼˜åŒ–å»ºè®®]
        
        F[ğŸ”„ å¾ªç¯æ£€æµ‹] --> G[ğŸ“‹ å†…å¾ªç¯è¯†åˆ«]
        G --> H[ğŸ›ï¸ å‘é‡åŒ–æœºä¼š]
        
        I[ğŸ“ è°ƒç”¨å›¾åˆ†æ] --> J[ğŸ¯ å…³é”®è·¯å¾„]
        J --> K[ğŸ’¡ å†…è”å€™é€‰]
    end
    
    style A fill:#4caf50
    style E fill:#ff9800
    style K fill:#2196f3
```

### ğŸ’¡ å®ç”¨æ€§èƒ½ä¼˜åŒ–æŒ‡å—

#### ğŸ¯ ä»£ç ç¼–å†™æœ€ä½³å®è·µ
```lua
-- âš¡ æ€§èƒ½ä¼˜åŒ–çš„Luaç¼–ç¨‹æŠ€å·§

-- ğŸ“Š 1. å±€éƒ¨å˜é‡ä¼˜åŒ–
local print = print  -- ğŸ¯ å±€éƒ¨åŒ–å…¨å±€å‡½æ•°ï¼Œå‡å°‘æŸ¥æ‰¾å¼€é”€
local table_insert = table.insert  -- ğŸ“‹ ç¼“å­˜è¡¨å‡½æ•°

-- ğŸ”„ 2. å¾ªç¯ä¼˜åŒ–
local n = #array
for i = 1, n do  -- ğŸ¯ é¢„è®¡ç®—é•¿åº¦ï¼Œé¿å…é‡å¤è°ƒç”¨#æ“ä½œç¬¦
  process(array[i])
end

-- ğŸ“Š 3. è¡¨è®¿é—®ä¼˜åŒ–  
local config = {
  host = "localhost",
  port = 8080,
  timeout = 30
}
-- âœ… å¥½çš„åšæ³•ï¼šä¸€æ¬¡æ€§è®¿é—®
local host, port, timeout = config.host, config.port, config.timeout

-- âŒ é¿å…çš„åšæ³•ï¼šé‡å¤è¡¨æŸ¥æ‰¾
-- for i = 1, 100 do
--   connect(config.host, config.port)  -- ğŸŒ æ¯æ¬¡å¾ªç¯éƒ½æŸ¥æ‰¾è¡¨
-- end

-- ğŸ”„ 4. å­—ç¬¦ä¸²æ“ä½œä¼˜åŒ–
-- âœ… ä½¿ç”¨è¡¨è¿æ¥æ›¿ä»£å­—ç¬¦ä¸²è¿æ¥
local parts = {}
for i = 1, 1000 do
  parts[i] = "item" .. i
end
local result = table.concat(parts)  -- ğŸš€ é«˜æ•ˆè¿æ¥

-- ğŸ“ 5. å‡½æ•°è°ƒç”¨ä¼˜åŒ–
-- âœ… å‡å°‘å‡½æ•°è°ƒç”¨å±‚æ¬¡
local function process_batch(items)
  local results = {}
  for i = 1, #items do
    results[i] = items[i] * 2  -- ğŸ¯ ç›´æ¥è®¡ç®—ï¼Œé¿å…å‡½æ•°è°ƒç”¨
  end
  return results
end
```

#### ğŸ”§ è™šæ‹Ÿæœºé…ç½®ä¼˜åŒ–
```c
/* è™šæ‹Ÿæœºæ€§èƒ½è°ƒä¼˜å‚æ•° */
#define LUA_OPTIMIZATION_CONFIG

#ifdef LUA_OPTIMIZATION_CONFIG
/* ğŸ“Š æ ˆå¤§å°ä¼˜åŒ– */
#define LUAI_MAXSTACK    65536    /* ğŸ”„ å¢å¤§æ ˆå®¹é‡ï¼Œå‡å°‘æ ˆæ‰©å±• */
#define LUAI_MAXCALLS    2000     /* ğŸ“ å¢å¤§è°ƒç”¨æ·±åº¦é™åˆ¶ */

/* ğŸ¯ å¯„å­˜å™¨ä¼˜åŒ– */
#define LUAI_MAXVARS     1000     /* ğŸ“‹ å¢å¤§å±€éƒ¨å˜é‡é™åˆ¶ */
#define LUAI_MAXUPVALUES 255      /* â¬†ï¸ å¢å¤§ä¸Šå€¼æ•°é‡ */

/* âš¡ å†…å­˜ç®¡ç†ä¼˜åŒ– */
#define LUA_USE_APICHECK 0        /* ğŸš« ç”Ÿäº§ç¯å¢ƒå…³é—­APIæ£€æŸ¥ */
#define LUA_USE_ASSERT   0        /* ğŸš« å…³é—­æ–­è¨€æ£€æŸ¥ */

/* ğŸ”§ ç¼–è¯‘å™¨ä¼˜åŒ–æç¤º */
#ifdef __GNUC__
#define LUA_LIKELY(x)    __builtin_expect(!!(x), 1)    /* ğŸ¯ åˆ†æ”¯é¢„æµ‹ */
#define LUA_UNLIKELY(x)  __builtin_expect(!!(x), 0)    /* ğŸ¯ åˆ†æ”¯é¢„æµ‹ */
#define LUA_INLINE       __attribute__((always_inline)) /* ğŸš€ å¼ºåˆ¶å†…è” */
#else
#define LUA_LIKELY(x)    (x)
#define LUA_UNLIKELY(x)  (x)  
#define LUA_INLINE       inline
#endif

#endif /* LUA_OPTIMIZATION_CONFIG */
```

## ğŸ“ å­¦ä¹ è·¯å¾„ä¸å®æˆ˜åº”ç”¨

### ğŸ“š æ·±å…¥å­¦ä¹ å»ºè®®

#### ğŸ¯ å­¦ä¹ é˜¶æ®µè§„åˆ’
```mermaid
graph TB
    subgraph "ğŸ“ Luaæ‰§è¡Œæœºåˆ¶å­¦ä¹ è·¯å¾„"
        A[ğŸ“– åŸºç¡€æ¦‚å¿µç†è§£] --> B[ğŸ” æºç é˜…è¯»]
        B --> C[ğŸ”§ è°ƒè¯•å®è·µ]
        C --> D[âš¡ æ€§èƒ½åˆ†æ]
        D --> E[ğŸ’¡ ä¼˜åŒ–å®æˆ˜]
        
        F[ğŸ“Š ç†è®ºå­¦ä¹ ] --> G[ğŸŒ ç¼–è¯‘åŸç†]
        F --> H[ğŸ’» è™šæ‹Ÿæœºè®¾è®¡]
        F --> I[ğŸ”„ ç¨‹åºåˆ†æ]
        
        J[ğŸ› ï¸ å·¥å…·ä½¿ç”¨] --> K[ğŸ” è°ƒè¯•å™¨ä½¿ç”¨]
        J --> L[ğŸ“ˆ æ€§èƒ½åˆ†æå™¨]
        J --> M[ğŸ”§ ä»£ç ç”Ÿæˆå™¨]
    end
    
    style A fill:#4caf50
    style E fill:#ff9800
    style J fill:#2196f3
```

#### ğŸ”§ è°ƒè¯•ä¸åˆ†æå·¥å…·
```bash
# ğŸ” Luaæ‰§è¡Œåˆ†æå·¥å…·é“¾

# 1. å­—èŠ‚ç åæ±…ç¼–å·¥å…·
luac -l script.lua                    # ğŸ“Š æŸ¥çœ‹å­—èŠ‚ç 
luac -l -l script.lua                 # ğŸ“‹ è¯¦ç»†å­—èŠ‚ç ä¿¡æ¯

# 2. æ€§èƒ½åˆ†æå·¥å…·
lua -j profile script.lua             # â±ï¸ LuaJITæ€§èƒ½åˆ†æ
valgrind --tool=callgrind lua script.lua  # ğŸ” è°ƒç”¨å›¾åˆ†æ

# 3. å†…å­˜åˆ†æå·¥å…·
valgrind --tool=massif lua script.lua  # ğŸ“Š å†…å­˜ä½¿ç”¨åˆ†æ
lua -j memprof script.lua             # ğŸ§  å†…å­˜åˆ†æå™¨

# 4. è‡ªå®šä¹‰è°ƒè¯•ç‰ˆæœ¬ç¼–è¯‘
make CFLAGS="-DLUA_USE_APICHECK -DLUA_USE_ASSERT -g -O0"  # ğŸ”§ è°ƒè¯•ç‰ˆæœ¬
```

#### ğŸ“Š å®éªŒé¡¹ç›®å»ºè®®
```lua
-- ğŸ§ª æ€§èƒ½æµ‹è¯•å®éªŒé¡¹ç›®

-- 1. ğŸ”„ å‡½æ•°è°ƒç”¨å¼€é”€æµ‹è¯•
local function test_call_overhead()
  local function empty_func() end
  local function func_with_params(a, b, c) return a + b + c end
  
  -- æµ‹è¯•ç›´æ¥è°ƒç”¨ vs é—´æ¥è°ƒç”¨
  local start_time = os.clock()
  for i = 1, 1000000 do
    empty_func()
  end
  local direct_time = os.clock() - start_time
  
  -- åˆ†æç»“æœ...
end

-- 2. ğŸ“Š è¡¨è®¿é—®æ€§èƒ½æµ‹è¯•
local function test_table_access()
  local large_table = {}
  for i = 1, 10000 do
    large_table[i] = i * 2
  end
  
  -- é¡ºåºè®¿é—® vs éšæœºè®¿é—®
  -- æ•°ç»„è®¿é—® vs å“ˆå¸Œè®¿é—®
  -- ...
end

-- 3. ğŸ¯ å­—ç¬¦ä¸²æ“ä½œæ€§èƒ½æµ‹è¯•
local function test_string_operations()
  -- å­—ç¬¦ä¸²è¿æ¥æ–¹æ³•æ¯”è¾ƒ
  -- æ¨¡å¼åŒ¹é…æ€§èƒ½æµ‹è¯•
  -- å­—ç¬¦ä¸²æ’å€¼æ€§èƒ½
  -- ...
end
```

### ğŸŒŸ ç›¸å…³æ–‡æ¡£é“¾æ¥

#### ğŸ“š æ·±åº¦å­¦ä¹ èµ„æº
- ğŸ¯ **æ ¸å¿ƒæ‰§è¡Œç»„ä»¶**
  - [ğŸ“‹ è™šæ‹ŸæœºçŠ¶æ€ç®¡ç†](wiki_vm_state.md) - æ‰§è¡ŒçŠ¶æ€çš„å®Œæ•´ç”Ÿå‘½å‘¨æœŸ
  - [âš¡ è™šæ‹Ÿæœºæ ¸å¿ƒ](wiki_vm.md) - è™šæ‹Ÿæœºæ¶æ„ä¸æŒ‡ä»¤ç³»ç»Ÿ
  - [ğŸ”§ å‡½æ•°æ‰§è¡Œå™¨](wiki_do.md) - dofile/dostringçš„æ‰§è¡Œæœºåˆ¶

- ğŸ“Š **ç¼–è¯‘æµç¨‹ç»„ä»¶**  
  - [ğŸ”¤ è¯æ³•åˆ†æå™¨](wiki_lexer.md) - Tokenè¯†åˆ«ä¸å¤„ç†
  - [ğŸŒ³ è¯­æ³•åˆ†æå™¨](wiki_parser.md) - ASTæ„å»ºä¸è¯­æ³•åˆ¶å¯¼ç¿»è¯‘
  - [ğŸ”§ ä»£ç ç”Ÿæˆå™¨](wiki_code.md) - å­—èŠ‚ç ç”Ÿæˆä¸ä¼˜åŒ–

- ğŸ›ï¸ **è¿è¡Œæ—¶ç³»ç»Ÿ**
  - [ğŸ“ å‡½æ•°è°ƒç”¨æœºåˆ¶](wiki_call.md) - å‡½æ•°è°ƒç”¨ä¸å‚æ•°ä¼ é€’
  - [ğŸ’¾ å­—èŠ‚ç ç³»ç»Ÿ](wiki_bytecode.md) - æŒ‡ä»¤æ ¼å¼ä¸æ‰§è¡Œæ¨¡å‹
  - [ğŸ”§ æ“ä½œç è¯¦è§£](wiki_opcodes.md) - æ‰€æœ‰æŒ‡ä»¤çš„è¯¦ç»†è¯´æ˜

- âš¡ **æ€§èƒ½ä¸ä¼˜åŒ–**
  - [â™»ï¸ åƒåœ¾å›æ”¶å™¨](wiki_gc.md) - å†…å­˜ç®¡ç†ä¸å›æ”¶ç­–ç•¥  
  - [ğŸ“Š è¡¨å®ç°](wiki_table.md) - é«˜æ•ˆçš„è¡¨æ•°æ®ç»“æ„
  - [ğŸ§  å†…å­˜ç®¡ç†](wiki_memory.md) - å†…å­˜åˆ†é…ä¸ä¼˜åŒ–

#### ğŸ”— å¤–éƒ¨å‚è€ƒèµ„æº
- ğŸ“– [Luaå®˜æ–¹æ–‡æ¡£](http://www.lua.org/docs.html) - æƒå¨è¯­è¨€å‚è€ƒ
- ğŸ“ [ç¼–è¯‘åŸç†æ•™ç¨‹](https://craftinginterpreters.com/) - è§£é‡Šå™¨è®¾è®¡æŒ‡å—
- ğŸ’¡ [è™šæ‹Ÿæœºè®¾è®¡æ¨¡å¼](https://www.lua.org/doc/jucs05.pdf) - Lua VMè®ºæ–‡
- ğŸš€ [æ€§èƒ½ä¼˜åŒ–æŒ‡å—](https://www.lua.org/gems/) - Luaæ€§èƒ½ä¼˜åŒ–æŠ€å·§

---

## ğŸ“‹ æ€»ç»“

### ğŸ¯ æ ¸å¿ƒè¦ç‚¹å›é¡¾

é€šè¿‡æ·±å…¥åˆ†æ`print("Hello, World")`è¿™ä¸ªç®€å•è¯­å¥çš„å®Œæ•´æ‰§è¡Œè¿‡ç¨‹ï¼Œæˆ‘ä»¬æ­ç¤ºäº†Luaæ‰§è¡Œå¼•æ“çš„ç²¾å¦™è®¾è®¡ï¼š

#### âš¡ å…³é”®æŠ€æœ¯äº®ç‚¹
1. **ğŸ”¤ è¯æ³•åˆ†æ**ï¼šé«˜æ•ˆçš„å­—ç¬¦æµå¤„ç†ä¸Tokenè¯†åˆ«
2. **ğŸŒ³ è¯­æ³•åˆ†æ**ï¼šè¾¹è§£æè¾¹ç”Ÿæˆçš„è¯­æ³•åˆ¶å¯¼ç¿»è¯‘  
3. **ğŸ”§ ä»£ç ç”Ÿæˆ**ï¼šä¼˜åŒ–çš„å­—èŠ‚ç ç”Ÿæˆä¸å¯„å­˜å™¨åˆ†é…
4. **âš¡ è™šæ‹Ÿæœºæ‰§è¡Œ**ï¼šåŸºäºå¯„å­˜å™¨çš„é«˜æ€§èƒ½æŒ‡ä»¤æ‰§è¡Œ
5. **ğŸ“ å‡½æ•°è°ƒç”¨**ï¼šçµæ´»çš„è°ƒç”¨æ ˆç®¡ç†ä¸å°¾è°ƒç”¨ä¼˜åŒ–

#### ğŸ“ å­¦ä¹ æ”¶è·
- ç†è§£äº†ç¼–è¯‘å™¨å‰ç«¯åˆ°åç«¯çš„å®Œæ•´æµç¨‹
- æŒæ¡äº†è™šæ‹Ÿæœºè®¾è®¡çš„æ ¸å¿ƒåŸç†
- å­¦ä¼šäº†æ€§èƒ½åˆ†æä¸ä¼˜åŒ–çš„æ–¹æ³•
- è·å¾—äº†ç³»ç»Ÿæ€§çš„æºç é˜…è¯»èƒ½åŠ›

#### ğŸš€ å®é™…åº”ç”¨ä»·å€¼
- **ğŸ“Š æ€§èƒ½ä¼˜åŒ–**ï¼šé’ˆå¯¹æ€§åœ°ä¼˜åŒ–Luaä»£ç æ€§èƒ½
- **ğŸ”§ å·¥å…·å¼€å‘**ï¼šå¼€å‘Luaç›¸å…³çš„å¼€å‘å·¥å…·
- **ğŸ’¡ è¯­è¨€è®¾è®¡**ï¼šå€Ÿé‰´Luaçš„è®¾è®¡æ€æƒ³
- **ğŸ¯ ç³»ç»Ÿé›†æˆ**ï¼šæ›´å¥½åœ°å°†Luaé›†æˆåˆ°C/C++é¡¹ç›®

è¿™ä¸ªæ‰§è¡Œæµç¨‹çš„æ·±å…¥åˆ†æä¸ºæˆ‘ä»¬æä¾›äº†ç†è§£ç°ä»£è§£é‡Šå™¨è®¾è®¡çš„å®è´µè§†è§’ï¼Œå±•ç°äº†Luaä½œä¸ºåµŒå…¥å¼è„šæœ¬è¯­è¨€çš„ç²¾å·§è®¾è®¡ç†å¿µã€‚âœ¨