# Lua 字节码生成器深度分析

## 概述

本文档深度分析 Lua 编译器中的字节码生成模块，主要涉及 `lcode.h` 和 `lcode.c` 文件。字节码生成器是 Lua 编译器的核心组件，负责将语法分析器构建的抽象语法树（AST）转换为 Lua 虚拟机可执行的字节码指令。

## 核心数据结构

### 1. 表达式描述符 (expdesc)

表达式描述符是字节码生成过程中的核心数据结构，定义在 `lparser.h` 中：

```c
typedef enum {
  VVOID,      /* 无值表达式 */
  VNIL,       /* nil 常量 */
  VTRUE,      /* true 常量 */
  VFALSE,     /* false 常量 */
  VK,         /* 常量表中的常量 */
  VKNUM,      /* 数值常量 */
  VLOCAL,     /* 局部变量 */
  VUPVAL,     /* upvalue */
  VGLOBAL,    /* 全局变量 */
  VINDEXED,   /* 索引表达式 */
  VJMP,       /* 跳转表达式 */
  VRELOCABLE, /* 可重定位表达式 */
  VNONRELOC,  /* 不可重定位表达式 */
  VCALL,      /* 函数调用 */
  VVARARG     /* 可变参数 */
} expkind;

typedef struct expdesc {
  expkind k;           /* 表达式类型 */
  union {
    struct { int info, aux; } s;
    lua_Number nval;   /* 数值常量的值 */
  } u;
  int t;              /* 真值跳转链表 */
  int f;              /* 假值跳转链表 */
} expdesc;
```

### 2. 操作符枚举

#### 二元操作符 (BinOpr)
```c
typedef enum BinOpr {
  OPR_ADD, OPR_SUB, OPR_MUL, OPR_DIV, OPR_MOD, OPR_POW,  /* 算术运算 */
  OPR_CONCAT,                                             /* 字符串连接 */
  OPR_NE, OPR_EQ,                                        /* 相等比较 */
  OPR_LT, OPR_LE, OPR_GT, OPR_GE,                       /* 大小比较 */
  OPR_AND, OPR_OR,                                       /* 逻辑运算 */
  OPR_NOBINOPR                                           /* 无二元操作 */
} BinOpr;
```

#### 一元操作符 (UnOpr)
```c
typedef enum UnOpr {
  OPR_MINUS,    /* 负号 */
  OPR_NOT,      /* 逻辑非 */
  OPR_LEN,      /* 长度操作符 # */
  OPR_NOUNOPR   /* 无一元操作 */
} UnOpr;
```

## 字节码指令格式

### 指令编码格式

Lua 字节码指令采用 32 位编码，支持三种格式：

1. **iABC 格式**: `[6位操作码][8位A][9位B][9位C]`
2. **iABx 格式**: `[6位操作码][8位A][18位Bx]`
3. **iAsBx 格式**: `[6位操作码][8位A][18位有符号Bx]`

### 关键宏定义

```c
/* 指令字段大小 */
#define SIZE_C    9
#define SIZE_B    9
#define SIZE_Bx   (SIZE_C + SIZE_B)
#define SIZE_A    8
#define SIZE_OP   6

/* 创建指令的宏 */
#define CREATE_ABC(o,a,b,c) ((cast(Instruction, o)<<POS_OP) \
                           | (cast(Instruction, a)<<POS_A) \
                           | (cast(Instruction, b)<<POS_B) \
                           | (cast(Instruction, c)<<POS_C))

#define CREATE_ABx(o,a,bc)  ((cast(Instruction, o)<<POS_OP) \
                           | (cast(Instruction, a)<<POS_A) \
                           | (cast(Instruction, bc)<<POS_Bx))

/* RK 操作数处理 */
#define BITRK     (1 << (SIZE_B - 1))  /* 常量标志位 */
#define ISK(x)    ((x) & BITRK)        /* 测试是否为常量 */
#define INDEXK(r) ((int)(r) & ~BITRK)  /* 获取常量索引 */
#define RKASK(x)  ((x) | BITRK)        /* 标记为常量 */
```

## 核心字节码指令

### 1. 数据移动指令

- **OP_MOVE**: `R(A) := R(B)` - 寄存器间数据移动
- **OP_LOADK**: `R(A) := Kst(Bx)` - 加载常量
- **OP_LOADBOOL**: `R(A) := (Bool)B; if (C) pc++` - 加载布尔值
- **OP_LOADNIL**: `R(A) := ... := R(B) := nil` - 加载 nil 值

### 2. 变量访问指令

- **OP_GETUPVAL**: `R(A) := UpValue[B]` - 获取 upvalue
- **OP_GETGLOBAL**: `R(A) := Gbl[Kst(Bx)]` - 获取全局变量
- **OP_GETTABLE**: `R(A) := R(B)[RK(C)]` - 表索引访问
- **OP_SETGLOBAL**: `Gbl[Kst(Bx)] := R(A)` - 设置全局变量
- **OP_SETUPVAL**: `UpValue[B] := R(A)` - 设置 upvalue
- **OP_SETTABLE**: `R(A)[RK(B)] := RK(C)` - 表索引赋值

### 3. 算术运算指令

- **OP_ADD**: `R(A) := RK(B) + RK(C)` - 加法
- **OP_SUB**: `R(A) := RK(B) - RK(C)` - 减法
- **OP_MUL**: `R(A) := RK(B) * RK(C)` - 乘法
- **OP_DIV**: `R(A) := RK(B) / RK(C)` - 除法
- **OP_MOD**: `R(A) := RK(B) % RK(C)` - 取模
- **OP_POW**: `R(A) := RK(B) ^ RK(C)` - 幂运算
- **OP_UNM**: `R(A) := -R(B)` - 负号
- **OP_NOT**: `R(A) := not R(B)` - 逻辑非
- **OP_LEN**: `R(A) := length of R(B)` - 长度操作

### 4. 比较和跳转指令

- **OP_EQ**: `if ((RK(B) == RK(C)) ~= A) then pc++` - 相等比较
- **OP_LT**: `if ((RK(B) < RK(C)) ~= A) then pc++` - 小于比较
- **OP_LE**: `if ((RK(B) <= RK(C)) ~= A) then pc++` - 小于等于比较
- **OP_TEST**: `if not (R(A) <=> C) then pc++` - 条件测试
- **OP_TESTSET**: `if (R(B) <=> C) then R(A) := R(B) else pc++` - 条件测试并设置
- **OP_JMP**: `pc += sBx` - 无条件跳转

### 5. 函数调用指令

- **OP_CALL**: `R(A), ..., R(A+C-2) := R(A)(R(A+1), ..., R(A+B-1))` - 函数调用
- **OP_TAILCALL**: `return R(A)(R(A+1), ..., R(A+B-1))` - 尾调用
- **OP_RETURN**: `return R(A), ..., R(A+B-2)` - 函数返回

## 关键函数分析

### 1. 字节码生成函数

#### luaK_codeABC
```c
int luaK_codeABC (FuncState *fs, OpCode o, int a, int b, int c) {
  lua_assert(getOpMode(o) == iABC);
  lua_assert(getBMode(o) != OpArgN || b == 0);
  lua_assert(getCMode(o) != OpArgN || c == 0);
  return luaK_code(fs, CREATE_ABC(o, a, b, c), fs->ls->lastline);
}
```

#### luaK_codeABx
```c
int luaK_codeABx (FuncState *fs, OpCode o, int a, unsigned int bc) {
  lua_assert(getOpMode(o) == iABx || getOpMode(o) == iAsBx);
  lua_assert(getCMode(o) == OpArgN);
  return luaK_code(fs, CREATE_ABx(o, a, bc), fs->ls->lastline);
}
```

### 2. 表达式处理函数

#### luaK_dischargevars - 变量解引用
```c
void luaK_dischargevars (FuncState *fs, expdesc *e) {
  switch (e->k) {
    case VLOCAL: {
      e->k = VNONRELOC;  /* 局部变量直接转为非重定位 */
      break;
    }
    case VUPVAL: {
      e->u.s.info = luaK_codeABC(fs, OP_GETUPVAL, 0, e->u.s.info, 0);
      e->k = VRELOCABLE;
      break;
    }
    case VGLOBAL: {
      e->u.s.info = luaK_codeABx(fs, OP_GETGLOBAL, 0, e->u.s.info);
      e->k = VRELOCABLE;
      break;
    }
    case VINDEXED: {
      freereg(fs, e->u.s.aux);
      freereg(fs, e->u.s.info);
      e->u.s.info = luaK_codeABC(fs, OP_GETTABLE, 0, e->u.s.info, e->u.s.aux);
      e->k = VRELOCABLE;
      break;
    }
    /* ... */
  }
}
```

#### luaK_exp2RK - 表达式转换为 RK 操作数
```c
int luaK_exp2RK (FuncState *fs, expdesc *e) {
  luaK_exp2val(fs, e);
  switch (e->k) {
    case VKNUM:
    case VTRUE:
    case VFALSE:
    case VNIL: {
      if (fs->nk <= MAXINDEXRK) {  /* 常量表未满？ */
        e->u.s.info = (e->k == VNIL)  ? nilK(fs) :
                      (e->k == VKNUM) ? luaK_numberK(fs, e->u.nval) :
                                        boolK(fs, (e->k == VTRUE));
        e->k = VK;
        return RKASK(e->u.s.info);  /* 返回常量索引 */
      }
      else break;
    }
    case VK: {
      if (e->u.s.info <= MAXINDEXRK)  /* 常量索引在范围内？ */
        return RKASK(e->u.s.info);
      else break;
    }
    default: break;
  }
  /* 不是合适的常量：放入寄存器 */
  return luaK_exp2anyreg(fs, e);
}
```

### 3. 常量管理函数

#### addk - 添加常量到常量表
```c
static int addk (FuncState *fs, TValue *k, TValue *v) {
  lua_State *L = fs->L;
  TValue *idx = luaH_set(L, fs->h, k);  /* 在哈希表中查找 */
  Proto *f = fs->f;
  int oldsize = f->sizek;
  if (ttisnumber(idx)) {
    /* 常量已存在，返回索引 */
    lua_assert(luaO_rawequalObj(&fs->f->k[cast_int(nvalue(idx))], v));
    return cast_int(nvalue(idx));
  }
  else {  /* 新常量 */
    setnvalue(idx, cast_num(fs->nk));
    luaM_growvector(L, f->k, fs->nk, f->sizek, TValue,
                    MAXARG_Bx, "constant table overflow");
    while (oldsize < f->sizek) setnilvalue(&f->k[oldsize++]);
    setobj(L, &f->k[fs->nk], v);
    luaC_barrier(L, f, v);
    return fs->nk++;
  }
}
```

### 4. 跳转处理函数

#### luaK_jump - 生成跳转指令
```c
int luaK_jump (FuncState *fs) {
  int jpc = fs->jpc;  /* 保存待处理跳转列表 */
  int j;
  fs->jpc = NO_JUMP;
  j = luaK_codeAsBx(fs, OP_JMP, 0, NO_JUMP);  /* 生成跳转指令 */
  luaK_concat(fs, &j, jpc);  /* 连接到跳转链 */
  return j;
}
```

#### luaK_patchlist - 修补跳转列表
```c
void luaK_patchlist (FuncState *fs, int list, int target) {
  if (target == fs->pc)
    luaK_patchtohere(fs, list);
  else {
    lua_assert(target < fs->pc);
    patchlistaux(fs, list, target, NO_REG, target);
  }
}
```

### 5. 算术运算处理

#### constfolding - 常量折叠优化
```c
static int constfolding (OpCode op, expdesc *e1, expdesc *e2) {
  lua_Number v1, v2, r;
  if (!isnumeral(e1) || !isnumeral(e2)) return 0;
  v1 = e1->u.nval;
  v2 = e2->u.nval;
  switch (op) {
    case OP_ADD: r = luai_numadd(v1, v2); break;
    case OP_SUB: r = luai_numsub(v1, v2); break;
    case OP_MUL: r = luai_nummul(v1, v2); break;
    case OP_DIV:
      if (v2 == 0) return 0;  /* 避免除零 */
      r = luai_numdiv(v1, v2); break;
    /* ... */
  }
  if (luai_numisnan(r)) return 0;  /* 避免产生 NaN */
  e1->u.nval = r;
  return 1;
}
```

#### codearith - 生成算术运算指令
```c
static void codearith (FuncState *fs, OpCode op, expdesc *e1, expdesc *e2) {
  if (constfolding(op, e1, e2))  /* 尝试常量折叠 */
    return;
  else {
    int o1 = luaK_exp2RK(fs, e1);
    int o2 = (op != OP_UNM && op != OP_LEN) ? luaK_exp2RK(fs, e2) : 0;
    freeexp(fs, e2);
    freeexp(fs, e1);
    e1->u.s.info = luaK_codeABC(fs, op, 0, o1, o2);
    e1->k = VRELOCABLE;
  }
}
```

## 寄存器分配机制

### 1. 寄存器管理

```c
/* 检查栈空间 */
void luaK_checkstack (FuncState *fs, int n) {
  int newstack = fs->freereg + n;
  if (newstack > fs->f->maxstacksize) {
    if (newstack >= MAXSTACK)
      luaX_syntaxerror(fs->ls, "function or expression too complex");
    fs->f->maxstacksize = cast_byte(newstack);
  }
}

/* 预留寄存器 */
void luaK_reserveregs (FuncState *fs, int n) {
  luaK_checkstack(fs, n);
  fs->freereg += n;
}

/* 释放寄存器 */
static void freereg (FuncState *fs, int reg) {
  if (!ISK(reg) && reg >= fs->nactvar) {
    fs->freereg--;
    lua_assert(reg == fs->freereg);
  }
}
```

### 2. 表达式到寄存器的转换

```c
/* 将表达式放入指定寄存器 */
static void discharge2reg (FuncState *fs, expdesc *e, int reg) {
  luaK_dischargevars(fs, e);
  switch (e->k) {
    case VNIL: {
      luaK_nil(fs, reg, 1);
      break;
    }
    case VFALSE: case VTRUE: {
      luaK_codeABC(fs, OP_LOADBOOL, reg, e->k == VTRUE, 0);
      break;
    }
    case VK: {
      luaK_codeABx(fs, OP_LOADK, reg, e->u.s.info);
      break;
    }
    case VKNUM: {
      luaK_codeABx(fs, OP_LOADK, reg, luaK_numberK(fs, e->u.nval));
      break;
    }
    case VRELOCABLE: {
      Instruction *pc = &getcode(fs, e);
      SETARG_A(*pc, reg);  /* 修改目标寄存器 */
      break;
    }
    case VNONRELOC: {
      if (reg != e->u.s.info)
        luaK_codeABC(fs, OP_MOVE, reg, e->u.s.info, 0);
      break;
    }
    /* ... */
  }
  e->u.s.info = reg;
  e->k = VNONRELOC;
}
```

## 优化策略

### 1. 常量折叠

编译时计算常量表达式的值，减少运行时计算：

```c
/* 示例：2 + 3 在编译时直接计算为 5 */
if (constfolding(OP_ADD, e1, e2)) {
  /* 常量折叠成功，无需生成指令 */
  return;
}
```

### 2. 跳转优化

- **跳转链合并**: 将多个跳转指令链接成列表，统一处理
- **条件跳转优化**: 利用 `OP_TEST` 和 `OP_TESTSET` 指令优化布尔表达式

### 3. 寄存器复用

- **及时释放**: 表达式计算完成后立即释放临时寄存器
- **局部变量优先**: 局部变量直接使用栈位置，避免额外的 MOVE 指令

### 4. 指令合并

```c
/* OP_LOADNIL 指令合并 */
void luaK_nil (FuncState *fs, int from, int n) {
  Instruction *previous;
  if (fs->pc > fs->lasttarget) {
    if (fs->pc == 0) return;  /* 函数开始位置已经是 nil */
    if (GET_OPCODE(*(previous = &fs->f->code[fs->pc-1])) == OP_LOADNIL) {
      int pfrom = GETARG_A(*previous);
      int pto = GETARG_B(*previous);
      if (pfrom <= from && from <= pto+1) {
        /* 可以合并到前一个 LOADNIL 指令 */
        if (from+n-1 > pto)
          SETARG_B(*previous, from+n-1);
        return;
      }
    }
  }
  luaK_codeABC(fs, OP_LOADNIL, from, from+n-1, 0);
}
```

## 字节码生成流程

### 1. 表达式处理流程

```
源代码表达式
     ↓
语法分析器构建 expdesc
     ↓
luaK_dischargevars (解引用变量)
     ↓
luaK_exp2RK/luaK_exp2anyreg (转换为操作数)
     ↓
生成相应字节码指令
     ↓
更新表达式状态
```

### 2. 语句处理流程

```
赋值语句: var = expr
     ↓
处理右侧表达式 (luaK_exp2anyreg)
     ↓
处理左侧变量 (luaK_storevar)
     ↓
生成存储指令 (SETGLOBAL/SETUPVAL/SETTABLE)
```

### 3. 控制流处理

```
if 语句
     ↓
处理条件表达式 (luaK_goiftrue/luaK_goiffalse)
     ↓
生成条件跳转指令
     ↓
处理 then/else 分支
     ↓
修补跳转地址 (luaK_patchlist)
```

## 错误处理和边界检查

### 1. 栈溢出检查

```c
void luaK_checkstack (FuncState *fs, int n) {
  int newstack = fs->freereg + n;
  if (newstack > fs->f->maxstacksize) {
    if (newstack >= MAXSTACK)
      luaX_syntaxerror(fs->ls, "function or expression too complex");
    fs->f->maxstacksize = cast_byte(newstack);
  }
}
```

### 2. 跳转距离检查

```c
static void fixjump (FuncState *fs, int pc, int dest) {
  Instruction *jmp = &fs->f->code[pc];
  int offset = dest-(pc+1);
  lua_assert(dest != NO_JUMP);
  if (abs(offset) > MAXARG_sBx)
    luaX_syntaxerror(fs->ls, "control structure too long");
  SETARG_sBx(*jmp, offset);
}
```

### 3. 常量表溢出检查

```c
static int addk (FuncState *fs, TValue *k, TValue *v) {
  /* ... */
  luaM_growvector(L, f->k, fs->nk, f->sizek, TValue,
                  MAXARG_Bx, "constant table overflow");
  /* ... */
}
```

## 性能考虑

### 1. 内存管理

- **增量扩展**: 代码数组和常量表采用增量扩展策略
- **垃圾回收屏障**: 使用 `luaC_barrier` 确保垃圾回收正确性

### 2. 指令密度

- **紧凑编码**: 32 位指令格式最大化信息密度
- **操作数复用**: RK 操作数可以是寄存器或常量

### 3. 编译时优化

- **常量折叠**: 编译时计算常量表达式
- **死代码消除**: 跳转优化可以消除部分死代码
- **指令合并**: 相邻的相似指令可以合并

## 总结

Lua 的字节码生成器设计精巧，具有以下特点：

1. **模块化设计**: 清晰的接口分离，便于维护和扩展
2. **高效的寄存器分配**: 基于栈的寄存器管理，减少内存访问
3. **智能的优化策略**: 常量折叠、跳转优化等提高代码质量
4. **健壮的错误处理**: 全面的边界检查和错误报告
5. **紧凑的指令格式**: 最大化指令信息密度

这些设计使得 Lua 能够生成高效、紧凑的字节码，为虚拟机的高性能执行奠定了基础。